Workbook

Sheet Portada
C9: TRABAJO FINAL DE INGENIERÍA
C21: Alumno:
C22: Legajo:
C23: Docentes: Scali, Jorge
C24: Comisión:
C25: Localización:
C26: Email:

Sheet Indice
D2: Índice
D4: Hipótesis
D5: Proyección de ventas
D6: Modelo de ingresos
D7: Estructura de costos fijos
D8: Estructura de costos variables
D9: Estructura de costos de RRHH
D10: Modelo de egresos
D11: Modelo de inversión
D12: Amortizaciones
D13: Presupuesto Financiero
D14: Matriz de riesgos
... D18: Plan de contingencia

Sheet Hipótesis
E1: Hipótesis
B3: 1 - Descripción del negocio
B7: 2 - Mercado meta
B11: Clientes | C11: Gasto promedio (anual) | D11: Total mercado
B12: 427 | C12: 12000000 | D12: =B12*C12 -> 5124000000
B15: 3 - Participación del mercado
B16: participación del 10%
A22: Evolución de la participación en el mercado
A23: Año | B23: Cantidad | C23: Porcentaje | D23: Total
A24: 2026 | B24: 6 empresas medianas | C24: 0.02 | D24: =C24*$D$12 -> 102480000
A25: 2027 | B25: 15 empresas medianas | C25: 0.06 | D25: =C25*$D$12 -> 307440000
A26: 2028 | B26: 33 empresas medianas | C26: 0.1 | D26: =C26*$D$12 -> 512400000
B28: Detalle: Consideramos que una empresa mediana contrata unos 15 vehiculos promedio
B33: 4 - Otros datos
B35: Líneas de servicios
C36: AMPLITUD DE LA MEZCLA DE SERVICIOS
C39: Linea A | D39: Linea B
B40: PROFUNDIDAD DE LAS LÍNEAS DE SERVICIOS | C40: Instalación A | D40: Plan A
C43: Instalación B | D43: Plan B
C46: Instalación C | D46: Plan C
B56: Lista de precios por vehiculo
B57: Servicio | C57: Precio | D57: Detalle
B58: Instalación A | C58: 190000 | D58: Instalación de unidad central + sensor temperatura
B59: Instalación B | C59: 240000 | D59: Instalación sensor apertura puertas + bronce
B60: Instalación C | C60: 310000 | D60: Instalación gps, humedad y sensor motor + plata
B61: Plan A | C61: 88000 | D61: Monitoreo de temperatura | E61: Cobro mensual
B62: Plan B | C62: 108000 | D62: Incluye control de apertura de puertas + bronce | E62: Cobro mensual
B63: Plan C | C63: 132000 | D63: Incluye geolocalización, humedad y sensor de funcionamiento del motor + plata | E63: Cobro mensual

Sheet Proy. ventas
B1: Proyección de ventas
B5: Evolución de la participación | G5: Justificación ingresos
B6: 2026 | C6: 2027 | D6: 2028 | G6: En la proyección de ventas se podrá apreciar el efecto de la estacionalidad remarcada por las siguientes situaciones: a) Efecto temporada alta: Preveemos mayores ventas en los meses de septiembre, octubre y noviembre ya que las empresas de logística refrigerada se preparan para la temporada alta en el verano. Así mismo preveemos un incremento en las ventas en el mes de abril por esta misma causa. b) Estrategia de promoción: 30% de descuento en el precio de instalación para todos los planes durante los 3 años 30% de descuento en el mantenimiento del primer mes post-contratación durante el primer año y luego 100% bonificado el primer mes de mantenimiento.
B7: =Hipótesis!C24 -> 0.02 | C7: =Hipótesis!C25 -> 0.06 | D7: =Hipótesis!C26 -> 0.1
B8: =Hipótesis!D24 -> 102480000 | C8: =Hipótesis!D25 -> 307440000 | D8: =Hipótesis!D26 -> 512400000
A10: .
A15: Proyección de ventas 2026
A16: Producto | B16: Precio | C16: Anual | E16: Enero | G16: Febrero | I16: Marzo | K16: Abril | M16: Mayo | O16: Junio | Q16: Julio | S16: Agosto | U16: Septiembre | W16: Octubre | Y16: Noviembre | AA16: Diciembre
C17: Cantidad de vehiculos | D17: Ingresos | E17: =F32/$D$32 -> 0.060797799 | G17: =H32/$D$32 -> 0.056396149 | I17: =J32/$D$32 -> 0.030261348 | K17: =L32/$D$32 -> 0.078129298 | M17: =N32/$D$32 -> 0.045116919 | O17: =P32/$D$32 -> 0.045116919 | Q17: =R32/$D$32 -> 0.092984869 | S17: =T32/$D$32 -> 0.05997249 | U17: =V32/$D$32 -> 0.12077029 | W17: =X32/$D$32 -> 0.1389271 | Y17: =Z32/$D$32 -> 0.15708391 | AA17: =AB32/$D$32 -> 0.11444292
E18: Cantidad | F18: Ingresos | G18: Cantidad | H18: Ingresos | I18: Cantidad | J18: Ingresos | K18: Cantidad | L18: Ingresos | M18: Cantidad | N18: Ingresos | O18: Cantidad | P18: Ingresos | Q18: Cantidad | R18: Ingresos | S18: Cantidad | T18: Ingresos | U18: Cantidad | V18: Ingresos | W18: Cantidad | X18: Ingresos | Y18: Cantidad | Z18: Ingresos | AA18: Cantidad | AB18: Ingresos
A19: =Hipótesis!$B$58 -> Instalación A | B19: =Hipótesis!C58 -> 190000 | C19: =E19+G19+I19+K19+M19+O19+Q19+S19+U19+W19+Y19+AA19 -> 15 | D19: =B19*C19 -> 2850000 | E19: 0 | F19: =E19*$B$19 -> 0 | G19: 15 | H19: =G19*$B19 -> 2850000 | I19: 0 | J19: =I19*$B$19 -> 0 | K19: 0 | L19: =K19*$B$19 -> 0 | M19: 0 | N19: =M19*$B$19 -> 0 | O19: 0 | P19: =O19*$B$19 -> 0 | Q19: 0 | R19: =Q19*$B$19 -> 0 | S19: 0 | T19: =S19*$B$19 -> 0 | U19: 0 | V19: =U19*$B$19 -> 0 | W19: 0 | X19: =W19*$B$19 -> 0 | Y19: 0 | Z19: =Y19*$B$19 -> 0 | AA19: 0 | AB19: =AA19*$B$19 -> 0
A20: =Hipótesis!$B$59 -> Instalación B | B20: =Hipótesis!C59 -> 240000 | C20: =E20+G20+I20+K20+M20+O20+Q20+S20+U20+W20+Y20+AA20 -> 30 | D20: =B20*C20 -> 7200000 | E20: 0 | F20: =E20*$B$20 -> 0 | G20: 0 | H20: =G20*$B20 -> 0 | I20: 0 | J20: =I20*$B$20 -> 0 | K20: 15 | L20: =K20*$B$20 -> 3600000 | M20: 0 | N20: =M20*$B$20 -> 0 | O20: 0 | P20: =O20*$B$20 -> 0 | Q20: 15 | R20: =Q20*$B$20 -> 3600000 | S20: 0 | T20: =S20*$B$20 -> 0 | U20: 0 | V20: =U20*$B$20 -> 0 | W20: 0 | X20: =W20*$B$20 -> 0 | Y20: 0 | Z20: =Y20*$B$20 -> 0 | AA20: 0 | AB20: =AA20*$B$20 -> 0
A21: =Hipótesis!$B$60 -> Instalación C | B21: =Hipótesis!C60 -> 310000 | C21: =E21+G21+I21+K21+M21+O21+Q21+S21+U21+W21+Y21+AA21 -> 60 | D21: =B21*C21 -> 18600000 | E21: 15 | F21: =E21*$B$21 -> 4650000 | G21: 0 | H21: =G21*$B21 -> 0 | I21: 0 | J21: =I21*$B$21 -> 0 | K21: 0 | L21: =K21*$B$21 -> 0 | M21: 0 | N21: =M21*$B$21 -> 0 | O21: 0 | P21: =O21*$B$21 -> 0 | Q21: 0 | R21: =Q21*$B$21 -> 0 | S21: 0 | T21: =S21*$B$21 -> 0 | U21: 15 | V21: =U21*$B$21 -> 4650000 | W21: 15 | X21: =W21*$B$21 -> 4650000 | Y21: 15 | Z21: =Y21*$B$21 -> 4650000 | AA21: 0 | AB21: =AA21*$B$21 -> 0
A22: =Hipótesis!$B$61 -> Plan A | B22: =Hipótesis!C61 -> 88000 | C22: =E22+G22+I22+K22+M22+O22+Q22+S22+U22+W22+Y22+AA22 -> 165 | D22: =B22*C22 -> 14520000 | E22: =E19 -> 0 | F22: =E22*$B$22 -> 0 | G22: =E22+G19 -> 15 | H22: =G22*$B22 -> 1320000 | I22: =G22+I19 -> 15 | J22: =I22*$B$22 -> 1320000 | K22: =I22+K19 -> 15 | L22: =K22*$B$22 -> 1320000 | M22: =K22+M19 -> 15 | N22: =M22*$B$22 -> 1320000 | O22: =M22+O19 -> 15 | P22: =O22*$B$22 -> 1320000 | Q22: =O22+Q19 -> 15 | R22: =Q22*$B$22 -> 1320000 | S22: =Q22+S19 -> 15 | T22: =S22*$B$22 -> 1320000 | U22: =S22+U19 -> 15 | V22: =U22*$B$22 -> 1320000 | W22: =U22+W19 -> 15 | X22: =W22*$B$22 -> 1320000 | Y22: =W22+Y19 -> 15 | Z22: =Y22*$B$22 -> 1320000 | AA22: =Y22+AA19 -> 15 | AB22: =AA22*$B$22 -> 1320000
A23: =Hipótesis!$B$62 -> Plan B | B23: =Hipótesis!C62 -> 108000 | C23: =E23+G23+I23+K23+M23+O23+Q23+S23+U23+W23+Y23+AA23 -> 225 | D23: =B23*C23 -> 24300000 | E23: =E20 -> 0 | F23: =E23*$B$23 -> 0 | G23: =E23+G20 -> 0 | H23: =G23*$B23 -> 0 | I23: =G23+I20 -> 0 | J23: =I23*$B$23 -> 0 | K23: =I23+K20 -> 15 | L23: =K23*$B$23 -> 1620000 | M23: =K23+M20 -> 15 | N23: =M23*$B$23 -> 1620000 | O23: =M23+O20 -> 15 | P23: =O23*$B$23 -> 1620000 | Q23: =O23+Q20 -> 30 | R23: =Q23*$B$23 -> 3240000 | S23: =Q23+S20 -> 30 | T23: =S23*$B$23 -> 3240000 | U23: =S23+U20 -> 30 | V23: =U23*$B$23 -> 3240000 | W23: =U23+W20 -> 30 | X23: =W23*$B$23 -> 3240000 | Y23: =W23+Y20 -> 30 | Z23: =Y23*$B$23 -> 3240000 | AA23: =Y23+AA20 -> 30 | AB23: =AA23*$B$23 -> 3240000
A24: =Hipótesis!$B$63 -> Plan C | B24: =Hipótesis!C63 -> 132000 | C24: =E24+G24+I24+K24+M24+O24+Q24+S24+U24+W24+Y24+AA24 -> 315 | D24: =B24*C24 -> 41580000 | E24: =E21 -> 15 | F24: =E24*$B$24 -> 1980000 | G24: =E24+G21 -> 15 | H24: =G24*$B24 -> 1980000 | I24: =G24+I21 -> 15 | J24: =I24*$B$24 -> 1980000 | K24: =I24+K21 -> 15 | L24: =K24*$B$24 -> 1980000 | M24: =K24+M21 -> 15 | N24: =M24*$B$24 -> 1980000 | O24: =M24+O21 -> 15 | P24: =O24*$B$24 -> 1980000 | Q24: =O24+Q21 -> 15 | R24: =Q24*$B$24 -> 1980000 | S24: =Q24+S21 -> 15 | T24: =S24*$B$24 -> 1980000 | U24: =S24+U21 -> 30 | V24: =U24*$B$24 -> 3960000 | W24: =U24+W21 -> 45 | X24: =W24*$B$24 -> 5940000 | Y24: =W24+Y21 -> 60 | Z24: =Y24*$B$24 -> 7920000 | AA24: =Y24+AA21 -> 60 | AB24: =AA24*$B$24 -> 7920000
B25: =Hipótesis!C64 -> 0 | D25: =B25*C25 -> 0 | E25: 0 | F25: =E25*$B$25 -> 0 | G25: 0 | H25: =G25*$B25 -> 0 | I25: 0 | J25: =I25*$B$25 -> 0 | K25: 0 | L25: =K25*$B$25 -> 0 | M25: 0 | N25: =M25*$B$25 -> 0 | O25: 0 | P25: =O25*$B$25 -> 0 | Q25: 0 | R25: =Q25*$B$25 -> 0 | S25: 0 | T25: =S25*$B$25 -> 0 | U25: 0 | V25: =U25*$B$25 -> 0 | W25: 0 | X25: =W25*$B$25 -> 0 | Y25: 0 | Z25: =Y25*$B$25 -> 0 | AA25: 0 | AB25: =AA25*$B$25 -> 0
B26: =Hipótesis!C65 -> 0 | D26: =B26*C26 -> 0 | E26: 0 | F26: 0 | G26: 0 | H26: 0 | I26: 0 | J26: 0 | K26: 0 | L26: 0 | M26: 0 | N26: 0 | O26: 0 | P26: 0 | Q26: 0 | R26: 0 | S26: 0 | T26: 0 | U26: 0 | V26: 0 | W26: 0 | X26: 0 | Y26: 0 | Z26: 0 | AA26: 0 | AB26: 0
B27: =Hipótesis!C66 -> 0 | D27: =B27*C27 -> 0 | E27: 0 | F27: 0 | G27: 0 | H27: 0 | I27: 0 | J27: 0 | K27: 0 | L27: 0 | M27: 0 | N27: 0 | O27: 0 | P27: 0 | Q27: 0 | R27: 0 | S27: 0 | T27: 0 | U27: 0 | V27: 0 | W27: 0 | X27: 0 | Y27: 0 | Z27: 0 | AA27: 0 | AB27: 0
B28: =Hipótesis!C67 -> 0 | D28: =B28*C28 -> 0 | E28: 0 | F28: 0 | G28: 0 | H28: 0 | I28: 0 | J28: 0 | K28: 0 | L28: 0 | M28: 0 | N28: 0 | O28: 0 | P28: 0 | Q28: 0 | R28: 0 | S28: 0 | T28: 0 | U28: 0 | V28: 0 | W28: 0 | X28: 0 | Y28: 0 | Z28: 0 | AA28: 0 | AB28: 0
B29: =Hipótesis!C68 -> 0 | D29: =B29*C29 -> 0 | E29: 0 | F29: 0 | G29: 0 | H29: 0 | I29: 0 | J29: 0 | K29: 0 | L29: 0 | M29: 0 | N29: 0 | O29: 0 | P29: 0 | Q29: 0 | R29: 0 | S29: 0 | T29: 0 | U29: 0 | V29: 0 | W29: 0 | X29: 0 | Y29: 0 | Z29: 0 | AA29: 0 | AB29: 0
B30: =Hipótesis!C69 -> 0 | D30: =B30*C30 -> 0 | E30: 0 | F30: 0 | G30: 0 | H30: 0 | I30: 0 | J30: 0 | K30: 0 | L30: 0 | M30: 0 | N30: 0 | O30: 0 | P30: 0 | Q30: 0 | R30: 0 | S30: 0 | T30: 0 | U30: 0 | V30: 0 | W30: 0 | X30: 0 | Y30: 0 | Z30: 0 | AA30: 0 | AB30: 0
B31: =Hipótesis!C70 -> 0 | D31: =B31*C31 -> 0 | E31: 0 | F31: 0 | G31: 0 | H31: 0 | I31: 0 | J31: 0 | K31: 0 | L31: 0 | M31: 0 | N31: 0 | O31: 0 | P31: 0 | Q31: 0 | R31: 0 | S31: 0 | T31: 0 | U31: 0 | V31: 0 | W31: 0 | X31: 0 | Y31: 0 | Z31: 0 | AA31: 0 | AB31: 0
A32: Ingreso Total | D32: =SUM(D19:D31) -> 109050000 | F32: =SUM(F19:F31) -> 6630000 | H32: =SUM(H19:H31) -> 6150000 | J32: =SUM(J19:J31) -> 3300000 | L32: =SUM(L19:L31) -> 8520000 | N32: =SUM(N19:N31) -> 4920000 | P32: =SUM(P19:P31) -> 4920000 | R32: =SUM(R19:R31) -> 10140000 | T32: =SUM(T19:T31) -> 6540000 | V32: =SUM(V19:V31) -> 13170000 | X32: =SUM(X19:X31) -> 15150000 | Z32: =SUM(Z19:Z31) -> 17130000 | AB32: =SUM(AB19:AB31) -> 12480000
C33: =C19 -> 15 | E33: =E19 -> 0 | G33: =G19 -> 15 | I33: =I19 -> 0 | K33: =K19 -> 0 | M33: =M19 -> 0 | O33: =O19 -> 0 | Q33: =Q19 -> 0 | S33: =S19 -> 0 | U33: =U19 -> 0 | W33: =W19 -> 0 | Y33: =Y19 -> 0 | AA33: =AA19 -> 0
C34: =C20 -> 30 | E34: =E20 -> 0 | G34: =G20 -> 0 | I34: =I20 -> 0 | K34: =K20 -> 15 | M34: =M20 -> 0 | O34: =O20 -> 0 | Q34: =Q20 -> 15 | S34: =S20 -> 0 | U34: =U20 -> 0 | W34: =W20 -> 0 | Y34: =Y20 -> 0 | AA34: =AA20 -> 0
C35: =C21 -> 60 | E35: =E21 -> 15 | G35: =G21 -> 0 | I35: =I21 -> 0 | K35: =K21 -> 0 | M35: =M21 -> 0 | O35: =O21 -> 0 | Q35: =Q21 -> 0 | S35: =S21 -> 0 | U35: =U21 -> 15 | W35: =W21 -> 15 | Y35: =Y21 -> 15 | AA35: =AA21 -> 0
C36: =SUM(C22:C25) -> 705 | E36: =SUM(E22:E25) -> 15 | G36: =SUM(G22:G25) -> 30 | I36: =SUM(I22:I25) -> 30 | K36: =SUM(K22:K25) -> 45 | M36: =SUM(M22:M25) -> 45 | O36: =SUM(O22:O25) -> 45 | Q36: =SUM(Q22:Q25) -> 60 | S36: =SUM(S22:S25) -> 60 | U36: =SUM(U22:U25) -> 75 | W36: =SUM(W22:W25) -> 90 | Y36: =SUM(Y22:Y25) -> 105 | AA36: =SUM(AA22:AA25) -> 105
C37: =SUM(C26:C30) -> 0 | E37: =SUM(E26:E30) -> 0 | G37: =SUM(G26:G30) -> 0 | I37: =SUM(I26:I30) -> 0 | K37: =SUM(K26:K30) -> 0 | M37: =SUM(M26:M30) -> 0 | O37: =SUM(O26:O30) -> 0 | Q37: =SUM(Q26:Q30) -> 0 | S37: =SUM(S26:S30) -> 0 | U37: =SUM(U26:U30) -> 0 | W37: =SUM(W26:W30) -> 0 | Y37: =SUM(Y26:Y30) -> 0 | AA37: =SUM(AA26:AA30) -> 0
C38: =C31 -> 0 | E38: =E31 -> 0 | G38: =G31 -> 0 | I38: =I31 -> 0 | K38: =K31 -> 0 | M38: =M31 -> 0 | O38: =O31 -> 0 | Q38: =Q31 -> 0 | S38: =S31 -> 0 | U38: =U31 -> 0 | W38: =W31 -> 0 | Y38: =Y31 -> 0 | AA38: =AA31 -> 0
A40: Capacidad operativa Kick off - Año 2026
A41: Comentarios | B41: El emprendimiento saldrá al mercado habiendo invertido previamente en: * La plataforma digital, cuyo desarrollo fue realizado por los 2 socios fundadores, sumado a 2 desarrolladores jr tercerizados con una consultora. Será mantenido y ampliado por este equipo en una primera instancia. * Infraestructura: Oficina con sector de atención al público y depósito del hardware necesario para los clientes. * Capital de trabajo: se deberá contar con un stock inicial de sensores que irá incrementándose para cubrir las instalaciones de los nuevos clientes y posibles fallos que puedan suceder de clientes ya existentes. Además: * En Julio se contratará un encargado de soporte que trabajará de forma remota y rotando horarios con el anterior para cubrir una mayor franja horaria de soporte.
A42: Concepto | C42: Año cero - Kick off | E42: Año 2026
C43: Cantidad | E43: Enero | G43: Febrero | I43: Marzo | K43: Abril | M43: Mayo | O43: Junio | Q43: Julio | S43: Agosto | U43: Septiembre | W43: Octubre | Y43: Noviembre | AA43: Diciembre
A44: RRHH | C44: Gerente de administración | E44: Gerente de administración (+1) | G44: Sin cambios | I44: Sin cambios | K44: Sin cambios | M44: Sin cambios | O44: Sin cambios | Q44: Sin cambios | S44: Sin cambios | U44: Sin cambios | W44: Sin cambios | Y44: Sin cambios | AA44: Sin cambios
C45: Gerente de marketing | E45: Sin cambios | G45: Sin cambios | I45: Sin cambios | K45: Sin cambios | M45: Sin cambios | O45: Sin cambios | Q45: Sin cambios | S45: Sin cambios | U45: Sin cambios | W45: Sin cambios | Y45: Sin cambios | AA45: Sin cambios
C46: Gerente de sistemas | E46: Gerente de sistemas (+1) | G46: Sin cambios | I46: Sin cambios | K46: Sin cambios | M46: Sin cambios | O46: Sin cambios | Q46: Sin cambios | S46: Sin cambios | U46: Sin cambios | W46: Sin cambios | Y46: Sin cambios | AA46: Sin cambios
C47: Coordinador de soporte | E47: Sin cambios | G47: Sin cambios | I47: Sin cambios | K47: Sin cambios | M47: Sin cambios | O47: Sin cambios | Q47: Coordinador de soporte (+1) | S47: Sin cambios | U47: Sin cambios | W47: Sin cambios | Y47: Sin cambios | AA47: Sin cambios
C48: Soporte de nivel 1 | E48: Sin cambios | G48: Sin cambios | I48: Sin cambios | K48: Sin cambios | M48: Sin cambios | O48: Sin cambios | Q48: Sin cambios | S48: Sin cambios | U48: Sin cambios | W48: Sin cambios | Y48: Sin cambios | AA48: Sin cambios
C49: Auxiliar de ventas | E49: Sin cambios | G49: Sin cambios | I49: Sin cambios | K49: Sin cambios | M49: Sin cambios | O49: Sin cambios | Q49: Sin cambios | S49: Sin cambios | U49: Sin cambios | W49: Sin cambios | Y49: Sin cambios | AA49: Sin cambios
C50: Gerente comercial | E50: Sin cambios | G50: Sin cambios | I50: Sin cambios | K50: Sin cambios | M50: Sin cambios | O50: Sin cambios | Q50: Sin cambios | S50: Sin cambios | U50: Sin cambios | W50: Sin cambios | Y50: Sin cambios | AA50: Sin cambios
C51: 0 | E51: Sin cambios | G51: Sin cambios | I51: Sin cambios | K51: Sin cambios | M51: Sin cambios | O51: Sin cambios | Q51: Sin cambios | S51: Sin cambios | U51: Sin cambios | W51: Sin cambios | Y51: Sin cambios | AA51: Sin cambios
C52: 0 | E52: Sin cambios | G52: Sin cambios | I52: Sin cambios | K52: Sin cambios | M52: Sin cambios | O52: Sin cambios | Q52: Sin cambios | S52: Sin cambios | U52: Sin cambios | W52: Sin cambios | Y52: Sin cambios | AA52: Sin cambios
C53: 0 | E53: Sin cambios | G53: Sin cambios | I53: Sin cambios | K53: Sin cambios | M53: Sin cambios | O53: Sin cambios | Q53: Sin cambios | S53: Sin cambios | U53: Sin cambios | W53: Sin cambios | Y53: Sin cambios | AA53: Sin cambios
C54: 0 | E54: Sin cambios | G54: Sin cambios | I54: Sin cambios | K54: Sin cambios | M54: Sin cambios | O54: Sin cambios | Q54: Sin cambios | S54: Sin cambios | U54: Sin cambios | W54: Sin cambios | Y54: Sin cambios | AA54: Sin cambios
C55: 0 | E55: Sin cambios | G55: Sin cambios | I55: Sin cambios | K55: Sin cambios | M55: Sin cambios | O55: Sin cambios | Q55: Sin cambios | S55: Sin cambios | U55: Sin cambios | W55: Sin cambios | Y55: Sin cambios | AA55: Sin cambios
C56: 0 | E56: Sin cambios | G56: Sin cambios | I56: Sin cambios | K56: Sin cambios | M56: Sin cambios | O56: Sin cambios | Q56: Sin cambios | S56: Sin cambios | U56: Sin cambios | W56: Sin cambios | Y56: Sin cambios | AA56: Sin cambios
C57: 0 | E57: Sin cambios | G57: Sin cambios | I57: Sin cambios | K57: Sin cambios | M57: Sin cambios | O57: Sin cambios | Q57: Sin cambios | S57: Sin cambios | U57: Sin cambios | W57: Sin cambios | Y57: Sin cambios | AA57: Sin cambios
C58: 0 | E58: Sin cambios | G58: Sin cambios | I58: Sin cambios | K58: Sin cambios | M58: Sin cambios | O58: Sin cambios | Q58: Sin cambios | S58: Sin cambios | U58: Sin cambios | W58: Sin cambios | Y58: Sin cambios | AA58: Sin cambios
C59: 0 | E59: Sin cambios | G59: Sin cambios | I59: Sin cambios | K59: Sin cambios | M59: Sin cambios | O59: Sin cambios | Q59: Sin cambios | S59: Sin cambios | U59: Sin cambios | W59: Sin cambios | Y59: Sin cambios | AA59: Sin cambios
C60: 0 | E60: Sin cambios | G60: Sin cambios | I60: Sin cambios | K60: Sin cambios | M60: Sin cambios | O60: Sin cambios | Q60: Sin cambios | S60: Sin cambios | U60: Sin cambios | W60: Sin cambios | Y60: Sin cambios | AA60: Sin cambios
C61: 0 | E61: Sin cambios | G61: Sin cambios | I61: Sin cambios | K61: Sin cambios | M61: Sin cambios | O61: Sin cambios | Q61: Sin cambios | S61: Sin cambios | U61: Sin cambios | W61: Sin cambios | Y61: Sin cambios | AA61: Sin cambios
A62: Infraestructura | C62: Oficina | E62: Oficina (+1 alquiler) | G62: Sin cambios | I62: Sin cambios | K62: Sin cambios | M62: Sin cambios | O62: Sin cambios | Q62: Sin cambios | S62: Sin cambios | U62: Sin cambios | W62: Sin cambios | Y62: Sin cambios | AA62: Sin cambios
C63: Notebooks | E63: Notebooks (+3) | G63: Sin cambios | I63: Sin cambios | K63: Sin cambios | M63: Sin cambios | O63: Sin cambios | Q63: Notebooks (+1) | S63: Sin cambios | U63: Sin cambios | W63: Sin cambios | Y63: Sin cambios | AA63: Sin cambios
C64: Escritorios | E64: Escritorios (+2) | G64: Sin cambios | I64: Sin cambios | K64: Sin cambios | M64: Sin cambios | O64: Sin cambios | Q64: Sin cambios | S64: Sin cambios | U64: Sin cambios | W64: Sin cambios | Y64: Sin cambios | AA64: Sin cambios
C65: Sillas de escritorio | E65: Sillas de escritorio (+4) | G65: Sin cambios | I65: Sin cambios | K65: Sin cambios | M65: Sin cambios | O65: Sin cambios | Q65: Sin cambios | S65: Sin cambios | U65: Sin cambios | W65: Sin cambios | Y65: Sin cambios | AA65: Sin cambios
C66: 0 | E66: Sin cambios | G66: Sin cambios | I66: Sin cambios | K66: Sin cambios | M66: Sin cambios | O66: Sin cambios | Q66: Sin cambios | S66: Sin cambios | U66: Sin cambios | W66: Sin cambios | Y66: Sin cambios | AA66: Sin cambios
C67: 0 | E67: Sin cambios | G67: Sin cambios | I67: Sin cambios | K67: Sin cambios | M67: Sin cambios | O67: Sin cambios | Q67: Sin cambios | S67: Sin cambios | U67: Sin cambios | W67: Sin cambios | Y67: Sin cambios | AA67: Sin cambios
C68: 0 | E68: Sin cambios | G68: Sin cambios | I68: Sin cambios | K68: Sin cambios | M68: Sin cambios | O68: Sin cambios | Q68: Sin cambios | S68: Sin cambios | U68: Sin cambios | W68: Sin cambios | Y68: Sin cambios | AA68: Sin cambios
A69: Capital de trabajo | C69: Sensores temperatura | E69: Sesores temperatura (+30) | G69: Sesores temperatura (+15) | I69: Sesores temperatura (+15) | K69: Sesores temperatura (+15) | M69: Sin cambios | O69: Sin cambios | Q69: Sesores temperatura (+60) | S69: Sin cambios | U69: Sin cambios | W69: Sin cambios | Y69: Sin cambios | AA69: Sin cambios
C70: Sensores puertas | E70: Sensores puertas (+30) | G70: Sensores puertas (+15) | I70: Sin cambios | K70: Sensores puertas (+15) | M70: Sin cambios | O70: Sin cambios | Q70: Sensores puertas (+60) | S70: Sin cambios | U70: Sin cambios | W70: Sin cambios | Y70: Sin cambios | AA70: Sin cambios
C71: Sensores humedad | E71: Sensores humedad (+30) | G71: Sensores humedad (+15) | I71: Sin cambios | K71: Sin cambios | M71: Sin cambios | O71: Sin cambios | Q71: Sensores humedad (+60) | S71: Sin cambios | U71: Sin cambios | W71: Sin cambios | Y71: Sin cambios | AA71: Sin cambios
C72: Sensores geolocalizacion | E72: Sensores geolocalización (+30) | G72: Sensores geolocalización (+15) | I72: Sin cambios | K72: Sin cambios | M72: Sin cambios | O72: Sin cambios | Q72: Sensores geolocalización (+60) | S72: Sin cambios | U72: Sin cambios | W72: Sin cambios | Y72: Sin cambios | AA72: Sin cambios
C73: Sensores motor refrigeración | E73: Sensores motor refrigeracion (+30) | G73: Sensores motor refrigeracion (+15) | I73: Sin cambios | K73: Sin cambios | M73: Sin cambios | O73: Sin cambios | Q73: Sensores motor refrigeracion (+60) | S73: Sin cambios | U73: Sin cambios | W73: Sin cambios | Y73: Sin cambios | AA73: Sin cambios
C74: Unidad central | E74: Unidad central (+5) | G74: Unidad central (+3) | I74: Sin cambios | K74: Sin cambios | M74: Sin cambios | O74: Sin cambios | Q74: Unidad central (+10) | S74: Sin cambios | U74: Sin cambios | W74: Sin cambios | Y74: Sin cambios | AA74: Sin cambios
A78: Proyección de ventas 2027
A79: Producto | B79: Precio | C79: Anual | E79: Enero | G79: Febrero | I79: Marzo | K79: Abril | M79: Mayo | O79: Junio | Q79: Julio | S79: Agosto | U79: Septiembre | W79: Octubre | Y79: Noviembre | AA79: Diciembre
C80: Cantidad de vehiculos | D80: Ingresos | E80: 0.05 | G80: 0.05 | I80: 0.05 | K80: 0.15 | M80: 0.1 | O80: 0.075 | Q80: 0.05 | S80: 0.05 | U80: 0.1 | W80: 0.1 | Y80: 0.1 | AA80: 0.075
E81: Cantidad | F81: Ingresos | G81: Cantidad | H81: Ingresos | I81: Cantidad | J81: Ingresos | K81: Cantidad | L81: Ingresos | M81: Cantidad | N81: Ingresos | O81: Cantidad | P81: Ingresos | Q81: Cantidad | R81: Ingresos | S81: Cantidad | T81: Ingresos | U81: Cantidad | V81: Ingresos | W81: Cantidad | X81: Ingresos | Y81: Cantidad | Z81: Ingresos | AA81: Cantidad | AB81: Ingresos
A82: =Hipótesis!$B$58 -> Instalación A | B82: =Hipótesis!C58 -> 190000 | C82: =E82+G82+I82+K82+M82+O82+Q82+S82+U82+W82+Y82+AA82 -> 30 | D82: =B82*C82 -> 5700000 | E82: 0 | F82: =E82*$B82 -> 0 | G82: 0 | H82: =G82*$B82 -> 0 | I82: 0 | J82: =I82*$B82 -> 0 | K82: 15 | L82: =K82*$B82 -> 2850000 | M82: 0 | N82: =M82*$B82 -> 0 | O82: 0 | P82: =O82*$B82 -> 0 | Q82: 0 | R82: =Q82*$B82 -> 0 | S82: 0 | T82: =S82*$B82 -> 0 | U82: 15 | V82: =U82*$B82 -> 2850000 | W82: 0 | X82: =W82*$B82 -> 0 | Y82: 0 | Z82: =Y82*$B82 -> 0 | AA82: 0 | AB82: =AA82*$B82 -> 0
A83: =Hipótesis!$B$59 -> Instalación B | B83: =Hipótesis!C59 -> 240000 | C83: =E83+G83+I83+K83+M83+O83+Q83+S83+U83+W83+Y83+AA83 -> 15 | D83: =B83*C83 -> 3600000 | E83: 0 | F83: =E83*$B83 -> 0 | G83: 0 | H83: =G83*$B83 -> 0 | I83: 15 | J83: =I83*$B83 -> 3600000 | K83: 0 | L83: =K83*$B83 -> 0 | M83: 0 | N83: =M83*$B83 -> 0 | O83: 0 | P83: =O83*$B83 -> 0 | Q83: 0 | R83: =Q83*$B83 -> 0 | S83: 0 | T83: =S83*$B83 -> 0 | U83: 0 | V83: =U83*$B83 -> 0 | W83: 0 | X83: =W83*$B83 -> 0 | Y83: 0 | Z83: =Y83*$B83 -> 0 | AA83: 0 | AB83: =AA83*$B83 -> 0
A84: =Hipótesis!$B$60 -> Instalación C | B84: =Hipótesis!C60 -> 310000 | C84: =E84+G84+I84+K84+M84+O84+Q84+S84+U84+W84+Y84+AA84 -> 90 | D84: =B84*C84 -> 27900000 | E84: 15 | F84: =E84*$B84 -> 4650000 | G84: 0 | H84: =G84*$B84 -> 0 | I84: 0 | J84: =I84*$B84 -> 0 | K84: 15 | L84: =K84*$B84 -> 4650000 | M84: 0 | N84: =M84*$B84 -> 0 | O84: 0 | P84: =O84*$B84 -> 0 | Q84: 0 | R84: =Q84*$B84 -> 0 | S84: 0 | T84: =S84*$B84 -> 0 | U84: 0 | V84: =U84*$B84 -> 0 | W84: 30 | X84: =W84*$B84 -> 9300000 | Y84: 30 | Z84: =Y84*$B84 -> 9300000 | AA84: 0 | AB84: =AA84*$B84 -> 0
A85: =Hipótesis!$B$61 -> Plan A | B85: =Hipótesis!C61 -> 88000 | C85: =E85+G85+I85+K85+M85+O85+Q85+S85+U85+W85+Y85+AA85 -> 375 | D85: =B85*C85 -> 33000000 | E85: =Y22+E82 -> 15 | F85: =E85*$B85 -> 1320000 | G85: =E85+G82 -> 15 | H85: =G85*$B85 -> 1320000 | I85: =G85+I82 -> 15 | J85: =I85*$B85 -> 1320000 | K85: =I85+K82 -> 30 | L85: =K85*$B85 -> 2640000 | M85: =K85+M82 -> 30 | N85: =M85*$B85 -> 2640000 | O85: =M85+O82 -> 30 | P85: =O85*$B85 -> 2640000 | Q85: =O85+Q82 -> 30 | R85: =Q85*$B85 -> 2640000 | S85: =Q85+S82 -> 30 | T85: =S85*$B85 -> 2640000 | U85: =S85+U82 -> 45 | V85: =U85*$B85 -> 3960000 | W85: =U85+W82 -> 45 | X85: =W85*$B85 -> 3960000 | Y85: =W85+Y82 -> 45 | Z85: =Y85*$B85 -> 3960000 | AA85: =Y85+AA82 -> 45 | AB85: =AA85*$B85 -> 3960000
A86: =Hipótesis!$B$62 -> Plan B | B86: =Hipótesis!C62 -> 108000 | C86: =E86+G86+I86+K86+M86+O86+Q86+S86+U86+W86+Y86+AA86 -> 510 | D86: =B86*C86 -> 55080000 | E86: =Y23+E83 -> 30 | F86: =E86*$B86 -> 3240000 | G86: =E86+G83 -> 30 | H86: =G86*$B86 -> 3240000 | I86: =G86+I83 -> 45 | J86: =I86*$B86 -> 4860000 | K86: =I86+K83 -> 45 | L86: =K86*$B86 -> 4860000 | M86: =K86+M83 -> 45 | N86: =M86*$B86 -> 4860000 | O86: =M86+O83 -> 45 | P86: =O86*$B86 -> 4860000 | Q86: =O86+Q83 -> 45 | R86: =Q86*$B86 -> 4860000 | S86: =Q86+S83 -> 45 | T86: =S86*$B86 -> 4860000 | U86: =S86+U83 -> 45 | V86: =U86*$B86 -> 4860000 | W86: =U86+W83 -> 45 | X86: =W86*$B86 -> 4860000 | Y86: =W86+Y83 -> 45 | Z86: =Y86*$B86 -> 4860000 | AA86: =Y86+AA83 -> 45 | AB86: =AA86*$B86 -> 4860000
A87: =Hipótesis!$B$63 -> Plan C | B87: =Hipótesis!C63 -> 132000 | C87: =E87+G87+I87+K87+M87+O87+Q87+S87+U87+W87+Y87+AA87 -> 1185 | D87: =B87*C87 -> 156420000 | E87: =Y24+E84 -> 75 | F87: =E87*$B87 -> 9900000 | G87: =E87+G84 -> 75 | H87: =G87*$B87 -> 9900000 | I87: =G87+I84 -> 75 | J87: =I87*$B87 -> 9900000 | K87: =I87+K84 -> 90 | L87: =K87*$B87 -> 11880000 | M87: =K87+M84 -> 90 | N87: =M87*$B87 -> 11880000 | O87: =M87+O84 -> 90 | P87: =O87*$B87 -> 11880000 | Q87: =O87+Q84 -> 90 | R87: =Q87*$B87 -> 11880000 | S87: =Q87+S84 -> 90 | T87: =S87*$B87 -> 11880000 | U87: =S87+U84 -> 90 | V87: =U87*$B87 -> 11880000 | W87: =U87+W84 -> 120 | X87: =W87*$B87 -> 15840000 | Y87: =W87+Y84 -> 150 | Z87: =Y87*$B87 -> 19800000 | AA87: =Y87+AA84 -> 150 | AB87: =AA87*$B87 -> 19800000
B88: =Hipótesis!C64 -> 0 | C88: 0 | D88: =B88*C88 -> 0 | E88: 0 | F88: =E88*$B88 -> 0 | G88: 0 | H88: =G88*$B88 -> 0 | I88: 0 | J88: =I88*$B88 -> 0 | K88: 0 | L88: =K88*$B88 -> 0 | M88: 0 | N88: =M88*$B88 -> 0 | O88: 0 | P88: =O88*$B88 -> 0 | Q88: 0 | R88: =Q88*$B88 -> 0 | S88: 0 | T88: =S88*$B88 -> 0 | U88: 0 | V88: =U88*$B88 -> 0 | W88: 0 | X88: =W88*$B88 -> 0 | Y88: 0 | Z88: =Y88*$B88 -> 0 | AA88: 0 | AB88: =AA88*$B88 -> 0
B89: =Hipótesis!C65 -> 0 | D89: =B89*C89 -> 0 | E89: =C89*$E$80 -> 0 | F89: =D89*$E$17 -> 0 | G89: =C89*$G$80 -> 0 | H89: =D89*$G$17 -> 0 | I89: =C89*$I$80 -> 0 | J89: =D89*$I$17 -> 0 | K89: =C89*$K$80 -> 0 | L89: =D89*$K$17 -> 0 | M89: =C89*$M$80 -> 0 | N89: =D89*$M$17 -> 0 | O89: =C89*$O$80 -> 0 | P89: =D89*$O$17 -> 0 | Q89: =C89*$Q$80 -> 0 | R89: =D89*$Q$17 -> 0 | S89: =C89*$S$80 -> 0 | T89: =D89*$S$17 -> 0 | U89: =C89*$U$80 -> 0 | V89: =D89*$U$17 -> 0 | W89: =C89*$W$80 -> 0 | X89: =D89*$W$17 -> 0 | Y89: =C89*$Y$80 -> 0 | Z89: =D89*$Y$17 -> 0 | AA89: =C89*$AA$80 -> 0 | AB89: =D89*$AA$17 -> 0
B90: =Hipótesis!C66 -> 0 | D90: =B90*C90 -> 0 | E90: =C90*$E$80 -> 0 | F90: =D90*$E$17 -> 0 | G90: =C90*$G$80 -> 0 | H90: =D90*$G$17 -> 0 | I90: =C90*$I$80 -> 0 | J90: =D90*$I$17 -> 0 | K90: =C90*$K$80 -> 0 | L90: =D90*$K$17 -> 0 | M90: =C90*$M$80 -> 0 | N90: =D90*$M$17 -> 0 | O90: =C90*$O$80 -> 0 | P90: =D90*$O$17 -> 0 | Q90: =C90*$Q$80 -> 0 | R90: =D90*$Q$17 -> 0 | S90: =C90*$S$80 -> 0 | T90: =D90*$S$17 -> 0 | U90: =C90*$U$80 -> 0 | V90: =D90*$U$17 -> 0 | W90: =C90*$W$80 -> 0 | X90: =D90*$W$17 -> 0 | Y90: =C90*$Y$80 -> 0 | Z90: =D90*$Y$17 -> 0 | AA90: =C90*$AA$80 -> 0 | AB90: =D90*$AA$17 -> 0
B91: =Hipótesis!C67 -> 0 | D91: =B91*C91 -> 0 | E91: =C91*$E$80 -> 0 | F91: =D91*$E$17 -> 0 | G91: =C91*$G$80 -> 0 | H91: =D91*$G$17 -> 0 | I91: =C91*$I$80 -> 0 | J91: =D91*$I$17 -> 0 | K91: =C91*$K$80 -> 0 | L91: =D91*$K$17 -> 0 | M91: =C91*$M$80 -> 0 | N91: =D91*$M$17 -> 0 | O91: =C91*$O$80 -> 0 | P91: =D91*$O$17 -> 0 | Q91: =C91*$Q$80 -> 0 | R91: =D91*$Q$17 -> 0 | S91: =C91*$S$80 -> 0 | T91: =D91*$S$17 -> 0 | U91: =C91*$U$80 -> 0 | V91: =D91*$U$17 -> 0 | W91: =C91*$W$80 -> 0 | X91: =D91*$W$17 -> 0 | Y91: =C91*$Y$80 -> 0 | Z91: =D91*$Y$17 -> 0 | AA91: =C91*$AA$80 -> 0 | AB91: =D91*$AA$17 -> 0
B92: =Hipótesis!C68 -> 0 | D92: =B92*C92 -> 0 | E92: =C92*$E$80 -> 0 | F92: =D92*$E$17 -> 0 | G92: =C92*$G$80 -> 0 | H92: =D92*$G$17 -> 0 | I92: =C92*$I$80 -> 0 | J92: =D92*$I$17 -> 0 | K92: =C92*$K$80 -> 0 | L92: =D92*$K$17 -> 0 | M92: =C92*$M$80 -> 0 | N92: =D92*$M$17 -> 0 | O92: =C92*$O$80 -> 0 | P92: =D92*$O$17 -> 0 | Q92: =C92*$Q$80 -> 0 | R92: =D92*$Q$17 -> 0 | S92: =C92*$S$80 -> 0 | T92: =D92*$S$17 -> 0 | U92: =C92*$U$80 -> 0 | V92: =D92*$U$17 -> 0 | W92: =C92*$W$80 -> 0 | X92: =D92*$W$17 -> 0 | Y92: =C92*$Y$80 -> 0 | Z92: =D92*$Y$17 -> 0 | AA92: =C92*$AA$80 -> 0 | AB92: =D92*$AA$17 -> 0
B93: =Hipótesis!C69 -> 0 | D93: =B93*C93 -> 0 | E93: =C93*$E$80 -> 0 | F93: =D93*$E$17 -> 0 | G93: =C93*$G$80 -> 0 | H93: =D93*$G$17 -> 0 | I93: =C93*$I$80 -> 0 | J93: =D93*$I$17 -> 0 | K93: =C93*$K$80 -> 0 | L93: =D93*$K$17 -> 0 | M93: =C93*$M$80 -> 0 | N93: =D93*$M$17 -> 0 | O93: =C93*$O$80 -> 0 | P93: =D93*$O$17 -> 0 | Q93: =C93*$Q$80 -> 0 | R93: =D93*$Q$17 -> 0 | S93: =C93*$S$80 -> 0 | T93: =D93*$S$17 -> 0 | U93: =C93*$U$80 -> 0 | V93: =D93*$U$17 -> 0 | W93: =C93*$W$80 -> 0 | X93: =D93*$W$17 -> 0 | Y93: =C93*$Y$80 -> 0 | Z93: =D93*$Y$17 -> 0 | AA93: =C93*$AA$80 -> 0 | AB93: =D93*$AA$17 -> 0
B94: =Hipótesis!C70 -> 0 | D94: =B94*C94 -> 0 | E94: =C94*$E$17 -> 0 | F94: =D94*$E$17 -> 0 | G94: =C94*$G$80 -> 0 | H94: =D94*$G$17 -> 0 | I94: =C94*$I$80 -> 0 | J94: =D94*$I$17 -> 0 | K94: =C94*$K$80 -> 0 | L94: =D94*$K$17 -> 0 | M94: =C94*$M$80 -> 0 | N94: =D94*$M$17 -> 0 | O94: =C94*$O$80 -> 0 | P94: =D94*$O$17 -> 0 | Q94: =C94*$Q$80 -> 0 | R94: =D94*$Q$17 -> 0 | S94: =C94*$S$80 -> 0 | T94: =D94*$S$17 -> 0 | U94: =C94*$U$80 -> 0 | V94: =D94*$U$17 -> 0 | W94: =C94*$W$80 -> 0 | X94: =D94*$W$17 -> 0 | Y94: =C94*$Y$80 -> 0 | Z94: =D94*$Y$17 -> 0 | AA94: =C94*$AA$80 -> 0 | AB94: =D94*$AA$17 -> 0
A95: Ingreso Total | D95: =SUM(D82:D94) -> 281700000 | F95: =SUM(F82:F94) -> 19110000 | H95: =SUM(H82:H94) -> 14460000 | J95: =SUM(J82:J94) -> 19680000 | L95: =SUM(L82:L94) -> 26880000 | N95: =SUM(N82:N94) -> 19380000 | P95: =SUM(P82:P94) -> 19380000 | R95: =SUM(R82:R94) -> 19380000 | T95: =SUM(T82:T94) -> 19380000 | V95: =SUM(V82:V94) -> 23550000 | X95: =SUM(X82:X94) -> 33960000 | Z95: =SUM(Z82:Z94) -> 37920000 | AB95: =SUM(AB82:AB94) -> 28620000
C96: =C82 -> 30 | E96: =E82 -> 0 | G96: =G82 -> 0 | I96: =I82 -> 0 | K96: =K82 -> 15 | M96: =M82 -> 0 | O96: =O82 -> 0 | Q96: =Q82 -> 0 | S96: =S82 -> 0 | U96: =U82 -> 15 | W96: =W82 -> 0 | Y96: =Y82 -> 0 | AA96: =AA82 -> 0
C97: =C83 -> 15 | E97: =E83 -> 0 | G97: =G83 -> 0 | I97: =I83 -> 15 | K97: =K83 -> 0 | M97: =M83 -> 0 | O97: =O83 -> 0 | Q97: =Q83 -> 0 | S97: =S83 -> 0 | U97: =U83 -> 0 | W97: =W83 -> 0 | Y97: =Y83 -> 0 | AA97: =AA83 -> 0
C98: =C84 -> 90 | E98: =E84 -> 15 | G98: =G84 -> 0 | I98: =I84 -> 0 | K98: =K84 -> 15 | M98: =M84 -> 0 | O98: =O84 -> 0 | Q98: =Q84 -> 0 | S98: =S84 -> 0 | U98: =U84 -> 0 | W98: =W84 -> 30 | Y98: =Y84 -> 30 | AA98: =AA84 -> 0
C99: =SUM(C85:C88) -> 2070 | E99: =SUM(E85:E88) -> 120 | G99: =SUM(G85:G88) -> 120 | I99: =SUM(I85:I88) -> 135 | K99: =SUM(K85:K88) -> 165 | M99: =SUM(M85:M88) -> 165 | O99: =SUM(O85:O88) -> 165 | Q99: =SUM(Q85:Q88) -> 165 | S99: =SUM(S85:S88) -> 165 | U99: =SUM(U85:U88) -> 180 | W99: =SUM(W85:W88) -> 210 | Y99: =SUM(Y85:Y88) -> 240 | AA99: =SUM(AA85:AA88) -> 240
C100: =SUM(C89:C93) -> 0 | E100: =SUM(E89:E93) -> 0 | G100: =SUM(G89:G93) -> 0 | I100: =SUM(I89:I93) -> 0 | K100: =SUM(K89:K93) -> 0 | M100: =SUM(M89:M93) -> 0 | O100: =SUM(O89:O93) -> 0 | Q100: =SUM(Q89:Q93) -> 0 | S100: =SUM(S89:S93) -> 0 | U100: =SUM(U89:U93) -> 0 | W100: =SUM(W89:W93) -> 0 | Y100: =SUM(Y89:Y93) -> 0 | AA100: =SUM(AA89:AA93) -> 0
C101: =C94 -> 0 | E101: =E94 -> 0 | G101: =G94 -> 0 | I101: =I94 -> 0 | K101: =K94 -> 0 | M101: =M94 -> 0 | O101: =O94 -> 0 | Q101: =Q94 -> 0 | S101: =S94 -> 0 | U101: =U94 -> 0 | W101: =W94 -> 0 | Y101: =Y94 -> 0 | AA101: =AA94 -> 0
A103: Capacidad operativa - Año 2027
A104: Comentarios | B104: * En enero se contratará un auxiliar de soporte que trabajará con horarios rotativos en conjunto con el anterior empleado para cubrir una mayor franja horaria de soporte. * En marzo se contratará un auxiliar de ventas para poder cumplir con los objetivos del nuevo año. * Capital de trabajo: se seguira incrementando el stock de sensores para cubrir las instalaciones de los nuevos clientes y posibles fallos que puedan suceder de clientes ya existentes.
C105: Concepto | E105: Enero | G105: Febrero | I105: Marzo | K105: Abril | M105: Mayo | O105: Junio | Q105: Julio | S105: Agosto | U105: Septiembre | W105: Octubre | Y105: Noviembre | AA105: Diciembre
A106: RRHH | C106: Gerente de administración | E106: Sin cambios | G106: Sin cambios | I106: Sin cambios | K106: Sin cambios | M106: Sin cambios | O106: Sin cambios | Q106: Sin cambios | S106: Sin cambios | U106: Sin cambios | W106: Sin cambios | Y106: Sin cambios | AA106: Sin cambios
C107: Gerente de marketing | E107: Gerente de marketing (+1) | G107: Sin cambios | I107: Sin cambios | K107: Sin cambios | M107: Sin cambios | O107: Sin cambios | Q107: Sin cambios | S107: Sin cambios | U107: Sin cambios | W107: Sin cambios | Y107: Sin cambios | AA107: Sin cambios
C108: Gerente de sistemas | E108: Sin cambios | G108: Sin cambios | I108: Sin cambios | K108: Sin cambios | M108: Sin cambios | O108: Sin cambios | Q108: Sin cambios | S108: Sin cambios | U108: Sin cambios | W108: Sin cambios | Y108: Sin cambios | AA108: Sin cambios
C109: Coordinador de soporte | E109: Sin cambios | G109: Sin cambios | I109: Sin cambios | K109: Sin cambios | M109: Sin cambios | O109: Sin cambios | Q109: Sin cambios | S109: Sin cambios | U109: Sin cambios | W109: Sin cambios | Y109: Sin cambios | AA109: Sin cambios
C110: Soporte de nivel 1 | E110: Soporte de nivel 1 (+1) | G110: Sin cambios | I110: Sin cambios | K110: Sin cambios | M110: Sin cambios | O110: Sin cambios | Q110: Sin cambios | S110: Sin cambios | U110: Sin cambios | W110: Sin cambios | Y110: Sin cambios | AA110: Sin cambios
C111: Auxiliar de ventas | E111: Sin cambios | G111: Sin cambios | I111: Auxiliar de ventas (+1) | K111: Sin cambios | M111: Sin cambios | O111: Sin cambios | Q111: Sin cambios | S111: Sin cambios | U111: Sin cambios | W111: Sin cambios | Y111: Sin cambios | AA111: Sin cambios
C112: Gerente comercial | E112: Sin cambios | G112: Sin cambios | I112: Sin cambios | K112: Sin cambios | M112: Sin cambios | O112: Sin cambios | Q112: Sin cambios | S112: Sin cambios | U112: Sin cambios | W112: Sin cambios | Y112: Sin cambios | AA112: Sin cambios
C113: 0 | E113: Sin cambios | G113: Sin cambios | I113: Sin cambios | K113: Sin cambios | M113: Sin cambios | O113: Sin cambios | Q113: Sin cambios | S113: Sin cambios | U113: Sin cambios | W113: Sin cambios | Y113: Sin cambios | AA113: Sin cambios
...

Sheet Anexo capacidad operativa
C1: Anexo capacidad operativa
A3: Instalación de sensores PuntoSens | H3: Mantenimiento plan | O3: Sueldo tecnico por hora: | P3: 12500 | S3: Coste instalación sensores | Y3: Coste mantenimiento sensores
A6: Cálculo de horas laborables de un empleado por mes
A7: Semanas por año | B7: 52 | C7: semanas
A8: Semanas de licencias varias al año | B8: 2 | C8: semanas
A9: Días festivos | B9: 14 | C9: días
A10: Días laborales totales | B10: =(B7-B8)*5 -B9 -> 236 | C10: días
A11: Jornada laboral | B11: 8 | C11: horas | T11: Instalación de unidad central + sensor temperatura
A12: Horas laborables anuales por empleado | B12: =B10*B11 -> 1888 | C12: horas | T12: Instalación sensor apertura puertas + bronce
A13: Consideraremos en promedio: | B13: 1800 | C13: Horas laborables anuales / empleado | T13: Instalación gps y sensor motor + plata
B14: 150 | C14: Horas laborables mensuales / empleado [HsLaboralesXMes]
A18: Instalación A | H18: Plan A | S18: Plan A | Y18: Mantenimiento plan A
A19: N° de tarea | B19: Descripción | C19: Base horaria [BH] | D19: Cantidad requerida [Cant] | E19: Horas por tarea Fórmula = Cant * BH | H19: N° de tarea | I19: Descripción | J19: Base horaria [BH] | K19: Cantidad requerida [Cant] | L19: Horas por tarea Fórmula = Cant * BH | S19: Componente | U19: Cantidad | V19: Precio unitario | W19: Subtotal | Y19: Componente | AA19: Cantidad | AB19: Precio unitario | AC19: Subtotal
A20: 1 | B20: Preparación | C20: 0.17 | D20: 1 | E20: =D20*C20 -> 0.17 | H20: 1 | I20: Revisión de sensores temp | J20: 0.1 | K20: 1 | L20: =K20*J20 -> 0.1 | S20: Unidad central | U20: 1 | V20: 30000 | W20: =V20*U20 -> 30000 | Y20: Servicio tecnico | AA20: =L32 -> 0.3 | AB20: =P3 -> 12500 | AC20: =AB20*AA20 -> 3750
A21: 2 | B21: Instalación sensores temperatura | C21: 0.42 | D21: 1 | E21: =D21*C21 -> 0.42 | H21: 2 | I21: Calibración remota | J21: 0.05 | K21: 1 | L21: =K21*J21 -> 0.05 | S21: Sensor temperatura | U21: 4 | V21: 12500 | W21: =V21*U21 -> 50000
A22: 3 | B22: Cableado/conexión | C22: 0.25 | D22: 1 | E22: =D22*C22 -> 0.25 | H22: 3 | I22: Monitoreo de alertas | J22: 0.1 | K22: 1 | L22: =K22*J22 -> 0.1 | S22: Instalación | U22: =E32 -> 1.01 | V22: =P3 -> 12500 | W22: =V22*U22 -> 12625 | AB22: =V3 -> 0
A23: 4 | B23: Calibración/pruebas | C23: 0.17 | D23: 1 | E23: =D23*C23 -> 0.17 | H23: 4 | I23: Reporte preventivo | J23: 0.05 | K23: 1 | L23: =K23*J23 -> 0.05
A24: 5 | E24: =D24*C24 -> 0 | H24: 5 | L24: =K24*J24 -> 0
A25: 6 | E25: =D25*C25 -> 0 | H25: 6
A26: 7 | E26: =D26*C26 -> 0 | H26: 7
A27: 8 | E27: =D27*C27 -> 0 | H27: 8
A28: 9 | E28: =D28*C28 -> 0 | H28: 9 | S28: Total | W28: =SUM(W20:W25) -> 92625 | Y28: Total | AC28: =SUM(AC20:AC25) -> 3750
A29: 10 | E29: =D29*C29 -> 0 | H29: 10
A30: 11 | E30: =D30*C30 -> 0 | H30: 11
A31: 12 | E31: =D31*C31 -> 0 | H31: 12
A32: Comentarios: | D32: Horas totales por servicio [HsTotalesXServicio] Fórmula = Σ Horas por tarea del servicio | E32: =SUM(E20:E31) -> 1.01 | F32: Coste por instalación | H32: Comentarios: | K32: Horas totales por servicio [HsTotalesXServicio] | L32: =SUM(L20:L31) -> 0.3
D33: Capacidad operativa mensual por proyecto Fórmula = HsTotalesXSer / HsLaboralesXMes | E33: =E32/$B$14 -> 0.0067333333 | F33: =$P$3*E32 -> 12625 | K33: Capacidad operativa mensual por proyecto | L33: =L32/$B$14 -> 0.002
A37: Instalación B | H37: Plan plata | S37: Plan B | Y37: Mantenimiento plan B
A38: N° de tarea | B38: Descripción | C38: Base horaria [BH] | D38: Cantidad requerida [Cant] | E38: Horas por tarea Fórmula = Cant * BH | H38: N° de tarea | I38: Descripción | J38: Base horaria [BH] | K38: Cantidad requerida [Cant] | L38: Horas por tarea Fórmula = Cant * BH | S38: Componente | U38: Cantidad | V38: Precio unitario | W38: Subtotal | Y38: Componente | AA38: Cantidad | AB38: Precio unitario | AC38: Subtotal
A39: 1 | B39: Preparación | C39: 0.25 | D39: 1 | E39: =D39*C39 -> 0.25 | H39: 1 | I39: Revision sensores temp | J39: 0.1 | K39: 1 | L39: =K39*J39 -> 0.1 | S39: Unidad central | U39: 1 | V39: 30000 | W39: =V39*U39 -> 30000 | Y39: Servicio tecnico | AA39: =L51 -> 0.6 | AB39: =P3 -> 12500 | AC39: =AB39*AA39 -> 7500
A40: 2 | B40: Instalación sensores temperatura | C40: 0.42 | D40: 1 | E40: =D40*C40 -> 0.42 | H40: 2 | I40: Revision sensores puertas | J40: 0.2 | K40: 1 | L40: =K40*J40 -> 0.2 | S40: Sensor temperatura | U40: 4 | V40: 12500 | W40: =V40*U40 -> 50000
A41: 3 | B41: Instalación sensores puertas | C41: 0.75 | D41: 1 | E41: =D41*C41 -> 0.75 | H41: 3 | I41: Calibración remota | J41: 0.1 | K41: 1 | L41: =K41*J41 -> 0.1 | S41: Sensor apertura puertas | U41: 1 | V41: 10000 | W41: =V41*U41 -> 10000
A42: 4 | B42: Cableado/conexión | C42: 0.33 | D42: 1 | E42: =D42*C42 -> 0.33 | H42: 4 | I42: Monitoreo de alertas | J42: 0.1 | K42: 1 | L42: =K42*J42 -> 0.1 | S42: Instalación | U42: =E51 -> 2 | V42: =P3 -> 12500 | W42: =V42*U42 -> 25000
A43: 5 | B43: Calibración/pruebas | C43: 0.25 | D43: 1 | E43: =D43*C43 -> 0.25 | H43: 5 | I43: Reporte preventivo | J43: 0.1 | K43: 1 | L43: =K43*J43 -> 0.1
A44: 6 | E44: =D44*C44 -> 0 | H44: 6 | L44: =K44*J44 -> 0
A45: 7 | E45: =D45*C45 -> 0 | H45: 7 | L45: 0
A46: 8 | E46: =D46*C46 -> 0 | H46: 8 | L46: 0
A47: 9 | E47: =D47*C47 -> 0 | H47: 9 | L47: 0 | S47: Total | W47: =SUM(W39:W44) -> 115000 | Y47: Total | AC47: =SUM(AC39:AC44) -> 7500
A48: 10 | E48: =D48*C48 -> 0 | H48: 10 | L48: 0
A49: 11 | E49: =D49*C49 -> 0 | H49: 11 | L49: 0
A50: 12 | E50: =D50*C50 -> 0 | H50: 12 | L50: 0
D51: Horas totales por servicio [HsTotalesXServicio] Fórmula = Σ Horas por tarea del servicio | E51: =SUM(E39:E50) -> 2 | F51: Coste por instalación | H51: Comentarios: | K51: Horas totales por servicio [HsTotalesXServicio] | L51: =SUM(L39:L50) -> 0.6
D52: Capacidad operativa mensual por empleado Fórmula = HsTotalesXSer / HsLaboralesXMes | E52: =E51/$B$14 -> 0.013333333 | F52: =$P$3*E51 -> 25000 | K52: Capacidad operativa mensual por proyecto | L52: =L51/$B$14 -> 0.004
A56: Instalación C | H56: Plan C | S56: Plan C | Y56: Mantenimiento plan C
A57: N° de tarea | B57: Descripción | C57: Base horaria [BH] | D57: Cantidad requerida [Cant] | E57: Horas por tarea Fórmula = Cant * BH | H57: N° de tarea | I57: Descripción | J57: Base horaria [BH] | K57: Cantidad requerida [Cant] | L57: Horas por tarea Fórmula = Cant * BH | S57: Componente | U57: Cantidad | V57: Precio unitario | W57: Subtotal | Y57: Componente | AA57: Cantidad | AB57: Precio unitario | AC57: Subtotal
A58: 1 | B58: Preparación avanzada | C58: 0.33 | D58: 1 | E58: =D58*C58 -> 0.33 | H58: 1 | I58: Revisión sensores temp | J58: 0.1 | K58: 1 | L58: =K58*J58 -> 0.1 | S58: Unidad central | U58: 1 | V58: 30000 | W58: =V58*U58 -> 30000 | Y58: Servicio tecnico | AA58: 1 | AB58: =P3 -> 12500 | AC58: =AB58*AA58 -> 12500
A59: 2 | B59: Instalacion sensores temp | C59: 0.42 | D59: 1 | E59: =D59*C59 -> 0.42 | H59: 2 | I59: Revision sensores puertas | J59: 0.2 | K59: 1 | L59: =K59*J59 -> 0.2 | S59: Sensor temperatura | U59: 4 | V59: 12500 | W59: =V59*U59 -> 50000
A60: 3 | B60: Instalacion sensores puertas | C60: 0.67 | D60: 1 | E60: =D60*C60 -> 0.67 | H60: 3 | I60: Revision GPS | J60: 0.2 | K60: 1 | L60: =K60*J60 -> 0.2 | S60: Sensor apertura puertas | U60: 1 | V60: 10000 | W60: =V60*U60 -> 10000
A61: 4 | B61: Instalacion modulo GPS | C61: 0.58 | D61: 1 | E61: =D61*C61 -> 0.58 | H61: 4 | I61: Revision sensores humedad | J61: 0.1 | K61: 1 | L61: =K61*J61 -> 0.1 | S61: Gps | U61: 1 | V61: 10000 | W61: =V61*U61 -> 10000
A62: 5 | B62: Instalacion sensores de humedad | C62: 0.42 | D62: 1 | E62: =D62*C62 -> 0.42 | H62: 5 | I62: Chequeo de conexion motor | J62: 0.2 | K62: 1 | L62: =K62*J62 -> 0.2 | S62: Sensor motor | U62: 2 | V62: 15000 | W62: =V62*U62 -> 30000
A63: 6 | B63: Conexión a motor | C63: 0.92 | D63: 1 | E63: =D63*C63 -> 0.92 | H63: 6 | I63: Monitoreo de alertas | J63: 0.2 | K63: 1 | L63: =K63*J63 -> 0.2 | S63: Sensor humedad | U63: 2 | V63: 14000 | W63: =V63*U63 -> 28000
A64: 7 | B64: Cableado/conexión general | C64: 0.33 | D64: 1 | E64: =D64*C64 -> 0.33 | H64: 7 | I64: Reporte preventivo | J64: 0.1 | K64: 1 | L64: =K64*J64 -> 0.1 | S64: Instalación | U64: =E70 -> 4 | V64: =P3 -> 12500 | W64: =V64*U64 -> 50000
A65: 8 | B65: Pruebas integrales | C65: 0.33 | D65: 1 | E65: =D65*C65 -> 0.33 | H65: 8 | L65: =K65*J65 -> 0 | S65: Total | W65: =SUM(W58:W64) -> 208000 | Y65: Total | AC65: =SUM(AC58:AC64) -> 12500
A66: 9 | E66: =D66*C66 -> 0 | H66: 9 | L66: 0
A67: 10 | E67: =D67*C67 -> 0 | H67: 10 | L67: 0
A68: 11 | E68: =D68*C68 -> 0 | H68: 11 | L68: 0
A69: 12 | E69: =D69*C69 -> 0 | H69: 12 | L69: 0
D70: Horas totales por servicio [HsTotalesXServicio] Fórmula = Σ Horas por tarea del servicio | E70: =SUM(E58:E69) -> 4 | F70: Coste por instalación | H70: Comentarios: | K70: Horas totales por servicio [HsTotalesXServicio] | L70: =SUM(L58:L69) -> 1.1
D71: Capacidad operativa mensual por empleado Fórmula = HsTotalesXSer / HsLaboralesXMes | E71: =E70/$B$14 -> 0.026666667 | F71: =$P$3*E70 -> 50000 | K71: Capacidad operativa mensual por proyecto | L71: =L70/$B$14 -> 0.0073333333
A76: Detalle: El mantenimiento por plan es anual
A77: ANALISIS CAPACIDAD OPERATIVA ANUAL POR SERVICIO EN HORAS HOMBRE
A78: CAPACIDAD OPERATIVA AÑO 2026 | C78: Enero | E78: Febrero | G78: Marzo | I78: Abril | K78: Mayo | M78: Junio | O78: Julio | Q78: Agosto | S78: Septiembre | U78: Octubre | W78: Noviembre | Y78: Diciembre
C79: Unidades requeridas | D79: Horas Hombre requeridas | E79: Unidades requeridas | F79: Horas Hombre requeridos | G79: Unidades requeridas | H79: Horas Hombre requeridas | I79: Unidades requeridas | J79: Horas Hombre requeridos | K79: Unidades requeridas | L79: Horas Hombre requeridas | M79: Unidades requeridas | N79: Horas Hombre requeridas | O79: Unidades requeridas | P79: Horas Hombre requeridas | Q79: Unidades requeridas | R79: Horas Hombre requeridas | S79: Unidades requeridas | T79: Horas Hombre requeridas | U79: Unidades requeridas | V79: Horas Hombre requeridas | W79: Unidades requeridas | X79: Horas Hombre requeridas | Y79: Unidades requeridas | Z79: Horas Hombre requeridas
A80: =Hipótesis!B$58 -> Instalación A | B80: =D80+F80+H80+J80+L80+N80+P80+R80+T80+V80+X80+Z80 -> 15.15 | C80: ='Proy. ventas'!E19 -> 0 | D80: =C80*$E$32 -> 0 | E80: ='Proy. ventas'!G33 -> 15 | F80: =E80*$E$32 -> 15.15 | G80: ='Proy. ventas'!I33 -> 0 | H80: =G80*$E$32 -> 0 | I80: ='Proy. ventas'!K33 -> 0 | J80: =I80*$E$32 -> 0 | K80: ='Proy. ventas'!M33 -> 0 | L80: =K80*$E$32 -> 0 | M80: ='Proy. ventas'!O33 -> 0 | N80: =M80*$E$32 -> 0 | O80: ='Proy. ventas'!Q33 -> 0 | P80: =O80*$E$32 -> 0 | Q80: ='Proy. ventas'!S33 -> 0 | R80: =Q80*$E$32 -> 0 | S80: ='Proy. ventas'!U33 -> 0 | T80: =S80*$E$32 -> 0 | U80: ='Proy. ventas'!W33 -> 0 | V80: =U80*$E$32 -> 0 | W80: ='Proy. ventas'!Y33 -> 0 | X80: =W80*$E$32 -> 0 | Y80: ='Proy. ventas'!AA33 -> 0 | Z80: =Y80*$E$32 -> 0
A81: =Hipótesis!B$59 -> Instalación B | B81: =D81+F81+H81+J81+L81+N81+P81+R81+T81+V81+X81+Z81 -> 60 | C81: ='Proy. ventas'!E20 -> 0 | D81: =C81*$E$51 -> 0 | E81: ='Proy. ventas'!G34 -> 0 | F81: =E81*$E$51 -> 0 | G81: ='Proy. ventas'!I34 -> 0 | H81: =G81*$E$51 -> 0 | I81: ='Proy. ventas'!K34 -> 15 | J81: =I81*$E$51 -> 30 | K81: ='Proy. ventas'!M34 -> 0 | L81: =K81*$E$51 -> 0 | M81: ='Proy. ventas'!O34 -> 0 | N81: =M81*$E$51 -> 0 | O81: ='Proy. ventas'!Q34 -> 15 | P81: =O81*$E$51 -> 30 | Q81: ='Proy. ventas'!S34 -> 0 | R81: =Q81*$E$51 -> 0 | S81: ='Proy. ventas'!U34 -> 0 | T81: =S81*$E$51 -> 0 | U81: ='Proy. ventas'!W34 -> 0 | V81: =U81*$E$51 -> 0 | W81: ='Proy. ventas'!Y34 -> 0 | X81: =W81*$E$51 -> 0 | Y81: ='Proy. ventas'!AA34 -> 0 | Z81: =Y81*$E$51 -> 0
A82: =Hipótesis!B$60 -> Instalación C | B82: =D82+F82+H82+J82+L82+N82+P82+R82+T82+V82+X82+Z82 -> 240 | C82: ='Proy. ventas'!E21 -> 15 | D82: =C82*$E$70 -> 60 | E82: ='Proy. ventas'!G35 -> 0 | F82: =E82*$E$70 -> 0 | G82: ='Proy. ventas'!I35 -> 0 | H82: =G82*$E$70 -> 0 | I82: ='Proy. ventas'!K35 -> 0 | J82: =I82*$E$70 -> 0 | K82: ='Proy. ventas'!M35 -> 0 | L82: =K82*$E$70 -> 0 | M82: ='Proy. ventas'!O35 -> 0 | N82: =M82*$E$70 -> 0 | O82: ='Proy. ventas'!Q35 -> 0 | P82: =O82*$E$70 -> 0 | Q82: ='Proy. ventas'!S35 -> 0 | R82: =Q82*$E$70 -> 0 | S82: ='Proy. ventas'!U35 -> 15 | T82: =S82*$E$70 -> 60 | U82: ='Proy. ventas'!W35 -> 15 | V82: =U82*$E$70 -> 60 | W82: ='Proy. ventas'!Y35 -> 15 | X82: =W82*$E$70 -> 60 | Y82: ='Proy. ventas'!AA35 -> 0 | Z82: =Y82*$E$70 -> 0
A83: =Hipótesis!B$61 -> Plan A | B83: =D83+F83+H83+J83+L83+N83+P83+R83+T83+V83+X83+Z83 -> 0 | C83: ='Proy. ventas'!E22 -> 0 | D83: =C83*$L$32 -> 0 | E83: 0 | F83: =E83*$L$32 -> 0 | G83: 0 | H83: =G83*$L$32 -> 0 | I83: 0 | J83: =I83*$L$32 -> 0 | K83: 0 | L83: =K83*$L$32 -> 0 | M83: 0 | N83: =M83*$L$32 -> 0 | O83: 0 | P83: =O83*$L$32 -> 0 | Q83: 0 | R83: =Q83*$L$32 -> 0 | S83: 0 | T83: =S83*$L$32 -> 0 | U83: 0 | V83: =U83*$L$32 -> 0 | W83: 0 | X83: =W83*$L$32 -> 0 | Y83: 0 | Z83: =Y83*$L$32 -> 0
A84: =Hipótesis!B$62 -> Plan B | B84: =D84+F84+H84+J84+L84+N84+P84+R84+T84+V84+X84+Z84 -> 0 | C84: ='Proy. ventas'!E23 -> 0 | D84: =C84*$L$51 -> 0 | E84: 0 | F84: =E84*$L$51 -> 0 | G84: 0 | H84: =G84*$L$51 -> 0 | I84: 0 | J84: =I84*$L$51 -> 0 | K84: 0 | L84: =K84*$L$51 -> 0 | M84: 0 | N84: =M84*$L$51 -> 0 | O84: 0 | P84: =O84*$L$51 -> 0 | Q84: 0 | R84: =Q84*$L$51 -> 0 | S84: 0 | T84: =S84*$L$51 -> 0 | U84: 0 | V84: =U84*$L$51 -> 0 | W84: 0 | X84: =W84*$L$51 -> 0 | Y84: 0 | Z84: =Y84*$L$51 -> 0
A85: =Hipótesis!B$63 -> Plan C | B85: =D85+F85+H85+J85+L85+N85+P85+R85+T85+V85+X85+Z85 -> 0 | C85: 0 | D85: =C85*$L$70 -> 0 | E85: 0 | F85: =E85*$L$70 -> 0 | G85: 0 | H85: =G85*$L$70 -> 0 | I85: 0 | J85: =I85*$L$70 -> 0 | K85: 0 | L85: =K85*$L$70 -> 0 | M85: 0 | N85: =M85*$L$70 -> 0 | O85: 0 | P85: =O85*$L$70 -> 0 | Q85: 0 | R85: =Q85*$L$70 -> 0 | S85: 0 | T85: =S85*$L$70 -> 0 | U85: 0 | V85: =U85*$L$70 -> 0 | W85: 0 | X85: =W85*$L$70 -> 0 | Y85: 0 | Z85: =Y85*$L$70 -> 0
A86: TOTALES | B86: =D86+F86+H86+J86+L86+N86+P86+R86+T86+V86+X86+Z86 -> 315.15 | C86: =SUM(C80:C85) -> 15 | D86: =SUM(D80:D85) -> 60 | E86: =SUM(E80:E85) -> 15 | F86: =SUM(F80:F85) -> 15.15 | G86: =SUM(G80:G85) -> 0 | H86: =SUM(H80:H85) -> 0 | I86: =SUM(I80:I85) -> 15 | J86: =SUM(J80:J85) -> 30 | ... Z86: =SUM(Z80:Z85) -> 0
A89: CAPACIDAD OPERATIVA AÑO 2027 | C89: Enero | E89: Febrero | G89: Marzo | I89: Abril | K89: Mayo | M89: Junio | O89: Julio | Q89: Agosto | S89: Septiembre | U89: Octubre | W89: Noviembre | Y89: Diciembre
C90: Unidades requeridas | D90: Horas Hombre requeridas | E90: Unidades requeridas | F90: Horas Hombre requeridos | G90: Unidades requeridas | H90: Horas Hombre requeridas | I90: Unidades requeridas | J90: Horas Hombre requeridos | K90: Unidades requeridas | L90: Horas Hombre requeridas | M90: Unidades requeridas | N90: Horas Hombre requeridas | O90: Unidades requeridas | P90: Horas Hombre requeridas | Q90: Unidades requeridas | R90: Horas Hombre requeridas | S90: Unidades requeridas | T90: Horas Hombre requeridas | U90: Unidades requeridas | V90: Horas Hombre requeridas | W90: Unidades requeridas | X90: Horas Hombre requeridas | Y90: Unidades requeridas | Z90: Horas Hombre requeridas
A91: =Hipótesis!B$58 -> Instalación A | B91: =D91+F91+H91+J91+L91+N91+P91+R91+T91+V91+X91+Z91 -> 30.3 | C91: ='Proy. ventas'!E82 -> 0 | D91: =C91*$E$32 -> 0 | E91: ='Proy. ventas'!G82 -> 0 | F91: =E91*$E$32 -> 0 | G91: ='Proy. ventas'!I82 -> 0 | H91: =G91*$E$32 -> 0 | I91: ='Proy. ventas'!K82 -> 15 | J91: =I91*$E$32 -> 15.15 | K91: ='Proy. ventas'!M82 -> 0 | L91: =K91*$E$32 -> 0 | M91: ='Proy. ventas'!O82 -> 0 | N91: =M91*$E$32 -> 0 | O91: ='Proy. ventas'!Q82 -> 0 | P91: =O91*$E$32 -> 0 | Q91: ='Proy. ventas'!S82 -> 0 | R91: =Q91*$E$32 -> 0 | S91: ='Proy. ventas'!U82 -> 15 | T91: =S91*$E$32 -> 15.15 | U91: ='Proy. ventas'!W82 -> 0 | V91: =U91*$E$32 -> 0 | W91: ='Proy. ventas'!Y82 -> 0 | X91: =W91*$E$32 -> 0 | Y91: ='Proy. ventas'!AA82 -> 0 | Z91: =Y91*$E$32 -> 0
A92: =Hipótesis!B$59 -> Instalación B | B92: =D92+F92+H92+J92+L92+N92+P92+R92+T92+V92+X92+Z92 -> 30 | C92: ='Proy. ventas'!E83 -> 0 | D92: =C92*$E$51 -> 0 | E92: ='Proy. ventas'!G83 -> 0 | F92: =E92*$E$51 -> 0 | G92: ='Proy. ventas'!I83 -> 15 | H92: =G92*$E$51 -> 30 | I92: ='Proy. ventas'!K83 -> 0 | J92: =I92*$E$51 -> 0 | K92: ='Proy. ventas'!M83 -> 0 | L92: =K92*$E$51 -> 0 | M92: ='Proy. ventas'!O83 -> 0 | N92: =M92*$E$51 -> 0 | O92: ='Proy. ventas'!Q83 -> 0 | P92: =O92*$E$51 -> 0 | Q92: ='Proy. ventas'!S83 -> 0 | R92: =Q92*$E$51 -> 0 | S92: ='Proy. ventas'!U83 -> 0 | T92: =S92*$E$51 -> 0 | U92: ='Proy. ventas'!W83 -> 0 | V92: =U92*$E$51 -> 0 | W92: ='Proy. ventas'!Y83 -> 0 | X92: =W92*$E$51 -> 0 | Y92: ='Proy. ventas'!AA83 -> 0 | Z92: =Y92*$E$51 -> 0
A93: =Hipótesis!B$60 -> Instalación C | B93: =D93+F93+H93+J93+L93+N93+P93+R93+T93+V93+X93+Z93 -> 360 | C93: ='Proy. ventas'!E84 -> 15 | D93: =C93*$E$70 -> 60 | E93: ='Proy. ventas'!G84 -> 0 | F93: =E93*$E$70 -> 0 | G93: ='Proy. ventas'!I84 -> 0 | H93: =G93*$E$70 -> 0 | I93: ='Proy. ventas'!K84 -> 15 | J93: =I93*$E$70 -> 60 | K93: ='Proy. ventas'!M84 -> 0 | L93: =K93*$E$70 -> 0 | M93: ='Proy. ventas'!O84 -> 0 | N93: =M93*$E$70 -> 0 | O93: ='Proy. ventas'!Q84 -> 0 | P93: =O93*$E$70 -> 0 | Q93: ='Proy. ventas'!S84 -> 0 | R93: =Q93*$E$70 -> 0 | S93: ='Proy. ventas'!U84 -> 0 | T93: =S93*$E$70 -> 0 | U93: ='Proy. ventas'!W84 -> 30 | V93: =U93*$E$70 -> 120 | W93: ='Proy. ventas'!Y84 -> 30 | X93: =W93*$E$70 -> 120 | Y93: ='Proy. ventas'!AA84 -> 0 | Z93: =Y93*$E$70 -> 0
A94: =Hipótesis!B$61 -> Plan A | B94: =D94+F94+H94+J94+L94+N94+P94+R94+T94+V94+X94+Z94 -> 4.5 | C94: =C80 -> 0 | D94: =C94*$L$32 -> 0 | E94: =E80 -> 15 | F94: =E94*$L$32 -> 4.5 | G94: =G80 -> 0 | H94: =G94*$L$32 -> 0 | I94: =I80 -> 0 | J94: =I94*$L$32 -> 0 | K94: =K80 -> 0 | L94: =K94*$L$32 -> 0 | M94: =M80 -> 0 | N94: =M94*$L$32 -> 0 | O94: =O80 -> 0 | P94: =O94*$L$32 -> 0 | Q94: =Q80 -> 0 | R94: =Q94*$L$32 -> 0 | S94: =S80 -> 0 | T94: =S94*$L$32 -> 0 | U94: =U80 -> 0 | V94: =U94*$L$32 -> 0 | W94: =W80 -> 0 | X94: =W94*$L$32 -> 0 | Y94: =Y80 -> 0 | Z94: =Y94*$L$32 -> 0
A95: =Hipótesis!B$62 -> Plan B | B95: =D95+F95+H95+J95+L95+N95+P95+R95+T95+V95+X95+Z95 -> 18 | C95: =C81 -> 0 | D95: =C95*$L$51 -> 0 | E95: =E81 -> 0 | F95: =E95*$L$51 -> 0 | G95: =G81 -> 0 | H95: =G95*$L$51 -> 0 | I95: =I81 -> 15 | J95: =I95*$L$51 -> 9 | K95: =K81 -> 0 | L95: =K95*$L$51 -> 0 | M95: =M81 -> 0 | N95: =M95*$L$51 -> 0 | O95: =O81 -> 15 | P95: =O95*$L$51 -> 9 | Q95: =Q81 -> 0 | R95: =Q95*$L$51 -> 0 | S95: =S81 -> 0 | T95: =S95*$L$51 -> 0 | U95: =U81 -> 0 | V95: =U95*$L$51 -> 0 | W95: =W81 -> 0 | X95: =W95*$L$51 -> 0 | Y95: =Y81 -> 0 | Z95: =Y95*$L$51 -> 0
A96: =Hipótesis!B$63 -> Plan C | B96: =D96+F96+H96+J96+L96+N96+P96+R96+T96+V96+X96+Z96 -> 66 | C96: =C82 -> 15 | D96: =C96*$L$70 -> 16.5 | E96: =E82 -> 0 | F96: =E96*$L$70 -> 0 | G96: =G82 -> 0 | H96: =G96*$L$70 -> 0 | I96: =I82 -> 0 | J96: =I96*$L$70 -> 0 | K96: =K82 -> 0 | L96: =K96*$L$70 -> 0 | M96: =M82 -> 0 | N96: =M96*$L$70 -> 0 | O96: =O82 -> 0 | P96: =O96*$L$70 -> 0 | Q96: =Q82 -> 0 | R96: =Q96*$L$70 -> 0 | S96: =S82 -> 15 | T96: =S96*$L$70 -> 16.5 | U96: =U82 -> 15 | V96: =U96*$L$70 -> 16.5 | W96: =W82 -> 15 | X96: =W96*$L$70 -> 16.5 | Y96: =Y82 -> 0 | Z96: =Y96*$L$70 -> 0
A97: TOTALES | B97: =D97+F97+H97+J97+L97+N97+P97+R97+T97+V97+X97+Z97 -> 508.8 | C97: =SUM(C91:C96) -> 30 | D97: =SUM(D91:D96) -> 76.5 | E97: =SUM(E91:E96) -> 15 | F97: =SUM(F91:F96) -> 4.5 | G97: =SUM(G91:G96) -> 15 | H97: =SUM(H91:H96) -> 30 | I97: =SUM(I91:I96) -> 45 | J97: =SUM(J91:J96) -> 84.15 | ... Z97: =SUM(Z91:Z96) -> 0
A100: CAPACIDAD OPERATIVA AÑO 2028 | C100: Enero | E100: Febrero | G100: Marzo | I100: Abril | K100: Mayo | M100: Junio | O100: Julio | Q100: Agosto | S100: Septiembre | U100: Octubre | W100: Noviembre | Y100: Diciembre
C101: Unidades requeridas | D101: Horas Hombre requeridas | E101: Unidades requeridas | F101: Horas Hombre requeridos | G101: Unidades requeridas | H101: Horas Hombre requeridas | I101: Unidades requeridas | J101: Horas Hombre requeridos | K101: Unidades requeridas | L101: Horas Hombre requeridas | M101: Unidades requeridas | N101: Horas Hombre requeridas | O101: Unidades requeridas | P101: Horas Hombre requeridas | Q101: Unidades requeridas | R101: Horas Hombre requeridas | S101: Unidades requeridas | T101: Horas Hombre requeridas | U101: Unidades requeridas | V101: Horas Hombre requeridas | W101: Unidades requeridas | X101: Horas Hombre requeridas | Y101: Unidades requeridas | Z101: Horas Hombre requeridas
A102: =Hipótesis!B$58 -> Instalación A | B102: =D102+F102+H102+J102+L102+N102+P102+R102+T102+V102+X102+Z102 -> 75.75 | C102: ='Proy. ventas'!E144 -> 0 | D102: =C102*$E$32 -> 0 | E102: ='Proy. ventas'!G144 -> 15 | F102: =E102*$E$32 -> 15.15 | G102: ='Proy. ventas'!I144 -> 15 | H102: =G102*$E$32 -> 15.15 | I102: ='Proy. ventas'!K144 -> 15 | J102: =I102*$E$32 -> 15.15 | K102: ='Proy. ventas'!M144 -> 15 | L102: =K102*$E$32 -> 15.15 | M102: ='Proy. ventas'!O144 -> 0 | N102: =M102*$E$32 -> 0 | O102: ='Proy. ventas'!Q144 -> 0 | P102: =O102*$E$32 -> 0 | Q102: ='Proy. ventas'!S144 -> 15 | R102: =Q102*$E$32 -> 15.15 | S102: ='Proy. ventas'!U144 -> 0 | T102: =S102*$E$32 -> 0 | U102: ='Proy. ventas'!W144 -> 0 | V102: =U102*$E$32 -> 0 | W102: ='Proy. ventas'!Y144 -> 0 | X102: =W102*$E$32 -> 0 | Y102: ='Proy. ventas'!AA144 -> 0 | Z102: =Y102*$E$32 -> 0
A103: =Hipótesis!B$59 -> Instalación B | B103: =D103+F103+H103+J103+L103+N103+P103+R103+T103+V103+X103+Z103 -> 120 | C103: ='Proy. ventas'!E145 -> 0 | D103: =C103*$E$51 -> 0 | E103: ='Proy. ventas'!G145 -> 0 | F103: =E103*$E$51 -> 0 | G103: ='Proy. ventas'!I145 -> 0 | H103: =G103*$E$51 -> 0 | I103: ='Proy. ventas'!K145 -> 15 | J103: =I103*$E$51 -> 30 | K103: ='Proy. ventas'!M145 -> 0 | L103: =K103*$E$51 -> 0 | M103: ='Proy. ventas'!O145 -> 15 | N103: =M103*$E$51 -> 30 | O103: ='Proy. ventas'!Q145 -> 0 | P103: =O103*$E$51 -> 0 | Q103: ='Proy. ventas'!S145 -> 0 | R103: =Q103*$E$51 -> 0 | S103: ='Proy. ventas'!U145 -> 15 | T103: =S103*$E$51 -> 30 | U103: ='Proy. ventas'!W145 -> 15 | V103: =U103*$E$51 -> 30 | W103: ='Proy. ventas'!Y145 -> 0 | X103: =W103*$E$51 -> 0 | Y103: ='Proy. ventas'!AA145 -> 0 | Z103: =Y103*$E$51 -> 0
A104: =Hipótesis!B$60 -> Instalación C | B104: =D104+F104+H104+J104+L104+N104+P104+R104+T104+V104+X104+Z104 -> 300 | C104: ='Proy. ventas'!E146 -> 0 | D104: =C104*$E$70 -> 0 | E104: ='Proy. ventas'!G146 -> 15 | F104: =E104*$E$70 -> 60 | G104: ='Proy. ventas'!I146 -> 0 | H104: =G104*$E$70 -> 0 | I104: ='Proy. ventas'!K146 -> 0 | J104: =I104*$E$70 -> 0 | K104: ='Proy. ventas'!M146 -> 0 | L104: =K104*$E$70 -> 0 | M104: ='Proy. ventas'!O146 -> 0 | N104: =M104*$E$70 -> 0 | O104: ='Proy. ventas'!Q146 -> 0 | P104: =O104*$E$70 -> 0 | Q104: ='Proy. ventas'!S146 -> 0 | R104: =Q104*$E$70 -> 0 | S104: ='Proy. ventas'!U146 -> 30 | T104: =S104*$E$70 -> 120 | U104: ='Proy. ventas'!W146 -> 15 | V104: =U104*$E$70 -> 60 | W104: ='Proy. ventas'!Y146 -> 15 | X104: =W104*$E$70 -> 60 | Y104: ='Proy. ventas'!AA146 -> 0 | Z104: =Y104*$E$70 -> 0
A105: =Hipótesis!B$61 -> Plan A | B105: =D105+F105+H105+J105+L105+N105+P105+R105+T105+V105+X105+Z105 -> 13.5 | C105: =C91+C80 -> 0 | D105: =C105*$L$32 -> 0 | E105: =E91+E80 -> 15 | F105: =E105*$L$32 -> 4.5 | G105: =G91+G80 -> 0 | H105: =G105*$L$32 -> 0 | I105: =I91+I80 -> 15 | J105: =I105*$L$32 -> 4.5 | K105: =K91+K80 -> 0 | L105: =K105*$L$32 -> 0 | M105: =M91+M80 -> 0 | N105: =M105*$L$32 -> 0 | O105: =O91+O80 -> 0 | P105: =O105*$L$32 -> 0 | Q105: =Q91+Q80 -> 0 | R105: =Q105*$L$32 -> 0 | S105: =S91+S80 -> 15 | T105: =S105*$L$32 -> 4.5 | U105: =U91+U80 -> 0 | V105: =U105*$L$32 -> 0 | W105: =W91+W80 -> 0 | X105: =W105*$L$32 -> 0 | Y105: =Y91+Y80 -> 0 | Z105: =Y105*$L$32 -> 0
A106: =Hipótesis!B$62 -> Plan B | B106: =D106+F106+H106+J106+L106+N106+P106+R106+T106+V106+X106+Z106 -> 27 | C106: =C92+C81 -> 0 | D106: =C106*$L$51 -> 0 | E106: =E92+E81 -> 0 | F106: =E106*$L$51 -> 0 | G106: =G92+G81 -> 15 | H106: =G106*$L$51 -> 9 | I106: =I92+I81 -> 15 | J106: =I106*$L$51 -> 9 | K106: =K92+K81 -> 0 | L106: =K106*$L$51 -> 0 | M106: =M92+M81 -> 0 | N106: =M106*$L$51 -> 0 | O106: =O92+O81 -> 15 | P106: =O106*$L$51 -> 9 | Q106: =Q92+Q81 -> 0 | R106: =Q106*$L$51 -> 0 | S106: =S92+S81 -> 0 | T106: =S106*$L$51 -> 0 | U106: =U92+U81 -> 0 | V106: =U106*$L$51 -> 0 | W106: =W92+W81 -> 0 | X106: =W106*$L$51 -> 0 | Y106: =Y92+Y81 -> 0 | Z106: =Y106*$L$51 -> 0
A107: =Hipótesis!B$63 -> Plan C | B107: =D107+F107+H107+J107+L107+N107+P107+R107+T107+V107+X107+Z107 -> 165 | C107: =C93+C82 -> 30 | D107: =C107*$L$70 -> 33 | E107: =E93+E82 -> 0 | F107: =E107*$L$70 -> 0 | G107: =G93+G82 -> 0 | H107: =G107*$L$70 -> 0 | I107: =I93+I82 -> 15 | J107: =I107*$L$70 -> 16.5 | K107: =K93+K82 -> 0 | L107: =K107*$L$70 -> 0 | M107: =M93+M82 -> 0 | N107: =M107*$L$70 -> 0 | O107: =O93+O82 -> 0 | P107: =O107*$L$70 -> 0 | Q107: =Q93+Q82 -> 0 | R107: =Q107*$L$70 -> 0 | S107: =S93+S82 -> 15 | T107: =S107*$L$70 -> 16.5 | U107: =U93+U82 -> 45 | V107: =U107*$L$70 -> 49.5 | W107: =W93+W82 -> 45 | X107: =W107*$L$70 -> 49.5 | Y107: =Y93+Y82 -> 0 | Z107: =Y107*$L$70 -> 0
A108: TOTALES | B108: =D108+F108+H108+J108+L108+N108+P108+R108+T108+V108+X108+Z108 -> 701.25 | C108: =SUM(C102:C107) -> 30 | D108: =SUM(D102:D107) -> 33 | E108: =SUM(E102:E107) -> 45 | F108: =SUM(F102:F107) -> 79.65 | G108: =SUM(G102:G107) -> 30 | H108: =SUM(H102:H107) -> 24.15 | I108: =SUM(I102:I107) -> 75 | J108: =SUM(J102:J107) -> 75.15 | ... Z108: =SUM(Z102:Z107) -> 0
A110: CONCLUSIÓN
A111: El costo de instalación por plan nos queda en: Plan bronce: $100200 Plan plata: $130000 Plan oro: $238000 Se puede observar que tanto para el mantenimiento, como para la instalación de los servicios, la capacidad operativa proyectada es mucho menor a la que podría realizar un empleado a tiempo completo. Por este motivo se tercerizará la operatoria.

Sheet Mod. ingresos
E1: Modelo de ingresos
B7: Evolución de la participación
B8: 2026 | C8: 2027 | D8: 2028
B9: =Hipótesis!C24 -> 0.02 | C9: =Hipótesis!C25 -> 0.06 | D9: =Hipótesis!C26 -> 0.1
B10: =Hipótesis!D24 -> 102480000 | C10: =Hipótesis!D25 -> 307440000 | D10: =Hipótesis!D26 -> 512400000
B15: Ingresos por servicios
B16: Servicio | C16: Ingresos 2026 | D16: Ingresos 2027 | E16: Ingresos 2028
B17: =Hipótesis!$B$58 -> Instalación A | C17: ='Proy. ventas'!D19 -> 2850000 | D17: ='Proy. ventas'!D82 -> 5700000 | E17: ='Proy. ventas'!D144 -> 14250000
B18: =Hipótesis!$B$59 -> Instalación B | C18: ='Proy. ventas'!D20 -> 7200000 | D18: ='Proy. ventas'!D83 -> 3600000 | E18: ='Proy. ventas'!D145 -> 14400000
B19: =Hipótesis!$B$60 -> Instalación C | C19: ='Proy. ventas'!D21 -> 18600000 | D19: ='Proy. ventas'!D84 -> 27900000 | E19: ='Proy. ventas'!D146 -> 23250000
B20: =Hipótesis!$B$61 -> Plan A | C20: ='Proy. ventas'!D22 -> 14520000 | D20: ='Proy. ventas'!D85 -> 33000000 | E20: ='Proy. ventas'!D147 -> 104280000
B21: =Hipótesis!$B$62 -> Plan B | C21: ='Proy. ventas'!D23 -> 24300000 | D21: ='Proy. ventas'!D86 -> 55080000 | E21: ='Proy. ventas'!D148 -> 95580000
B22: =Hipótesis!$B$63 -> Plan C | C22: ='Proy. ventas'!D24 -> 41580000 | D22: ='Proy. ventas'!D87 -> 156420000 | E22: ='Proy. ventas'!D149 -> 285120000
C23: ='Proy. ventas'!D25 -> 0 | D23: ='Proy. ventas'!D88 -> 0 | E23: ='Proy. ventas'!D150 -> 0
C24: ='Proy. ventas'!D26 -> 0 | D24: ='Proy. ventas'!D89 -> 0 | E24: ='Proy. ventas'!D151 -> 0
C25: ='Proy. ventas'!D27 -> 0 | D25: ='Proy. ventas'!D90 -> 0 | E25: ='Proy. ventas'!D152 -> 0
C26: ='Proy. ventas'!D28 -> 0 | D26: ='Proy. ventas'!D91 -> 0 | E26: ='Proy. ventas'!D153 -> 0
C27: ='Proy. ventas'!D29 -> 0 | D27: ='Proy. ventas'!D92 -> 0 | E27: ='Proy. ventas'!D154 -> 0
C28: ='Proy. ventas'!D30 -> 0 | D28: ='Proy. ventas'!D93 -> 0 | E28: ='Proy. ventas'!D155 -> 0
C29: ='Proy. ventas'!D31 -> 0 | D29: ='Proy. ventas'!D94 -> 0 | E29: ='Proy. ventas'!D156 -> 0
B30: TOTALES | C30: =SUM(C17:C29) -> 109050000 | D30: =SUM(D17:D29) -> 281700000 | E30: =SUM(E17:E29) -> 536880000

Sheet Costos fijos
F1: Estructura de costos fijos
C3: Evolución de la participación | G3: Costos fijos - Totales
C4: 2026 | D4: 2027 | E4: 2028 | G4: 2026 | H4: 2027 | I4: 2028
C5: =Hipótesis!C24 -> 0.02 | D5: =Hipótesis!C25 -> 0.06 | E5: =Hipótesis!C26 -> 0.1 | G5: =P25 -> 26772000 | H5: =P42 -> 30638000 | I5: =P60 -> 37452000
C6: =Hipótesis!D24 -> 102480000 | D6: =Hipótesis!D25 -> 307440000 | E6: =Hipótesis!D26 -> 512400000
G7: Costos fijos promocion - Totales
G8: 2026 | H8: 2027 | I8: 2028
G9: =SUM(P23:P24) -> 1260000 | H9: =SUM(P40:P41) -> 1806000 | I9: =SUM(P58:P59) -> 2400000
B11: Costos fijos - Año 2026
B12: Conceptos | D12: Enero | E12: Febrero | F12: Marzo | G12: Abril | H12: Mayo | I12: Junio | J12: Julio | K12: Agosto | L12: Septiembre | M12: Octubre | N12: Noviembre | O12: Diciembre | P12: Total anual | Q12: Observaciones
B13: Servicios | C13: Luz | D13: 55000 | E13: 55000 | F13: 55000 | G13: 55000 | H13: 55000 | I13: 55000 | J13: 55000 | K13: 55000 | L13: 55000 | M13: 55000 | N13: 55000 | O13: 55000 | P13: =SUM(D13:O13) -> 660000
C14: Agua | D14: 19000 | E14: 19000 | F14: 19000 | G14: 19000 | H14: 19000 | I14: 19000 | J14: 19000 | K14: 19000 | L14: 19000 | M14: 19000 | N14: 19000 | O14: 19000 | P14: =SUM(D14:O14) -> 228000
C15: Telefonía móvil | D15: 0 | E15: 0 | F15: 0 | G15: 0 | H15: 0 | I15: 0 | J15: 0 | K15: 0 | L15: 0 | M15: 0 | N15: 0 | O15: 0 | P15: =SUM(D15:O15) -> 0
C16: Internet + Telefonía | D16: 40000 | E16: 40000 | F16: 40000 | G16: 40000 | H16: 40000 | I16: 40000 | J16: 40000 | K16: 40000 | L16: 40000 | M16: 40000 | N16: 40000 | O16: 40000 | P16: =SUM(D16:O16) -> 480000
C17: Infraestructura cloud | D17: 250000 | E17: 250000 | F17: 250000 | G17: 250000 | H17: 250000 | I17: 250000 | J17: 250000 | K17: 250000 | L17: 250000 | M17: 250000 | N17: 250000 | O17: 250000 | P17: =SUM(D17:O17) -> 3000000
C18: Impuesto municipal (Indicado en alquiler) | D18: 42000 | E18: 42000 | F18: 42000 | G18: 42000 | H18: 42000 | I18: 42000 | J18: 42000 | K18: 42000 | L18: 42000 | M18: 42000 | N18: 42000 | O18: 42000 | P18: =SUM(D18:O18) -> 504000
B19: Alquiler | C19: Oficina | D19: 1100000 | E19: 1100000 | F19: 1100000 | G19: 1100000 | H19: 1100000 | I19: 1100000 | J19: 1100000 | K19: 1100000 | L19: 1100000 | M19: 1100000 | N19: 1100000 | O19: 1100000 | P19: =SUM(D19:O19) -> 13200000 | Q19: En agosto, debido al crecimiento de empleados contratados, se adquiere una segunda oficina.
C20: Expensas (no posee) | D20: 0 | E20: 0 | F20: 0 | G20: 0 | H20: 0 | I20: 0 | J20: 0 | K20: 0 | L20: 0 | M20: 0 | N20: 0 | O20: 0 | P20: =SUM(D20:O20) -> 0
B21: Honorarios | C21: Estudio Contable | D21: 400000 | E21: 400000 | F21: 400000 | G21: 400000 | H21: 400000 | I21: 400000 | J21: 400000 | K21: 400000 | L21: 400000 | M21: 400000 | N21: 400000 | O21: 400000 | P21: =SUM(D21:O21) -> 4800000
C22: Consultora de RRHH - Liquidación sueldos y nuevas búsquedas | D22: 220000 | E22: 220000 | F22: 220000 | G22: 220000 | H22: 220000 | I22: 220000 | J22: 220000 | K22: 220000 | L22: 220000 | M22: 220000 | N22: 220000 | O22: 220000 | P22: =SUM(D22:O22) -> 2640000
B23: Publicidad online | C23: MetaAds | D23: 45000 | E23: 45000 | F23: 45000 | G23: 45000 | H23: 45000 | I23: 45000 | J23: 45000 | K23: 45000 | L23: 45000 | M23: 45000 | N23: 45000 | O23: 45000 | P23: =SUM(D23:O23) -> 540000
C24: GoogleAds | D24: 60000 | E24: 60000 | F24: 60000 | G24: 60000 | H24: 60000 | I24: 60000 | J24: 60000 | K24: 60000 | L24: 60000 | M24: 60000 | N24: 60000 | O24: 60000 | P24: =SUM(D24:O24) -> 720000
C25: Total | D25: =SUM(D13:D24) -> 2231000 | E25: =SUM(E13:E24) -> 2231000 | F25: =SUM(F13:F24) -> 2231000 | G25: =SUM(G13:G24) -> 2231000 | H25: =SUM(H13:H24) -> 2231000 | I25: =SUM(I13:I24) -> 2231000 | J25: =SUM(J13:J24) -> 2231000 | K25: =SUM(K13:K24) -> 2231000 | ... P25: =SUM(P13:P24) -> 26772000
B28: Costos fijos - Año 2027
B29: Conceptos | D29: Enero | E29: Febrero | F29: Marzo | G29: Abril | H29: Mayo | I29: Junio | J29: Julio | K29: Agosto | L29: Septiembre | M29: Octubre | N29: Noviembre | O29: Diciembre | P29: Total anual | Q29: Observaciones
B30: Servicios | C30: Luz | D30: 55000 | E30: 55000 | F30: 55000 | G30: 55000 | H30: 55000 | I30: 55000 | J30: 55000 | K30: 55000 | L30: 55000 | M30: 55000 | N30: 55000 | O30: 55000 | P30: =SUM(D30:O30) -> 660000
C31: Agua | D31: 19000 | E31: 19000 | F31: 19000 | G31: 19000 | H31: 19000 | I31: 19000 | J31: 19000 | K31: 19000 | L31: 19000 | M31: 19000 | N31: 19000 | O31: 19000 | P31: =SUM(D31:O31) -> 228000
C32: Telefonía móvil | D32: 0 | E32: 0 | F32: 20000 | G32: 20000 | H32: 20000 | I32: 20000 | J32: 20000 | K32: 20000 | L32: 20000 | M32: 20000 | N32: 20000 | O32: 20000 | P32: =SUM(D32:O32) -> 200000 | Q32: Debido a la incorporación de 2 recursos de Soporte técnico, se agregan 2 lineas más en Marzo y Julio.
C33: Internet + Telfonía | D33: 40000 | E33: 40000 | F33: 40000 | G33: 40000 | H33: 40000 | I33: 40000 | J33: 40000 | K33: 40000 | L33: 40000 | M33: 40000 | N33: 40000 | O33: 40000 | P33: =SUM(D33:O33) -> 480000
C34: Infraestructura cloud | D34: 300000 | E34: 300000 | F34: 300000 | G34: 300000 | H34: 300000 | I34: 300000 | J34: 300000 | K34: 300000 | L34: 300000 | M34: 300000 | N34: 300000 | O34: 300000 | P34: =SUM(D34:O34) -> 3600000
C35: Impuesto municipal (Indicado en alquiler) | D35: 42000 | E35: 42000 | F35: 42000 | G35: 42000 | H35: 42000 | I35: 42000 | J35: 42000 | K35: 42000 | L35: 42000 | M35: 42000 | N35: 42000 | O35: 42000 | P35: =SUM(D35:O35) -> 504000
B36: Alquiler | C36: Oficina | D36: 1100000 | E36: 1100000 | F36: 1100000 | G36: 1100000 | H36: 1100000 | I36: 1100000 | J36: 1100000 | K36: 1100000 | L36: 1100000 | M36: 1100000 | N36: 1100000 | O36: 1100000 | P36: =SUM(D36:O36) -> 13200000
C37: Expensas (no posee) | D37: 0 | E37: 0 | F37: 0 | G37: 0 | H37: 0 | I37: 0 | J37: 0 | K37: 0 | L37: 0 | M37: 0 | N37: 0 | O37: 0 | P37: =SUM(D37:O37) -> 0
B38: Honorarios | C38: Estudio Contable | D38: 500000 | E38: 500000 | F38: 500000 | G38: 500000 | H38: 500000 | I38: 500000 | J38: 500000 | K38: 500000 | L38: 500000 | M38: 500000 | N38: 500000 | O38: 500000 | P38: =SUM(D38:O38) -> 6000000
C39: Consultora de RRHH - Liquidación sueldos y nuevas búsquedas | D39: 330000 | E39: 330000 | F39: 330000 | G39: 330000 | H39: 330000 | I39: 330000 | J39: 330000 | K39: 330000 | L39: 330000 | M39: 330000 | N39: 330000 | O39: 330000 | P39: =SUM(D39:O39) -> 3960000
B40: Publicidad online | C40: MetaAds | D40: 65000 | E40: 65000 | F40: 65000 | G40: 65000 | H40: 65000 | I40: 65000 | J40: 65000 | K40: 65000 | L40: 65000 | M40: 65000 | N40: 65000 | O40: 65000 | P40: =SUM(D40:O40) -> 780000
C41: GoogleAds | D41: =950*60*1.5 -> 85500 | E41: =950*60*1.5 -> 85500 | F41: =950*60*1.5 -> 85500 | G41: =950*60*1.5 -> 85500 | H41: =950*60*1.5 -> 85500 | I41: =950*60*1.5 -> 85500 | J41: =950*60*1.5 -> 85500 | K41: =950*60*1.5 -> 85500 | ... O41: =950*60*1.5 -> 85500 | P41: =SUM(D41:O41) -> 1026000
C42: Total | D42: =SUM(D30:D41) -> 2536500 | E42: =SUM(E30:E41) -> 2536500 | F42: =SUM(F30:F41) -> 2556500 | G42: =SUM(G30:G41) -> 2556500 | H42: =SUM(H30:H41) -> 2556500 | I42: =SUM(I30:I41) -> 2556500 | J42: =SUM(J30:J41) -> 2556500 | K42: =SUM(K30:K41) -> 2556500 | ... P42: =SUM(P30:P41) -> 30638000
B46: Costos fijos - Año 2028
B47: Conceptos | D47: Enero | E47: Febrero | F47: Marzo | G47: Abril | H47: Mayo | I47: Junio | J47: Julio | K47: Agosto | L47: Septiembre | M47: Octubre | N47: Noviembre | O47: Diciembre | P47: Total anual | Q47: Observaciones
B48: Servicios | C48: Luz | D48: 55000 | E48: 55000 | F48: 55000 | G48: 55000 | H48: 55000 | I48: 55000 | J48: 55000 | K48: 55000 | L48: 55000 | M48: 55000 | N48: 55000 | O48: 55000 | P48: =SUM(D48:O48) -> 660000
C49: Agua | D49: 19000 | E49: 19000 | F49: 19000 | G49: 19000 | H49: 19000 | I49: 19000 | J49: 19000 | K49: 19000 | L49: 19000 | M49: 19000 | N49: 19000 | O49: 19000 | P49: =SUM(D49:O49) -> 228000
C50: Telefonía móvil | D50: 40000 | E50: 40000 | F50: 40000 | G50: 40000 | H50: 40000 | I50: 40000 | J50: 40000 | K50: 40000 | L50: 40000 | M50: 40000 | N50: 40000 | O50: 40000 | P50: =SUM(D50:O50) -> 480000 | Q50: Debido a la incorporación de 4 recursos de Soporte técnico, se agregan 4 lineas más en enero, abril y Julio.
C51: Internet + Telefonia | D51: 40000 | E51: 40000 | F51: 40000 | G51: 40000 | H51: 40000 | I51: 40000 | J51: 40000 | K51: 40000 | L51: 40000 | M51: 40000 | N51: 40000 | O51: 40000 | P51: =SUM(D51:O51) -> 480000
C52: Infraestructura cloud | D52: 400000 | E52: 400000 | F52: 400000 | G52: 400000 | H52: 400000 | I52: 400000 | J52: 400000 | K52: 400000 | L52: 400000 | M52: 400000 | N52: 400000 | O52: 400000 | P52: =SUM(D52:O52) -> 4800000
C53: Impuesto municipal (Indicado en alquiler) | D53: 42000 | E53: 42000 | F53: 42000 | G53: 42000 | H53: 42000 | I53: 42000 | J53: 42000 | K53: 42000 | L53: 42000 | M53: 42000 | N53: 42000 | O53: 42000 | P53: =SUM(D53:O53) -> 504000
B54: Alquiler | C54: Oficinas | D54: 1100000 | E54: 1100000 | F54: 1100000 | G54: 1100000 | H54: 1100000 | I54: 1100000 | J54: 1100000 | K54: 1100000 | L54: 1100000 | M54: 1100000 | N54: 1100000 | O54: 1100000 | P54: =SUM(D54:O54) -> 13200000
C55: Expensas (no posee) | D55: 0 | E55: 0 | F55: 0 | G55: 0 | H55: 0 | I55: 0 | J55: 0 | K55: 0 | L55: 0 | M55: 0 | N55: 0 | O55: 0 | P55: =SUM(D55:O55) -> 0
B56: Honorarios | C56: Estudio Contable | D56: 625000 | E56: 625000 | F56: 625000 | G56: 625000 | H56: 625000 | I56: 625000 | J56: 625000 | K56: 625000 | L56: 625000 | M56: 625000 | N56: 625000 | O56: 625000 | P56: =SUM(D56:O56) -> 7500000
C57: Consultora de RRHH - Liquidación sueldos y nuevas búsquedas | D57: 600000 | E57: 600000 | F57: 600000 | G57: 600000 | H57: 600000 | I57: 600000 | J57: 600000 | K57: 600000 | L57: 600000 | M57: 600000 | N57: 600000 | O57: 600000 | P57: =SUM(D57:O57) -> 7200000
B58: Publicidad online | C58: MetaAds | D58: 80000 | E58: 80000 | F58: 80000 | G58: 80000 | H58: 80000 | I58: 80000 | J58: 80000 | K58: 80000 | L58: 80000 | M58: 80000 | N58: 80000 | O58: 80000 | P58: =SUM(D58:O58) -> 960000
C59: GoogleAds | D59: 120000 | E59: 120000 | F59: 120000 | G59: 120000 | H59: 120000 | I59: 120000 | J59: 120000 | K59: 120000 | L59: 120000 | M59: 120000 | N59: 120000 | O59: 120000 | P59: =SUM(D59:O59) -> 1440000
C60: Total | D60: =SUM(D48:D59) -> 3121000 | E60: =SUM(E48:E59) -> 3121000 | F60: =SUM(F48:F59) -> 3121000 | G60: =SUM(G48:G59) -> 3121000 | H60: =SUM(H48:H59) -> 3121000 | I60: =SUM(I48:I59) -> 3121000 | J60: =SUM(J48:J59) -> 3121000 | K60: =SUM(K48:K59) -> 3121000 | ... P60: =SUM(P48:P59) -> 37452000

Sheet Costos variables
F1: Estructura de costos variables
B4: Evolución de la participación | H4: Costos variables - Totales
B5: 2026 | C5: 2027 | D5: 2028 | H5: 2026 | I5: 2027 | J5: 2028
B6: =Hipótesis!C24 -> 0.02 | C6: =Hipótesis!C25 -> 0.06 | D6: =Hipótesis!C26 -> 0.1 | H6: =AB32 -> 32918375 | I6: =AB55 -> 59495000 | J6: =AB78 -> 87758125
B7: =Hipótesis!D24 -> 102480000 | C7: =Hipótesis!D25 -> 307440000 | D7: =Hipótesis!D26 -> 512400000
H8: Costos de promoción - Totales
H9: 2026 | I9: 2027 | J9: 2028
H10: =SUM(AB21:AB29) -> 15599000 | I10: =SUM(AB44:AB52) -> 35240000 | J10: =SUM(AB67:AB75) -> 55930000
B12: Costos variables - Año 2026
B13: Concepto | D13: Enero | F13: Febrero | H13: Marzo | J13: Abril | L13: Mayo | N13: Junio | P13: Julio | R13: Agosto | T13: Septiembre | V13: Octubre | X13: Noviembre | Z13: Diciembre | AB13: Total
B14: Descripción | C14: Costo unitario | D14: Cantidad | E14: Costo | F14: Cantidad | G14: Costo | H14: Cantidad | I14: Costo | J14: Cantidad | K14: Costo | L14: Cantidad | M14: Costo | N14: Cantidad | O14: Costo | P14: Cantidad | Q14: Costo | R14: Cantidad | S14: Costo | T14: Cantidad | U14: Costo | V14: Cantidad | W14: Costo | X14: Cantidad | Y14: Costo | Z14: Cantidad | AA14: Costo
A15: Tipo de servicio | B15: ='Anexo capacidad operativa'!$S$18 -> Plan A | C15: ='Anexo capacidad operativa'!$W$28 -> 92625 | D15: ='Anexo capacidad operativa'!C80 -> 0 | E15: =D15*$C15 -> 0 | F15: ='Anexo capacidad operativa'!E80 -> 15 | G15: =F15*$C15 -> 1389375 | H15: ='Anexo capacidad operativa'!G80 -> 0 | I15: =H15*$C15 -> 0 | J15: ='Anexo capacidad operativa'!I80 -> 0 | K15: =J15*$C15 -> 0 | L15: ='Anexo capacidad operativa'!K80 -> 0 | M15: =L15*$C15 -> 0 | N15: ='Anexo capacidad operativa'!M80 -> 0 | O15: =N15*$C15 -> 0 | P15: ='Anexo capacidad operativa'!O80 -> 0 | Q15: =P15*$C15 -> 0 | R15: ='Anexo capacidad operativa'!Q80 -> 0 | S15: =R15*$C15 -> 0 | T15: ='Anexo capacidad operativa'!S80 -> 0 | U15: =T15*$C15 -> 0 | V15: ='Anexo capacidad operativa'!U80 -> 0 | W15: =V15*$C15 -> 0 | X15: ='Anexo capacidad operativa'!W80 -> 0 | Y15: =X15*$C15 -> 0 | Z15: ='Anexo capacidad operativa'!Y80 -> 0 | AA15: =Z15*$C15 -> 0 | AB15: =E15+G15+I15+K15+M15+O15+Q15+S15++U15+W15+Y15+AA15 -> 1389375
B16: ='Anexo capacidad operativa'!$S$37 -> Plan B | C16: ='Anexo capacidad operativa'!$W$47 -> 115000 | D16: ='Anexo capacidad operativa'!C81 -> 0 | E16: =D16*$C16 -> 0 | F16: ='Anexo capacidad operativa'!E81 -> 0 | G16: =F16*$C16 -> 0 | H16: ='Anexo capacidad operativa'!G81 -> 0 | I16: =H16*$C16 -> 0 | J16: ='Anexo capacidad operativa'!I81 -> 15 | K16: =J16*$C16 -> 1725000 | L16: ='Anexo capacidad operativa'!K81 -> 0 | M16: =L16*$C16 -> 0 | N16: ='Anexo capacidad operativa'!M81 -> 0 | O16: =N16*$C16 -> 0 | P16: ='Anexo capacidad operativa'!O81 -> 15 | Q16: =P16*$C16 -> 1725000 | R16: ='Anexo capacidad operativa'!Q81 -> 0 | S16: =R16*$C16 -> 0 | T16: ='Anexo capacidad operativa'!S81 -> 0 | U16: =T16*$C16 -> 0 | V16: ='Anexo capacidad operativa'!U81 -> 0 | W16: =V16*$C16 -> 0 | X16: ='Anexo capacidad operativa'!W81 -> 0 | Y16: =X16*$C16 -> 0 | Z16: ='Anexo capacidad operativa'!Y81 -> 0 | AA16: =Z16*$C16 -> 0 | AB16: =E16+G16+I16+K16+M16+O16+Q16+S16++U16+W16+Y16+AA16 -> 3450000
B17: ='Anexo capacidad operativa'!$S$56 -> Plan C | C17: ='Anexo capacidad operativa'!$W$65 -> 208000 | D17: ='Anexo capacidad operativa'!C82 -> 15 | E17: =D17*$C17 -> 3120000 | F17: ='Anexo capacidad operativa'!E82 -> 0 | G17: =F17*$C17 -> 0 | H17: ='Anexo capacidad operativa'!G82 -> 0 | I17: =H17*$C17 -> 0 | J17: ='Anexo capacidad operativa'!I82 -> 0 | K17: =J17*$C17 -> 0 | L17: ='Anexo capacidad operativa'!K82 -> 0 | M17: =L17*$C17 -> 0 | N17: ='Anexo capacidad operativa'!M82 -> 0 | O17: =N17*$C17 -> 0 | P17: ='Anexo capacidad operativa'!O82 -> 0 | Q17: =P17*$C17 -> 0 | R17: ='Anexo capacidad operativa'!Q82 -> 0 | S17: =R17*$C17 -> 0 | T17: ='Anexo capacidad operativa'!S82 -> 15 | U17: =T17*$C17 -> 3120000 | V17: ='Anexo capacidad operativa'!U82 -> 15 | W17: =V17*$C17 -> 3120000 | X17: ='Anexo capacidad operativa'!W82 -> 15 | Y17: =X17*$C17 -> 3120000 | Z17: ='Anexo capacidad operativa'!Y82 -> 0 | AA17: =Z17*$C17 -> 0 | AB17: =E17+G17+I17+K17+M17+O17+Q17+S17++U17+W17+Y17+AA17 -> 12480000
B18: ='Anexo capacidad operativa'!$Y$18 -> Mantenimiento plan A | C18: ='Anexo capacidad operativa'!$AC$28 -> 3750 | D18: ='Anexo capacidad operativa'!C83 -> 0 | E18: =D18*$C18 -> 0 | F18: ='Anexo capacidad operativa'!E83 -> 0 | G18: =F18*$C18 -> 0 | H18: ='Anexo capacidad operativa'!G83 -> 0 | I18: =H18*$C18 -> 0 | J18: ='Anexo capacidad operativa'!I83 -> 0 | K18: =J18*$C18 -> 0 | L18: ='Anexo capacidad operativa'!K83 -> 0 | M18: =L18*$C18 -> 0 | N18: ='Anexo capacidad operativa'!M83 -> 0 | O18: =N18*$C18 -> 0 | P18: ='Anexo capacidad operativa'!O83 -> 0 | Q18: =P18*$C18 -> 0 | R18: ='Anexo capacidad operativa'!Q83 -> 0 | S18: =R18*$C18 -> 0 | T18: ='Anexo capacidad operativa'!S83 -> 0 | U18: =T18*$C18 -> 0 | V18: ='Anexo capacidad operativa'!U83 -> 0 | W18: =V18*$C18 -> 0 | X18: ='Anexo capacidad operativa'!W83 -> 0 | Y18: =X18*$C18 -> 0 | Z18: ='Anexo capacidad operativa'!Y83 -> 0 | AA18: =Z18*$C18 -> 0 | AB18: =E18+G18+I18+K18+M18+O18+Q18+S18++U18+W18+Y18+AA18 -> 0
B19: ='Anexo capacidad operativa'!$Y$37 -> Mantenimiento plan B | C19: ='Anexo capacidad operativa'!$AC$47 -> 7500 | D19: ='Anexo capacidad operativa'!C84 -> 0 | E19: =D19*$C19 -> 0 | F19: ='Anexo capacidad operativa'!E84 -> 0 | G19: =F19*$C19 -> 0 | H19: ='Anexo capacidad operativa'!G84 -> 0 | I19: =H19*$C19 -> 0 | J19: ='Anexo capacidad operativa'!I84 -> 0 | K19: =J19*$C19 -> 0 | L19: ='Anexo capacidad operativa'!K84 -> 0 | M19: =L19*$C19 -> 0 | N19: ='Anexo capacidad operativa'!M84 -> 0 | O19: =N19*$C19 -> 0 | P19: ='Anexo capacidad operativa'!O84 -> 0 | Q19: =P19*$C19 -> 0 | R19: ='Anexo capacidad operativa'!Q84 -> 0 | S19: =R19*$C19 -> 0 | T19: ='Anexo capacidad operativa'!S84 -> 0 | U19: =T19*$C19 -> 0 | V19: ='Anexo capacidad operativa'!U84 -> 0 | W19: =V19*$C19 -> 0 | X19: ='Anexo capacidad operativa'!W84 -> 0 | Y19: =X19*$C19 -> 0 | Z19: ='Anexo capacidad operativa'!Y84 -> 0 | AA19: =Z19*$C19 -> 0 | AB19: =E19+G19+I19+K19+M19+O19+Q19+S19++U19+W19+Y19+AA19 -> 0
B20: ='Anexo capacidad operativa'!$Y$56 -> Mantenimiento plan C | C20: ='Anexo capacidad operativa'!$AC$65 -> 12500 | D20: ='Anexo capacidad operativa'!C85 -> 0 | E20: =D20*$C20 -> 0 | F20: ='Anexo capacidad operativa'!E85 -> 0 | G20: =F20*$C20 -> 0 | H20: ='Anexo capacidad operativa'!G85 -> 0 | I20: =H20*$C20 -> 0 | J20: ='Anexo capacidad operativa'!I85 -> 0 | K20: =J20*$C20 -> 0 | L20: ='Anexo capacidad operativa'!K85 -> 0 | M20: =L20*$C20 -> 0 | N20: ='Anexo capacidad operativa'!M85 -> 0 | O20: =N20*$C20 -> 0 | P20: ='Anexo capacidad operativa'!O85 -> 0 | Q20: =P20*$C20 -> 0 | R20: ='Anexo capacidad operativa'!Q85 -> 0 | S20: =R20*$C20 -> 0 | T20: ='Anexo capacidad operativa'!S85 -> 0 | U20: =T20*$C20 -> 0 | V20: ='Anexo capacidad operativa'!U85 -> 0 | W20: =V20*$C20 -> 0 | X20: ='Anexo capacidad operativa'!W85 -> 0 | Y20: =X20*$C20 -> 0 | Z20: ='Anexo capacidad operativa'!Y85 -> 0 | AA20: =Z20*$C20 -> 0 | AB20: =E20+G20+I20+K20+M20+O20+Q20+S20++U20+W20+Y20+AA20 -> 0
A21: Publicidad y promoción | B21: Ferias | C21: 300000 | D21: 0 | E21: =D21*$C21 -> 0 | F21: 0 | G21: =F21*$C21 -> 0 | H21: 1 | I21: =H21*$C21 -> 300000 | J21: 0 | K21: =J21*$C21 -> 0 | L21: 0 | M21: =L21*$C21 -> 0 | N21: 0 | O21: =N21*$C21 -> 0 | P21: 0 | Q21: =P21*$C21 -> 0 | R21: 0 | S21: =R21*$C21 -> 0 | T21: 0 | U21: =T21*$C21 -> 0 | V21: 0 | W21: =V21*$C21 -> 0 | X21: 0 | Y21: =X21*$C21 -> 0 | Z21: 0 | AA21: =Z21*$C21 -> 0 | AB21: =E21+G21+I21+K21+M21+O21+Q21+S21++U21+W21+Y21+AA21 -> 300000
B22: Carteleria | C22: 400000 | D22: 0 | E22: =D22*$C22 -> 0 | F22: 0 | G22: =F22*$C22 -> 0 | H22: 0 | I22: =H22*$C22 -> 0 | J22: 0 | K22: =J22*$C22 -> 0 | L22: 0 | M22: =L22*$C22 -> 0 | N22: 0 | O22: =N22*$C22 -> 0 | P22: 0 | Q22: =P22*$C22 -> 0 | R22: 1 | S22: =R22*$C22 -> 400000 | T22: 1 | U22: =T22*$C22 -> 400000 | V22: 1 | W22: =V22*$C22 -> 400000 | X22: 1 | Y22: =X22*$C22 -> 400000 | Z22: 1 | AA22: =Z22*$C22 -> 400000 | AB22: =E22+G22+I22+K22+M22+O22+Q22+S22++U22+W22+Y22+AA22 -> 2000000
B23: Radio | C23: 120000 | D23: 0 | E23: =D23*$C23 -> 0 | F23: 0 | G23: =F23*$C23 -> 0 | H23: 0 | I23: =H23*$C23 -> 0 | J23: 0 | K23: =J23*$C23 -> 0 | L23: 1 | M23: =L23*$C23 -> 120000 | N23: 1 | O23: =N23*$C23 -> 120000 | P23: 1 | Q23: =P23*$C23 -> 120000 | R23: 1 | S23: =R23*$C23 -> 120000 | T23: 1 | U23: =T23*$C23 -> 120000 | V23: 1 | W23: =V23*$C23 -> 120000 | X23: 1 | Y23: =X23*$C23 -> 120000 | Z23: 1 | AA23: =Z23*$C23 -> 120000 | AB23: =E23+G23+I23+K23+M23+O23+Q23+S23++U23+W23+Y23+AA23 -> 960000
B24: Bonificación de mantenimiento por contratación A | C24: =Hipótesis!$C$61*0.3 -> 26400 | D24: =D15 -> 0 | E24: =D24*$C24 -> 0 | F24: =F15 -> 15 | G24: =F24*$C24 -> 396000 | H24: =H15 -> 0 | I24: =H24*$C24 -> 0 | J24: =J15 -> 0 | K24: =J24*$C24 -> 0 | L24: =L15 -> 0 | M24: =L24*$C24 -> 0 | N24: =N15 -> 0 | O24: =N24*$C24 -> 0 | P24: =P15 -> 0 | Q24: =P24*$C24 -> 0 | R24: =R15 -> 0 | S24: =R24*$C24 -> 0 | T24: =T15 -> 0 | U24: =T24*$C24 -> 0 | V24: =V15 -> 0 | W24: =V24*$C24 -> 0 | X24: =X15 -> 0 | Y24: =X24*$C24 -> 0 | Z24: =Z15 -> 0 | AA24: =Z24*$C24 -> 0 | AB24: =E24+G24+I24+K24+M24+O24+Q24+S24++U24+W24+Y24+AA24 -> 396000
B25: Bonificación de mantenimiento por contratación B | C25: =Hipótesis!$C$62*0.3 -> 32400 | D25: =D16 -> 0 | E25: =D25*$C25 -> 0 | F25: =F16 -> 0 | G25: =F25*$C25 -> 0 | H25: =H16 -> 0 | I25: =H25*$C25 -> 0 | J25: =J16 -> 15 | K25: =J25*$C25 -> 486000 | L25: =L16 -> 0 | M25: =L25*$C25 -> 0 | N25: =N16 -> 0 | O25: =N25*$C25 -> 0 | P25: =P16 -> 15 | Q25: =P25*$C25 -> 486000 | R25: =R16 -> 0 | S25: =R25*$C25 -> 0 | T25: =T16 -> 0 | U25: =T25*$C25 -> 0 | V25: =V16 -> 0 | W25: =V25*$C25 -> 0 | X25: =X16 -> 0 | Y25: =X25*$C25 -> 0 | Z25: =Z16 -> 0 | AA25: =Z25*$C25 -> 0 | AB25: =E25+G25+I25+K25+M25+O25+Q25+S25++U25+W25+Y25+AA25 -> 972000
B26: Bonificación de mantenimiento por contratación C | C26: =Hipótesis!$C$63*0.3 -> 39600 | D26: =D17 -> 15 | E26: =D26*$C26 -> 594000 | F26: =F17 -> 0 | G26: =F26*$C26 -> 0 | H26: =H17 -> 0 | I26: =H26*$C26 -> 0 | J26: =J17 -> 0 | K26: =J26*$C26 -> 0 | L26: =L17 -> 0 | M26: =L26*$C26 -> 0 | N26: =N17 -> 0 | O26: =N26*$C26 -> 0 | P26: =P17 -> 0 | Q26: =P26*$C26 -> 0 | R26: =R17 -> 0 | S26: =R26*$C26 -> 0 | T26: =T17 -> 15 | U26: =T26*$C26 -> 594000 | V26: =V17 -> 15 | W26: =V26*$C26 -> 594000 | X26: =X17 -> 15 | Y26: =X26*$C26 -> 594000 | Z26: =Z17 -> 0 | AA26: =Z26*$C26 -> 0 | AB26: =E26+G26+I26+K26+M26+O26+Q26+S26++U26+W26+Y26+AA26 -> 2376000
B27: Bonificación de instalación por contratación A | C27: =Hipótesis!$C$58*0.3 -> 57000 | D27: =D15 -> 0 | E27: =D27*$C27 -> 0 | F27: =F15 -> 15 | G27: =F27*$C27 -> 855000 | H27: =H15 -> 0 | I27: =H27*$C27 -> 0 | J27: =J15 -> 0 | K27: =J27*$C27 -> 0 | L27: =L15 -> 0 | M27: =L27*$C27 -> 0 | N27: =N15 -> 0 | O27: =N27*$C27 -> 0 | P27: =P15 -> 0 | Q27: =P27*$C27 -> 0 | R27: =R15 -> 0 | S27: =R27*$C27 -> 0 | T27: =T15 -> 0 | U27: =T27*$C27 -> 0 | V27: =V15 -> 0 | W27: =V27*$C27 -> 0 | X27: =X15 -> 0 | Y27: =X27*$C27 -> 0 | Z27: =Z15 -> 0 | AA27: =Z27*$C27 -> 0 | AB27: =E27+G27+I27+K27+M27+O27+Q27+S27++U27+W27+Y27+AA27 -> 855000
B28: Bonificación de instalación por contratación B | C28: =Hipótesis!$C$59*0.3 -> 72000 | D28: =D16 -> 0 | E28: =D28*$C28 -> 0 | F28: =F16 -> 0 | G28: =F28*$C28 -> 0 | H28: =H16 -> 0 | I28: =H28*$C28 -> 0 | J28: =J16 -> 15 | K28: =J28*$C28 -> 1080000 | L28: =L16 -> 0 | M28: =L28*$C28 -> 0 | N28: =N16 -> 0 | O28: =N28*$C28 -> 0 | P28: =P16 -> 15 | Q28: =P28*$C28 -> 1080000 | R28: =R16 -> 0 | S28: =R28*$C28 -> 0 | T28: =T16 -> 0 | U28: =T28*$C28 -> 0 | V28: =V16 -> 0 | W28: =V28*$C28 -> 0 | X28: =X16 -> 0 | Y28: =X28*$C28 -> 0 | Z28: =Z16 -> 0 | AA28: =Z28*$C28 -> 0 | AB28: =E28+G28+I28+K28+M28+O28+Q28+S28++U28+W28+Y28+AA28 -> 2160000
B29: Bonificación de instalación por contratación C | C29: =Hipótesis!$C$60*0.3 -> 93000 | D29: =D17 -> 15 | E29: =D29*$C29 -> 1395000 | F29: =F17 -> 0 | G29: =F29*$C29 -> 0 | H29: =H17 -> 0 | I29: =H29*$C29 -> 0 | J29: =J17 -> 0 | K29: =J29*$C29 -> 0 | L29: =L17 -> 0 | M29: =L29*$C29 -> 0 | N29: =N17 -> 0 | O29: =N29*$C29 -> 0 | P29: =P17 -> 0 | Q29: =P29*$C29 -> 0 | R29: =R17 -> 0 | S29: =R29*$C29 -> 0 | T29: =T17 -> 15 | U29: =T29*$C29 -> 1395000 | V29: =V17 -> 15 | W29: =V29*$C29 -> 1395000 | X29: =X17 -> 15 | Y29: =X29*$C29 -> 1395000 | Z29: =Z17 -> 0 | AA29: =Z29*$C29 -> 0 | AB29: =E29+G29+I29+K29+M29+O29+Q29+S29++U29+W29+Y29+AA29 -> 5580000
C30: 0 | D30: 0 | E30: 0 | F30: 0 | G30: 0 | H30: 0 | I30: 0 | J30: 0 | K30: 0 | L30: 0 | M30: 0 | N30: 0 | O30: =($C$15*N15 + $C$16*N16+$C$17*N17)*0.15 -> 0 | P30: 0 | Q30: 0 | R30: 0 | S30: 0 | T30: 0 | U30: 0 | V30: 0 | W30: 0 | X30: 0 | Y30: 0 | Z30: 0 | AA30: 0 | AB30: =E30+G30+I30+K30+M30+O30+Q30+S30+U30+W30+Y30+AA30 -> 0
C31: 0 | D31: 0 | E31: 0 | F31: 0 | G31: 0 | H31: 0 | I31: =((H17*24)+(H16*18)+(H15*12))*6*1034 -> 0 | J31: 0 | K31: 0 | L31: 0 | M31: =((L17*24)+(L16*18)+(L15*12))*6*1034 -> 0 | N31: 0 | O31: =(N17+N16+N15)*75 -> 0 | P31: 0 | Q31: 0 | R31: 0 | S31: =((R17*24)+(R16*18)+(R15*12))*6*1034 -> 0 | T31: 0 | U31: 0 | V31: 0 | W31: 0 | X31: 0 | Y31: 0 | Z31: 0 | AA31: =((Z17*24)+(Z16*18)+(Z15*12))*6*1034 -> 0 | AB31: =E31+G31+I31+K31+M31+O31+Q31+S31+U31+W31+Y31+AA31 -> 0
B32: TOTAL | E32: =SUM(E15:E31) -> 5109000 | G32: =SUM(G15:G31) -> 2640375 | I32: =SUM(I15:I31) -> 300000 | K32: =SUM(K15:K31) -> 3291000 | M32: =SUM(M15:M31) -> 120000 | O32: =SUM(O15:O31) -> 120000 | Q32: =SUM(Q15:Q31) -> 3411000 | S32: =SUM(S15:S31) -> 520000 | U32: =SUM(U15:U31) -> 5629000 | W32: =SUM(W15:W31) -> 5629000 | Y32: =SUM(Y15:Y31) -> 5629000 | AA32: =SUM(AA15:AA31) -> 520000 | AB32: =SUM(E32:AA32) -> 32918375
B35: Costos variables - Año 2027
B36: Concepto | D36: Enero | F36: Febrero | H36: Marzo | J36: Abril | L36: Mayo | N36: Junio | P36: Julio | R36: Agosto | T36: Septiembre | V36: Octubre | X36: Noviembre | Z36: Diciembre | AB36: Total
B37: Descripción | C37: Costo unitario | D37: Cantidad | E37: Costo | F37: Cantidad | G37: Costo | H37: Cantidad | I37: Costo | J37: Cantidad | K37: Costo | L37: Cantidad | M37: Costo | N37: Cantidad | O37: Costo | P37: Cantidad | Q37: Costo | R37: Cantidad | S37: Costo | T37: Cantidad | U37: Costo | V37: Cantidad | W37: Costo | X37: Cantidad | Y37: Costo | Z37: Cantidad | AA37: Costo
A38: Tipo de servicio | B38: ='Anexo capacidad operativa'!$S$18 -> Plan A | C38: ='Anexo capacidad operativa'!$W$28 -> 92625 | D38: ='Anexo capacidad operativa'!C91 -> 0 | E38: =D38*$C38 -> 0 | F38: ='Anexo capacidad operativa'!E91 -> 0 | G38: =F38*$C38 -> 0 | H38: ='Anexo capacidad operativa'!G91 -> 0 | I38: =H38*$C38 -> 0 | J38: ='Anexo capacidad operativa'!I91 -> 15 | K38: =J38*$C38 -> 1389375 | L38: ='Anexo capacidad operativa'!K91 -> 0 | M38: =L38*$C38 -> 0 | N38: ='Anexo capacidad operativa'!M91 -> 0 | O38: =N38*$C38 -> 0 | P38: ='Anexo capacidad operativa'!O91 -> 0 | Q38: =P38*$C38 -> 0 | R38: ='Anexo capacidad operativa'!Q91 -> 0 | S38: =R38*$C38 -> 0 | T38: ='Anexo capacidad operativa'!S91 -> 15 | U38: =T38*$C38 -> 1389375 | V38: ='Anexo capacidad operativa'!U91 -> 0 | W38: =V38*$C38 -> 0 | X38: ='Anexo capacidad operativa'!W91 -> 0 | Y38: =X38*$C38 -> 0 | Z38: ='Anexo capacidad operativa'!Y91 -> 0 | AA38: =Z38*$C38 -> 0 | AB38: =E38+G38+I38+K38+M38+O38+Q38+S38++U38+W38+Y38+AA38 -> 2778750
B39: ='Anexo capacidad operativa'!$S$37 -> Plan B | C39: ='Anexo capacidad operativa'!$W$47 -> 115000 | D39: ='Anexo capacidad operativa'!C92 -> 0 | E39: =D39*$C39 -> 0 | F39: ='Anexo capacidad operativa'!E92 -> 0 | G39: =F39*$C39 -> 0 | H39: ='Anexo capacidad operativa'!G92 -> 15 | I39: =H39*$C39 -> 1725000 | J39: ='Anexo capacidad operativa'!I92 -> 0 | K39: =J39*$C39 -> 0 | L39: ='Anexo capacidad operativa'!K92 -> 0 | M39: =L39*$C39 -> 0 | N39: ='Anexo capacidad operativa'!M92 -> 0 | O39: =N39*$C39 -> 0 | P39: ='Anexo capacidad operativa'!O92 -> 0 | Q39: =P39*$C39 -> 0 | R39: ='Anexo capacidad operativa'!Q92 -> 0 | S39: =R39*$C39 -> 0 | T39: ='Anexo capacidad operativa'!S92 -> 0 | U39: =T39*$C39 -> 0 | V39: ='Anexo capacidad operativa'!U92 -> 0 | W39: =V39*$C39 -> 0 | X39: ='Anexo capacidad operativa'!W92 -> 0 | Y39: =X39*$C39 -> 0 | Z39: ='Anexo capacidad operativa'!Y92 -> 0 | AA39: =Z39*$C39 -> 0 | AB39: =E39+G39+I39+K39+M39+O39+Q39+S39++U39+W39+Y39+AA39 -> 1725000
B40: ='Anexo capacidad operativa'!$S$56 -> Plan C | C40: ='Anexo capacidad operativa'!$W$65 -> 208000 | D40: ='Anexo capacidad operativa'!C93 -> 15 | E40: =D40*$C40 -> 3120000 | F40: ='Anexo capacidad operativa'!E93 -> 0 | G40: =F40*$C40 -> 0 | H40: ='Anexo capacidad operativa'!G93 -> 0 | I40: =H40*$C40 -> 0 | J40: ='Anexo capacidad operativa'!I93 -> 15 | K40: =J40*$C40 -> 3120000 | L40: ='Anexo capacidad operativa'!K93 -> 0 | M40: =L40*$C40 -> 0 | N40: ='Anexo capacidad operativa'!M93 -> 0 | O40: =N40*$C40 -> 0 | P40: ='Anexo capacidad operativa'!O93 -> 0 | Q40: =P40*$C40 -> 0 | R40: ='Anexo capacidad operativa'!Q93 -> 0 | S40: =R40*$C40 -> 0 | T40: ='Anexo capacidad operativa'!S93 -> 0 | U40: =T40*$C40 -> 0 | V40: ='Anexo capacidad operativa'!U93 -> 30 | W40: =V40*$C40 -> 6240000 | X40: ='Anexo capacidad operativa'!W93 -> 30 | Y40: =X40*$C40 -> 6240000 | Z40: ='Anexo capacidad operativa'!Y93 -> 0 | AA40: =Z40*$C40 -> 0 | AB40: =E40+G40+I40+K40+M40+O40+Q40+S40++U40+W40+Y40+AA40 -> 18720000
B41: ='Anexo capacidad operativa'!$Y$18 -> Mantenimiento plan A | C41: ='Anexo capacidad operativa'!$AC$28 -> 3750 | D41: ='Anexo capacidad operativa'!C94 -> 0 | E41: =D41*$C41 -> 0 | F41: ='Anexo capacidad operativa'!E94 -> 15 | G41: =F41*$C41 -> 56250 | H41: ='Anexo capacidad operativa'!G94 -> 0 | I41: =H41*$C41 -> 0 | J41: ='Anexo capacidad operativa'!I94 -> 0 | K41: =J41*$C41 -> 0 | L41: ='Anexo capacidad operativa'!K94 -> 0 | M41: =L41*$C41 -> 0 | N41: ='Anexo capacidad operativa'!M94 -> 0 | O41: =N41*$C41 -> 0 | P41: ='Anexo capacidad operativa'!O94 -> 0 | Q41: =P41*$C41 -> 0 | R41: ='Anexo capacidad operativa'!Q94 -> 0 | S41: =R41*$C41 -> 0 | T41: ='Anexo capacidad operativa'!S94 -> 0 | U41: =T41*$C41 -> 0 | V41: ='Anexo capacidad operativa'!U94 -> 0 | W41: =V41*$C41 -> 0 | X41: ='Anexo capacidad operativa'!W94 -> 0 | Y41: =X41*$C41 -> 0 | Z41: ='Anexo capacidad operativa'!Y94 -> 0 | AA41: =Z41*$C41 -> 0 | AB41: =E41+G41+I41+K41+M41+O41+Q41+S41++U41+W41+Y41+AA41 -> 56250
B42: ='Anexo capacidad operativa'!$Y$37 -> Mantenimiento plan B | C42: ='Anexo capacidad operativa'!$AC$47 -> 7500 | D42: ='Anexo capacidad operativa'!C95 -> 0 | E42: =D42*$C42 -> 0 | F42: ='Anexo capacidad operativa'!E95 -> 0 | G42: =F42*$C42 -> 0 | H42: ='Anexo capacidad operativa'!G95 -> 0 | I42: =H42*$C42 -> 0 | J42: ='Anexo capacidad operativa'!I95 -> 15 | K42: =J42*$C42 -> 112500 | L42: ='Anexo capacidad operativa'!K95 -> 0 | M42: =L42*$C42 -> 0 | N42: ='Anexo capacidad operativa'!M95 -> 0 | O42: =N42*$C42 -> 0 | P42: ='Anexo capacidad operativa'!O95 -> 15 | Q42: =P42*$C42 -> 112500 | R42: ='Anexo capacidad operativa'!Q95 -> 0 | S42: =R42*$C42 -> 0 | T42: ='Anexo capacidad operativa'!S95 -> 0 | U42: =T42*$C42 -> 0 | V42: ='Anexo capacidad operativa'!U95 -> 0 | W42: =V42*$C42 -> 0 | X42: ='Anexo capacidad operativa'!W95 -> 0 | Y42: =X42*$C42 -> 0 | Z42: ='Anexo capacidad operativa'!Y95 -> 0 | AA42: =Z42*$C42 -> 0 | AB42: =E42+G42+I42+K42+M42+O42+Q42+S42++U42+W42+Y42+AA42 -> 225000
B43: ='Anexo capacidad operativa'!$Y$56 -> Mantenimiento plan C | C43: ='Anexo capacidad operativa'!$AC$65 -> 12500 | D43: ='Anexo capacidad operativa'!C96 -> 15 | E43: =D43*$C43 -> 187500 | F43: ='Anexo capacidad operativa'!E96 -> 0 | G43: =F43*$C43 -> 0 | H43: ='Anexo capacidad operativa'!G96 -> 0 | I43: =H43*$C43 -> 0 | J43: ='Anexo capacidad operativa'!I96 -> 0 | K43: =J43*$C43 -> 0 | L43: ='Anexo capacidad operativa'!K96 -> 0 | M43: =L43*$C43 -> 0 | N43: ='Anexo capacidad operativa'!M96 -> 0 | O43: =N43*$C43 -> 0 | P43: ='Anexo capacidad operativa'!O96 -> 0 | Q43: =P43*$C43 -> 0 | R43: ='Anexo capacidad operativa'!Q96 -> 0 | S43: =R43*$C43 -> 0 | T43: ='Anexo capacidad operativa'!S96 -> 15 | U43: =T43*$C43 -> 187500 | V43: ='Anexo capacidad operativa'!U96 -> 15 | W43: =V43*$C43 -> 187500 | X43: ='Anexo capacidad operativa'!W96 -> 15 | Y43: =X43*$C43 -> 187500 | Z43: ='Anexo capacidad operativa'!Y96 -> 0 | AA43: =Z43*$C43 -> 0 | AB43: =E43+G43+I43+K43+M43+O43+Q43+S43++U43+W43+Y43+AA43 -> 750000
A44: Publicidad y promoción | B44: Ferias | C44: 300000 | D44: 0 | E44: =D44*$C44 -> 0 | F44: 0 | G44: =F44*$C44 -> 0 | H44: 1 | I44: =H44*$C44 -> 300000 | J44: 0 | K44: =J44*$C44 -> 0 | L44: 0 | M44: =L44*$C44 -> 0 | N44: 0 | O44: =N44*$C44 -> 0 | P44: 0 | Q44: =P44*$C44 -> 0 | R44: 0 | S44: =R44*$C44 -> 0 | T44: 0 | U44: =T44*$C44 -> 0 | V44: 0 | W44: =V44*$C44 -> 0 | X44: 0 | Y44: =X44*$C44 -> 0 | Z44: 0 | AA44: =Z44*$C44 -> 0 | AB44: =E44+G44+I44+K44+M44+O44+Q44+S44++U44+W44+Y44+AA44 -> 300000
B45: Carteleria | C45: 400000 | D45: 1 | E45: =D45*$C45 -> 400000 | F45: 1 | G45: =F45*$C45 -> 400000 | H45: 1 | I45: =H45*$C45 -> 400000 | J45: 1 | K45: =J45*$C45 -> 400000 | L45: 1 | M45: =L45*$C45 -> 400000 | N45: 1 | O45: =N45*$C45 -> 400000 | P45: 1 | Q45: =P45*$C45 -> 400000 | R45: 1 | S45: =R45*$C45 -> 400000 | T45: 1 | U45: =T45*$C45 -> 400000 | V45: 1 | W45: =V45*$C45 -> 400000 | X45: 2 | Y45: =X45*$C45 -> 800000 | Z45: 2 | AA45: =Z45*$C45 -> 800000 | AB45: =E45+G45+I45+K45+M45+O45+Q45+S45++U45+W45+Y45+AA45 -> 5600000
B46: Radio | C46: 120000 | D46: 1 | E46: =D46*$C46 -> 120000 | F46: 2 | G46: =F46*$C46 -> 240000 | H46: 0 | I46: =H46*$C46 -> 0 | J46: 1 | K46: =J46*$C46 -> 120000 | L46: 1 | M46: =L46*$C46 -> 120000 | N46: 1 | O46: =N46*$C46 -> 120000 | P46: 1 | Q46: =P46*$C46 -> 120000 | R46: 2 | S46: =R46*$C46 -> 240000 | T46: 2 | U46: =T46*$C46 -> 240000 | V46: 2 | W46: =V46*$C46 -> 240000 | X46: 2 | Y46: =X46*$C46 -> 240000 | Z46: 2 | AA46: =Z46*$C46 -> 240000 | AB46: =E46+G46+I46+K46+M46+O46+Q46+S46++U46+W46+Y46+AA46 -> 2040000
B47: Bonificación de mantenimiento por contratación A | C47: =Hipótesis!$C$61 -> 88000 | D47: =D38 -> 0 | E47: =D47*$C47 -> 0 | F47: =F38 -> 0 | G47: =F47*$C47 -> 0 | H47: =H38 -> 0 | I47: =H47*$C47 -> 0 | J47: =J38 -> 15 | K47: =J47*$C47 -> 1320000 | L47: =L38 -> 0 | M47: =L47*$C47 -> 0 | N47: =N38 -> 0 | O47: =N47*$C47 -> 0 | P47: =P38 -> 0 | Q47: =P47*$C47 -> 0 | R47: =R38 -> 0 | S47: =R47*$C47 -> 0 | T47: =T38 -> 15 | U47: =T47*$C47 -> 1320000 | V47: =V38 -> 0 | W47: =V47*$C47 -> 0 | X47: =X38 -> 0 | Y47: =X47*$C47 -> 0 | Z47: =Z38 -> 0 | AA47: =Z47*$C47 -> 0 | AB47: =E47+G47+I47+K47+M47+O47+Q47+S47++U47+W47+Y47+AA47 -> 2640000
B48: Bonificación de mantenimiento por contratación B | C48: =Hipótesis!$C$62 -> 108000 | D48: =D39 -> 0 | E48: =D48*$C48 -> 0 | F48: =F39 -> 0 | G48: =F48*$C48 -> 0 | H48: =H39 -> 15 | I48: =H48*$C48 -> 1620000 | J48: =J39 -> 0 | K48: =J48*$C48 -> 0 | L48: =L39 -> 0 | M48: =L48*$C48 -> 0 | N48: =N39 -> 0 | O48: =N48*$C48 -> 0 | P48: =P39 -> 0 | Q48: =P48*$C48 -> 0 | R48: =R39 -> 0 | S48: =R48*$C48 -> 0 | T48: =T39 -> 0 | U48: =T48*$C48 -> 0 | V48: =V39 -> 0 | W48: =V48*$C48 -> 0 | X48: =X39 -> 0 | Y48: =X48*$C48 -> 0 | Z48: =Z39 -> 0 | AA48: =Z48*$C48 -> 0 | AB48: =E48+G48+I48+K48+M48+O48+Q48+S48++U48+W48+Y48+AA48 -> 1620000
B49: Bonificación de mantenimiento por contratación C | C49: =Hipótesis!$C$63 -> 132000 | D49: =D40 -> 15 | E49: =D49*$C49 -> 1980000 | F49: =F40 -> 0 | G49: =F49*$C49 -> 0 | H49: =H40 -> 0 | I49: =H49*$C49 -> 0 | J49: =J40 -> 15 | K49: =J49*$C49 -> 1980000 | L49: =L40 -> 0 | M49: =L49*$C49 -> 0 | N49: =N40 -> 0 | O49: =N49*$C49 -> 0 | P49: =P40 -> 0 | Q49: =P49*$C49 -> 0 | R49: =R40 -> 0 | S49: =R49*$C49 -> 0 | T49: =T40 -> 0 | U49: =T49*$C49 -> 0 | V49: =V40 -> 30 | W49: =V49*$C49 -> 3960000 | X49: =X40 -> 30 | Y49: =X49*$C49 -> 3960000 | Z49: =Z40 -> 0 | AA49: =Z49*$C49 -> 0 | AB49: =E49+G49+I49+K49+M49+O49+Q49+S49++U49+W49+Y49+AA49 -> 11880000
B50: Bonificación de instalación por contratación A | C50: =Hipótesis!$C$58*0.3 -> 57000 | D50: =D38 -> 0 | E50: =D50*$C50 -> 0 | F50: =F38 -> 0 | G50: =F50*$C50 -> 0 | H50: =H38 -> 0 | I50: =H50*$C50 -> 0 | J50: =J38 -> 15 | K50: =J50*$C50 -> 855000 | L50: =L38 -> 0 | M50: =L50*$C50 -> 0 | N50: =N38 -> 0 | O50: =N50*$C50 -> 0 | P50: =P38 -> 0 | Q50: =P50*$C50 -> 0 | R50: =R38 -> 0 | S50: =R50*$C50 -> 0 | T50: =T38 -> 15 | U50: =T50*$C50 -> 855000 | V50: =V38 -> 0 | W50: =V50*$C50 -> 0 | X50: =X38 -> 0 | Y50: =X50*$C50 -> 0 | Z50: =Z38 -> 0 | AA50: =Z50*$C50 -> 0 | AB50: =E50+G50+I50+K50+M50+O50+Q50+S50++U50+W50+Y50+AA50 -> 1710000
B51: Bonificación de instalación por contratación B | C51: =Hipótesis!$C$59*0.3 -> 72000 | D51: =D39 -> 0 | E51: =D51*$C51 -> 0 | F51: =F39 -> 0 | G51: =F51*$C51 -> 0 | H51: =H39 -> 15 | I51: =H51*$C51 -> 1080000 | J51: =J39 -> 0 | K51: =J51*$C51 -> 0 | L51: =L39 -> 0 | M51: =L51*$C51 -> 0 | N51: =N39 -> 0 | O51: =N51*$C51 -> 0 | P51: =P39 -> 0 | Q51: =P51*$C51 -> 0 | R51: =R39 -> 0 | S51: =R51*$C51 -> 0 | T51: =T39 -> 0 | U51: =T51*$C51 -> 0 | V51: =V39 -> 0 | W51: =V51*$C51 -> 0 | X51: =X39 -> 0 | Y51: =X51*$C51 -> 0 | Z51: =Z39 -> 0 | AA51: =Z51*$C51 -> 0 | AB51: =E51+G51+I51+K51+M51+O51+Q51+S51++U51+W51+Y51+AA51 -> 1080000
B52: Bonificación de instalación por contratación C | C52: =Hipótesis!$C$60*0.3 -> 93000 | D52: =D40 -> 15 | E52: =D52*$C52 -> 1395000 | F52: =F40 -> 0 | G52: =F52*$C52 -> 0 | H52: =H40 -> 0 | I52: =H52*$C52 -> 0 | J52: =J40 -> 15 | K52: =J52*$C52 -> 1395000 | L52: =L40 -> 0 | M52: =L52*$C52 -> 0 | N52: =N40 -> 0 | O52: =N52*$C52 -> 0 | P52: =P40 -> 0 | Q52: =P52*$C52 -> 0 | R52: =R40 -> 0 | S52: =R52*$C52 -> 0 | T52: =T40 -> 0 | U52: =T52*$C52 -> 0 | V52: =V40 -> 30 | W52: =V52*$C52 -> 2790000 | X52: =X40 -> 30 | Y52: =X52*$C52 -> 2790000 | Z52: =Z40 -> 0 | AA52: =Z52*$C52 -> 0 | AB52: =E52+G52+I52+K52+M52+O52+Q52+S52++U52+W52+Y52+AA52 -> 8370000
C53: 0 | D53: 0 | E53: 0 | F53: 0 | G53: 0 | H53: 0 | I53: 0 | J53: 0 | K53: 0 | L53: 0 | M53: 0 | N53: 0 | O53: 0 | P53: 0 | Q53: 0 | R53: 0 | S53: 0 | T53: 0 | U53: 0 | V53: 0 | W53: 0 | X53: 0 | Y53: 0 | Z53: 0 | AA53: 0 | AB53: =E53+G53+I53+K53+M53+O53+Q53+S53+U53+W53+Y53+AA53 -> 0
C54: 0 | D54: 0 | E54: 0 | F54: 0 | G54: =(F40+F39+F38)*75 -> 0 | H54: 0 | I54: 0 | J54: 0 | K54: 0 | L54: 0 | M54: =((L40*24)+(L39*18)+(L38*12))*6*1034 -> 0 | N54: 0 | O54: =((N40*24)+(N39*18)+(N38*12))*6*1034 -> 0 | P54: 0 | Q54: =((P40*24)+(P39*18)+(P38*12))*6*1034 -> 0 | R54: 0 | S54: =((R40*24)+(R39*18)+(R38*12))*6*1034 -> 0 | T54: 0 | U54: 0 | V54: 0 | W54: 0 | X54: 0 | Y54: 0 | Z54: 0 | AA54: =((Z40*24)+(Z39*18)+(Z38*12))*6*1034 -> 0 | AB54: =E54+G54+I54+K54+M54+O54+Q54+S54+U54+W54+Y54+AA54 -> 0
B55: TOTAL | E55: =SUM(E38:E54) -> 7202500 | G55: =SUM(G38:G54) -> 696250 | I55: =SUM(I38:I54) -> 5125000 | K55: =SUM(K38:K54) -> 10691875 | M55: =SUM(M38:M54) -> 520000 | O55: =SUM(O38:O54) -> 520000 | Q55: =SUM(Q38:Q54) -> 632500 | S55: =SUM(S38:S54) -> 640000 | U55: =SUM(U38:U54) -> 4391875 | W55: =SUM(W38:W54) -> 13817500 | Y55: =SUM(Y38:Y54) -> 14217500 | AA55: =SUM(AA38:AA54) -> 1040000 | AB55: =SUM(E55:AA55) -> 59495000
B58: Costos variables - Año 2028
B59: Concepto | D59: Enero | F59: Febrero | H59: Marzo | J59: Abril | L59: Mayo | N59: Junio | P59: Julio | R59: Agosto | T59: Septiembre | V59: Octubre | X59: Noviembre | Z59: Diciembre | AB59: Total
B60: Descripción | C60: Costo unitario | D60: Cantidad | E60: Costo | F60: Cantidad | G60: Costo | H60: Cantidad | I60: Costo | J60: Cantidad | K60: Costo | L60: Cantidad | M60: Costo | N60: Cantidad | O60: Costo | P60: Cantidad | Q60: Costo | R60: Cantidad | S60: Costo | T60: Cantidad | U60: Costo | V60: Cantidad | W60: Costo | X60: Cantidad | Y60: Costo | Z60: Cantidad | AA60: Costo
A61: Tipo de servicio | B61: ='Anexo capacidad operativa'!$S$18 -> Plan A | C61: ='Anexo capacidad operativa'!$W$28 -> 92625 | D61: ='Anexo capacidad operativa'!C102 -> 0 | E61: =D61*$C61 -> 0 | F61: ='Anexo capacidad operativa'!E102 -> 15 | G61: =F61*$C61 -> 1389375 | H61: ='Anexo capacidad operativa'!G102 -> 15 | I61: =H61*$C61 -> 1389375 | J61: ='Anexo capacidad operativa'!I102 -> 15 | K61: =J61*$C61 -> 1389375 | L61: ='Anexo capacidad operativa'!K102 -> 15 | M61: =L61*$C61 -> 1389375 | N61: ='Anexo capacidad operativa'!M102 -> 0 | O61: =N61*$C61 -> 0 | P61: ='Anexo capacidad operativa'!O102 -> 0 | Q61: =P61*$C61 -> 0 | R61: ='Anexo capacidad operativa'!Q102 -> 15 | S61: =R61*$C61 -> 1389375 | T61: ='Anexo capacidad operativa'!S102 -> 0 | U61: =T61*$C61 -> 0 | V61: ='Anexo capacidad operativa'!U102 -> 0 | W61: =V61*$C61 -> 0 | X61: ='Anexo capacidad operativa'!W102 -> 0 | Y61: =X61*$C61 -> 0 | Z61: ='Anexo capacidad operativa'!Y102 -> 0 | AA61: =Z61*$C61 -> 0 | AB61: =E61+G61+I61+K61+M61+O61+Q61+S61++U61+W61+Y61+AA61 -> 6946875
B62: ='Anexo capacidad operativa'!$S$37 -> Plan B | C62: ='Anexo capacidad operativa'!$W$47 -> 115000 | D62: ='Anexo capacidad operativa'!C103 -> 0 | E62: =D62*$C62 -> 0 | F62: ='Anexo capacidad operativa'!E103 -> 0 | G62: =F62*$C62 -> 0 | H62: ='Anexo capacidad operativa'!G103 -> 0 | I62: =H62*$C62 -> 0 | J62: ='Anexo capacidad operativa'!I103 -> 15 | K62: =J62*$C62 -> 1725000 | L62: ='Anexo capacidad operativa'!K103 -> 0 | M62: =L62*$C62 -> 0 | N62: ='Anexo capacidad operativa'!M103 -> 15 | O62: =N62*$C62 -> 1725000 | P62: ='Anexo capacidad operativa'!O103 -> 0 | Q62: =P62*$C62 -> 0 | R62: ='Anexo capacidad operativa'!Q103 -> 0 | S62: =R62*$C62 -> 0 | T62: ='Anexo capacidad operativa'!S103 -> 15 | U62: =T62*$C62 -> 1725000 | V62: ='Anexo capacidad operativa'!U103 -> 15 | W62: =V62*$C62 -> 1725000 | X62: ='Anexo capacidad operativa'!W103 -> 0 | Y62: =X62*$C62 -> 0 | Z62: ='Anexo capacidad operativa'!Y103 -> 0 | AA62: =Z62*$C62 -> 0 | AB62: =E62+G62+I62+K62+M62+O62+Q62+S62++U62+W62+Y62+AA62 -> 6900000
B63: ='Anexo capacidad operativa'!$S$56 -> Plan C | C63: ='Anexo capacidad operativa'!$W$65 -> 208000 | D63: ='Anexo capacidad operativa'!C104 -> 0 | E63: =D63*$C63 -> 0 | F63: ='Anexo capacidad operativa'!E104 -> 15 | G63: =F63*$C63 -> 3120000 | H63: ='Anexo capacidad operativa'!G104 -> 0 | I63: =H63*$C63 -> 0 | J63: ='Anexo capacidad operativa'!I104 -> 0 | K63: =J63*$C63 -> 0 | L63: ='Anexo capacidad operativa'!K104 -> 0 | M63: =L63*$C63 -> 0 | N63: ='Anexo capacidad operativa'!M104 -> 0 | O63: =N63*$C63 -> 0 | P63: ='Anexo capacidad operativa'!O104 -> 0 | Q63: =P63*$C63 -> 0 | R63: ='Anexo capacidad operativa'!Q104 -> 0 | S63: =R63*$C63 -> 0 | T63: ='Anexo capacidad operativa'!S104 -> 30 | U63: =T63*$C63 -> 6240000 | V63: ='Anexo capacidad operativa'!U104 -> 15 | W63: =V63*$C63 -> 3120000 | X63: ='Anexo capacidad operativa'!W104 -> 15 | Y63: =X63*$C63 -> 3120000 | Z63: ='Anexo capacidad operativa'!Y104 -> 0 | AA63: =Z63*$C63 -> 0 | AB63: =E63+G63+I63+K63+M63+O63+Q63+S63++U63+W63+Y63+AA63 -> 15600000
B64: ='Anexo capacidad operativa'!$Y$18 -> Mantenimiento plan A | C64: ='Anexo capacidad operativa'!$AC$28 -> 3750 | D64: ='Anexo capacidad operativa'!C105 -> 0 | E64: =D64*$C64 -> 0 | F64: ='Anexo capacidad operativa'!E105 -> 15 | G64: =F64*$C64 -> 56250 | H64: ='Anexo capacidad operativa'!G105 -> 0 | I64: =H64*$C64 -> 0 | J64: ='Anexo capacidad operativa'!I105 -> 15 | K64: =J64*$C64 -> 56250 | L64: ='Anexo capacidad operativa'!K105 -> 0 | M64: =L64*$C64 -> 0 | N64: ='Anexo capacidad operativa'!M105 -> 0 | O64: =N64*$C64 -> 0 | P64: ='Anexo capacidad operativa'!O105 -> 0 | Q64: =P64*$C64 -> 0 | R64: ='Anexo capacidad operativa'!Q105 -> 0 | S64: =R64*$C64 -> 0 | T64: ='Anexo capacidad operativa'!S105 -> 15 | U64: =T64*$C64 -> 56250 | V64: ='Anexo capacidad operativa'!U105 -> 0 | W64: =V64*$C64 -> 0 | X64: ='Anexo capacidad operativa'!W105 -> 0 | Y64: =X64*$C64 -> 0 | Z64: ='Anexo capacidad operativa'!Y105 -> 0 | AA64: =Z64*$C64 -> 0 | AB64: =E64+G64+I64+K64+M64+O64+Q64+S64++U64+W64+Y64+AA64 -> 168750
B65: ='Anexo capacidad operativa'!$Y$37 -> Mantenimiento plan B | C65: ='Anexo capacidad operativa'!$AC$47 -> 7500 | D65: ='Anexo capacidad operativa'!C106 -> 0 | E65: =D65*$C65 -> 0 | F65: ='Anexo capacidad operativa'!E106 -> 0 | G65: =F65*$C65 -> 0 | H65: ='Anexo capacidad operativa'!G106 -> 15 | I65: =H65*$C65 -> 112500 | J65: ='Anexo capacidad operativa'!I106 -> 15 | K65: =J65*$C65 -> 112500 | L65: ='Anexo capacidad operativa'!K106 -> 0 | M65: =L65*$C65 -> 0 | N65: ='Anexo capacidad operativa'!M106 -> 0 | O65: =N65*$C65 -> 0 | P65: ='Anexo capacidad operativa'!O106 -> 15 | Q65: =P65*$C65 -> 112500 | R65: ='Anexo capacidad operativa'!Q106 -> 0 | S65: =R65*$C65 -> 0 | T65: ='Anexo capacidad operativa'!S106 -> 0 | U65: =T65*$C65 -> 0 | V65: ='Anexo capacidad operativa'!U106 -> 0 | W65: =V65*$C65 -> 0 | X65: ='Anexo capacidad operativa'!W106 -> 0 | Y65: =X65*$C65 -> 0 | Z65: ='Anexo capacidad operativa'!Y106 -> 0 | AA65: =Z65*$C65 -> 0 | AB65: =E65+G65+I65+K65+M65+O65+Q65+S65++U65+W65+Y65+AA65 -> 337500
B66: ='Anexo capacidad operativa'!$Y$56 -> Mantenimiento plan C | C66: ='Anexo capacidad operativa'!$AC$65 -> 12500 | D66: ='Anexo capacidad operativa'!C107 -> 30 | E66: =D66*$C66 -> 375000 | F66: ='Anexo capacidad operativa'!E107 -> 0 | G66: =F66*$C66 -> 0 | H66: ='Anexo capacidad operativa'!G107 -> 0 | I66: =H66*$C66 -> 0 | J66: ='Anexo capacidad operativa'!I107 -> 15 | K66: =J66*$C66 -> 187500 | L66: ='Anexo capacidad operativa'!K107 -> 0 | M66: =L66*$C66 -> 0 | N66: ='Anexo capacidad operativa'!M107 -> 0 | O66: =N66*$C66 -> 0 | P66: ='Anexo capacidad operativa'!O107 -> 0 | Q66: =P66*$C66 -> 0 | R66: ='Anexo capacidad operativa'!Q107 -> 0 | S66: =R66*$C66 -> 0 | T66: ='Anexo capacidad operativa'!S107 -> 15 | U66: =T66*$C66 -> 187500 | V66: ='Anexo capacidad operativa'!U107 -> 45 | W66: =V66*$C66 -> 562500 | X66: ='Anexo capacidad operativa'!W107 -> 45 | Y66: =X66*$C66 -> 562500 | Z66: ='Anexo capacidad operativa'!Y107 -> 0 | AA66: =Z66*$C66 -> 0 | AB66: =E66+G66+I66+K66+M66+O66+Q66+S66++U66+W66+Y66+AA66 -> 1875000
A67: Publicidad y promoción | B67: Ferias | C67: 300000 | D67: 0 | E67: =D67*$C67 -> 0 | F67: 0 | G67: =F67*$C67 -> 0 | H67: 1 | I67: =H67*$C67 -> 300000 | J67: 0 | K67: =J67*$C67 -> 0 | L67: 0 | M67: =L67*$C67 -> 0 | N67: 0 | O67: =N67*$C67 -> 0 | P67: 0 | Q67: =P67*$C67 -> 0 | R67: 0 | S67: =R67*$C67 -> 0 | T67: 0 | U67: =T67*$C67 -> 0 | V67: 0 | W67: =V67*$C67 -> 0 | X67: 0 | Y67: =X67*$C67 -> 0 | Z67: 0 | AA67: =Z67*$C67 -> 0 | AB67: =E67+G67+I67+K67+M67+O67+Q67+S67++U67+W67+Y67+AA67 -> 300000
B68: Carteleria | C68: 400000 | D68: 1 | E68: =D68*$C68 -> 400000 | F68: 3 | G68: =F68*$C68 -> 1200000 | H68: 2 | I68: =H68*$C68 -> 800000 | J68: 2 | K68: =J68*$C68 -> 800000 | L68: 2 | M68: =L68*$C68 -> 800000 | N68: 2 | O68: =N68*$C68 -> 800000 | P68: 3 | Q68: =P68*$C68 -> 1200000 | R68: 3 | S68: =R68*$C68 -> 1200000 | T68: 4 | U68: =T68*$C68 -> 1600000 | V68: 4 | W68: =V68*$C68 -> 1600000 | X68: 4 | Y68: =X68*$C68 -> 1600000 | Z68: 4 | AA68: =Z68*$C68 -> 1600000 | AB68: =E68+G68+I68+K68+M68+O68+Q68+S68++U68+W68+Y68+AA68 -> 13600000
B69: Radio | C69: 120000 | D69: 2 | E69: =D69*$C69 -> 240000 | F69: 2 | G69: =F69*$C69 -> 240000 | H69: 1 | I69: =H69*$C69 -> 120000 | J69: 2 | K69: =J69*$C69 -> 240000 | L69: 1 | M69: =L69*$C69 -> 120000 | N69: 2 | O69: =N69*$C69 -> 240000 | P69: 3 | Q69: =P69*$C69 -> 360000 | R69: 3 | S69: =R69*$C69 -> 360000 | T69: 3 | U69: =T69*$C69 -> 360000 | V69: 3 | W69: =V69*$C69 -> 360000 | X69: 3 | Y69: =X69*$C69 -> 360000 | Z69: 4 | AA69: =Z69*$C69 -> 480000 | AB69: =E69+G69+I69+K69+M69+O69+Q69+S69++U69+W69+Y69+AA69 -> 3480000
B70: Bonificación de mantenimiento por contratación A | C70: =Hipótesis!$C$61 -> 88000 | D70: =D61 -> 0 | E70: =D70*$C70 -> 0 | F70: =F61 -> 15 | G70: =F70*$C70 -> 1320000 | H70: =H61 -> 15 | I70: =H70*$C70 -> 1320000 | J70: =J61 -> 15 | K70: =J70*$C70 -> 1320000 | L70: =L61 -> 15 | M70: =L70*$C70 -> 1320000 | N70: =N61 -> 0 | O70: =N70*$C70 -> 0 | P70: =P61 -> 0 | Q70: =P70*$C70 -> 0 | R70: =R61 -> 15 | S70: =R70*$C70 -> 1320000 | T70: =T61 -> 0 | U70: =T70*$C70 -> 0 | V70: =V61 -> 0 | W70: =V70*$C70 -> 0 | X70: =X61 -> 0 | Y70: =X70*$C70 -> 0 | Z70: =Z61 -> 0 | AA70: =Z70*$C70 -> 0 | AB70: =E70+G70+I70+K70+M70+O70+Q70+S70++U70+W70+Y70+AA70 -> 6600000
B71: Bonificación de mantenimiento por contratación B | C71: =Hipótesis!$C$62 -> 108000 | D71: =D62 -> 0 | E71: =D71*$C71 -> 0 | F71: =F62 -> 0 | G71: =F71*$C71 -> 0 | H71: =H62 -> 0 | I71: =H71*$C71 -> 0 | J71: =J62 -> 15 | K71: =J71*$C71 -> 1620000 | L71: =L62 -> 0 | M71: =L71*$C71 -> 0 | N71: =N62 -> 15 | O71: =N71*$C71 -> 1620000 | P71: =P62 -> 0 | Q71: =P71*$C71 -> 0 | R71: =R62 -> 0 | S71: =R71*$C71 -> 0 | T71: =T62 -> 15 | U71: =T71*$C71 -> 1620000 | V71: =V62 -> 15 | W71: =V71*$C71 -> 1620000 | X71: =X62 -> 0 | Y71: =X71*$C71 -> 0 | Z71: =Z62 -> 0 | AA71: =Z71*$C71 -> 0 | AB71: =E71+G71+I71+K71+M71+O71+Q71+S71++U71+W71+Y71+AA71 -> 6480000
B72: Bonificación de mantenimiento por contratación C | C72: =Hipótesis!$C$63 -> 132000 | D72: =D63 -> 0 | E72: =D72*$C72 -> 0 | F72: =F63 -> 15 | G72: =F72*$C72 -> 1980000 | H72: =H63 -> 0 | I72: =H72*$C72 -> 0 | J72: =J63 -> 0 | K72: =J72*$C72 -> 0 | L72: =L63 -> 0 | M72: =L72*$C72 -> 0 | N72: =N63 -> 0 | O72: =N72*$C72 -> 0 | P72: =P63 -> 0 | Q72: =P72*$C72 -> 0 | R72: =R63 -> 0 | S72: =R72*$C72 -> 0 | T72: =T63 -> 30 | U72: =T72*$C72 -> 3960000 | V72: =V63 -> 15 | W72: =V72*$C72 -> 1980000 | X72: =X63 -> 15 | Y72: =X72*$C72 -> 1980000 | Z72: =Z63 -> 0 | AA72: =Z72*$C72 -> 0 | AB72: =E72+G72+I72+K72+M72+O72+Q72+S72++U72+W72+Y72+AA72 -> 9900000
B73: Bonificación de instalación por contratación A | C73: =Hipótesis!$C$58*0.3 -> 57000 | D73: =D61 -> 0 | E73: =D73*$C73 -> 0 | F73: =F61 -> 15 | G73: =F73*$C73 -> 855000 | H73: =H61 -> 15 | I73: =H73*$C73 -> 855000 | J73: =J61 -> 15 | K73: =J73*$C73 -> 855000 | L73: =L61 -> 15 | M73: =L73*$C73 -> 855000 | N73: =N61 -> 0 | O73: =N73*$C73 -> 0 | P73: =P61 -> 0 | Q73: =P73*$C73 -> 0 | R73: =R61 -> 15 | S73: =R73*$C73 -> 855000 | T73: =T61 -> 0 | U73: =T73*$C73 -> 0 | V73: =V61 -> 0 | W73: =V73*$C73 -> 0 | X73: =X61 -> 0 | Y73: =X73*$C73 -> 0 | Z73: =Z61 -> 0 | AA73: =Z73*$C73 -> 0 | AB73: =E73+G73+I73+K73+M73+O73+Q73+S73++U73+W73+Y73+AA73 -> 4275000
B74: Bonificación de instalación por contratación B | C74: =Hipótesis!$C$59*0.3 -> 72000 | D74: =D62 -> 0 | E74: =D74*$C74 -> 0 | F74: =F62 -> 0 | G74: =F74*$C74 -> 0 | H74: =H62 -> 0 | I74: =H74*$C74 -> 0 | J74: =J62 -> 15 | K74: =J74*$C74 -> 1080000 | L74: =L62 -> 0 | M74: =L74*$C74 -> 0 | N74: =N62 -> 15 | O74: =N74*$C74 -> 1080000 | P74: =P62 -> 0 | Q74: =P74*$C74 -> 0 | R74: =R62 -> 0 | S74: =R74*$C74 -> 0 | T74: =T62 -> 15 | U74: =T74*$C74 -> 1080000 | V74: =V62 -> 15 | W74: =V74*$C74 -> 1080000 | X74: =X62 -> 0 | Y74: =X74*$C74 -> 0 | Z74: =Z62 -> 0 | AA74: =Z74*$C74 -> 0 | AB74: =E74+G74+I74+K74+M74+O74+Q74+S74++U74+W74+Y74+AA74 -> 4320000
B75: Bonificación de instalación por contratación C | C75: =Hipótesis!$C$60*0.3 -> 93000 | D75: =D63 -> 0 | E75: =D75*$C75 -> 0 | F75: =F63 -> 15 | G75: =F75*$C75 -> 1395000 | H75: =H63 -> 0 | I75: =H75*$C75 -> 0 | J75: =J63 -> 0 | K75: =J75*$C75 -> 0 | L75: =L63 -> 0 | M75: =L75*$C75 -> 0 | N75: =N63 -> 0 | O75: =N75*$C75 -> 0 | P75: =P63 -> 0 | Q75: =P75*$C75 -> 0 | R75: =R63 -> 0 | S75: =R75*$C75 -> 0 | T75: =T63 -> 30 | U75: =T75*$C75 -> 2790000 | V75: =V63 -> 15 | W75: =V75*$C75 -> 1395000 | X75: =X63 -> 15 | Y75: =X75*$C75 -> 1395000 | Z75: =Z63 -> 0 | AA75: =Z75*$C75 -> 0 | AB75: =E75+G75+I75+K75+M75+O75+Q75+S75++U75+W75+Y75+AA75 -> 6975000
C76: 0 | D76: 0 | E76: 0 | F76: 0 | G76: 0 | H76: 0 | I76: 0 | J76: 0 | K76: 0 | L76: 0 | M76: 0 | N76: 0 | O76: 0 | P76: 0 | Q76: 0 | R76: 0 | S76: 0 | T76: 0 | U76: 0 | V76: 0 | W76: 0 | X76: 0 | Y76: 0 | Z76: 0 | AA76: 0 | AB76: =E76+G76+I76+K76+M76+O76+Q76+S76+U76+W76+Y76+AA76 -> 0
C77: 0 | D77: 0 | E77: 0 | F77: 0 | G77: 0 | H77: 0 | I77: 0 | J77: 0 | K77: 0 | L77: 0 | M77: =((L66*24)+(L65*18)+(L64*12))*6*1034 -> 0 | N77: 0 | O77: =((N66*24)+(N65*18)+(N64*12))*6*1034 -> 0 | P77: 0 | Q77: 0 | R77: 0 | S77: =((R66*24)+(R65*18)+(R64*12))*6*1034 -> 0 | T77: 0 | U77: 0 | V77: 0 | W77: 0 | X77: 0 | Y77: 0 | Z77: 0 | AA77: =((Z66*24)+(Z65*18)+(Z64*12))*6*1034 -> 0 | AB77: =E77+G77+I77+K77+M77+O77+Q77+S77+U77+W77+Y77+AA77 -> 0
B78: TOTAL | E78: =SUM(E61:E77) -> 1015000 | G78: =SUM(G61:G77) -> 11555625 | I78: =SUM(I61:I77) -> 4896875 | K78: =SUM(K61:K77) -> 9385625 | M78: =SUM(M61:M77) -> 4484375 | O78: =SUM(O61:O77) -> 5465000 | Q78: =SUM(Q61:Q77) -> 1672500 | S78: =SUM(S61:S77) -> 5124375 | U78: =SUM(U61:U77) -> 19618750 | W78: =SUM(W61:W77) -> 13442500 | Y78: =SUM(Y61:Y77) -> 9017500 | AA78: =SUM(AA64:AA77) -> 2080000 | AB78: =SUM(E78:AA78) -> 87758125

Sheet Costos RRHH
E1: Estructura de costos de RRHH
B4: Evolución de la participación | H4: Costos de RRHH - Totales
B5: 2026 | C5: 2027 | D5: 2028 | H5: 2026 | I5: 2027 | J5: 2028
B6: =Hipótesis!C24 -> 0.02 | C6: =Hipótesis!C25 -> 0.06 | D6: =Hipótesis!C26 -> 0.1 | H6: =$AA$134 -> 77670014 | I6: =$AA$195 -> 1.4973145e+08 | J6: =$AA$256 -> 2.2191489e+08
B7: =Hipótesis!D24 -> 102480000 | C7: =Hipótesis!D25 -> 307440000 | D7: =Hipótesis!D26 -> 512400000
B9: Posición cubierta por otro puesto
B10: Posicion tercerizada
B13: Costo mensual por puesto
B14: Area | C14: Puesto | D14: Sueldo bruto | E14: Jubilación | F14: Ley 1932 | G14: Obra social | H14: F. Nac. Des. | I14: S. de Vida | J14: ART (Aprox.) | K14: Total aportes | L14: Costo mensual para empresa
E15: 0.1047 | F15: 0.0154 | G15: 0.06 | H15: 0.0092 | I15: $ 18,57 c/u | J15: 0.03
B16: Gerencia | C16: Gerente general | D16: 2400000 | E16: =$D$16*E15 -> 251280 | F16: =$D$16*F15 -> 36960 | G16: =$D$16*G15 -> 144000 | H16: =$D$16*H15 -> 22080 | I16: 18.57 | J16: =$D$16*J15 -> 72000 | K16: =SUM(E16:J16) -> 526338.57 | L16: =D16+K16 -> 2926338.6
B17: Administracion | C17: Gerente de administración | D17: 2000000 | E17: =$D17*$E$15 -> 209400 | F17: =$D17*F$15 -> 30800 | G17: =$D17*G$15 -> 120000 | H17: =$D17*H$15 -> 18400 | I17: 18.57 | J17: =$D17*J$15 -> 60000 | K17: =SUM(E17:J17) -> 438618.57 | L17: =D17+K17 -> 2438618.6
C18: Jefe de compras | D18: 1900000 | E18: =$D18*$E$15 -> 198930 | F18: =$D18*F$15 -> 29260 | G18: =$D18*G$15 -> 114000 | H18: =$D18*H$15 -> 17480 | I18: 18.57 | J18: =$D18*J$15 -> 57000 | K18: =SUM(E18:J18) -> 416688.57 | L18: =D18+K18 -> 2316688.6
C19: Jefe de finanzas | D19: 1900000 | E19: =$D19*$E$15 -> 198930 | F19: =$D19*F$15 -> 29260 | G19: =$D19*G$15 -> 114000 | H19: =$D19*H$15 -> 17480 | I19: 18.57 | J19: =$D19*J$15 -> 57000 | K19: =SUM(E19:J19) -> 416688.57 | L19: =D19+K19 -> 2316688.6
C20: Jefe de ventas | D20: 1900000 | E20: =$D20*$E$15 -> 198930 | F20: =$D20*F$15 -> 29260 | G20: =$D20*G$15 -> 114000 | H20: =$D20*H$15 -> 17480 | I20: 18.57 | J20: =$D20*J$15 -> 57000 | K20: =SUM(E20:J20) -> 416688.57 | L20: =D20+K20 -> 2316688.6
C21: Jefe de RRHH | D21: 1700000 | E21: =$D21*$E$15 -> 177990 | F21: =$D21*F$15 -> 26180 | G21: =$D21*G$15 -> 102000 | H21: =$D21*H$15 -> 15640 | I21: 18.57 | J21: =$D21*J$15 -> 51000 | K21: =SUM(E21:J21) -> 372828.57 | L21: =D21+K21 -> 2072828.6
C22: Subjefe de ventas | D22: 1600000 | E22: =$D22*$E$15 -> 167520 | F22: =$D22*F$15 -> 24640 | G22: =$D22*G$15 -> 96000 | H22: =$D22*H$15 -> 14720 | I22: 18.57 | J22: =$D22*J$15 -> 48000 | K22: =SUM(E22:J22) -> 350898.57 | L22: =D22+K22 -> 1950898.6
C23: Analista contable | D23: 1300000 | E23: =$D23*$E$15 -> 136110 | F23: =$D23*F$15 -> 20020 | G23: =$D23*G$15 -> 78000 | H23: =$D23*H$15 -> 11960 | I23: 18.57 | J23: =$D23*J$15 -> 39000 | K23: =SUM(E23:J23) -> 285108.57 | L23: =D23+K23 -> 1585108.6
C24: Analista de compras | D24: 1300000 | E24: =$D24*$E$15 -> 136110 | F24: =$D24*F$15 -> 20020 | G24: =$D24*G$15 -> 78000 | H24: =$D24*H$15 -> 11960 | I24: 18.57 | J24: =$D24*J$15 -> 39000 | K24: =SUM(E24:J24) -> 285108.57 | L24: =D24+K24 -> 1585108.6
C25: Administrativo de ventas | D25: 1200000 | E25: =$D25*$E$15 -> 125640 | F25: =$D25*F$15 -> 18480 | G25: =$D25*G$15 -> 72000 | H25: =$D25*H$15 -> 11040 | I25: 18.57 | J25: =$D25*J$15 -> 36000 | K25: =SUM(E25:J25) -> 263178.57 | L25: =D25+K25 -> 1463178.6
C26: Administrativo contable | D26: 1200000 | E26: =$D26*$E$15 -> 125640 | F26: =$D26*F$15 -> 18480 | G26: =$D26*G$15 -> 72000 | H26: =$D26*H$15 -> 11040 | I26: 18.57 | J26: =$D26*J$15 -> 36000 | K26: =SUM(E26:J26) -> 263178.57 | L26: =D26+K26 -> 1463178.6
C27: Administrativo de cobranzas | D27: 1200000 | E27: =$D27*$E$15 -> 125640 | F27: =$D27*F$15 -> 18480 | G27: =$D27*G$15 -> 72000 | H27: =$D27*H$15 -> 11040 | I27: 18.57 | J27: =$D27*J$15 -> 36000 | K27: =SUM(E27:J27) -> 263178.57 | L27: =D27+K27 -> 1463178.6
C28: Administrativo de compras | D28: 1100000 | E28: =$D28*$E$15 -> 115170 | F28: =$D28*F$15 -> 16940 | G28: =$D28*G$15 -> 66000 | H28: =$D28*H$15 -> 10120 | I28: 18.57 | J28: =$D28*J$15 -> 33000 | K28: =SUM(E28:J28) -> 241248.57 | L28: =D28+K28 -> 1341248.6
C29: Administrativo de pagos | D29: 1100000 | E29: =$D29*$E$15 -> 115170 | F29: =$D29*F$15 -> 16940 | G29: =$D29*G$15 -> 66000 | H29: =$D29*H$15 -> 10120 | I29: 18.57 | J29: =$D29*J$15 -> 33000 | K29: =SUM(E29:J29) -> 241248.57 | L29: =D29+K29 -> 1341248.6
... C31: Auxiliar administrativo | D31: 950000 | E31: =$D31*$E$15 -> 99465 | F31: =$D31*F$15 -> 14630 | G31: =$D31*G$15 -> 57000 | H31: =$D31*H$15 -> 8740 | I31: 18.57 | J31: =$D31*J$15 -> 28500 | K31: =SUM(E31:J31) -> 208353.57 | L31: =D31+K31 -> 1158353.6
B32: Marketing | C32: Gerente de marketing | D32: 2000000 | E32: =$D32*$E$15 -> 209400 | F32: =$D32*F$15 -> 30800 | G32: =$D32*G$15 -> 120000 | H32: =$D32*H$15 -> 18400 | I32: 18.57 | J32: =$D32*J$15 -> 60000 | K32: =SUM(E32:J32) -> 438618.57 | L32: =D32+K32 -> 2438618.6
C33: Lider de finanzas | D33: 2000000 | E33: =$D33*$E$15 -> 209400 | F33: =$D33*F$15 -> 30800 | G33: =$D33*G$15 -> 120000 | H33: =$D33*H$15 -> 18400 | I33: 18.57 | J33: =$D33*J$15 -> 60000 | K33: =SUM(E33:J33) -> 438618.57 | L33: =D33+K33 -> 2438618.6
C34: Lider de operaciones comerciales | D34: 1800000 | E34: =$D34*$E$15 -> 188460 | F34: =$D34*F$15 -> 27720 | G34: =$D34*G$15 -> 108000 | H34: =$D34*H$15 -> 16560 | I34: 18.57 | J34: =$D34*J$15 -> 54000 | K34: =SUM(E34:J34) -> 394758.57 | L34: =D34+K34 -> 2194758.6
C35: Coordinador de instalaciones | D35: 1500000 | E35: =$D35*$E$15 -> 157050 | F35: =$D35*F$15 -> 23100 | G35: =$D35*G$15 -> 90000 | H35: =$D35*H$15 -> 13800 | I35: 18.57 | J35: =$D35*J$15 -> 45000 | K35: =SUM(E35:J35) -> 328968.57 | L35: =D35+K35 -> 1828968.6
C36: Analista de producto | D36: 1500000 | E36: =$D36*$E$15 -> 157050 | F36: =$D36*F$15 -> 23100 | G36: =$D36*G$15 -> 90000 | H36: =$D36*H$15 -> 13800 | I36: 18.57 | J36: =$D36*J$15 -> 45000 | K36: =SUM(E36:J36) -> 328968.57 | L36: =D36+K36 -> 1828968.6
C37: Ejecutivo comercial | D37: 1500000 | E37: =$D37*$E$15 -> 157050 | F37: =$D37*F$15 -> 23100 | G37: =$D37*G$15 -> 90000 | H37: =$D37*H$15 -> 13800 | I37: 18.57 | J37: =$D37*J$15 -> 45000 | K37: =SUM(E37:J37) -> 328968.57 | L37: =D37+K37 -> 1828968.6
C38: Analista de logística | D38: 1300000 | E38: =$D38*$E$15 -> 136110 | F38: =$D38*F$15 -> 20020 | G38: =$D38*G$15 -> 78000 | H38: =$D38*H$15 -> 11960 | I38: 18.57 | J38: =$D38*J$15 -> 39000 | K38: =SUM(E38:J38) -> 285108.57 | L38: =D38+K38 -> 1585108.6
C39: Analista de marketing | D39: 1200000 | E39: =$D39*$E$15 -> 125640 | F39: =$D39*F$15 -> 18480 | G39: =$D39*G$15 -> 72000 | H39: =$D39*H$15 -> 11040 | I39: 18.57 | J39: =$D39*J$15 -> 36000 | K39: =SUM(E39:J39) -> 263178.57 | L39: =D39+K39 -> 1463178.6
C40: Diseñador de contenido | D40: 1200000 | E40: =$D40*$E$15 -> 125640 | F40: =$D40*F$15 -> 18480 | G40: =$D40*G$15 -> 72000 | H40: =$D40*H$15 -> 11040 | I40: 18.57 | J40: =$D40*J$15 -> 36000 | K40: =SUM(E40:J40) -> 263178.57 | L40: =D40+K40 -> 1463178.6
C41: Asistente de marketing | D41: 950000 | E41: =$D41*$E$15 -> 99465 | F41: =$D41*F$15 -> 14630 | G41: =$D41*G$15 -> 57000 | H41: =$D41*H$15 -> 8740 | I41: 18.57 | J41: =$D41*J$15 -> 28500 | K41: =SUM(E41:J41) -> 208353.57 | L41: =D41+K41 -> 1158353.6
B42: Tecnología | C42: Gerente de sistemas | D42: 2200000 | E42: =$D42*$E$15 -> 230340 | F42: =$D42*F$15 -> 33880 | G42: =$D42*G$15 -> 132000 | H42: =$D42*H$15 -> 20240 | I42: 18.57 | J42: =$D42*J$15 -> 66000 | K42: =SUM(E42:J42) -> 482478.57 | L42: =D42+K42 -> 2682478.6
C43: DevOps | D43: 2200000 | E43: =$D43*$E$15 -> 230340 | F43: =$D43*F$15 -> 33880 | G43: =$D43*G$15 -> 132000 | H43: =$D43*H$15 -> 20240 | I43: 18.57 | J43: =$D43*J$15 -> 66000 | K43: =SUM(E43:J43) -> 482478.57 | L43: =D43+K43 -> 2682478.6
C44: Arquitecto cloud | D44: 2100000 | E44: =$D44*$E$15 -> 219870 | F44: =$D44*F$15 -> 32340 | G44: =$D44*G$15 -> 126000 | H44: =$D44*H$15 -> 19320 | I44: 18.57 | J44: =$D44*J$15 -> 63000 | K44: =SUM(E44:J44) -> 460548.57 | L44: =D44+K44 -> 2560548.6
C45: Especialista en hardware | D45: 2000000 | E45: =$D45*$E$15 -> 209400 | F45: =$D45*F$15 -> 30800 | G45: =$D45*G$15 -> 120000 | H45: =$D45*H$15 -> 18400 | I45: 18.57 | J45: =$D45*J$15 -> 60000 | K45: =SUM(E45:J45) -> 438618.57 | L45: =D45+K45 -> 2438618.6
C46: Desarrollador backend SR | D46: 2100000 | E46: =$D46*$E$15 -> 219870 | F46: =$D46*F$15 -> 32340 | G46: =$D46*G$15 -> 126000 | H46: =$D46*H$15 -> 19320 | I46: 18.57 | J46: =$D46*J$15 -> 63000 | K46: =SUM(E46:J46) -> 460548.57 | L46: =D46+K46 -> 2560548.6
C47: Desarrollador frontend SR | D47: 1900000 | E47: =$D47*$E$15 -> 198930 | F47: =$D47*F$15 -> 29260 | G47: =$D47*G$15 -> 114000 | H47: =$D47*H$15 -> 17480 | I47: 18.57 | J47: =$D47*J$15 -> 57000 | K47: =SUM(E47:J47) -> 416688.57 | L47: =D47+K47 -> 2316688.6
C48: Coordinador tecnico | D48: 1900000 | E48: =$D48*$E$15 -> 198930 | F48: =$D48*F$15 -> 29260 | G48: =$D48*G$15 -> 114000 | H48: =$D48*H$15 -> 17480 | I48: 18.57 | J48: =$D48*J$15 -> 57000 | K48: =SUM(E48:J48) -> 416688.57 | L48: =D48+K48 -> 2316688.6
C49: Especialista en redes | D49: 1800000 | E49: =$D49*$E$15 -> 188460 | F49: =$D49*F$15 -> 27720 | G49: =$D49*G$15 -> 108000 | H49: =$D49*H$15 -> 16560 | I49: 18.57 | J49: =$D49*J$15 -> 54000 | K49: =SUM(E49:J49) -> 394758.57 | L49: =D49+K49 -> 2194758.6
C50: Tecnico instalador tecnología | D50: 1600000 | E50: =$D50*$E$15 -> 167520 | F50: =$D50*F$15 -> 24640 | G50: =$D50*G$15 -> 96000 | H50: =$D50*H$15 -> 14720 | I50: 18.57 | J50: =$D50*J$15 -> 48000 | K50: =SUM(E50:J50) -> 350898.57 | L50: =D50+K50 -> 1950898.6
C51: Soporte tecnico | D51: 1600000 | E51: =$D51*$E$15 -> 167520 | F51: =$D51*F$15 -> 24640 | G51: =$D51*G$15 -> 96000 | H51: =$D51*H$15 -> 14720 | I51: 18.57 | J51: =$D51*J$15 -> 48000 | K51: =SUM(E51:J51) -> 350898.57 | L51: =D51+K51 -> 1950898.6
C52: QA | D52: 1000000 | E52: =$D52*$E$15 -> 104700 | F52: =$D52*F$15 -> 15400 | G52: =$D52*G$15 -> 60000 | H52: =$D52*H$15 -> 9200 | I52: 18.57 | J52: =$D52*J$15 -> 30000 | K52: =SUM(E52:J52) -> 219318.57 | L52: =D52+K52 -> 1219318.6
C53: Auxiliar tecnico | D53: 950000 | E53: =$D53*$E$15 -> 99465 | F53: =$D53*F$15 -> 14630 | G53: =$D53*G$15 -> 57000 | H53: =$D53*H$15 -> 8740 | I53: 18.57 | J53: =$D53*J$15 -> 28500 | K53: =SUM(E53:J53) -> 208353.57 | L53: =D53+K53 -> 1158353.6
B54: Servicios | C54: Gerente de servicio tecnico | D54: 1950000 | E54: =$D54*$E$15 -> 204165 | F54: =$D54*F$15 -> 30030 | G54: =$D54*G$15 -> 117000 | H54: =$D54*H$15 -> 17940 | I54: 18.57 | J54: =$D54*J$15 -> 58500 | K54: =SUM(E54:J54) -> 427653.57 | L54: =D54+K54 -> 2377653.6
C55: Coordinador tecnico | D55: 1900000 | E55: =$D55*$E$15 -> 198930 | F55: =$D55*F$15 -> 29260 | G55: =$D55*G$15 -> 114000 | H55: =$D55*H$15 -> 17480 | I55: 18.57 | J55: =$D55*J$15 -> 57000 | K55: =SUM(E55:J55) -> 416688.57 | L55: =D55+K55 -> 2316688.6
C56: Coordinador de operaciones | D56: 1650000 | E56: =$D56*$E$15 -> 172755 | F56: =$D56*F$15 -> 25410 | G56: =$D56*G$15 -> 99000 | H56: =$D56*H$15 -> 15180 | I56: 18.57 | J56: =$D56*J$15 -> 49500 | K56: =SUM(E56:J56) -> 361863.57 | L56: =D56+K56 -> 2011863.6
C57: Tecnico instalador servicios | D57: 1600000 | E57: =$D57*$E$15 -> 167520 | F57: =$D57*F$15 -> 24640 | G57: =$D57*G$15 -> 96000 | H57: =$D57*H$15 -> 14720 | I57: 18.57 | J57: =$D57*J$15 -> 48000 | K57: =SUM(E57:J57) -> 350898.57 | L57: =D57+K57 -> 1950898.6
C58: Coordinador de soporte | D58: 1400000 | E58: =$D58*$E$15 -> 146580 | F58: =$D58*F$15 -> 21560 | G58: =$D58*G$15 -> 84000 | H58: =$D58*H$15 -> 12880 | I58: 18.57 | J58: =$D58*J$15 -> 42000 | K58: =SUM(E58:J58) -> 307038.57 | L58: =D58+K58 -> 1707038.6
C59: Tecnico de plataforma | D59: 1400000 | E59: =$D59*$E$15 -> 146580 | F59: =$D59*F$15 -> 21560 | G59: =$D59*G$15 -> 84000 | H59: =$D59*H$15 -> 12880 | I59: 18.57 | J59: =$D59*J$15 -> 42000 | K59: =SUM(E59:J59) -> 307038.57 | L59: =D59+K59 -> 1707038.6
C60: Operador de monitoreo | D60: 1200000 | E60: =$D60*$E$15 -> 125640 | F60: =$D60*F$15 -> 18480 | G60: =$D60*G$15 -> 72000 | H60: =$D60*H$15 -> 11040 | I60: 18.57 | J60: =$D60*J$15 -> 36000 | K60: =SUM(E60:J60) -> 263178.57 | L60: =D60+K60 -> 1463178.6
C61: Tecnico de soporte | D61: 1100000 | E61: =$D61*$E$15 -> 115170 | F61: =$D61*F$15 -> 16940 | G61: =$D61*G$15 -> 66000 | H61: =$D61*H$15 -> 10120 | I61: 18.57 | J61: =$D61*J$15 -> 33000 | K61: =SUM(E61:J61) -> 241248.57 | L61: =D61+K61 -> 1341248.6
C62: Soporte de nivel 1 | D62: 1000000 | E62: =$D62*$E$15 -> 104700 | F62: =$D62*F$15 -> 15400 | G62: =$D62*G$15 -> 60000 | H62: =$D62*H$15 -> 9200 | I62: 18.57 | J62: =$D62*J$15 -> 30000 | K62: =SUM(E62:J62) -> 219318.57 | L62: =D62+K62 -> 1219318.6
C63: Tecnico de inventario | D63: 1000000 | E63: =$D63*$E$15 -> 104700 | F63: =$D63*F$15 -> 15400 | G63: =$D63*G$15 -> 60000 | H63: =$D63*H$15 -> 9200 | I63: 18.57 | J63: =$D63*J$15 -> 30000 | K63: =SUM(E63:J63) -> 219318.57 | L63: =D63+K63 -> 1219318.6
C64: Tecnico de apoyo | D64: 1000000 | E64: =$D64*$E$15 -> 104700 | F64: =$D64*F$15 -> 15400 | G64: =$D64*G$15 -> 60000 | H64: =$D64*H$15 -> 9200 | I64: 18.57 | J64: =$D64*J$15 -> 30000 | K64: =SUM(E64:J64) -> 219318.57 | L64: =D64+K64 -> 1219318.6
C65: Auxiliar administrativo | D65: 950000 | E65: =$D65*$E$15 -> 99465 | F65: =$D65*F$15 -> 14630 | G65: =$D65*G$15 -> 57000 | H65: =$D65*H$15 -> 8740 | I65: 18.57 | J65: =$D65*J$15 -> 28500 | K65: =SUM(E65:J65) -> 208353.57 | L65: =D65+K65 -> 1158353.6
C66: Auxiliar logístico | D66: 950000 | E66: =$D66*$E$15 -> 99465 | F66: =$D66*F$15 -> 14630 | G66: =$D66*G$15 -> 57000 | H66: =$D66*H$15 -> 8740 | I66: 18.57 | J66: =$D66*J$15 -> 28500 | K66: =SUM(E66:J66) -> 208353.57 | L66: =D66+K66 -> 1158353.6
C67: Auxiliar operativo | D67: 950000 | E67: =$D67*$E$15 -> 99465 | F67: =$D67*F$15 -> 14630 | G67: =$D67*G$15 -> 57000 | H67: =$D67*H$15 -> 8740 | I67: 18.57 | J67: =$D67*J$15 -> 28500 | K67: =SUM(E67:J67) -> 208353.57 | L67: =D67+K67 -> 1158353.6
B68: Comercial | C68: Gerente comercial | D68: 1900000 | E68: =$D68*$E$15 -> 198930 | F68: =$D68*F$15 -> 29260 | G68: =$D68*G$15 -> 114000 | H68: =$D68*H$15 -> 17480 | I68: 18.57 | J68: =$D68*J$15 -> 57000 | K68: =SUM(E68:J68) -> 416688.57 | L68: =D68+K68 -> 2316688.6
C69: Ejecutivo de cuentas | D69: 1600000 | E69: =$D69*$E$15 -> 167520 | F69: =$D69*F$15 -> 24640 | G69: =$D69*G$15 -> 96000 | H69: =$D69*H$15 -> 14720 | I69: 18.57 | J69: =$D69*J$15 -> 48000 | K69: =SUM(E69:J69) -> 350898.57 | L69: =D69+K69 -> 1950898.6
C70: Representante de posventa | D70: 1200000 | E70: =$D70*$E$15 -> 125640 | F70: =$D70*F$15 -> 18480 | G70: =$D70*G$15 -> 72000 | H70: =$D70*H$15 -> 11040 | I70: 18.57 | J70: =$D70*J$15 -> 36000 | K70: =SUM(E70:J70) -> 263178.57 | L70: =D70+K70 -> 1463178.6
C71: Asistente de ventas | D71: 1000000 | E71: =$D71*$E$15 -> 104700 | F71: =$D71*F$15 -> 15400 | G71: =$D71*G$15 -> 60000 | H71: =$D71*H$15 -> 9200 | I71: 18.57 | J71: =$D71*J$15 -> 30000 | K71: =SUM(E71:J71) -> 219318.57 | L71: =D71+K71 -> 1219318.6
B75: Costos de RRHH - Año 2026
B76: Puesto | C76: Enero | E76: Febrero | G76: Marzo | I76: Abril | K76: Mayo | M76: Junio + SAC | O76: Julio | Q76: Agosto | S76: Septiembre | U76: Octubre | W76: Noviembre | Y76: Diciembre + SAC | AA76: Total anual
C77: Cantidad | D77: Costo | E77: Cantidad | F77: Costo | G77: Cantidad | H77: Costo | I77: Cantidad | J77: Costo | K77: Cantidad | L77: Costo | M77: Cantidad | N77: Costo | O77: Cantidad | P77: Costo | Q77: Cantidad | R77: Costo | S77: Cantidad | T77: Costo | U77: Cantidad | V77: Costo | W77: Cantidad | X77: Costo | Y77: Cantidad | Z77: Costo
B78: =C$16 -> Gerente general | C78: 0 | D78: =C78*$L16 -> 0 | E78: 0 | F78: =E78*$L16 -> 0 | G78: 0 | H78: =G78*$L16 -> 0 | I78: 0 | J78: =I78*$L16 -> 0 | K78: 0 | L78: =K78*$L16 -> 0 | M78: 0 | N78: =M78*$L16*1.5 -> 0 | O78: 0 | P78: =O78*$L16 -> 0 | Q78: 0 | R78: =Q78*$L16 -> 0 | S78: 0 | T78: =S78*$L16 -> 0 | U78: 0 | V78: =U78*$L16 -> 0 | W78: 0 | X78: =W78*$L16 -> 0 | Y78: 0 | Z78: =Y78*$L16*1.5 -> 0 | AA78: =D78+F78+H78+J78+L78+N78+P78+R78+T78+V78+X78+Z78 -> 0
B79: =C$17 -> Gerente de administración | C79: 1 | D79: =C79*$L17 -> 2438618.6 | E79: 1 | F79: =E79*$L17 -> 2438618.6 | G79: 1 | H79: =G79*$L17 -> 2438618.6 | I79: 1 | J79: =I79*$L17 -> 2438618.6 | K79: 1 | L79: =K79*$L17 -> 2438618.6 | M79: 1 | N79: =M79*$L17*1.5 -> 3657927.9 | O79: 1 | P79: =O79*$L17 -> 2438618.6 | Q79: 1 | R79: =Q79*$L17 -> 2438618.6 | S79: 1 | T79: =S79*$L17 -> 2438618.6 | U79: 1 | V79: =U79*$L17 -> 2438618.6 | W79: 1 | X79: =W79*$L17 -> 2438618.6 | Y79: 1 | Z79: =Y79*$L17*1.5 -> 3657927.9 | AA79: =D79+F79+H79+J79+L79+N79+P79+R79+T79+V79+X79+Z79 -> 31702041
B80: =C$18 -> Jefe de compras | C80: 0 | D80: =C80*$L18 -> 0 | E80: 0 | F80: =E80*$L18 -> 0 | G80: 0 | H80: =G80*$L18 -> 0 | I80: 0 | J80: =I80*$L18 -> 0 | K80: 0 | L80: =K80*$L18 -> 0 | M80: 0 | N80: =M80*$L18*1.5 -> 0 | O80: 0 | P80: =O80*$L18 -> 0 | Q80: 0 | R80: =Q80*$L18 -> 0 | S80: 0 | T80: =S80*$L18 -> 0 | U80: 0 | V80: =U80*$L18 -> 0 | W80: 0 | X80: =W80*$L18 -> 0 | Y80: 0 | Z80: =Y80*$L18*1.5 -> 0 | AA80: =D80+F80+H80+J80+L80+N80+P80+R80+T80+V80+X80+Z80 -> 0
B81: =C$19 -> Jefe de finanzas | C81: 0 | D81: =C81*$L19 -> 0 | E81: 0 | F81: =E81*$L19 -> 0 | G81: 0 | H81: =G81*$L19 -> 0 | I81: 0 | J81: =I81*$L19 -> 0 | K81: 0 | L81: =K81*$L19 -> 0 | M81: 0 | N81: =M81*$L19*1.5 -> 0 | O81: 0 | P81: =O81*$L19 -> 0 | Q81: 0 | R81: =Q81*$L19 -> 0 | S81: 0 | T81: =S81*$L19 -> 0 | U81: 0 | V81: =U81*$L19 -> 0 | W81: 0 | X81: =W81*$L19 -> 0 | Y81: 0 | Z81: =Y81*$L19*1.5 -> 0 | AA81: =D81+F81+H81+J81+L81+N81+P81+R81+T81+V81+X81+Z81 -> 0
B82: =C20 -> Jefe de ventas | C82: 0 | D82: =C82*$L20 -> 0 | E82: 0 | F82: =E82*$L20 -> 0 | G82: 0 | H82: =G82*$L20 -> 0 | I82: 0 | J82: =I82*$L20 -> 0 | K82: 0 | L82: =K82*$L20 -> 0 | M82: 0 | N82: =M82*$L20*1.5 -> 0 | O82: 0 | P82: =O82*$L20 -> 0 | Q82: 0 | R82: =Q82*$L20 -> 0 | S82: 0 | T82: =S82*$L20 -> 0 | U82: 0 | V82: =U82*$L20 -> 0 | W82: 0 | X82: =W82*$L20 -> 0 | Y82: 0 | Z82: =Y82*$L20*1.5 -> 0 | AA82: =D82+F82+H82+J82+L82+N82+P82+R82+T82+V82+X82+Z82 -> 0
B83: =C21 -> Jefe de RRHH | C83: 0 | D83: =C83*$L21 -> 0 | E83: 0 | F83: =E83*$L21 -> 0 | G83: 0 | H83: =G83*$L21 -> 0 | I83: 0 | J83: =I83*$L21 -> 0 | K83: 0 | L83: =K83*$L21 -> 0 | M83: 0 | N83: =M83*$L21*1.5 -> 0 | O83: 0 | P83: =O83*$L21 -> 0 | Q83: 0 | R83: =Q83*$L21 -> 0 | S83: 0 | T83: =S83*$L21 -> 0 | U83: 0 | V83: =U83*$L21 -> 0 | W83: 0 | X83: =W83*$L21 -> 0 | Y83: 0 | Z83: =Y83*$L21*1.5 -> 0 | AA83: =D83+F83+H83+J83+L83+N83+P83+R83+T83+V83+X83+Z83 -> 0
B84: =C22 -> Subjefe de ventas | C84: 0 | D84: =C84*$L22 -> 0 | E84: 0 | F84: =E84*$L22 -> 0 | G84: 0 | H84: =G84*$L22 -> 0 | I84: 0 | J84: =I84*$L22 -> 0 | K84: 0 | L84: =K84*$L22 -> 0 | M84: 0 | N84: =M84*$L22*1.5 -> 0 | O84: 0 | P84: =O84*$L22 -> 0 | Q84: 0 | R84: =Q84*$L22 -> 0 | S84: 0 | T84: =S84*$L22 -> 0 | U84: 0 | V84: =U84*$L22 -> 0 | W84: 0 | X84: =W84*$L22 -> 0 | Y84: 0 | Z84: =Y84*$L22*1.5 -> 0 | AA84: =D84+F84+H84+J84+L84+N84+P84+R84+T84+V84+X84+Z84 -> 0
B85: =C23 -> Analista contable | C85: 0 | D85: =C85*$L23 -> 0 | E85: 0 | F85: =E85*$L23 -> 0 | G85: 0 | H85: =G85*$L23 -> 0 | I85: 0 | J85: =I85*$L23 -> 0 | K85: 0 | L85: =K85*$L23 -> 0 | M85: 0 | N85: =M85*$L23*1.5 -> 0 | O85: 0 | P85: =O85*$L23 -> 0 | Q85: 0 | R85: =Q85*$L23 -> 0 | S85: 0 | T85: =S85*$L23 -> 0 | U85: 0 | V85: =U85*$L23 -> 0 | W85: 0 | X85: =W85*$L23 -> 0 | Y85: 0 | Z85: =Y85*$L23*1.5 -> 0 | AA85: =D85+F85+H85+J85+L85+N85+P85+R85+T85+V85+X85+Z85 -> 0
B86: =C24 -> Analista de compras | C86: 0 | D86: =C86*$L24 -> 0 | E86: 0 | F86: =E86*$L24 -> 0 | G86: 0 | H86: =G86*$L24 -> 0 | I86: 0 | J86: =I86*$L24 -> 0 | K86: 0 | L86: =K86*$L24 -> 0 | M86: 0 | N86: =M86*$L24*1.5 -> 0 | O86: 0 | P86: =O86*$L24 -> 0 | Q86: 0 | R86: =Q86*$L24 -> 0 | S86: 0 | T86: =S86*$L24 -> 0 | U86: 0 | V86: =U86*$L24 -> 0 | W86: 0 | X86: =W86*$L24 -> 0 | Y86: 0 | Z86: =Y86*$L24*1.5 -> 0 | AA86: =D86+F86+H86+J86+L86+N86+P86+R86+T86+V86+X86+Z86 -> 0
B87: =C25 -> Administrativo de ventas | C87: 0 | D87: =C87*$L25 -> 0 | E87: 0 | F87: =E87*$L25 -> 0 | G87: 0 | H87: =G87*$L25 -> 0 | I87: 0 | J87: =I87*$L25 -> 0 | K87: 0 | L87: =K87*$L25 -> 0 | M87: 0 | N87: =M87*$L25*1.5 -> 0 | O87: 0 | P87: =O87*$L25 -> 0 | Q87: 0 | R87: =Q87*$L25 -> 0 | S87: 0 | T87: =S87*$L25 -> 0 | U87: 0 | V87: =U87*$L25 -> 0 | W87: 0 | X87: =W87*$L25 -> 0 | Y87: 0 | Z87: =Y87*$L25*1.5 -> 0 | AA87: =D87+F87+H87+J87+L87+N87+P87+R87+T87+V87+X87+Z87 -> 0
B88: =C26 -> Administrativo contable | C88: 0 | D88: =C88*$L26 -> 0 | E88: 0 | F88: =E88*$L26 -> 0 | G88: 0 | H88: =G88*$L26 -> 0 | I88: 0 | J88: =I88*$L26 -> 0 | K88: 0 | L88: =K88*$L26 -> 0 | M88: 0 | N88: =M88*$L26*1.5 -> 0 | O88: 0 | P88: =O88*$L26 -> 0 | Q88: 0 | R88: =Q88*$L26 -> 0 | S88: 0 | T88: =S88*$L26 -> 0 | U88: 0 | V88: =U88*$L26 -> 0 | W88: 0 | X88: =W88*$L26 -> 0 | Y88: 0 | Z88: =Y88*$L26*1.5 -> 0 | AA88: =D88+F88+H88+J88+L88+N88+P88+R88+T88+V88+X88+Z88 -> 0
B89: =C27 -> Administrativo de cobranzas | C89: 0 | D89: =C89*$L27 -> 0 | E89: 0 | F89: =E89*$L27 -> 0 | G89: 0 | H89: =G89*$L27 -> 0 | I89: 0 | J89: =I89*$L27 -> 0 | K89: 0 | L89: =K89*$L27 -> 0 | M89: 0 | N89: =M89*$L27*1.5 -> 0 | O89: 0 | P89: =O89*$L27 -> 0 | Q89: 0 | R89: =Q89*$L27 -> 0 | S89: 0 | T89: =S89*$L27 -> 0 | U89: 0 | V89: =U89*$L27 -> 0 | W89: 0 | X89: =W89*$L27 -> 0 | Y89: 0 | Z89: =Y89*$L27*1.5 -> 0 | AA89: =D89+F89+H89+J89+L89+N89+P89+R89+T89+V89+X89+Z89 -> 0
B90: =C28 -> Administrativo de compras | C90: 0 | D90: =C90*$L28 -> 0 | E90: 0 | F90: =E90*$L28 -> 0 | G90: 0 | H90: =G90*$L28 -> 0 | I90: 0 | J90: =I90*$L28 -> 0 | K90: 0 | L90: =K90*$L28 -> 0 | M90: 0 | N90: =M90*$L28*1.5 -> 0 | O90: 0 | P90: =O90*$L28 -> 0 | Q90: 0 | R90: =Q90*$L28 -> 0 | S90: 0 | T90: =S90*$L28 -> 0 | U90: 0 | V90: =U90*$L28 -> 0 | W90: 0 | X90: =W90*$L28 -> 0 | Y90: 0 | Z90: =Y90*$L28*1.5 -> 0 | AA90: =D90+F90+H90+J90+L90+N90+P90+R90+T90+V90+X90+Z90 -> 0
B91: =C29 -> Administrativo de pagos | C91: 0 | D91: =C91*$L29 -> 0 | E91: 0 | F91: =E91*$L29 -> 0 | G91: 0 | H91: =G91*$L29 -> 0 | I91: 0 | J91: =I91*$L29 -> 0 | K91: 0 | L91: =K91*$L29 -> 0 | M91: 0 | N91: =M91*$L29*1.5 -> 0 | O91: 0 | P91: =O91*$L29 -> 0 | Q91: 0 | R91: =Q91*$L29 -> 0 | S91: 0 | T91: =S91*$L29 -> 0 | U91: 0 | V91: =U91*$L29 -> 0 | W91: 0 | X91: =W91*$L29 -> 0 | Y91: 0 | Z91: =Y91*$L29*1.5 -> 0 | AA91: =D91+F91+H91+J91+L91+N91+P91+R91+T91+V91+X91+Z91 -> 0
B92: =C30 -> Administrativo de RRHH | C92: 0 | D92: =C92*$L30 -> 0 | E92: 0 | F92: =E92*$L30 -> 0 | G92: 0 | H92: =G92*$L30 -> 0 | I92: 0 | J92: =I92*$L30 -> 0 | K92: 0 | L92: =K92*$L30 -> 0 | M92: 0 | N92: =M92*$L30*1.5 -> 0 | O92: 0 | P92: =O92*$L30 -> 0 | Q92: 0 | R92: =Q92*$L30 -> 0 | S92: 0 | T92: =S92*$L30 -> 0 | U92: 0 | V92: =U92*$L30 -> 0 | W92: 0 | X92: =W92*$L30 -> 0 | Y92: 0 | Z92: =Y92*$L30*1.5 -> 0 | AA92: =D92+F92+H92+J92+L92+N92+P92+R92+T92+V92+X92+Z92 -> 0
B93: =C31 -> Auxiliar administrativo | C93: 0 | D93: =C93*$L31 -> 0 | E93: 0 | F93: =E93*$L31 -> 0 | G93: 0 | H93: =G93*$L31 -> 0 | I93: 0 | J93: =I93*$L31 -> 0 | K93: 0 | L93: =K93*$L31 -> 0 | M93: 0 | N93: =M93*$L31*1.5 -> 0 | O93: 0 | P93: =O93*$L31 -> 0 | Q93: 0 | R93: =Q93*$L31 -> 0 | S93: 0 | T93: =S93*$L31 -> 0 | U93: 0 | V93: =U93*$L31 -> 0 | W93: 0 | X93: =W93*$L31 -> 0 | Y93: 0 | Z93: =Y93*$L31*1.5 -> 0 | AA93: =D93+F93+H93+J93+L93+N93+P93+R93+T93+V93+X93+Z93 -> 0
... B102: =C40 -> Diseñador de contenido | C102: 0 | D102: =C102*$L40 -> 0 | E102: 0 | F102: =E102*$L40 -> 0 | G102: 0 | H102: =G102*$L40 -> 0 | I102: 0 | J102: =I102*$L40 -> 0 | K102: 0 | L102: =K102*$L40 -> 0 | M102: 0 | N102: =M102*$L40*1.5 -> 0 | O102: 0 | P102: =O102*$L40 -> 0 | Q102: 0 | R102: =Q102*$L40 -> 0 | S102: 0 | T102: =S102*$L40 -> 0 | U102: 0 | V102: =U102*$L40 -> 0 | W102: 0 | X102: =W102*$L40 -> 0 | Y102: 0 | Z102: =Y102*$L40*1.5 -> 0 | AA102: =D102+F102+H102+J102+L102+N102+P102+R102+T102+V102+X102+Z102 -> 0
B103: =C$41 -> Asistente de marketing | C103: 0 | D103: =C103*$L41 -> 0 | E103: 0 | F103: =E103*$L41 -> 0 | G103: 0 | H103: =G103*$L41 -> 0 | I103: 0 | J103: =I103*$L41 -> 0 | K103: 0 | L103: =K103*$L41 -> 0 | M103: 0 | N103: =M103*$L41*1.5 -> 0 | O103: 0 | P103: =O103*$L41 -> 0 | Q103: 0 | R103: =Q103*$L41 -> 0 | S103: 0 | T103: =S103*$L41 -> 0 | U103: 0 | V103: =U103*$L41 -> 0 | W103: 0 | X103: =W103*$L41 -> 0 | Y103: 0 | Z103: =Y103*$L41*1.5 -> 0 | AA103: =D103+F103+H103+J103+L103+N103+P103+R103+T103+V103+X103+Z103 -> 0
B104: =C$42 -> Gerente de sistemas | C104: 1 | D104: =C104*$L42 -> 2682478.6 | E104: 1 | F104: =E104*$L42 -> 2682478.6 | G104: 1 | H104: =G104*$L42 -> 2682478.6 | I104: 1 | J104: =I104*$L42 -> 2682478.6 | K104: 1 | L104: =K104*$L42 -> 2682478.6 | M104: 1 | N104: =M104*$L42*1.5 -> 4023717.9 | O104: 1 | P104: =O104*$L42 -> 2682478.6 | Q104: 1 | R104: =Q104*$L42 -> 2682478.6 | S104: 1 | T104: =S104*$L42 -> 2682478.6 | U104: 1 | V104: =U104*$L42 -> 2682478.6 | W104: 1 | X104: =W104*$L42 -> 2682478.6 | Y104: 1 | Z104: =Y104*$L42*1.5 -> 4023717.9 | AA104: =D104+F104+H104+J104+L104+N104+P104+R104+T104+V104+X104+Z104 -> 34872221
B105: =C$43 -> DevOps | C105: 0 | D105: =C105*$L43 -> 0 | E105: 0 | F105: =E105*$L43 -> 0 | G105: 0 | H105: =G105*$L43 -> 0 | I105: 0 | J105: =I105*$L43 -> 0 | K105: 0 | L105: =K105*$L43 -> 0 | M105: 0 | N105: =M105*$L43*1.5 -> 0 | O105: 0 | P105: =O105*$L43 -> 0 | Q105: 0 | R105: =Q105*$L43 -> 0 | S105: 0 | T105: =S105*$L43 -> 0 | U105: 0 | V105: =U105*$L43 -> 0 | W105: 0 | X105: =W105*$L43 -> 0 | Y105: 0 | Z105: =Y105*$L43*1.5 -> 0 | AA105: =D105+F105+H105+J105+L105+N105+P105+R105+T105+V105+X105+Z105 -> 0
B106: =C$44 -> Arquitecto cloud | C106: 0 | D106: =C106*$L44 -> 0 | E106: 0 | F106: =E106*$L44 -> 0 | G106: 0 | H106: =G106*$L44 -> 0 | I106: 0 | J106: =I106*$L44 -> 0 | K106: 0 | L106: =K106*$L44 -> 0 | M106: 0 | N106: =M106*$L44*1.5 -> 0 | O106: 0 | P106: =O106*$L44 -> 0 | Q106: 0 | R106: =Q106*$L44 -> 0 | S106: 0 | T106: =S106*$L44 -> 0 | U106: 0 | V106: =U106*$L44 -> 0 | W106: 0 | X106: =W106*$L44 -> 0 | Y106: 0 | Z106: =Y106*$L44*1.5 -> 0 | AA106: =D106+F106+H106+J106+L106+N106+P106+R106+T106+V106+X106+Z106 -> 0
B107: =C$45 -> Especialista en hardware | C107: 0 | D107: =C107*$L45 -> 0 | E107: 0 | F107: =E107*$L45 -> 0 | G107: 0 | H107: =G107*$L45 -> 0 | I107: 0 | J107: =I107*$L45 -> 0 | K107: 0 | L107: =K107*$L45 -> 0 | M107: 0 | N107: =M107*$L45*1.5 -> 0 | O107: 0 | P107: =O107*$L45 -> 0 | Q107: 0 | R107: =Q107*$L45 -> 0 | S107: 0 | T107: =S107*$L45 -> 0 | U107: 0 | V107: =U107*$L45 -> 0 | W107: 0 | X107: =W107*$L45 -> 0 | Y107: 0 | Z107: =Y107*$L45*1.5 -> 0 | AA107: =D107+F107+H107+J107+L107+N107+P107+R107+T107+V107+X107+Z107 -> 0
B108: =C$46 -> Desarrollador backend SR | C108: 0 | D108: =C108*$L46 -> 0 | E108: 0 | F108: =E108*$L46 -> 0 | G108: 0 | H108: =G108*$L46 -> 0 | I108: 0 | J108: =I108*$L46 -> 0 | K108: 0 | L108: =K108*$L46 -> 0 | M108: 0 | N108: =M108*$L46*1.5 -> 0 | O108: 0 | P108: =O108*$L46 -> 0 | Q108: 0 | R108: =Q108*$L46 -> 0 | S108: 0 | T108: =S108*$L46 -> 0 | U108: 0 | V108: =U108*$L46 -> 0 | W108: 0 | X108: =W108*$L46 -> 0 | Y108: 0 | Z108: =Y108*$L46*1.5 -> 0 | AA108: =D108+F108+H108+J108+L108+N108+P108+R108+T108+V108+X108+Z108 -> 0
B109: =C47 -> Desarrollador frontend SR | C109: 0 | D109: =C109*$L47 -> 0 | E109: 0 | F109: =E109*$L47 -> 0 | G109: 0 | H109: =G109*$L47 -> 0 | I109: 0 | J109: =I109*$L47 -> 0 | K109: 0 | L109: =K109*$L47 -> 0 | M109: 0 | N109: =M109*$L47*1.5 -> 0 | O109: 0 | P109: =O109*$L47 -> 0 | Q109: 0 | R109: =Q109*$L47 -> 0 | S109: 0 | T109: =S109*$L47 -> 0 | U109: 0 | V109: =U109*$L47 -> 0 | W109: 0 | X109: =W109*$L47 -> 0 | Y109: 0 | Z109: =Y109*$L47*1.5 -> 0 | AA109: =D109+F109+H109+J109+L109+N109+P109+R109+T109+V109+X109+Z109 -> 0
B110: =C48 -> Coordinador tecnico | C110: 0 | D110: =C110*$L48 -> 0 | E110: 0 | F110: =E110*$L48 -> 0 | G110: 0 | H110: =G110*$L48 -> 0 | I110: 0 | J110: =I110*$L48 -> 0 | K110: 0 | L110: =K110*$L48 -> 0 | M110: 0 | N110: =M110*$L48*1.5 -> 0 | O110: 0 | P110: =O110*$L48 -> 0 | Q110: 0 | R110: =Q110*$L48 -> 0 | S110: 0 | T110: =S110*$L48 -> 0 | U110: 0 | V110: =U110*$L48 -> 0 | W110: 0 | X110: =W110*$L48 -> 0 | Y110: 0 | Z110: =Y110*$L48*1.5 -> 0 | AA110: =D110+F110+H110+J110+L110+N110+P110+R110+T110+V110+X110+Z110 -> 0
B111: =C49 -> Especialista en redes | C111: 0 | D111: =C111*$L49 -> 0 | E111: 0 | F111: =E111*$L49 -> 0 | G111: 0 | H111: =G111*$L49 -> 0 | I111: 0 | J111: =I111*$L49 -> 0 | K111: 0 | L111: =K111*$L49 -> 0 | M111: 0 | N111: =M111*$L49*1.5 -> 0 | O111: 0 | P111: =O111*$L49 -> 0 | Q111: 0 | R111: =Q111*$L49 -> 0 | S111: 0 | T111: =S111*$L49 -> 0 | U111: 0 | V111: =U111*$L49 -> 0 | W111: 0 | X111: =W111*$L49 -> 0 | Y111: 0 | Z111: =Y111*$L49*1.5 -> 0 | AA111: =D111+F111+H111+J111+L111+N111+P111+R111+T111+V111+X111+Z111 -> 0
B112: =C50 -> Tecnico instalador tecnología | C112: 0 | D112: =C112*$L50 -> 0 | E112: 0 | F112: =E112*$L50 -> 0 | G112: 0 | H112: =G112*$L50 -> 0 | I112: 0 | J112: =I112*$L50 -> 0 | K112: 0 | L112: =K112*$L50 -> 0 | M112: 0 | N112: =M112*$L50*1.5 -> 0 | O112: 0 | P112: =O112*$L50 -> 0 | Q112: 0 | R112: =Q112*$L50 -> 0 | S112: 0 | T112: =S112*$L50 -> 0 | U112: 0 | V112: =U112*$L50 -> 0 | W112: 0 | X112: =W112*$L50 -> 0 | Y112: 0 | Z112: =Y112*$L50*1.5 -> 0 | AA112: =D112+F112+H112+J112+L112+N112+P112+R112+T112+V112+X112+Z112 -> 0
B113: =C51 -> Soporte tecnico | C113: 0 | D113: =C113*$L51 -> 0 | E113: 0 | F113: =E113*$L51 -> 0 | G113: 0 | H113: =G113*$L51 -> 0 | I113: 0 | J113: =I113*$L51 -> 0 | K113: 0 | L113: =K113*$L51 -> 0 | M113: 0 | N113: =M113*$L51*1.5 -> 0 | O113: 0 | P113: =O113*$L51 -> 0 | Q113: 0 | R113: =Q113*$L51 -> 0 | S113: 0 | T113: =S113*$L51 -> 0 | U113: 0 | V113: =U113*$L51 -> 0 | W113: 0 | X113: =W113*$L51 -> 0 | Y113: 0 | Z113: =Y113*$L51*1.5 -> 0 | AA113: =D113+F113+H113+J113+L113+N113+P113+R113+T113+V113+X113+Z113 -> 0
B114: =C52 -> QA | C114: 0 | D114: =C114*$L52 -> 0 | E114: 0 | F114: =E114*$L52 -> 0 | G114: 0 | H114: =G114*$L52 -> 0 | I114: 0 | J114: =I114*$L52 -> 0 | K114: 0 | L114: =K114*$L52 -> 0 | M114: 0 | N114: =M114*$L52*1.5 -> 0 | O114: 0 | P114: =O114*$L52 -> 0 | Q114: 0 | R114: =Q114*$L52 -> 0 | S114: 0 | T114: =S114*$L52 -> 0 | U114: 0 | V114: =U114*$L52 -> 0 | W114: 0 | X114: =W114*$L52 -> 0 | Y114: 0 | Z114: =Y114*$L52*1.5 -> 0 | AA114: =D114+F114+H114+J114+L114+N114+P114+R114+T114+V114+X114+Z114 -> 0
B115: =C53 -> Auxiliar tecnico | C115: 0 | D115: =C115*$L53 -> 0 | E115: 0 | F115: =E115*$L53 -> 0 | G115: 0 | H115: =G115*$L53 -> 0 | I115: 0 | J115: =I115*$L53 -> 0 | K115: 0 | L115: =K115*$L53 -> 0 | M115: 0 | N115: =M115*$L53*1.5 -> 0 | O115: 0 | P115: =O115*$L53 -> 0 | Q115: 0 | R115: =Q115*$L53 -> 0 | S115: 0 | T115: =S115*$L53 -> 0 | U115: 0 | V115: =U115*$L53 -> 0 | W115: 0 | X115: =W115*$L53 -> 0 | Y115: 0 | Z115: =Y115*$L53*1.5 -> 0 | AA115: =D115+F115+H115+J115+L115+N115+P115+R115+T115+V115+X115+Z115 -> 0
B116: =C54 -> Gerente de servicio tecnico | C116: 0 | D116: =C116*$L54 -> 0 | E116: 0 | F116: =E116*$L54 -> 0 | G116: 0 | H116: =G116*$L54 -> 0 | I116: 0 | J116: =I116*$L54 -> 0 | K116: 0 | L116: =K116*$L54 -> 0 | M116: 0 | N116: =M116*$L54*1.5 -> 0 | O116: 0 | P116: =O116*$L54 -> 0 | Q116: 0 | R116: =Q116*$L54 -> 0 | S116: 0 | T116: =S116*$L54 -> 0 | U116: 0 | V116: =U116*$L54 -> 0 | W116: 0 | X116: =W116*$L54 -> 0 | Y116: 0 | Z116: =Y116*$L54*1.5 -> 0 | AA116: =D116+F116+H116+J116+L116+N116+P116+R116+T116+V116+X116+Z116 -> 0
B117: =C55 -> Coordinador tecnico | C117: 0 | D117: =C117*$L55 -> 0 | E117: 0 | F117: =E117*$L55 -> 0 | G117: 0 | H117: =G117*$L55 -> 0 | I117: 0 | J117: =I117*$L55 -> 0 | K117: 0 | L117: =K117*$L55 -> 0 | M117: 0 | N117: =M117*$L55*1.5 -> 0 | O117: 0 | P117: =O117*$L55 -> 0 | Q117: 0 | R117: =Q117*$L55 -> 0 | S117: 0 | T117: =S117*$L55 -> 0 | U117: 0 | V117: =U117*$L55 -> 0 | W117: 0 | X117: =W117*$L55 -> 0 | Y117: 0 | Z117: =Y117*$L55*1.5 -> 0 | AA117: =D117+F117+H117+J117+L117+N117+P117+R117+T117+V117+X117+Z117 -> 0
...

Sheet Mod. egresos
F1: Modelo de egresos
B3: Evolución de la participación
B4: 2026 | C4: 2027 | D4: 2028
B5: =Hipótesis!C24 -> 0.02 | C5: =Hipótesis!C25 -> 0.06 | D5: =Hipótesis!C26 -> 0.1
B6: =Hipótesis!D24 -> 102480000 | C6: =Hipótesis!D25 -> 307440000 | D6: =Hipótesis!D26 -> 512400000
B8: Costos totales
B9: 2026 | C9: 2027 | D9: 2028
A10: Costos Fijos | B10: ='Costos fijos'!$G$5 -> 26772000 | C10: ='Costos fijos'!$H$5 -> 30638000 | D10: ='Costos fijos'!$I$5 -> 37452000
A11: Costos variables | B11: ='Costos variables'!$H$6 -> 32918375 | C11: ='Costos variables'!$I$6 -> 59495000 | D11: ='Costos variables'!$J$6 -> 87758125
A12: Costos de RRHH | B12: ='Costos RRHH'!$H$6 -> 77670014 | C12: ='Costos RRHH'!$I$6 -> 1.4973145e+08 | D12: ='Costos RRHH'!$J$6 -> 2.2191489e+08
A13: Costos totales | B13: =SUM(B9:B12) -> 1.3736241e+08 | C13: =SUM(C9:C12) -> 2.3986648e+08 | D13: =SUM(D9:D12) -> 3.4712705e+08
A14: Objetivo ingresos | B14: =+'Mod. ingresos'!C30 -> 109050000 | C14: =+'Mod. ingresos'!D30 -> 281700000 | D14: =+'Mod. ingresos'!E30 -> 536880000

Sheet Mod. inversión
F1: Modelo de inversión
B3: Evolución de la participación | G3: Modelo de Inversión
B4: 2026 | C4: 2027 | D4: 2028 | G4: Inversión Inicial | H4: 2026 | I4: 2027 | J4: 2028
B5: =Hipótesis!$C$24 -> 0.02 | C5: =Hipótesis!$C$25 -> 0.06 | D5: =Hipótesis!$C$26 -> 0.1 | G5: =$E$28 -> 18499000 | H5: =$E$45 -> 800000 | I5: =$E$63 -> 1864000 | J5: =$E$81 -> 4264000
B6: =Hipótesis!$D$24 -> 102480000 | C6: =Hipótesis!$D$25 -> 307440000 | D6: =Hipótesis!$D$26 -> 512400000
B9: Inversión inicial - Año cero
B10: Concepto | C10: Cantidad | D10: Precio unitario | E10: Subtotal | F10: Referencia
B11: Notebooks | C11: 3 | D11: 800000 | E11: =C11*D11 -> 2400000 | F11: Notebook Hp 255 G10 Amd Ryzen 5 7520u 16gb Ram 512gb Ssd 15.6 Full Hd Gráficos Integrados Radeon 610m
B12: Escritorios | C12: 2 | D12: 100000 | E12: =C12*D12 -> 200000
B13: Sillas de escritorio | C13: 4 | D13: 82000 | E13: =C13*D13 -> 328000
B14: Sensores temperatura | C14: 30 | D14: 12500 | E14: =C14*D14 -> 375000
B15: Sensores puertas | C15: 30 | D15: 10000 | E15: =C15*D15 -> 300000
B16: Sensores humedad | C16: 30 | D16: 14000 | E16: =C16*D16 -> 420000
B17: Sensores geolocalizacion | C17: 30 | D17: 10000 | E17: =C17*D17 -> 300000
B18: Sensores motor refrigeración | C18: 30 | D18: 15000 | E18: =C18*D18 -> 450000
B19: Unidad central | C19: 5 | D19: 30000 | E19: =C19*D19 -> 150000
B20: Sistema | C20: 1 | D20: 13576000 | E20: =C20*D20 -> 13576000
B28: Total | E28: =SUM(E11:E27) -> 18499000
B30: Inversión - Año 2026
B31: Concepto | C31: Cantidad | D31: Precio unitario | E31: Subtotal
B32: Notebooks | C32: 1 | D32: 800000 | E32: =C32*D32 -> 800000
B33: Escritorios | C33: 0 | D33: 100000 | E33: =C33*D33 -> 0
B34: Sillas de escritorio | C34: 0 | D34: 82000 | E34: =C34*D34 -> 0
B35: Sensores temperatura | C35: 0 | D35: 12500 | E35: =C35*D35 -> 0
B36: Sensores puertas | C36: 0 | D36: 10000 | E36: =C36*D36 -> 0
B37: Sensores humedad | C37: 0 | D37: 14000 | E37: =C37*D37 -> 0
B38: Sensores geolocalizacion | C38: 0 | D38: 10000 | E38: =C38*D38 -> 0
B39: Sensores motor refrigeración | C39: 0 | D39: 15000 | E39: =C39*D39 -> 0
B40: Unidad central | C40: 0 | D40: 30000 | E40: =C40*D40 -> 0
B41: Sistema | C41: 0 | D41: 13576000 | E41: =C41*D41 -> 0
B45: Total | E45: =SUM(E32:E44) -> 800000
B48: Inversión - Año 2027
B49: Concepto | C49: Cantidad | D49: Precio unitario | E49: Subtotal
B50: Notebooks | C50: 2 | D50: 800000 | E50: =C50*D50 -> 1600000
B51: Escritorios | C51: 1 | D51: 100000 | E51: =C51*D51 -> 100000
B52: Sillas de escritorio | C52: 2 | D52: 82000 | E52: =C52*D52 -> 164000
B53: Sensores temperatura | C53: 0 | D53: 12500 | E53: =C53*D53 -> 0
B54: Sensores puertas | C54: 0 | D54: 10000 | E54: =C54*D54 -> 0
B55: Sensores humedad | C55: 0 | D55: 14000 | E55: =C55*D55 -> 0
B56: Sensores geolocalizacion | C56: 0 | D56: 10000 | E56: =C56*D56 -> 0
B57: Sensores motor refrigeración | C57: 0 | D57: 15000 | E57: =C57*D57 -> 0
B58: Unidad central | C58: 0 | D58: 30000 | E58: =C58*D58 -> 0
B59: Sistema | C59: 0 | D59: 13576000 | E59: =C59*D59 -> 0
B63: Total | E63: =SUM(E50:E62) -> 1864000
B66: Inversión - Año 2028
B67: Concepto | C67: Cantidad | D67: Precio unitario | E67: Subtotal
B68: Notebooks | C68: 5 | D68: 800000 | E68: =C68*D68 -> 4000000
B69: Escritorios | C69: 1 | D69: 100000 | E69: =C69*D69 -> 100000
B70: Sillas de escritorio | C70: 2 | D70: 82000 | E70: =C70*D70 -> 164000
B71: Sensores temperatura | C71: 0 | D71: 12500 | E71: =C71*D71 -> 0
B72: Sensores puertas | C72: 0 | D72: 10000 | E72: =C72*D72 -> 0
B73: Sensores humedad | C73: 0 | D73: 14000 | E73: =C73*D73 -> 0
B74: Sensores geolocalizacion | C74: 0 | D74: 10000 | E74: =C74*D74 -> 0
B75: Sensores motor refrigeración | C75: 0 | D75: 15000 | E75: =C75*D75 -> 0
B76: Unidad central | C76: 0 | D76: 30000 | E76: =C76*D76 -> 0
B77: Sistema | C77: 0 | D77: 13576000 | E77: =C77*D77 -> 0
B81: Total | E81: =SUM(E68:E80) -> 4264000

Sheet Amortizaciones
G1: Amortizaciones
B3: Evolución de la participación | I3: Amortizaciones
B4: 2025 | C4: 2026 | D4: 2027 | I4: 2025 | J4: 2026 | K4: 2027
B5: =Hipótesis!$C$24 -> 0.02 | C5: =Hipótesis!$C$25 -> 0.06 | D5: =Hipótesis!$C$26 -> 0.1 | I5: =$K$27 -> 852800 | J5: =$L$27 -> 1119466.7 | K5: =$M$27 -> 1671000
B6: =Hipótesis!$D$24 -> 102480000 | C6: =Hipótesis!D25 -> 307440000 | D6: =Hipótesis!D26 -> 512400000
B8: Amortizaciones
B9: Rubro | C9: Concepto | D9: Cantidad | E9: Precio unitario | F9: Amortización ( en años ) | G9: Valor de adquisiciones | K9: Amortización
G10: Año cero | H10: Año 2026 | I10: Año 2027 | J10: Año 2028 | K10: Año 2026 | L10: Año 2027 | M10: Año 2028
B11: Informática y comunicaciones | C11: Notebook | D11: ='Mod. inversión'!C11 -> 3 | E11: ='Mod. inversión'!D11 -> 800000 | F11: 3 | G11: =D11*E11 -> 2400000 | H11: 0 | I11: 0 | J11: 0 | K11: =$G$11/$F$11 -> 800000 | L11: =$G$11/$F$11 -> 800000 | M11: =$G$11/$F$11 -> 800000
C12: Notebook | D12: ='Mod. inversión'!C32 -> 1 | E12: ='Mod. inversión'!D32 -> 800000 | F12: 3 | G12: 0 | H12: =D12*E12 -> 800000 | I12: 0 | J12: 0 | K12: 0 | L12: =$H$12/$F$12 -> 266666.67 | M12: =$H$12/$F$12 -> 266666.67
C13: Notebook | D13: ='Mod. inversión'!C50 -> 2 | E13: ='Mod. inversión'!D50 -> 800000 | F13: 3 | G13: 0 | H13: 0 | I13: =D13*E13 -> 1600000 | J13: 0 | K13: 0 | L13: 0 | M13: =I13/F13 -> 533333.33
C14: Notebook | D14: ='Mod. inversión'!C68 -> 5 | E14: ='Mod. inversión'!D68 -> 800000 | F14: 3 | G14: 0 | H14: 0 | I14: 0 | J14: =D14*E14 -> 4000000 | K14: 0 | L14: 0 | M14: 0
B15: Muebles de oficina | C15: Escritorio de oficina | D15: ='Mod. inversión'!C12 -> 2 | E15: ='Mod. inversión'!D12 -> 100000 | F15: 10 | G15: =D15*E15 -> 200000 | H15: 0 | I15: 0 | J15: 0 | K15: =$G$15/$F$15 -> 20000 | L15: =$G$15/$F$15 -> 20000 | M15: =$G$15/$F$15 -> 20000
C16: Escritorio de oficina | D16: ='Mod. inversión'!C51 -> 1 | E16: ='Mod. inversión'!D51 -> 100000 | F16: 10 | G16: 0 | H16: 0 | I16: =D16*E16 -> 100000 | J16: 0 | K16: 0 | L16: 0 | M16: =I16/F16 -> 10000
C17: Escritorio de oficina | D17: ='Mod. inversión'!C69 -> 1 | E17: ='Mod. inversión'!D69 -> 100000 | F17: 10 | G17: 0 | H17: 0 | I17: 0 | J17: =D17*E17 -> 100000 | K17: 0 | L17: 0 | M17: 0
C18: Silla de escritorio | D18: ='Mod. inversión'!C13 -> 4 | E18: ='Mod. inversión'!D13 -> 82000 | F18: 10 | G18: =D18*E18 -> 328000 | H18: 0 | I18: 0 | J18: 0 | K18: =$G$18/$F$18 -> 32800 | L18: =$G$18/$F$18 -> 32800 | M18: =$G$18/$F$18 -> 32800
C19: Silla de escritorio | D19: ='Mod. inversión'!C51 -> 1 | E19: ='Mod. inversión'!D52 -> 82000 | F19: 10 | G19: 0 | H19: 0 | I19: =D19*E19 -> 82000 | J19: 0 | K19: 0 | L19: 0 | M19: =I19/F19 -> 8200
C20: Silla de escritorio | D20: ='Mod. inversión'!C70 -> 2 | E20: ='Mod. inversión'!D70 -> 82000 | F20: 10 | G20: 0 | H20: 0 | I20: 0 | J20: =D20*E20 -> 164000 | K20: 0 | L20: 0 | M20: 0
B21: Sensores y unidad de procesamiento | C21: Sensores temperatura | D21: 30 | E21: 12500 | F21: 3 | G21: =E21*D21 -> 375000 | H21: 0 | I21: 0 | J21: 0 | K21: =$G21/$F21 -> 125000 | L21: =$G21/$F21 -> 125000 | M21: =$G21/$F21 -> 125000
C22: Sensores puertas | D22: 30 | E22: 10000 | F22: 3 | G22: =E22*D22 -> 300000 | H22: 0 | I22: 0 | J22: 0 | K22: =$G22/$F22 -> 100000 | L22: =$G22/$F22 -> 100000 | M22: =$G22/$F22 -> 100000
C23: Sensores humedad | D23: 30 | E23: 14000 | F23: 3 | G23: =E23*D23 -> 420000 | H23: 0 | I23: 0 | J23: 0 | K23: =$G23/$F23 -> 140000 | L23: =$G23/$F23 -> 140000 | M23: =$G23/$F23 -> 140000
C24: Sensores geolocalizacion | D24: 30 | E24: 10000 | F24: 3 | G24: =E24*D24 -> 300000 | H24: 0 | I24: 0 | J24: 0 | K24: =$G24/$F24 -> 100000 | L24: =$G24/$F24 -> 100000 | M24: =$G24/$F24 -> 100000
C25: Sensores motor refrigeración | D25: 30 | E25: 15000 | F25: 3 | G25: =E25*D25 -> 450000 | H25: 0 | I25: 0 | J25: 0 | K25: =$G25/$F25 -> 150000 | L25: =$G25/$F25 -> 150000 | M25: =$G25/$F25 -> 150000
C26: Unidad central | D26: 5 | E26: 30000 | F26: 3 | G26: =E26*D26 -> 150000 | H26: 0 | I26: 0 | J26: 0 | K26: =$G26/$F26 -> 50000 | L26: =$G26/$F26 -> 50000 | M26: =$G26/$F26 -> 50000
B27: Totales | K27: =SUM(K11:K20) -> 852800 | L27: =SUM(L11:L20) -> 1119466.7 | M27: =SUM(M11:M20) -> 1671000

Sheet Presupuesto financiero
E1: Presupuesto financiero
K3: Evolución de la participación
K4: 2026 | L4: 2027 | M4: 2028
K5: =Hipótesis!$C$24 -> 0.02 | L5: =Hipótesis!$C$25 -> 0.06 | M5: =Hipótesis!$C$26 -> 0.1
K6: =Hipótesis!$D$24 -> 102480000 | L6: =Hipótesis!$D$25 -> 307440000 | M6: =Hipótesis!$D$26 -> 512400000
K8: Costos
K9: 2026 | L9: 2027 | M9: 2028
B10: Presupuesto financiero | J10: Costos fijos | K10: ='Costos fijos'!$G$5 -> 26772000 | L10: ='Costos fijos'!$H$5 -> 30638000 | M10: ='Costos fijos'!$I$5 -> 37452000
B11: Ejercicio | D11: 0 | E11: 2026 | F11: 2027 | G11: 2028 | J11: Costos variables | K11: ='Costos variables'!$H$6 -> 32918375 | L11: ='Costos variables'!$I$6 -> 59495000 | M11: ='Costos variables'!$J$6 -> 87758125
B12: Ingresos | D12: - | E12: =+'Mod. ingresos'!C30 -> 109050000 | F12: =+'Mod. ingresos'!D30 -> 281700000 | G12: =+'Mod. ingresos'!E30 -> 536880000 | J12: Costos de RRHH | K12: ='Costos RRHH'!$H$6 -> 77670014 | L12: ='Costos RRHH'!$I$6 -> 1.4973145e+08 | M12: ='Costos RRHH'!$J$6 -> 2.2191489e+08
B13: Egresos | C13: Costos fijos | D13: - | E13: =+'Mod. egresos'!B10 -> 26772000 | F13: =+'Mod. egresos'!C10 -> 30638000 | G13: =+'Mod. egresos'!D10 -> 37452000
C14: Costos variables | D14: - | E14: =+'Mod. egresos'!B11 -> 32918375 | F14: =+'Mod. egresos'!C11 -> 59495000 | G14: =+'Mod. egresos'!D11 -> 87758125 | K14: Amortizaciones
C15: Costos de RRHH | D15: - | E15: =+'Mod. egresos'!B12 -> 77670014 | F15: =+'Mod. egresos'!C12 -> 1.4973145e+08 | G15: =+'Mod. egresos'!D12 -> 2.2191489e+08 | K15: 2026 | L15: 2027 | M15: 2028
B16: Utilidad Antes de Impuestos (UAII) | D16: - | E16: =E12-E13-E14-E15 -> -28310389 | F16: =F12-F13-F14-F15 -> 41835549 | G16: =G12-G13-G14-G15 -> 1.8975498e+08 | K16: =Amortizaciones!$I$5 -> 852800 | L16: =Amortizaciones!$J$5 -> 1119466.7 | M16: =Amortizaciones!$K$5 -> 1671000
B17: Impuesto Ingresos Brutos (3%) (IIB) | D17: - | E17: =E12*0.03 -> 3271500 | F17: =F12*0.03 -> 8451000 | G17: =G12*0.03 -> 16106400
J18: Modelo de Inversión
B19: Impuesto a las ganancias (35%) (IIGG) | D19: - | E19: 0 | F19: 0 | G19: =M23*0.35 -> 11292779 | J19: Inversión Inicial | K19: 2026 | L19: 2027 | M19: 2028
B20: Utilidad despues de Impuestos (UDII) | D20: - | E20: =E16-E17-E19 -> -31581889 | F20: =F16-F17-F19 -> 33384549 | G20: =G16-G17-G19 -> 1.623558e+08 | J20: ='Mod. inversión'!$G$5 -> 18499000 | K20: ='Mod. inversión'!$H$5 -> 800000 | L20: ='Mod. inversión'!$I$5 -> 1864000 | M20: ='Mod. inversión'!$J$5 -> 4264000
B21: Inversión | D21: =-J20 -> -18499000 | E21: =-K20 -> -800000 | F21: =-L20 -> -1864000 | G21: =-M20 -> -4264000
B22: Flujo de Fondos (FF) | D22: =D21 -> -18499000 | E22: =E20+E21 -> -32381889 | F22: =F20+F21 -> 31520549 | G22: =G20+G21 -> 1.580918e+08 | K22: 2025 | L22: 2026 | M22: 2027 | N22: 2028
I23: Monto Imponible | L23: =E16-E17-K16 -> -32434689 | M23: =F16-F17-L16 -> 32265082 | N23: =G16-G17-M16 -> 1.7197758e+08
B24: Costo de promoción y publicidad | D24: - | E24: ='Costos variables'!H10 + 'Costos fijos'!G9 -> 16859000 | F24: ='Costos variables'!I10 + 'Costos fijos'!H9 -> 37046000 | G24: ='Costos variables'!J10 + 'Costos fijos'!I9 -> 58330000
B25: Costo de promocion relacionado con ventas | E25: =E24/E$12 -> 0.15459881 | F25: =F24/F12 -> 0.1315087 | G25: =G24/G12 -> 0.10864625
B27: Costos fijos relacionadoc con ingresos | E27: =E13/E$12 -> 0.24550206 | F27: =F13/F$12 -> 0.10876109 | G27: =G13/G$12 -> 0.069758605
B28: Costos variables relacionado con ingresos | E28: =E14/E$12 -> 0.30186497 | F28: =F14/F$12 -> 0.21119986 | G28: =G14/G$12 -> 0.16345948
B29: Costos de RRHH relacionado con ingresos | E29: =E15/E$12 -> 0.71224221 | F29: =F15/F$12 -> 0.53152805 | G29: =G15/G$12 -> 0.4133417
B31: Se recupera la inversión en el 3er año
F33: Tasa de Corte | G33: 0.75
F34: VAN | G34: {=NPV(G33,D22:G22)} -> 1592952.4
F35: TIR | G35: =IRR(D22:G22,G33) -> 0.80761755

Sheet Estructura
B2: Escalas Comunes
B4: Probabilidad (1 a 5):
B5: 1: Muy improbable
B6: 2: No es probable
B7: 3: Posible
B8: 4: Probable
B9: 5: Muy probable
B10: Impacto (1 a 5):
B11: 1: Insignificante
B12: 2: Menor
B13: 3: Moderado
B14: 4: Importante
... B21: Esto indica que el riesgo tiene un nivel moderado-alto y debe ser monitoreado y gestionado adecuadamente.
B23: Interpretación del Nivel de Riesgo | E23: Impacto \ Probabilidad | F23: Muy improbable (1) | G23: No es probable (2) | H23: Posible (3) | I23: Probable (4) | J23: Muy probable (5)
E24: Catastrófico (5)
B25: Bajo (1-6) : Riesgos que probablemente no sucederán o que, si lo hacen, no tendrán consecuencias significativas. | E25: Importante (4)
B26: Moderado (7-12) : Riesgos que pueden causar contratiempos en el proyecto, pero son manejables con medidas adecuadas. | E26: Moderado (3)
B27: Alto (13-20) : Riesgos que requieren atención inmediata y estrategias de mitigación rigurosas. | E27: Menor (2)
B28: Crítico (21-25) : Riesgos extremadamente altos que pueden poner en peligro la viabilidad del proyecto y requieren acciones urgentes. | E28: Insignificante (1)

Sheet Riesgos
B2: Posibles riesgos
B4: R1: Pérdida total de datos críticos
B5: R2: Retraso en la entrega del proyecto por problemas técnicos
B6: R3: Problemas de comunicación entre equipos
B7: R4: Fallo en la infraestructura tecnológica
B8: R5: Desviaciones en el presupuesto por incremento de costos de hardware o conectividad
B9: R6: Cambios en los requisitos del cliente durante la implementación
B10: R7: Problemas con proveedores de sensores o conectividad M2M
B11: R8: Cambios regulatorios o aduaneros que afecten la importación de equipos IoT
B12: R9: Incumplimiento de pago o baja anticipada de clientes
B13: R10: Interrupción del servicio por pérdida de conectividad móvil

Sheet Matriz de riesgos
B2: Riesgo | C2: Descripción | D2: Causas | E2: Efectos cuantitativos | F2: Efectos Cualitativos (en $) | G2: Probabilidad (1-5) | H2: Impacto (1-5) | I2: Nivel de Riesgo (P x I)
B3: R1 | C3: Pérdida total de datos críticos | D3: - Fallos en el sistema | E3: - vCostos de recuperación de datos y reinstalación de servicios: $500.000 | F3: -Deterioro de la reputación: $2000000 (costos de marketing para recuperar imagen) | G3: 4 | H3: 5 | I3: =+G3*H3 -> 20 | L3: Probabilidad (1 a 5): | M3: Impacto (1 a 5): | N3: Impacto \ Probabilidad | O3: Muy improbable (1) | P3: No es probable (2) | Q3: Posible (3) | R3: Probable (4) | S3: Muy probable (5)
D4: - Errores humanos | F4: - Pérdida de nuevos contratos por falta de confianza: $20000000 | G4: 4 | H4: 5 | I4: =+G4*H4 -> 20 | L4: 1: Muy improbable | M4: 1: Insignificante | N4: Catastrófico (5)
D5: - Ataques ciberneticos | F5: - Estrés y desmotivación del equipo: $12000000 (costos asociados a la rotación de personal) | G5: 4 | H5: 5 | I5: =+H5*G5 -> 20 | L5: 2: No es probable | M5: 2: Menor | N5: Importante (4)
B6: R2 | C6: Retraso en la entrega del proyecto | D6: - Problemas técnicos | E6: - Mayor coste de desarrollo $2500000 | F6: - Pérdida de nuevos contratos por demora en la salida: $10000000 | G6: 4 | H6: 4 | I6: =+G6*H6 -> 16 | L6: 3: Posible | M6: 3: Moderado | N6: Moderado (3)
D7: - Falta de recursos | F7: - Perdida de nuevos contratos por funcionalidad incompleta: $2500000 | G7: 4 | H7: 4 | I7: =+G7*H7 -> 16 | L7: 4: Probable | M7: 4: Importante | N7: Menor (2)
D8: - Demoras en pruebas | G8: 4 | H8: 4 | I8: =+H8*G8 -> 16 | L8: 5: Muy probable | M8: 5: Catastrófico
B9: R3 | C9: Problemas de comunicación entre equipos | D9: - Falta de canales claros | E9: - Perdida de productividad $150000 | G9: 4 | H9: 4 | I9: =+H9*G9 -> 16 | O9: Bajo (1-6) : Riesgos que probablemente no sucederán o que, si lo hacen, no tendrán consecuencias significativas.
D10: - Dispersión geográfica | F10: - Reduccion en la cohesion y en la dinámica del grupo $100000 | G10: 4 | H10: 4 | I10: =+H10*G10 -> 16 | O10: Moderado (7-12) : Riesgos que pueden causar contratiempos en el proyecto, pero son manejables con medidas adecuadas.
B11: R4 | C11: Fallo en la infraestructura tecnológica | D11: - Falta de mantenimiento | E11: - Reparación o substitución de equipos $700000 | F11: - Perdida de confianza con clientes $500000 | G11: 5 | H11: 5 | I11: =+H11*G11 -> 25 | O11: Alto (13-20) : Riesgos que requieren atención inmediata y estrategias de mitigación rigurosas.
D12: - Deterioro del servicio de nube | F12: - Deterioro de la imagen corporativa $100000 | G12: 5 | H12: 5 | I12: =+H12*G12 -> 25 | O12: Crítico (21-25) : Riesgos extremadamente altos que pueden poner en peligro la viabilidad del proyecto y requieren acciones urgentes.
B13: R2 | C13: Retraso en la entrega del proyecto por problemas técnicos | D13: - Fallos en el software o hardware | E13: - Incremento en los costos operativos: $30,000 | F13: - Insatisfacción del cliente: $25,000 (posibles pérdidas futuras por no repetir negocio) | G13: 3 | H13: 4 | I13: 12 | L13: 5: Muy probable | M13: 5: Catastrófico | N13: Insignificante (1)
D14: - Falta de capacitación del personal | F14: - Estrés adicional para el equipo: $5,000 (costos asociados a horas extra y agotamiento) | G14: 3 | H14: 3 | I14: =+G14*H14 -> 9
D15: - Caida completa del servicio de nube | E15: - Plataforma sin acceso $1000000 | F15: - Perdida de posibles contratos $3000000 | G15: 5 | H15: 5 | I15: =+H15*G15 -> 25
B16: R5 | C16: Desviaciones en el presupuesto | D16: - Aumento de precios en los sensores | E16: - Incremento en costos operativos $1200000 | F16: - Disminución de rentabilidad por instalación $1200000 | G16: 3 | H16: 4 | I16: =+H16*G16 -> 12
D17: - Aumento en el alcance inicial del proyecto | E17: - Aumento en costo inicial por desarrollo de proyecto $5000000 | G17: 3 | H17: 4 | I17: =+H17*G17 -> 12
B18: R6 | C18: Cambios en los requisitos del cliente | D18: - Solicutudes adicionales no previstas | E18: - Costos de desarrollo y retrabajo $2500000 | F18: - Deterioro de relación comercial $400000 | G18: 4 | H18: 4 | I18: =+G18*H18 -> 16
D19: - Falta de claridad en roles y responsabilidades | E19: - Costos adicionales por retrabajo: $8,000 | G19: 4 | H19: 3 | I19: =+G19*H19 -> 12
B20: R7 | C20: Problemas con proveedores | D20: - Fallos de calidad en sensores | E20: - Costo por reemplazo de sensores $5000000 | F20: - Impacto negativo en la experiencia del cliente $500000 | G20: 4 | H20: 5 | I20: =+H20*G20 -> 20
D21: - Fallas en las instalaciones/mantenimiento | E21: - Costo por reparación de instalacion $1500000 | G21: 4 | H21: 5 | I21: =+H21*G21 -> 20
B22: R8 | C22: Cambios regulatorios o aduaneros | D22: - Restricciones de importacion o nuevas normas SENASA/AFIP | E22: - Costos de adecuación o sustitución de hardware: $1500000 | F22: - Retrasos en entregas y perdida de contratos: $20000000 | G22: 5 | H22: 5 | I22: =+G22*H22 -> 25
B23: R9 | C23: Incumplimiento de pago de clientes | D23: - Crisis económica, mora o disconformidad | E23: - Falta de ingresos $15000000 | F23: - Afectación del flujo de caja y continuidad operativa $15000000 | G23: 3 | H23: 5 | I23: =+G23*H23 -> 15
B24: R10 | C24: Interrupción de conectividad | D24: - Fallas en red celular | E24: - Perdida de datos de los sensores $1500000 | F24: - Perdida de la sensación de "Real time" con los datos y el cliente. $3000000 (costos asociados a marketing para recuperar la confianza) | G24: 5 | H24: 5 | I24: =+H24*G24 -> 25
B25: R5 | C25: Desviaciones menores en el presupuesto | D25: - Cambios menores en los costos de materiales o servicios | E25: Aumento moderado en los costos totales del proyecto: $6,000 | F25: - Preocupación leve entre los stakeholders: $2,000 (costos asociados a reuniones adicionales) | G25: 3 | H25: 2 | I25: =+G25*H25 -> 6
D26: - Errores en las estimaciones iniciales | E26: - Posible necesidad de reprogramar recursos financieros: $5,000 | F26: - Necesidad de ajustes menores en la planificación: $3,000 | G26: 3 | H26: 3 | I26: =+G26*H26 -> 9
B27: R6 | C27: Cambios en los requisitos del cliente | D27: - Falta de claridad inicial sobre los requisitos | E27: - Costos adicionales para implementar cambios: $20,000 | F27: - Frustración del cliente si no se gestionan adecuadamente los cambios: $15,000 (posibilidad de pérdida futura de contratos) | G27: 3 | H27: 4 | I27: 12
D28: - Cambios estratégicos por parte del cliente durante el proyecto | E28: - Retrasos en el cronograma debido a revisión necesaria: $10,000 | F28: - Impacto potencial en la relación con el cliente: $10,000 | G28: 3 | H28: 3 | I28: =+G28*H28 -> 9
B29: R7 | C29: Problemas menores con proveedores | D29: - Retrasos en entregas por parte del proveedor | E29: - Costos adicionales por buscar proveedores alternativos o compensar retrasos: $5,000 | G29: 1 | H29: 2 | I29: 2
D30: - Problemas de calidad con los suministros recibidos | F30: - Inconvenientes menores que pueden afectar temporalmente el flujo del proyecto: $1,500

Sheet Cuadro de evaluación de riesgos
C3: Impacto \ Probabilidad | D3: Muy improbable (1) | E3: No es probable (2) | F3: Posible (3) | G3: Probable (4) | H3: Muy probable (5)
C4: Catastrófico (5) | F4: R9 | G4: R1 - R4 - R7 | H4: R4 - R8 - R10 | K4: Bajo (1-6) : Riesgos que probablemente no sucederán o que, si lo hacen, no tendrán consecuencias significativas.
C5: Importante (4) | F5: R5 | G5: R2 - R3 - R6 | K5: Moderado (7-12) : Riesgos que pueden causar contratiempos en el proyecto, pero son manejables con medidas adecuadas.
C6: Moderado (3) | K6: Alto (13-20) : Riesgos que requieren atención inmediata y estrategias de mitigación rigurosas.
C7: Menor (2) | K7: Crítico (21-25) : Riesgos extremadamente altos que pueden poner en peligro la viabilidad del proyecto y requieren acciones urgentes.
C8: Insignificante (1)

Sheet Escenario 1
B2: Presupuesto financiero
B3: Ejercicio | D3: Inicio | E3: 2025 | F3: 2026 | G3: 2027 | I3: RIESGO: Fallo en la infraestructura tecnológica
B4: Ingresos | D4: - | E4: ='Presupuesto financiero'!E12 -> 109050000 | F4: ='Presupuesto financiero'!F12 -> 281700000 | G4: ='Presupuesto financiero'!G12 - 30000000 -> 506880000 | I4: R 4 | J4: - Caida completa del servicio de nube | K4: - Plataforma sin acceso $1000000 | L4: - Perdida de posibles contratos $3000000
B5: Egresos | C5: Costos fijos | D5: - | E5: ='Presupuesto financiero'!E13 -> 26772000 | F5: ='Presupuesto financiero'!F13 -> 30638000 | G5: ='Presupuesto financiero'!G13 -> 37452000
C6: Costos variables | D6: - | E6: ='Presupuesto financiero'!E14 -> 32918375 | F6: ='Presupuesto financiero'!F14 + 1000000 -> 60495000 | G6: ='Presupuesto financiero'!G14 -> 87758125
C7: Costos de RRHH | D7: - | E7: ='Presupuesto financiero'!E15 -> 77670014 | F7: ='Presupuesto financiero'!F15 -> 1.4973145e+08 | G7: ='Presupuesto financiero'!G15 -> 2.2191489e+08 | K7: Año 2 | L7: Año 3
B8: Utilidad Antes de Impuestos (UAII) | D8: - | E8: =+E4-E5-E6-E7 -> -28310389 | F8: =+F4-F5-F6-F7 -> 40835549 | G8: =+G4-G5-G6-G7 -> 1.5975498e+08
B9: Impuesto Ingresos Brutos | C9: 0.03 | D9: - | E9: =+E4*C9 -> 3271500 | F9: =+F4*C9 -> 8451000 | G9: =+G4*C9 -> 15206400
B10: Impuesto a las ganancias 35% | E10: ='Presupuesto financiero'!E19 -> 0 | F10: ='Presupuesto financiero'!F19 -> 0 | G10: ='Presupuesto financiero'!G19 -> 11292779
B12: Utilidad despues de Impuestos (UDII) | D12: - | E12: =+E8-E9-E10-E11 -> -31581889 | F12: =+F8-F9-F10-F11 -> 32384549 | G12: =+G8-G9-G10-G11 -> 1.332558e+08
B13: Inversión | D13: ='Mod. inversión'!E28 -> 18499000 | E13: ='Mod. inversión'!E45 -> 800000 | F13: ='Mod. inversión'!E63 -> 1864000 | G13: ='Mod. inversión'!E81 -> 4264000
B14: Flujo de Fondos (FF) | D14: =+D13*-1 -> -18499000 | E14: =+E12-E13 -> -32381889 | F14: =+F12-F13 -> 30520549 | G14: =+G12-G13 -> 1.289918e+08
E18: Tasa de Corte | F18: ='Presupuesto financiero'!G33 -> 0.75
E19: VAN | F19: {=+NPV(F18,D14:G14)} -> -1696343.7
E20: TIR | F20: =IRR(D14:G14,F18) -> 0.68490897

Sheet Escenario 2
B2: Presupuesto financiero
B3: Ejercicio | D3: Inicio | E3: 2025 | F3: 2026 | G3: 2027 | I3: RIESGO: Interrupción de la conectividad
B4: Ingresos | D4: - | E4: ='Presupuesto financiero'!E12 -> 109050000 | F4: ='Presupuesto financiero'!F12 -> 281700000 | G4: ='Presupuesto financiero'!G12 -> 536880000 | I4: R 10 | J4: - Fallas en red celular | K4: - Perdida de datos de los sensores $1500000 | L4: - Perdida de la sensación de "Real time" con los datos y el cliente. $3000000 (costos asociados a marketing para recuperar la confianza)
B5: Egresos | C5: Costos fijos | D5: - | E5: ='Presupuesto financiero'!E13 -> 26772000 | F5: ='Presupuesto financiero'!F13 -> 30638000 | G5: ='Presupuesto financiero'!G13 -> 37452000
C6: Costos variables | D6: - | E6: ='Presupuesto financiero'!E14 + 1500000 + 3000000 -> 37418375 | F6: ='Presupuesto financiero'!F14 -> 59495000 | G6: ='Presupuesto financiero'!G14 -> 87758125
C7: Costos de RRHH | D7: - | E7: ='Presupuesto financiero'!E15 -> 77670014 | F7: ='Presupuesto financiero'!F15 -> 1.4973145e+08 | G7: ='Presupuesto financiero'!G15 -> 2.2191489e+08 | K7: Año 1 | L7: Año 1
B8: Utilidad Antes de Impuestos (UAII) | D8: - | E8: =+E4-E5-E6-E7 -> -32810389 | F8: =+F4-F5-F6-F7 -> 41835549 | G8: =+G4-G5-G6-G7 -> 1.8975498e+08
B9: Impuesto Ingresos Brutos | C9: 0.03 | D9: - | E9: =+E4*C9 -> 3271500 | F9: =+F4*C9 -> 8451000 | G9: =+G4*C9 -> 16106400
B10: Impuesto a las ganancias 35% | E10: ='Presupuesto financiero'!E19 -> 0 | F10: ='Presupuesto financiero'!F19 -> 0 | G10: ='Presupuesto financiero'!G19 -> 11292779
B12: Utilidad despues de Impuestos (UDII) | D12: - | E12: =+E8-E9-E10-E11 -> -36081889 | F12: =+F8-F9-F10-F11 -> 33384549 | G12: =+G8-G9-G10-G11 -> 1.623558e+08
B13: Inversión | D13: ='Mod. inversión'!E28 -> 18499000 | E13: ='Mod. inversión'!E45 -> 800000 | F13: ='Mod. inversión'!E63 -> 1864000 | G13: ='Mod. inversión'!E81 -> 4264000
B14: Flujo de Fondos (FF) | D14: =+D13*-1 -> -18499000 | E14: =+E12-E13 -> -36881889 | F14: =+F12-F13 -> 31520549 | G14: =+G12-G13 -> 1.580918e+08
E18: Tasa de Corte | F18: ='Presupuesto financiero'!G33 -> 0.75
E19: VAN | F19: {=+NPV(F18,D14:G14)} -> 123564.66
E20: TIR | F20: =IRR(D14:G14,F18) -> 0.75432256

Sheet Escenario 3
B2: Presupuesto financiero
B3: Ejercicio | D3: Inicio | E3: 2025 | F3: 2026 | G3: 2027 | I3: RIESGO: Cambios regulatorios o aduaneros
B4: Ingresos | D4: - | E4: ='Presupuesto financiero'!E12 - 5000000 -> 104050000 | F4: ='Presupuesto financiero'!F12 -> 281700000 | G4: ='Presupuesto financiero'!G12 -> 536880000 | I4: R 8 | J4: - Restricciones de importacion o nuevas normas SENASA/AFIP | K4: - Costos de adecuación o sustitución de hardware: $1500000 | L4: - Retrasos en instalaciones: $5000000
B5: Egresos | C5: Costos fijos | D5: - | E5: ='Presupuesto financiero'!E13 -> 26772000 | F5: ='Presupuesto financiero'!F13 -> 30638000 | G5: ='Presupuesto financiero'!G13 -> 37452000
C6: Costos variables | D6: - | E6: ='Presupuesto financiero'!E14 + 1500000 -> 34418375 | F6: ='Presupuesto financiero'!F14 -> 59495000 | G6: ='Presupuesto financiero'!G14 -> 87758125
C7: Costos de RRHH | D7: - | E7: ='Presupuesto financiero'!E15 -> 77670014 | F7: ='Presupuesto financiero'!F15 -> 1.4973145e+08 | G7: ='Presupuesto financiero'!G15 -> 2.2191489e+08 | K7: Año 1 | L7: Año 2
B8: Utilidad Antes de Impuestos (UAII) | D8: - | E8: =+E4-E5-E6-E7 -> -34810389 | F8: =+F4-F5-F6-F7 -> 41835549 | G8: =+G4-G5-G6-G7 -> 1.8975498e+08
B9: Impuesto Ingresos Brutos | C9: 0.03 | D9: - | E9: =+E4*C9 -> 3121500 | F9: =+F4*C9 -> 8451000 | G9: =+G4*C9 -> 16106400
B10: Impuesto a las ganancias 35% | E10: ='Presupuesto financiero'!E19 -> 0 | F10: ='Presupuesto financiero'!F19 -> 0 | G10: ='Presupuesto financiero'!G19 -> 11292779
B12: Utilidad despues de Impuestos (UDII) | D12: - | E12: =+E8-E9-E10-E11 -> -37931889 | F12: =+F8-F9-F10-F11 -> 33384549 | G12: =+G8-G9-G10-G11 -> 1.623558e+08
B13: Inversión | D13: ='Mod. inversión'!E28 -> 18499000 | E13: ='Mod. inversión'!E45 -> 800000 | F13: ='Mod. inversión'!E63 -> 1864000 | G13: ='Mod. inversión'!E81 -> 4264000
B14: Flujo de Fondos (FF) | D14: =+D13*-1 -> -18499000 | E14: =+E12-E13 -> -38731889 | F14: =+F12-F13 -> 31520549 | G14: =+G12-G13 -> 1.580918e+08
E18: Tasa de Corte | F18: ='Presupuesto financiero'!G33 -> 0.75
E19: VAN | F19: {=+NPV(F18,D14:G14)} -> -480516.97
E20: TIR | F20: =IRR(D14:G14,F18) -> 0.73341609

Sheet Plan de Contingencia
B2: PLAN DE CONTINGENCIA
B4: Objetivos del Plan de Contingencia
B5: · Garantizar la continuidad operativa del proyecto.
B6: · Minimizar el impacto financiero y operativo del fallo tecnológico.
B7: · Proteger la satisfacción del cliente y la reputación de la empresa.
B10: Presupuesto financiero
B11: Ejercicio | D11: Inicio | E11: 2025 | F11: 2026 | G11: 2027 | I11: RIESGO: Fallo en la infraestructura tecnológica
B12: Ingresos | D12: - | E12: ='Presupuesto financiero'!E12 -> 109050000 | F12: ='Presupuesto financiero'!F12 + 5000000 -> 286700000 | G12: ='Presupuesto financiero'!G12 - 30000000 + 15000000 -> 521880000 | I12: R 4 | J12: - Caida completa del servicio de nube | K12: - Plataforma sin acceso $1000000 | L12: - Perdida de posibles contratos $3000000
B13: Egresos | C13: Costos fijos | D13: - | E13: ='Presupuesto financiero'!E13 -> 26772000 | F13: ='Presupuesto financiero'!F13 -> 30638000 | G13: ='Presupuesto financiero'!G13 -> 37452000
C14: Costos variables | D14: - | E14: ='Presupuesto financiero'!E14 -> 32918375 | F14: ='Presupuesto financiero'!F14 + 1000000 + 500000 + 1000000 -> 61995000 | G14: ='Presupuesto financiero'!G14 + 500000 -> 88258125
C15: Costos de RRHH | D15: - | E15: ='Presupuesto financiero'!E15 -> 77670014 | F15: ='Presupuesto financiero'!F15 -> 1.4973145e+08 | G15: ='Presupuesto financiero'!G15 -> 2.2191489e+08 | K15: Año 2 | L15: Año 3
B16: Utilidad Antes de Impuestos (UAII) | D16: - | E16: =+E12-E13-E14-E15 -> -28310389 | F16: =+F12-F13-F14-F15 -> 44335549 | G16: =+G12-G13-G14-G15 -> 1.7425498e+08
B17: Impuesto Ingresos Brutos | C17: 0.03 | D17: - | E17: =+E12*C17 -> 3271500 | F17: =+F12*C17 -> 8601000 | G17: =+G12*C17 -> 15656400 | I17: PLAN DE CONTINGENCIA
B18: Impuesto a las ganancias 35% | E18: ='Presupuesto financiero'!E19 -> 0 | F18: ='Presupuesto financiero'!F19 -> 0 | G18: ='Presupuesto financiero'!G19 -> 11292779 | I18: El plan de contingencia aplicado al escenario 1, donde se trata de ajustar inversion en hardware, y realizar acciones de marketing que impulsen las ventas. 1° Medida: Se generara un plan de fallback hacia otra nube en caso catastrófico. Suma $500.000 anuales al costo fijo por infraestructura cloud. 2° Medida (año 2): Se implementara un plan de marketing ($1.000.000) promocionando la nueva medida de fallback y tiempo de vuelta de servicio ante un caso catastrofico (15m). Este punto busca reducir la perdida de posibles contratos en un 50%. Con lo que buscamos captar nuevas ventas por $5.000.000 Con estas medidas, logramos un aumento en los costos fijos de $ 500.000, y mitigamos una perdida de $ 15.000.000 en nuevos contratos. Las tareas continuarán siendo realizadas con la misma estructura de RRHH que el año anterior.
B20: Utilidad despues de Impuestos (UDII) | D20: - | E20: =+E16-E17-E18-E19 -> -31581889 | F20: =+F16-F17-F18-F19 -> 35734549 | G20: =+G16-G17-G18-G19 -> 1.473058e+08
B21: Inversión | D21: ='Mod. inversión'!E28 -> 18499000 | E21: ='Mod. inversión'!E45 -> 800000 | F21: ='Mod. inversión'!E63 -> 1864000 | G21: ='Mod. inversión'!E81 -> 4264000
B22: Flujo de Fondos (FF) | D22: =+D21*-1 -> -18499000 | E22: =+E20-E21 -> -32381889 | F22: =+F20-F21 -> 33870549 | G22: =+G20-G21 -> 1.430418e+08
E26: Tasa de Corte | F26: ='Presupuesto financiero'!G33 -> 0.75
E27: VAN | F27: {=+NPV(F26,D22:G22)} -> 426771.66
E28: TIR | F28: =IRR(D22:G22,F26) -> 0.76591566
