Workbook

Sheet Portada
C9: TRABAJO FINAL DE INGENIERÍA
C21: Alumno: Gómez Avellaneda, Javier
C22: Legajo: B00074234-T1
C23: Docentes: Scali, Jorge — Vilaboa, Pablo
C24: Comisión: 5° A - Turno Noche
C25: Localización: Sede Centro
C26: Email: javieralejandro.gomezavellaneda@alumnos.uai.edu.ar

Sheet Indice
D2: Índice
D4: Hipótesis
D5: Proyección de ventas
D6: Anexo de capacidad operativa
D7: Modelo de ingresos
D8: Estructura de costos fijos
D9: Estructura de costos variables
D10: Estructura de costos de RRHH
D11: Modelo de egresos
D12: Modelo de inversión
D13: Amortizaciones
D14: Presupuesto financiero
... D19: Plan de contingencia

Sheet Hipótesis
E1: Hipótesis
B3: 1 - Descripción del negocio
B4: ShopMetrics es una Empresa de Base Tecnológica (EBT) que desarrolla y explota software propio bajo modalidad SaaS para el comercio minorista. El negocio no consiste en la venta de dispositivos de conteo, sino en la provisión de un ecosistema de medición del embudo comercial del local: cuántas personas pasan por delante, cuántas se detienen frente a la vidriera, cuántas entran y cuántas compran. Los datos se capturan con infraestructura propia instalada en el local (sensores de vidriera y contadores de puerta que publican únicamente cantidades, nunca imágenes) y se integran de forma automática con el sistema de punto de venta que el comercio ya utiliza; sobre esa base, modelos propios de Machine Learning convierten la medición en decisiones de exhibición, dotación de personal y horario de atención. El servicio se contrata con un abono mensual y un cargo de alta e instalación por única vez, y los equipos se entregan en comodato, de modo que el comercio no afronta inversión inicial. Todos los importes de este presupuesto están expresados en dólares.
B7: 2 - Mercado meta
B8: Comercios minoristas con local a la calle y vidriera a la vereda, de entre uno y cinco locales y hasta nueve ocupados, ubicados en los ejes comerciales de mayor densidad del AMBA, que ya operan con alguno de los siete sistemas de punto de venta cubiertos por los conectores propios. El rubro de arranque es indumentaria, textiles y calzado
B9: Segmentación del mercado meta. El universo se segmenta por rubro sobre los 14.083 locales ocupados que el Instituto de Estadística y Censos de la Ciudad de Buenos Aires releva en los 53 ejes comerciales de mayor densidad (tercer cuatrimestre de 2025), redondeados a 14.000. Los tres segmentos comparten el mismo tramo de tamaño —de uno a cinco locales y hasta nueve ocupados— y por eso el gasto anual de referencia en herramientas de gestión, facturación electrónica y analítica es común, USD 960 por comercio; lo que los diferencia es la densidad de pares por eje y la prioridad comercial de ingreso. Segmento A — Indumentaria, textiles y calzado: compuesto por 3.400 comercios, el 24,3% de los locales ocupados relevados; es el rubro de mayor concentración del relevamiento y la cabecera de entrada por el eje Avellaneda, que reúne 1.073 locales con la ocupación más alta del operativo, 96,6%. Con un gasto anual de USD 960 por comercio consolida un mercado direccionable de USD 3.264.000. Segmento B — Alojamiento y comida: compuesto por 1.600 comercios, el 11,3% de los locales ocupados relevados; gastronomía con vidriera a la vereda, que comparte el mismo embudo de paso, detención e ingreso y la misma infraestructura de medición. Con un gasto anual de USD 960 por comercio consolida un mercado direccionable de USD 1.536.000. Segmento C — Resto de rubros con vidriera: compuesto por 9.000 comercios, el 64,4% de los locales ocupados relevados; alimentos y bebidas, perfumería, calzado deportivo y servicios con local a la calle, que comparten la infraestructura de medición con menor densidad de pares por rubro. Con un gasto anual de USD 960 por comercio consolida un mercado direccionable de USD 8.640.000. Total consolidado: los tres segmentos suman 14.000 comercios y un mercado direccionable de USD 13.440.000 anuales, que es el total que toma el cuadro siguiente. El universo del Gran Buenos Aires amplía esta cifra, pero no existe un operativo equivalente que lo mida con la misma fuente, de modo que queda fuera del dimensionamiento y dentro del plan de expansión.
B11: Comercios | C11: Gasto promedio anual (USD) | D11: Total mercado (USD)
B12: 14000 | C12: 960 | D12: =B12*C12 -> 13440000
B13: Los 14.000 comercios son los locales ocupados que el IDECBA releva en los 53 ejes comerciales de mayor densidad (tercer cuatrimestre de 2025). Todos tienen local a la calle y vidriera, que es la condición para instalar el servicio. El detalle por rubro y la ampliación al Gran Buenos Aires están en el punto 4 del informe.
B15: 3 - Participación del mercado
B16: Participación del 5,2% del universo al cierre del tercer año, con una progresión del 0,8% el primer año, 2,9% el segundo y 5,2% el tercero. Es una progresión moderada: el rubro de arranque concentra el esfuerzo comercial del primer año y la ampliación a los otros rubros con vidriera de los mismos ejes recién se aborda una vez validado ese rubro, de modo que el universo crece más rápido que la captación.
A22: Evolución de la participación en el mercado
A23: Año | B23: Cantidad | C23: Porcentaje | D23: Valor del mercado captado (USD) | E23: Facturación proyectada (USD)
A24: 2026 | B24: =SUBSTITUTE(TEXT('Proy. ventas'!AA36,"#,##0"),",",".")&" comercios" -> 271 comercios | C24: 0.008 | D24: =C24*$D$12 -> 107520 | E24: =SUM('Proy. ventas'!F32,'Proy. ventas'!H32,'Proy. ventas'!J32,'Proy. ventas'!L32,'Proy. ventas'!N32,'Proy. ventas'!P32,'Proy. ventas'!R32,'Proy. ventas'!T32,'Proy. ventas'!V32,'Proy. ventas'!X32,'Proy. ventas'!Z32,'Proy. ventas'!AB32) -> 105865
A25: 2027 | B25: =SUBSTITUTE(TEXT('Proy. ventas'!AA99,"#,##0"),",",".")&" comercios" -> 597 comercios | C25: 0.029 | D25: =C25*$D$12 -> 389760 | E25: =SUM('Proy. ventas'!F95,'Proy. ventas'!H95,'Proy. ventas'!J95,'Proy. ventas'!L95,'Proy. ventas'!N95,'Proy. ventas'!P95,'Proy. ventas'!R95,'Proy. ventas'!T95,'Proy. ventas'!V95,'Proy. ventas'!X95,'Proy. ventas'!Z95,'Proy. ventas'!AB95) -> 386897
A26: 2028 | B26: =SUBSTITUTE(TEXT('Proy. ventas'!AA161,"#,##0"),",",".")&" comercios" -> 1.033 comercios | C26: 0.052 | D26: =C26*$D$12 -> 698880 | E26: =SUM('Proy. ventas'!F157,'Proy. ventas'!H157,'Proy. ventas'!J157,'Proy. ventas'!L157,'Proy. ventas'!N157,'Proy. ventas'!P157,'Proy. ventas'!R157,'Proy. ventas'!T157,'Proy. ventas'!V157,'Proy. ventas'!X157,'Proy. ventas'!Z157,'Proy. ventas'!AB157) -> 705506
B29: El valor del mercado captado es el objetivo de facturación de cada año: participación por mercado total. La proyección de ventas se arma para alcanzarlo, y de ahí se obtiene la cantidad de comercios abonados que hace falta al cierre de cada año. La cantidad es mayor que la que resultaría de dividir el mercado captado por el gasto de referencia, porque el ticket promedio de la lista de precios es menor que ese gasto.
B31: Detalle: el gasto promedio anual de referencia son USD 960 (USD 80 mensuales), lo que un comercio minorista destina a software de gestión, facturación electrónica y analítica. Referencias 2026: planes de punto de venta con facturación electrónica y stock multi-tienda en el orden de USD 79 mensuales, y el plan de entrada de Fudo, uno de los sistemas con los que la plataforma se integra, en USD 40 mensuales por sucursal.
B33: 4 - Otros datos
B35: Líneas de servicios
C36: VERSIONES DEL SERVICIO
C39: Alta e instalación | D39: Abono mensual
B40: PROFUNDIDAD DE LAS LÍNEAS DE SERVICIOS | C40: Plan Básico | D40: Plan Básico
C43: Plan Vidriera | D43: Plan Vidriera
C46: Plan Cadena | D46: Plan Cadena
B56: Lista de precios (USD)
B57: Servicio | C57: Precio | D57: Detalle | E57: Modalidad de cobro
B58: Alta e instalación Plan Básico | C58: 40 | D58: Por única vez. Alta remota: conexión con el sistema de punto de venta y verificación de datos. No requiere visita al local. | E58: Cobro por única vez
B59: Alta e instalación Plan Vidriera | C59: 120 | D59: Por única vez. Visita al local: montaje del sensor de vidriera y del contador de puerta, conexión del punto de venta y prueba del embudo. | E59: Cobro por única vez
B60: Alta e instalación Plan Cadena | C60: 450 | D60: Por única vez. Instalación en hasta cinco locales de una misma cadena. | E60: Cobro por única vez
B61: Abono Plan Básico | C61: 33 | D61: Analítica de ventas por hora, ticket promedio y rotación, a partir del punto de venta. Sin dispositivos de conteo. Es la puerta de entrada comercial. | E61: Cobro mensual
B62: Abono Plan Vidriera | C62: 65 | D62: Embudo completo del local: pasan, se detienen, entran y compran, más comparación anónima contra el rubro y alertas automáticas. Es el plan principal. | E62: Cobro mensual
B63: Abono Plan Cadena | C63: 175 | D63: Hasta cinco locales: embudo por local, comparación entre sucursales y consolidado de toda la red. | E63: Cobro mensual

Sheet Proy. ventas
B1: Proyección de ventas
B5: Evolución de la participación | G5: Justificación ingresos
B6: 2026 | C6: 2027 | D6: 2028 | G6: La proyección se arma desde la facturación objetivo, que es el valor del mercado captado de la hoja Hipótesis (participación por mercado total: USD 105.754 en 2026, 385.805 en 2027 y 705.677 en 2028). Con la lista de precios fija, se calcula cuántas altas por mes hacen falta para llegar a ese número: el alta e instalación se cobra una sola vez y el abono es mensual y se acumula (el comercio que se da de alta en marzo sigue pagando en abril), de modo que el ingreso crece mes a mes aunque las altas sean parejas. El primer trimestre de 2026 tiene pocas altas porque se destina a los primeros comercios del eje Avellaneda; a partir de allí la captación crece de manera sostenida. Los porcentajes de cada mes son la proporción del total anual que se factura ese mes.
B7: =Hipótesis!C24 -> 0.008 | C7: =Hipótesis!C25 -> 0.029 | D7: =Hipótesis!C26 -> 0.052
B8: =Hipótesis!D24 -> 107520 | C8: =Hipótesis!D25 -> 389760 | D8: =Hipótesis!D26 -> 698880
A10: .
A15: Proyección de ventas 2026
A16: Producto | B16: Precio | C16: Anual | E16: Enero | G16: Febrero | I16: Marzo | K16: Abril | M16: Mayo | O16: Junio | Q16: Julio | S16: Agosto | U16: Septiembre | W16: Octubre | Y16: Noviembre | AA16: Diciembre
C17: Cantidad | D17: Ingresos | E17: =F32/$D$32 -> 0 | G17: =H32/$D$32 -> 0.0041845747 | I17: =J32/$D$32 -> 0.0074717801 | K17: =L32/$D$32 -> 0.019713786 | M17: =N32/$D$32 -> 0.033429368 | O17: =P32/$D$32 -> 0.053691022 | Q17: =R32/$D$32 -> 0.072545223 | S17: =T32/$D$32 -> 0.10082652 | U17: =V32/$D$32 -> 0.12412979 | W17: =X32/$D$32 -> 0.16080858 | Y17: =Z32/$D$32 -> 0.18925046 | AA17: =AB32/$D$32 -> 0.2339489
E18: Cantidad | F18: Ingresos | G18: Cantidad | H18: Ingresos | I18: Cantidad | J18: Ingresos | K18: Cantidad | L18: Ingresos | M18: Cantidad | N18: Ingresos | O18: Cantidad | P18: Ingresos | Q18: Cantidad | R18: Ingresos | S18: Cantidad | T18: Ingresos | U18: Cantidad | V18: Ingresos | W18: Cantidad | X18: Ingresos | Y18: Cantidad | Z18: Ingresos | AA18: Cantidad | AB18: Ingresos
A19: =Hipótesis!$B$58 -> Alta e instalación Plan Básico | B19: =Hipótesis!C58 -> 40 | C19: =E19+G19+I19+K19+M19+O19+Q19+S19+U19+W19+Y19+AA19 -> 74 | D19: =B19*C19 -> 2960 | E19: 0 | F19: =E19*$B$19 -> 0 | G19: 1 | H19: =G19*$B$19 -> 40 | I19: 1 | J19: =I19*$B$19 -> 40 | K19: 2 | L19: =K19*$B$19 -> 80 | M19: 4 | N19: =M19*$B$19 -> 160 | O19: 5 | P19: =O19*$B$19 -> 200 | Q19: 7 | R19: =Q19*$B$19 -> 280 | S19: 8 | T19: =S19*$B$19 -> 320 | U19: 9 | V19: =U19*$B$19 -> 360 | W19: 11 | X19: =W19*$B$19 -> 440 | Y19: 12 | Z19: =Y19*$B$19 -> 480 | AA19: 14 | AB19: =AA19*$B$19 -> 560
A20: =Hipótesis!$B$59 -> Alta e instalación Plan Vidriera | B20: =Hipótesis!C59 -> 120 | C20: =E20+G20+I20+K20+M20+O20+Q20+S20+U20+W20+Y20+AA20 -> 172 | D20: =B20*C20 -> 20640 | E20: 0 | F20: =E20*$B$20 -> 0 | G20: 2 | H20: =G20*$B$20 -> 240 | I20: 3 | J20: =I20*$B$20 -> 360 | K20: 5 | L20: =K20*$B$20 -> 600 | M20: 9 | N20: =M20*$B$20 -> 1080 | O20: 12 | P20: =O20*$B$20 -> 1440 | Q20: 15 | R20: =Q20*$B$20 -> 1800 | S20: 19 | T20: =S20*$B$20 -> 2280 | U20: 21 | V20: =U20*$B$20 -> 2520 | W20: 26 | X20: =W20*$B$20 -> 3120 | Y20: 27 | Z20: =Y20*$B$20 -> 3240 | AA20: 33 | AB20: =AA20*$B$20 -> 3960
A21: =Hipótesis!$B$60 -> Alta e instalación Plan Cadena | B21: =Hipótesis!C60 -> 450 | C21: =E21+G21+I21+K21+M21+O21+Q21+S21+U21+W21+Y21+AA21 -> 25 | D21: =B21*C21 -> 11250 | E21: 0 | F21: =E21*$B$21 -> 0 | G21: 0 | H21: =G21*$B$21 -> 0 | I21: 0 | J21: =I21*$B$21 -> 0 | K21: 1 | L21: =K21*$B$21 -> 450 | M21: 1 | N21: =M21*$B$21 -> 450 | O21: 2 | P21: =O21*$B$21 -> 900 | Q21: 2 | R21: =Q21*$B$21 -> 900 | S21: 3 | T21: =S21*$B$21 -> 1350 | U21: 3 | V21: =U21*$B$21 -> 1350 | W21: 4 | X21: =W21*$B$21 -> 1800 | Y21: 4 | Z21: =Y21*$B$21 -> 1800 | AA21: 5 | AB21: =AA21*$B$21 -> 2250
A22: =Hipótesis!$B$61 -> Abono Plan Básico | B22: =Hipótesis!C61 -> 33 | C22: =E22+G22+I22+K22+M22+O22+Q22+S22+U22+W22+Y22+AA22 -> 295 | D22: =B22*C22 -> 9735 | E22: =E19 -> 0 | F22: =E22*$B$22 -> 0 | G22: =E22+G19 -> 1 | H22: =G22*$B$22 -> 33 | I22: =G22+I19 -> 2 | J22: =I22*$B$22 -> 66 | K22: =I22+K19 -> 4 | L22: =K22*$B$22 -> 132 | M22: =K22+M19 -> 8 | N22: =M22*$B$22 -> 264 | O22: =M22+O19 -> 13 | P22: =O22*$B$22 -> 429 | Q22: =O22+Q19 -> 20 | R22: =Q22*$B$22 -> 660 | S22: =Q22+S19 -> 28 | T22: =S22*$B$22 -> 924 | U22: =S22+U19 -> 37 | V22: =U22*$B$22 -> 1221 | W22: =U22+W19 -> 48 | X22: =W22*$B$22 -> 1584 | Y22: =W22+Y19 -> 60 | Z22: =Y22*$B$22 -> 1980 | AA22: =Y22+AA19 -> 74 | AB22: =AA22*$B$22 -> 2442
A23: =Hipótesis!$B$62 -> Abono Plan Vidriera | B23: =Hipótesis!C62 -> 65 | C23: =E23+G23+I23+K23+M23+O23+Q23+S23+U23+W23+Y23+AA23 -> 687 | D23: =B23*C23 -> 44655 | E23: =E20 -> 0 | F23: =E23*$B$23 -> 0 | G23: =E23+G20 -> 2 | H23: =G23*$B$23 -> 130 | I23: =G23+I20 -> 5 | J23: =I23*$B$23 -> 325 | K23: =I23+K20 -> 10 | L23: =K23*$B$23 -> 650 | M23: =K23+M20 -> 19 | N23: =M23*$B$23 -> 1235 | O23: =M23+O20 -> 31 | P23: =O23*$B$23 -> 2015 | Q23: =O23+Q20 -> 46 | R23: =Q23*$B$23 -> 2990 | S23: =Q23+S20 -> 65 | T23: =S23*$B$23 -> 4225 | U23: =S23+U20 -> 86 | V23: =U23*$B$23 -> 5590 | W23: =U23+W20 -> 112 | X23: =W23*$B$23 -> 7280 | Y23: =W23+Y20 -> 139 | Z23: =Y23*$B$23 -> 9035 | AA23: =Y23+AA20 -> 172 | AB23: =AA23*$B$23 -> 11180
A24: =Hipótesis!$B$63 -> Abono Plan Cadena | B24: =Hipótesis!C63 -> 175 | C24: =E24+G24+I24+K24+M24+O24+Q24+S24+U24+W24+Y24+AA24 -> 95 | D24: =B24*C24 -> 16625 | E24: =E21 -> 0 | F24: =E24*$B$24 -> 0 | G24: =E24+G21 -> 0 | H24: =G24*$B$24 -> 0 | I24: =G24+I21 -> 0 | J24: =I24*$B$24 -> 0 | K24: =I24+K21 -> 1 | L24: =K24*$B$24 -> 175 | M24: =K24+M21 -> 2 | N24: =M24*$B$24 -> 350 | O24: =M24+O21 -> 4 | P24: =O24*$B$24 -> 700 | Q24: =O24+Q21 -> 6 | R24: =Q24*$B$24 -> 1050 | S24: =Q24+S21 -> 9 | T24: =S24*$B$24 -> 1575 | U24: =S24+U21 -> 12 | V24: =U24*$B$24 -> 2100 | W24: =U24+W21 -> 16 | X24: =W24*$B$24 -> 2800 | Y24: =W24+Y21 -> 20 | Z24: =Y24*$B$24 -> 3500 | AA24: =Y24+AA21 -> 25 | AB24: =AA24*$B$24 -> 4375
A32: Ingreso Total | D32: =SUM(D19:D31) -> 105865 | F32: =SUM(F19:F31) -> 0 | H32: =SUM(H19:H31) -> 443 | J32: =SUM(J19:J31) -> 791 | L32: =SUM(L19:L31) -> 2087 | N32: =SUM(N19:N31) -> 3539 | P32: =SUM(P19:P31) -> 5684 | R32: =SUM(R19:R31) -> 7680 | T32: =SUM(T19:T31) -> 10674 | V32: =SUM(V19:V31) -> 13141 | X32: =SUM(X19:X31) -> 17024 | Z32: =SUM(Z19:Z31) -> 20035 | AB32: =SUM(AB19:AB31) -> 24767
C33: =C19 -> 74 | E33: =E19 -> 0 | G33: =G19 -> 1 | I33: =I19 -> 1 | K33: =K19 -> 2 | M33: =M19 -> 4 | O33: =O19 -> 5 | Q33: =Q19 -> 7 | S33: =S19 -> 8 | U33: =U19 -> 9 | W33: =W19 -> 11 | Y33: =Y19 -> 12 | AA33: =AA19 -> 14
C34: =C20 -> 172 | E34: =E20 -> 0 | G34: =G20 -> 2 | I34: =I20 -> 3 | K34: =K20 -> 5 | M34: =M20 -> 9 | O34: =O20 -> 12 | Q34: =Q20 -> 15 | S34: =S20 -> 19 | U34: =U20 -> 21 | W34: =W20 -> 26 | Y34: =Y20 -> 27 | AA34: =AA20 -> 33
C35: =C21 -> 25 | E35: =E21 -> 0 | G35: =G21 -> 0 | I35: =I21 -> 0 | K35: =K21 -> 1 | M35: =M21 -> 1 | O35: =O21 -> 2 | Q35: =Q21 -> 2 | S35: =S21 -> 3 | U35: =U21 -> 3 | W35: =W21 -> 4 | Y35: =Y21 -> 4 | AA35: =AA21 -> 5
C36: =SUM(C22:C25) -> 1077 | E36: =SUM(E22:E25) -> 0 | G36: =SUM(G22:G25) -> 3 | I36: =SUM(I22:I25) -> 7 | K36: =SUM(K22:K25) -> 15 | M36: =SUM(M22:M25) -> 29 | O36: =SUM(O22:O25) -> 48 | Q36: =SUM(Q22:Q25) -> 72 | S36: =SUM(S22:S25) -> 102 | U36: =SUM(U22:U25) -> 135 | W36: =SUM(W22:W25) -> 176 | Y36: =SUM(Y22:Y25) -> 219 | AA36: =SUM(AA22:AA25) -> 271
C37: =SUM(C26:C30) -> 0 | E37: =SUM(E26:E30) -> 0 | G37: =SUM(G26:G30) -> 0 | I37: =SUM(I26:I30) -> 0 | K37: =SUM(K26:K30) -> 0 | M37: =SUM(M26:M30) -> 0 | O37: =SUM(O26:O30) -> 0 | Q37: =SUM(Q26:Q30) -> 0 | S37: =SUM(S26:S30) -> 0 | U37: =SUM(U26:U30) -> 0 | W37: =SUM(W26:W30) -> 0 | Y37: =SUM(Y26:Y30) -> 0 | AA37: =SUM(AA26:AA30) -> 0
C38: =C31 -> 0 | E38: =E31 -> 0 | G38: =G31 -> 0 | I38: =I31 -> 0 | K38: =K31 -> 0 | M38: =M31 -> 0 | O38: =O31 -> 0 | Q38: =Q31 -> 0 | S38: =S31 -> 0 | U38: =U31 -> 0 | W38: =W31 -> 0 | Y38: =Y31 -> 0 | AA38: =AA31 -> 0
A40: Capacidad operativa Kick off - Año 2026
A41: Comentarios | B41: * Se arranca sólo con los dos fundadores (gerencia general y gerencia de sistemas), que cubren entre ambos todos los puestos de la estructura. La instalación y el soporte se contratan por hora a técnicos freelance según las altas de cada mes, la venta se paga por comisión sobre cada alta y el desarrollo, la contabilidad y el marketing están tercerizados en los costos fijos.
A42: Concepto | C42: Año cero - Kick off | E42: Año 2026
C43: Cantidad | E43: Enero | G43: Febrero | I43: Marzo | K43: Abril | M43: Mayo | O43: Junio | Q43: Julio | S43: Agosto | U43: Septiembre | W43: Octubre | Y43: Noviembre | AA43: Diciembre
A44: RRHH | C44: Gerente general | E44: Sin cambios | G44: Sin cambios | I44: Sin cambios | K44: Sin cambios | M44: Sin cambios | O44: Sin cambios | Q44: Sin cambios | S44: Sin cambios | U44: Sin cambios | W44: Sin cambios | Y44: Sin cambios | AA44: Sin cambios
C45: Gerente de sistemas | E45: Sin cambios | G45: Sin cambios | I45: Sin cambios | K45: Sin cambios | M45: Sin cambios | O45: Sin cambios | Q45: Sin cambios | S45: Sin cambios | U45: Sin cambios | W45: Sin cambios | Y45: Sin cambios | AA45: Sin cambios
C46: Desarrollador | E46: Tercerizado (costo fijo) | G46: Sin cambios | I46: Sin cambios | K46: Sin cambios | M46: Sin cambios | O46: Sin cambios | Q46: Sin cambios | S46: Sin cambios | U46: Sin cambios | W46: Sin cambios | Y46: Sin cambios | AA46: Sin cambios
C47: Técnico de instalación y soporte | E47: Freelance por hora (costo variable) | G47: Sin cambios | I47: Sin cambios | K47: Sin cambios | M47: Sin cambios | O47: Sin cambios | Q47: Sin cambios | S47: Sin cambios | U47: Sin cambios | W47: Sin cambios | Y47: Sin cambios | AA47: Sin cambios
C48: Vendedor | E48: Comisión por alta (costo variable) | G48: Sin cambios | I48: Sin cambios | K48: Sin cambios | M48: Sin cambios | O48: Sin cambios | Q48: Sin cambios | S48: Sin cambios | U48: Sin cambios | W48: Sin cambios | Y48: Sin cambios | AA48: Sin cambios
A62: Infraestructura | C62: Oficina | E62: Oficina (+1 alquiler) | G62: Sin cambios | I62: Sin cambios | K62: Sin cambios | M62: Sin cambios | O62: Sin cambios | Q62: Sin cambios | S62: Sin cambios | U62: Sin cambios | W62: Sin cambios | Y62: Sin cambios | AA62: Sin cambios
C63: Notebooks | E63: Sin cambios | G63: Sin cambios | I63: Sin cambios | K63: Sin cambios | M63: Sin cambios | O63: Sin cambios | Q63: Sin cambios | S63: Sin cambios | U63: Sin cambios | W63: Sin cambios | Y63: Sin cambios | AA63: Sin cambios
C64: Escritorios | E64: Sin cambios | G64: Sin cambios | I64: Sin cambios | K64: Sin cambios | M64: Sin cambios | O64: Sin cambios | Q64: Sin cambios | S64: Sin cambios | U64: Sin cambios | W64: Sin cambios | Y64: Sin cambios | AA64: Sin cambios
C65: Sillas de escritorio | E65: Sin cambios | G65: Sin cambios | I65: Sin cambios | K65: Sin cambios | M65: Sin cambios | O65: Sin cambios | Q65: Sin cambios | S65: Sin cambios | U65: Sin cambios | W65: Sin cambios | Y65: Sin cambios | AA65: Sin cambios
C66: 0 | E66: Sin cambios | G66: Sin cambios | I66: Sin cambios | K66: Sin cambios | M66: Sin cambios | O66: Sin cambios | Q66: Sin cambios | S66: Sin cambios | U66: Sin cambios | W66: Sin cambios | Y66: Sin cambios | AA66: Sin cambios
C67: 0 | E67: Sin cambios | G67: Sin cambios | I67: Sin cambios | K67: Sin cambios | M67: Sin cambios | O67: Sin cambios | Q67: Sin cambios | S67: Sin cambios | U67: Sin cambios | W67: Sin cambios | Y67: Sin cambios | AA67: Sin cambios
C68: 0 | E68: Sin cambios | G68: Sin cambios | I68: Sin cambios | K68: Sin cambios | M68: Sin cambios | O68: Sin cambios | Q68: Sin cambios | S68: Sin cambios | U68: Sin cambios | W68: Sin cambios | Y68: Sin cambios | AA68: Sin cambios
A69: Capital de trabajo | C69: Sensores de vidriera | E69: Sensores de vidriera (+30) | G69: Sin cambios | I69: Sin cambios | K69: Sensores de vidriera (+30) | M69: Sin cambios | O69: Sin cambios | Q69: Sensores de vidriera (+30) | S69: Sin cambios | U69: Sin cambios | W69: Sensores de vidriera (+30) | Y69: Sin cambios | AA69: Sin cambios
C70: Contadores de puerta | E70: Contadores de puerta (+30) | G70: Sin cambios | I70: Sin cambios | K70: Contadores de puerta (+30) | M70: Sin cambios | O70: Sin cambios | Q70: Contadores de puerta (+30) | S70: Sin cambios | U70: Sin cambios | W70: Contadores de puerta (+30) | Y70: Sin cambios | AA70: Sin cambios
C71: Gateways de conexión | E71: Gateways de conexión (+30) | G71: Sin cambios | I71: Sin cambios | K71: Gateways de conexión (+30) | M71: Sin cambios | O71: Sin cambios | Q71: Gateways de conexión (+30) | S71: Sin cambios | U71: Sin cambios | W71: Gateways de conexión (+30) | Y71: Sin cambios | AA71: Sin cambios
C72: Kits de montaje | E72: Kits de montaje (+30) | G72: Sin cambios | I72: Sin cambios | K72: Kits de montaje (+30) | M72: Sin cambios | O72: Sin cambios | Q72: Kits de montaje (+30) | S72: Sin cambios | U72: Sin cambios | W72: Kits de montaje (+30) | Y72: Sin cambios | AA72: Sin cambios
A78: Proyección de ventas 2027
A79: Producto | B79: Precio | C79: Anual | E79: Enero | G79: Febrero | I79: Marzo | K79: Abril | M79: Mayo | O79: Junio | Q79: Julio | S79: Agosto | U79: Septiembre | W79: Octubre | Y79: Noviembre | AA79: Diciembre
C80: Cantidad | D80: Ingresos | E80: =F95/$D$95 -> 0.057573463 | G80: =H95/$D$95 -> 0.061341908 | I80: =J95/$D$95 -> 0.06625536 | K80: =L95/$D$95 -> 0.070445106 | M80: =N95/$D$95 -> 0.075113015 | O80: =P95/$D$95 -> 0.079470764 | Q80: =R95/$D$95 -> 0.084306676 | S80: =T95/$D$95 -> 0.088832428 | U80: =V95/$D$95 -> 0.095640442 | W80: =X95/$D$95 -> 0.10087181 | Y80: =Z95/$D$95 -> 0.10724818 | AA80: =AB95/$D$95 -> 0.11290085
E81: Cantidad | F81: Ingresos | G81: Cantidad | H81: Ingresos | I81: Cantidad | J81: Ingresos | K81: Cantidad | L81: Ingresos | M81: Cantidad | N81: Ingresos | O81: Cantidad | P81: Ingresos | Q81: Cantidad | R81: Ingresos | S81: Cantidad | T81: Ingresos | U81: Cantidad | V81: Ingresos | W81: Cantidad | X81: Ingresos | Y81: Cantidad | Z81: Ingresos | AA81: Cantidad | AB81: Ingresos
A82: =Hipótesis!$B$58 -> Alta e instalación Plan Básico | B82: =Hipótesis!C58 -> 40 | C82: =E82+G82+I82+K82+M82+O82+Q82+S82+U82+W82+Y82+AA82 -> 88 | D82: =B82*C82 -> 3520 | E82: 6 | F82: =E82*$B$82 -> 240 | G82: 6 | H82: =G82*$B$82 -> 240 | I82: 7 | J82: =I82*$B$82 -> 280 | K82: 7 | L82: =K82*$B$82 -> 280 | M82: 7 | N82: =M82*$B$82 -> 280 | O82: 7 | P82: =O82*$B$82 -> 280 | Q82: 7 | R82: =Q82*$B$82 -> 280 | S82: 7 | T82: =S82*$B$82 -> 280 | U82: 8 | V82: =U82*$B$82 -> 320 | W82: 8 | X82: =W82*$B$82 -> 320 | Y82: 9 | Z82: =Y82*$B$82 -> 360 | AA82: 9 | AB82: =AA82*$B$82 -> 360
A83: =Hipótesis!$B$59 -> Alta e instalación Plan Vidriera | B83: =Hipótesis!C59 -> 120 | C83: =E83+G83+I83+K83+M83+O83+Q83+S83+U83+W83+Y83+AA83 -> 210 | D83: =B83*C83 -> 25200 | E83: 14 | F83: =E83*$B$83 -> 1680 | G83: 14 | H83: =G83*$B$83 -> 1680 | I83: 16 | J83: =I83*$B$83 -> 1920 | K83: 16 | L83: =K83*$B$83 -> 1920 | M83: 17 | N83: =M83*$B$83 -> 2040 | O83: 17 | P83: =O83*$B$83 -> 2040 | Q83: 18 | R83: =Q83*$B$83 -> 2160 | S83: 18 | T83: =S83*$B$83 -> 2160 | U83: 19 | V83: =U83*$B$83 -> 2280 | W83: 19 | X83: =W83*$B$83 -> 2280 | Y83: 21 | Z83: =Y83*$B$83 -> 2520 | AA83: 21 | AB83: =AA83*$B$83 -> 2520
A84: =Hipótesis!$B$60 -> Alta e instalación Plan Cadena | B84: =Hipótesis!C60 -> 450 | C84: =E84+G84+I84+K84+M84+O84+Q84+S84+U84+W84+Y84+AA84 -> 28 | D84: =B84*C84 -> 12600 | E84: 2 | F84: =E84*$B$84 -> 900 | G84: 2 | H84: =G84*$B$84 -> 900 | I84: 2 | J84: =I84*$B$84 -> 900 | K84: 2 | L84: =K84*$B$84 -> 900 | M84: 2 | N84: =M84*$B$84 -> 900 | O84: 2 | P84: =O84*$B$84 -> 900 | Q84: 2 | R84: =Q84*$B$84 -> 900 | S84: 2 | T84: =S84*$B$84 -> 900 | U84: 3 | V84: =U84*$B$84 -> 1350 | W84: 3 | X84: =W84*$B$84 -> 1350 | Y84: 3 | Z84: =Y84*$B$84 -> 1350 | AA84: 3 | AB84: =AA84*$B$84 -> 1350
A85: =Hipótesis!$B$61 -> Abono Plan Básico | B85: =Hipótesis!C61 -> 33 | C85: =E85+G85+I85+K85+M85+O85+Q85+S85+U85+W85+Y85+AA85 -> 1424 | D85: =B85*C85 -> 46992 | E85: =AA22+E82 -> 80 | F85: =E85*$B$85 -> 2640 | G85: =E85+G82 -> 86 | H85: =G85*$B$85 -> 2838 | I85: =G85+I82 -> 93 | J85: =I85*$B$85 -> 3069 | K85: =I85+K82 -> 100 | L85: =K85*$B$85 -> 3300 | M85: =K85+M82 -> 107 | N85: =M85*$B$85 -> 3531 | O85: =M85+O82 -> 114 | P85: =O85*$B$85 -> 3762 | Q85: =O85+Q82 -> 121 | R85: =Q85*$B$85 -> 3993 | S85: =Q85+S82 -> 128 | T85: =S85*$B$85 -> 4224 | U85: =S85+U82 -> 136 | V85: =U85*$B$85 -> 4488 | W85: =U85+W82 -> 144 | X85: =W85*$B$85 -> 4752 | Y85: =W85+Y82 -> 153 | Z85: =Y85*$B$85 -> 5049 | AA85: =Y85+AA82 -> 162 | AB85: =AA85*$B$85 -> 5346
A86: =Hipótesis!$B$62 -> Abono Plan Vidriera | B86: =Hipótesis!C62 -> 65 | C86: =E86+G86+I86+K86+M86+O86+Q86+S86+U86+W86+Y86+AA86 -> 3339 | D86: =B86*C86 -> 217035 | E86: =AA23+E83 -> 186 | F86: =E86*$B$86 -> 12090 | G86: =E86+G83 -> 200 | H86: =G86*$B$86 -> 13000 | I86: =G86+I83 -> 216 | J86: =I86*$B$86 -> 14040 | K86: =I86+K83 -> 232 | L86: =K86*$B$86 -> 15080 | M86: =K86+M83 -> 249 | N86: =M86*$B$86 -> 16185 | O86: =M86+O83 -> 266 | P86: =O86*$B$86 -> 17290 | Q86: =O86+Q83 -> 284 | R86: =Q86*$B$86 -> 18460 | S86: =Q86+S83 -> 302 | T86: =S86*$B$86 -> 19630 | U86: =S86+U83 -> 321 | V86: =U86*$B$86 -> 20865 | W86: =U86+W83 -> 340 | X86: =W86*$B$86 -> 22100 | Y86: =W86+Y83 -> 361 | Z86: =Y86*$B$86 -> 23465 | AA86: =Y86+AA83 -> 382 | AB86: =AA86*$B$86 -> 24830
A87: =Hipótesis!$B$63 -> Abono Plan Cadena | B87: =Hipótesis!C63 -> 175 | C87: =E87+G87+I87+K87+M87+O87+Q87+S87+U87+W87+Y87+AA87 -> 466 | D87: =B87*C87 -> 81550 | E87: =AA24+E84 -> 27 | F87: =E87*$B$87 -> 4725 | G87: =E87+G84 -> 29 | H87: =G87*$B$87 -> 5075 | I87: =G87+I84 -> 31 | J87: =I87*$B$87 -> 5425 | K87: =I87+K84 -> 33 | L87: =K87*$B$87 -> 5775 | M87: =K87+M84 -> 35 | N87: =M87*$B$87 -> 6125 | O87: =M87+O84 -> 37 | P87: =O87*$B$87 -> 6475 | Q87: =O87+Q84 -> 39 | R87: =Q87*$B$87 -> 6825 | S87: =Q87+S84 -> 41 | T87: =S87*$B$87 -> 7175 | U87: =S87+U84 -> 44 | V87: =U87*$B$87 -> 7700 | W87: =U87+W84 -> 47 | X87: =W87*$B$87 -> 8225 | Y87: =W87+Y84 -> 50 | Z87: =Y87*$B$87 -> 8750 | AA87: =Y87+AA84 -> 53 | AB87: =AA87*$B$87 -> 9275
A95: Ingreso Total | D95: =SUM(D82:D94) -> 386897 | F95: =SUM(F82:F94) -> 22275 | H95: =SUM(H82:H94) -> 23733 | J95: =SUM(J82:J94) -> 25634 | L95: =SUM(L82:L94) -> 27255 | N95: =SUM(N82:N94) -> 29061 | P95: =SUM(P82:P94) -> 30747 | R95: =SUM(R82:R94) -> 32618 | T95: =SUM(T82:T94) -> 34369 | V95: =SUM(V82:V94) -> 37003 | X95: =SUM(X82:X94) -> 39027 | Z95: =SUM(Z82:Z94) -> 41494 | AB95: =SUM(AB82:AB94) -> 43681
C96: =C82 -> 88 | E96: =E82 -> 6 | G96: =G82 -> 6 | I96: =I82 -> 7 | K96: =K82 -> 7 | M96: =M82 -> 7 | O96: =O82 -> 7 | Q96: =Q82 -> 7 | S96: =S82 -> 7 | U96: =U82 -> 8 | W96: =W82 -> 8 | Y96: =Y82 -> 9 | AA96: =AA82 -> 9
C97: =C83 -> 210 | E97: =E83 -> 14 | G97: =G83 -> 14 | I97: =I83 -> 16 | K97: =K83 -> 16 | M97: =M83 -> 17 | O97: =O83 -> 17 | Q97: =Q83 -> 18 | S97: =S83 -> 18 | U97: =U83 -> 19 | W97: =W83 -> 19 | Y97: =Y83 -> 21 | AA97: =AA83 -> 21
C98: =C84 -> 28 | E98: =E84 -> 2 | G98: =G84 -> 2 | I98: =I84 -> 2 | K98: =K84 -> 2 | M98: =M84 -> 2 | O98: =O84 -> 2 | Q98: =Q84 -> 2 | S98: =S84 -> 2 | U98: =U84 -> 3 | W98: =W84 -> 3 | Y98: =Y84 -> 3 | AA98: =AA84 -> 3
C99: =SUM(C85:C88) -> 5229 | E99: =SUM(E85:E88) -> 293 | G99: =SUM(G85:G88) -> 315 | I99: =SUM(I85:I88) -> 340 | K99: =SUM(K85:K88) -> 365 | M99: =SUM(M85:M88) -> 391 | O99: =SUM(O85:O88) -> 417 | Q99: =SUM(Q85:Q88) -> 444 | S99: =SUM(S85:S88) -> 471 | U99: =SUM(U85:U88) -> 501 | W99: =SUM(W85:W88) -> 531 | Y99: =SUM(Y85:Y88) -> 564 | AA99: =SUM(AA85:AA88) -> 597
C100: =SUM(C89:C93) -> 0 | E100: =SUM(E89:E93) -> 0 | G100: =SUM(G89:G93) -> 0 | I100: =SUM(I89:I93) -> 0 | K100: =SUM(K89:K93) -> 0 | M100: =SUM(M89:M93) -> 0 | O100: =SUM(O89:O93) -> 0 | Q100: =SUM(Q89:Q93) -> 0 | S100: =SUM(S89:S93) -> 0 | U100: =SUM(U89:U93) -> 0 | W100: =SUM(W89:W93) -> 0 | Y100: =SUM(Y89:Y93) -> 0 | AA100: =SUM(AA89:AA93) -> 0
C101: =C94 -> 0 | E101: =E94 -> 0 | G101: =G94 -> 0 | I101: =I94 -> 0 | K101: =K94 -> 0 | M101: =M94 -> 0 | O101: =O94 -> 0 | Q101: =Q94 -> 0 | S101: =S94 -> 0 | U101: =U94 -> 0 | W101: =W94 -> 0 | Y101: =Y94 -> 0 | AA101: =AA94 -> 0
A103: Capacidad operativa - Año 2027
A104: Comentarios | B104: * Sigue la estructura plana: los dos fundadores y todo lo demás tercerizado o por hora.
C105: Concepto | E105: Enero | G105: Febrero | I105: Marzo | K105: Abril | M105: Mayo | O105: Junio | Q105: Julio | S105: Agosto | U105: Septiembre | W105: Octubre | Y105: Noviembre | AA105: Diciembre
A106: RRHH | C106: Gerente general | E106: Sin cambios | G106: Sin cambios | I106: Sin cambios | K106: Sin cambios | M106: Sin cambios | O106: Sin cambios | Q106: Sin cambios | S106: Sin cambios | U106: Sin cambios | W106: Sin cambios | Y106: Sin cambios | AA106: Sin cambios
C107: Gerente de sistemas | E107: Sin cambios | G107: Sin cambios | I107: Sin cambios | K107: Sin cambios | M107: Sin cambios | O107: Sin cambios | Q107: Sin cambios | S107: Sin cambios | U107: Sin cambios | W107: Sin cambios | Y107: Sin cambios | AA107: Sin cambios
C108: Desarrollador | E108: Sin cambios | G108: Sin cambios | I108: Sin cambios | K108: Sin cambios | M108: Sin cambios | O108: Sin cambios | Q108: Sin cambios | S108: Sin cambios | U108: Sin cambios | W108: Sin cambios | Y108: Sin cambios | AA108: Sin cambios
C109: Técnico de instalación y soporte | E109: Sin cambios | G109: Sin cambios | I109: Sin cambios | K109: Sin cambios | M109: Sin cambios | O109: Sin cambios | Q109: Sin cambios | S109: Sin cambios | U109: Sin cambios | W109: Sin cambios | Y109: Sin cambios | AA109: Sin cambios
C110: Vendedor | E110: Sin cambios | G110: Sin cambios | I110: Sin cambios | K110: Sin cambios | M110: Sin cambios | O110: Sin cambios | Q110: Sin cambios | S110: Sin cambios | U110: Sin cambios | W110: Sin cambios | Y110: Sin cambios | AA110: Sin cambios
A124: Infraestructura | C124: Oficina | E124: Sin cambios | G124: Sin cambios | I124: Sin cambios | K124: Sin cambios | M124: Sin cambios | O124: Sin cambios | Q124: Sin cambios | S124: Sin cambios | U124: Sin cambios | W124: Sin cambios | Y124: Sin cambios | AA124: Sin cambios
C125: Notebooks | E125: Notebooks (+1) | G125: Sin cambios | I125: Notebooks (+1) | K125: Sin cambios | M125: Sin cambios | O125: Sin cambios | Q125: Sin cambios | S125: Sin cambios | U125: Sin cambios | W125: Sin cambios | Y125: Sin cambios | AA125: Sin cambios
C126: Escritorios | E126: Escritorios (+1) | G126: Sin cambios | I126: Sin cambios | K126: Sin cambios | M126: Sin cambios | O126: Sin cambios | Q126: Sin cambios | S126: Sin cambios | U126: Sin cambios | W126: Sin cambios | Y126: Sin cambios | AA126: Sin cambios
C127: Sillas de escritorio | E127: Sillas de escritorio (+2) | G127: Sin cambios | I127: Sin cambios | K127: Sin cambios | M127: Sin cambios | O127: Sin cambios | Q127: Sin cambios | S127: Sin cambios | U127: Sin cambios | W127: Sin cambios | Y127: Sin cambios | AA127: Sin cambios
C128: 0 | E128: Sin cambios | G128: Sin cambios | I128: Sin cambios | K128: Sin cambios | M128: Sin cambios | O128: Sin cambios | Q128: Sin cambios | S128: Sin cambios | U128: Sin cambios | W128: Sin cambios | Y128: Sin cambios | AA128: Sin cambios
C129: 0 | E129: Sin cambios | G129: Sin cambios | I129: Sin cambios | K129: Sin cambios | M129: Sin cambios | O129: Sin cambios | Q129: Sin cambios | S129: Sin cambios | U129: Sin cambios | W129: Sin cambios | Y129: Sin cambios | AA129: Sin cambios
C130: 0 | E130: Sin cambios | G130: Sin cambios | I130: Sin cambios | K130: Sin cambios | M130: Sin cambios | O130: Sin cambios | Q130: Sin cambios | S130: Sin cambios | U130: Sin cambios | W130: Sin cambios | Y130: Sin cambios | AA130: Sin cambios
A131: Capital de trabajo | C131: Sensores de vidriera | E131: Sensores de vidriera (+50) | G131: Sin cambios | I131: Sensores de vidriera (+50) | K131: Sin cambios | M131: Sin cambios | O131: Sensores de vidriera (+50) | Q131: Sin cambios | S131: Sin cambios | U131: Sensores de vidriera (+50) | W131: Sin cambios | Y131: Sin cambios | AA131: Sin cambios
C132: Contadores de puerta | E132: Contadores de puerta (+50) | G132: Sin cambios | I132: Contadores de puerta (+50) | K132: Sin cambios | M132: Sin cambios | O132: Contadores de puerta (+50) | Q132: Sin cambios | S132: Sin cambios | U132: Contadores de puerta (+50) | W132: Sin cambios | Y132: Sin cambios | AA132: Sin cambios
C133: Gateways de conexión | E133: Gateways de conexión (+50) | G133: Sin cambios | I133: Gateways de conexión (+50) | K133: Sin cambios | M133: Sin cambios | O133: Gateways de conexión (+50) | Q133: Sin cambios | S133: Sin cambios | U133: Gateways de conexión (+50) | W133: Sin cambios | Y133: Sin cambios | AA133: Sin cambios
C134: Kits de montaje | E134: Kits de montaje (+50) | G134: Sin cambios | I134: Kits de montaje (+50) | K134: Sin cambios | M134: Sin cambios | O134: Kits de montaje (+50) | Q134: Sin cambios | S134: Sin cambios | U134: Kits de montaje (+50) | W134: Sin cambios | Y134: Sin cambios | AA134: Sin cambios
A140: Proyección de ventas 2028
A141: Producto | B141: Precio | C141: Anual | E141: Enero | G141: Febrero | I141: Marzo | K141: Abril | M141: Mayo | O141: Junio | Q141: Julio | S141: Agosto | U141: Septiembre | W141: Octubre | Y141: Noviembre | AA141: Diciembre
C142: Cantidad | D142: Ingresos | E142: =F157/$D$157 -> 0.064386412 | G142: =H157/$D$157 -> 0.067255275 | I142: =J157/$D$157 -> 0.070752056 | K142: =L157/$D$157 -> 0.073851959 | M142: =N157/$D$157 -> 0.077214085 | O142: =P157/$D$157 -> 0.08040612 | Q142: =R157/$D$157 -> 0.084226073 | S142: =T157/$D$157 -> 0.087649148 | U142: =V157/$D$157 -> 0.092323807 | W142: =X157/$D$157 -> 0.096133839 | Y142: =Z157/$D$157 -> 0.10083401 | AA142: =AB157/$D$157 -> 0.10496722
E143: Cantidad | F143: Ingresos | G143: Cantidad | H143: Ingresos | I143: Cantidad | J143: Ingresos | K143: Cantidad | L143: Ingresos | M143: Cantidad | N143: Ingresos | O143: Cantidad | P143: Ingresos | Q143: Cantidad | R143: Ingresos | S143: Cantidad | T143: Ingresos | U143: Cantidad | V143: Ingresos | W143: Cantidad | X143: Ingresos | Y143: Cantidad | Z143: Ingresos | AA143: Cantidad | AB143: Ingresos
A144: =Hipótesis!$B$58 -> Alta e instalación Plan Básico | B144: =Hipótesis!C58 -> 40 | C144: =E144+G144+I144+K144+M144+O144+Q144+S144+U144+W144+Y144+AA144 -> 118 | D144: =B144*C144 -> 4720 | E144: 8 | F144: =E144*$B$144 -> 320 | G144: 8 | H144: =G144*$B$144 -> 320 | I144: 9 | J144: =I144*$B$144 -> 360 | K144: 9 | L144: =K144*$B$144 -> 360 | M144: 9 | N144: =M144*$B$144 -> 360 | O144: 9 | P144: =O144*$B$144 -> 360 | Q144: 10 | R144: =Q144*$B$144 -> 400 | S144: 10 | T144: =S144*$B$144 -> 400 | U144: 11 | V144: =U144*$B$144 -> 440 | W144: 11 | X144: =W144*$B$144 -> 440 | Y144: 12 | Z144: =Y144*$B$144 -> 480 | AA144: 12 | AB144: =AA144*$B$144 -> 480
A145: =Hipótesis!$B$59 -> Alta e instalación Plan Vidriera | B145: =Hipótesis!C59 -> 120 | C145: =E145+G145+I145+K145+M145+O145+Q145+S145+U145+W145+Y145+AA145 -> 278 | D145: =B145*C145 -> 33360 | E145: 19 | F145: =E145*$B$145 -> 2280 | G145: 19 | H145: =G145*$B$145 -> 2280 | I145: 21 | J145: =I145*$B$145 -> 2520 | K145: 21 | L145: =K145*$B$145 -> 2520 | M145: 22 | N145: =M145*$B$145 -> 2640 | O145: 22 | P145: =O145*$B$145 -> 2640 | Q145: 24 | R145: =Q145*$B$145 -> 2880 | S145: 24 | T145: =S145*$B$145 -> 2880 | U145: 25 | V145: =U145*$B$145 -> 3000 | W145: 25 | X145: =W145*$B$145 -> 3000 | Y145: 28 | Z145: =Y145*$B$145 -> 3360 | AA145: 28 | AB145: =AA145*$B$145 -> 3360
A146: =Hipótesis!$B$60 -> Alta e instalación Plan Cadena | B146: =Hipótesis!C60 -> 450 | C146: =E146+G146+I146+K146+M146+O146+Q146+S146+U146+W146+Y146+AA146 -> 40 | D146: =B146*C146 -> 18000 | E146: 3 | F146: =E146*$B$146 -> 1350 | G146: 3 | H146: =G146*$B$146 -> 1350 | I146: 3 | J146: =I146*$B$146 -> 1350 | K146: 3 | L146: =K146*$B$146 -> 1350 | M146: 3 | N146: =M146*$B$146 -> 1350 | O146: 3 | P146: =O146*$B$146 -> 1350 | Q146: 3 | R146: =Q146*$B$146 -> 1350 | S146: 3 | T146: =S146*$B$146 -> 1350 | U146: 4 | V146: =U146*$B$146 -> 1800 | W146: 4 | X146: =W146*$B$146 -> 1800 | Y146: 4 | Z146: =Y146*$B$146 -> 1800 | AA146: 4 | AB146: =AA146*$B$146 -> 1800
A147: =Hipótesis!$B$61 -> Abono Plan Básico | B147: =Hipótesis!C61 -> 33 | C147: =E147+G147+I147+K147+M147+O147+Q147+S147+U147+W147+Y147+AA147 -> 2657 | D147: =B147*C147 -> 87681 | E147: =AA85+E144 -> 170 | F147: =E147*$B$147 -> 5610 | G147: =E147+G144 -> 178 | H147: =G147*$B$147 -> 5874 | I147: =G147+I144 -> 187 | J147: =I147*$B$147 -> 6171 | K147: =I147+K144 -> 196 | L147: =K147*$B$147 -> 6468 | M147: =K147+M144 -> 205 | N147: =M147*$B$147 -> 6765 | O147: =M147+O144 -> 214 | P147: =O147*$B$147 -> 7062 | Q147: =O147+Q144 -> 224 | R147: =Q147*$B$147 -> 7392 | S147: =Q147+S144 -> 234 | T147: =S147*$B$147 -> 7722 | U147: =S147+U144 -> 245 | V147: =U147*$B$147 -> 8085 | W147: =U147+W144 -> 256 | X147: =W147*$B$147 -> 8448 | Y147: =W147+Y144 -> 268 | Z147: =Y147*$B$147 -> 8844 | AA147: =Y147+AA144 -> 280 | AB147: =AA147*$B$147 -> 9240
A148: =Hipótesis!$B$62 -> Abono Plan Vidriera | B148: =Hipótesis!C62 -> 65 | C148: =E148+G148+I148+K148+M148+O148+Q148+S148+U148+W148+Y148+AA148 -> 6273 | D148: =B148*C148 -> 407745 | E148: =AA86+E145 -> 401 | F148: =E148*$B$148 -> 26065 | G148: =E148+G145 -> 420 | H148: =G148*$B$148 -> 27300 | I148: =G148+I145 -> 441 | J148: =I148*$B$148 -> 28665 | K148: =I148+K145 -> 462 | L148: =K148*$B$148 -> 30030 | M148: =K148+M145 -> 484 | N148: =M148*$B$148 -> 31460 | O148: =M148+O145 -> 506 | P148: =O148*$B$148 -> 32890 | Q148: =O148+Q145 -> 530 | R148: =Q148*$B$148 -> 34450 | S148: =Q148+S145 -> 554 | T148: =S148*$B$148 -> 36010 | U148: =S148+U145 -> 579 | V148: =U148*$B$148 -> 37635 | W148: =U148+W145 -> 604 | X148: =W148*$B$148 -> 39260 | Y148: =W148+Y145 -> 632 | Z148: =Y148*$B$148 -> 41080 | AA148: =Y148+AA145 -> 660 | AB148: =AA148*$B$148 -> 42900
A149: =Hipótesis!$B$63 -> Abono Plan Cadena | B149: =Hipótesis!C63 -> 175 | C149: =E149+G149+I149+K149+M149+O149+Q149+S149+U149+W149+Y149+AA149 -> 880 | D149: =B149*C149 -> 154000 | E149: =AA87+E146 -> 56 | F149: =E149*$B$149 -> 9800 | G149: =E149+G146 -> 59 | H149: =G149*$B$149 -> 10325 | I149: =G149+I146 -> 62 | J149: =I149*$B$149 -> 10850 | K149: =I149+K146 -> 65 | L149: =K149*$B$149 -> 11375 | M149: =K149+M146 -> 68 | N149: =M149*$B$149 -> 11900 | O149: =M149+O146 -> 71 | P149: =O149*$B$149 -> 12425 | Q149: =O149+Q146 -> 74 | R149: =Q149*$B$149 -> 12950 | S149: =Q149+S146 -> 77 | T149: =S149*$B$149 -> 13475 | U149: =S149+U146 -> 81 | V149: =U149*$B$149 -> 14175 | W149: =U149+W146 -> 85 | X149: =W149*$B$149 -> 14875 | Y149: =W149+Y146 -> 89 | Z149: =Y149*$B$149 -> 15575 | AA149: =Y149+AA146 -> 93 | AB149: =AA149*$B$149 -> 16275
A157: Ingreso Total | D157: =SUM(D144:D156) -> 705506 | F157: =SUM(F144:F156) -> 45425 | H157: =SUM(H144:H156) -> 47449 | J157: =SUM(J144:J156) -> 49916 | L157: =SUM(L144:L156) -> 52103 | N157: =SUM(N144:N156) -> 54475 | P157: =SUM(P144:P156) -> 56727 | R157: =SUM(R144:R156) -> 59422 | T157: =SUM(T144:T156) -> 61837 | V157: =SUM(V144:V156) -> 65135 | X157: =SUM(X144:X156) -> 67823 | Z157: =SUM(Z144:Z156) -> 71139 | AB157: =SUM(AB144:AB156) -> 74055
C158: =C144 -> 118 | E158: =E144 -> 8 | G158: =G144 -> 8 | I158: =I144 -> 9 | K158: =K144 -> 9 | M158: =M144 -> 9 | O158: =O144 -> 9 | Q158: =Q144 -> 10 | S158: =S144 -> 10 | U158: =U144 -> 11 | W158: =W144 -> 11 | Y158: =Y144 -> 12 | AA158: =AA144 -> 12
C159: =C145 -> 278 | E159: =E145 -> 19 | G159: =G145 -> 19 | I159: =I145 -> 21 | K159: =K145 -> 21 | M159: =M145 -> 22 | O159: =O145 -> 22 | Q159: =Q145 -> 24 | S159: =S145 -> 24 | U159: =U145 -> 25 | W159: =W145 -> 25 | Y159: =Y145 -> 28 | AA159: =AA145 -> 28
C160: =C146 -> 40 | E160: =E146 -> 3 | G160: =G146 -> 3 | I160: =I146 -> 3 | K160: =K146 -> 3 | M160: =M146 -> 3 | O160: =O146 -> 3 | Q160: =Q146 -> 3 | S160: =S146 -> 3 | U160: =U146 -> 4 | W160: =W146 -> 4 | Y160: =Y146 -> 4 | AA160: =AA146 -> 4
C161: =SUM(C147:C150) -> 9810 | E161: =SUM(E147:E150) -> 627 | G161: =SUM(G147:G150) -> 657 | I161: =SUM(I147:I150) -> 690 | K161: =SUM(K147:K150) -> 723 | M161: =SUM(M147:M150) -> 757 | O161: =SUM(O147:O150) -> 791 | Q161: =SUM(Q147:Q150) -> 828 | S161: =SUM(S147:S150) -> 865 | U161: =SUM(U147:U150) -> 905 | W161: =SUM(W147:W150) -> 945 | Y161: =SUM(Y147:Y150) -> 989 | AA161: =SUM(AA147:AA150) -> 1033
C162: =SUM(C151:C155) -> 0 | E162: =SUM(E151:E155) -> 0 | G162: =SUM(G151:G155) -> 0 | I162: =SUM(I151:I155) -> 0 | K162: =SUM(K151:K155) -> 0 | M162: =SUM(M151:M155) -> 0 | O162: =SUM(O151:O155) -> 0 | Q162: =SUM(Q151:Q155) -> 0 | S162: =SUM(S151:S155) -> 0 | U162: =SUM(U151:U155) -> 0 | W162: =SUM(W151:W155) -> 0 | Y162: =SUM(Y151:Y155) -> 0 | AA162: =SUM(AA151:AA155) -> 0
C163: =C156 -> 0 | E163: =E156 -> 0 | G163: =G156 -> 0 | I163: =I156 -> 0 | K163: =K156 -> 0 | M163: =M156 -> 0 | O163: =O156 -> 0 | Q163: =Q156 -> 0 | S163: =S156 -> 0 | U163: =U156 -> 0 | W163: =W156 -> 0 | Y163: =Y156 -> 0 | AA163: =AA156 -> 0
A165: Capacidad operativa - Año 2028
A166: Comentarios | B166: * Sigue la estructura plana: los dos fundadores y todo lo demás tercerizado o por hora.
C167: Concepto | E167: Enero | G167: Febrero | I167: Marzo | K167: Abril | M167: Mayo | O167: Junio | Q167: Julio | S167: Agosto | U167: Septiembre | W167: Octubre | Y167: Noviembre | AA167: Diciembre
A168: RRHH | C168: Gerente general | E168: Sin cambios | G168: Sin cambios | I168: Sin cambios | K168: Sin cambios | M168: Sin cambios | O168: Sin cambios | Q168: Sin cambios | S168: Sin cambios | U168: Sin cambios | W168: Sin cambios | Y168: Sin cambios | AA168: Sin cambios
...

Sheet Anexo capacidad operativa
C1: Anexo capacidad operativa
A3: Instalación y alta de los planes ShopMetrics | H3: Soporte mensual por plan | O3: Sueldo tecnico por hora: | P3: 6 | S3: Coste del kit de instalación | Y3: Coste del soporte mensual
A6: Cálculo de horas laborables de un empleado por mes
A7: Semanas por año | B7: 52 | C7: semanas
A8: Semanas de licencias varias al año | B8: 2 | C8: semanas
A9: Días festivos | B9: 14 | C9: días
A10: Días laborales totales | B10: =(B7-B8)*5 -B9 -> 236 | C10: días
A11: Jornada laboral | B11: 8 | C11: horas | T11: Alta remota: conexión con el punto de venta
A12: Horas laborables anuales por empleado | B12: =B10*B11 -> 1888 | C12: horas | T12: Visita al local: sensor de vidriera + contador de puerta
A13: Consideraremos en promedio: | B13: 1800 | C13: Horas laborables anuales / empleado | T13: Instalación en hasta cinco locales de una cadena
B14: 150 | C14: Horas laborables mensuales / empleado [HsLaboralesXMes]
A18: Alta e instalación Plan Básico | H18: Soporte mensual Plan Básico | S18: Kit Plan Básico | Y18: Soporte mensual Plan Básico
A19: N° de tarea | B19: Descripción | C19: Base horaria [BH] | D19: Cantidad requerida [Cant] | E19: Horas por tarea Fórmula = Cant * BH | H19: N° de tarea | I19: Descripción | J19: Base horaria [BH] | K19: Cantidad requerida [Cant] | L19: Horas por tarea Fórmula = Cant * BH | S19: Componente | U19: Cantidad | V19: Precio unitario | W19: Subtotal | Y19: Componente | AA19: Cantidad | AB19: Precio unitario | AC19: Subtotal
A20: 1 | B20: Contacto y coordinación | C20: 0.08 | D20: 1 | E20: =D20*C20 -> 0.08 | H20: 1 | I20: Monitoreo de ingesta | J20: 0.05 | K20: 1 | L20: =K20*J20 -> 0.05 | S20: Instalación (mano de obra) | U20: =$E$32 -> 0.5 | V20: =$P$3 -> 6 | W20: =V20*U20 -> 3 | Y20: Servicio técnico | AA20: =$L$32 -> 0.15 | AB20: =$P$3 -> 6 | AC20: =AB20*AA20 -> 0.9
A21: 2 | B21: Alta en la plataforma | C21: 0.08 | D21: 1 | E21: =D21*C21 -> 0.08 | H21: 2 | I21: Atención de consultas | J21: 0.07 | K21: 1 | L21: =K21*J21 -> 0.07
A22: 3 | B22: Conexión con el punto de venta | C22: 0.17 | D22: 1 | E22: =D22*C22 -> 0.17 | H22: 3 | I22: Reporte mensual | J22: 0.03 | K22: 1 | L22: =K22*J22 -> 0.03 | AB22: =V3 -> 0
A23: 4 | B23: Verificación de los datos | C23: 0.12 | D23: 1 | E23: =D23*C23 -> 0.12 | H23: 4 | L23: =K23*J23 -> 0
A24: 5 | B24: Capacitación remota | C24: 0.05 | D24: 1 | E24: =D24*C24 -> 0.05 | H24: 5 | L24: =K24*J24 -> 0
A25: 6 | E25: =D25*C25 -> 0 | H25: 6
A26: 7 | E26: =D26*C26 -> 0 | H26: 7
A27: 8 | E27: =D27*C27 -> 0 | H27: 8
A28: 9 | E28: =D28*C28 -> 0 | H28: 9 | S28: Total | W28: =SUM(W20:W25) -> 3 | Y28: Total | AC28: =SUM(AC20:AC25) -> 0.9
A29: 10 | E29: =D29*C29 -> 0 | H29: 10
A30: 11 | E30: =D30*C30 -> 0 | H30: 11
A31: 12 | E31: =D31*C31 -> 0 | H31: 12
A32: Comentarios: el alta del Plan Básico es remota, no requiere visita. | D32: Horas totales por servicio [HsTotalesXServicio] Fórmula = Σ Horas por tarea del servicio | E32: =SUM(E20:E31) -> 0.5 | F32: Coste por instalación | H32: Comentarios: soporte enteramente remoto. | K32: Horas totales por servicio [HsTotalesXServicio] | L32: =SUM(L20:L31) -> 0.15
D33: Capacidad operativa mensual por proyecto Fórmula = HsTotalesXSer / HsLaboralesXMes | E33: =E32/$B$14 -> 0.0033333333 | F33: =$P$3*E32 -> 3 | K33: Capacidad operativa mensual por proyecto | L33: =L32/$B$14 -> 0.001
A37: Alta e instalación Plan Vidriera | H37: Soporte mensual Plan Vidriera | S37: Kit Plan Vidriera | Y37: Soporte mensual Plan Vidriera
A38: N° de tarea | B38: Descripción | C38: Base horaria [BH] | D38: Cantidad requerida [Cant] | E38: Horas por tarea Fórmula = Cant * BH | H38: N° de tarea | I38: Descripción | J38: Base horaria [BH] | K38: Cantidad requerida [Cant] | L38: Horas por tarea Fórmula = Cant * BH | S38: Componente | U38: Cantidad | V38: Precio unitario | W38: Subtotal | Y38: Componente | AA38: Cantidad | AB38: Precio unitario | AC38: Subtotal
A39: 1 | B39: Coordinación y armado del kit | C39: 0.25 | D39: 1 | E39: =D39*C39 -> 0.25 | H39: 1 | I39: Monitoreo de ingesta | J39: 0.05 | K39: 1 | L39: =K39*J39 -> 0.05 | S39: Sensor de vidriera | U39: 1 | V39: 14 | W39: =V39*U39 -> 14 | Y39: Servicio técnico | AA39: =$L$51 -> 0.25 | AB39: =$P$3 -> 6 | AC39: =AB39*AA39 -> 1.5
A40: 2 | B40: Traslado al local | C40: 0.5 | D40: 1 | E40: =D40*C40 -> 0.5 | H40: 2 | I40: Control del sensor | J40: 0.07 | K40: 1 | L40: =K40*J40 -> 0.07 | S40: Contador de puerta | U40: 1 | V40: 9 | W40: =V40*U40 -> 9
A41: 3 | B41: Montaje del sensor de vidriera | C41: 0.75 | D41: 1 | E41: =D41*C41 -> 0.75 | H41: 3 | I41: Atención de consultas | J41: 0.08 | K41: 1 | L41: =K41*J41 -> 0.08 | S41: Gateway de conexión | U41: 1 | V41: 7 | W41: =V41*U41 -> 7
A42: 4 | B42: Instalación contador de puerta | C42: 0.5 | D42: 1 | E42: =D42*C42 -> 0.5 | H42: 4 | I42: Reporte mensual | J42: 0.05 | K42: 1 | L42: =K42*J42 -> 0.05 | S42: Kit de montaje | U42: 1 | V42: 4 | W42: =V42*U42 -> 4
A43: 5 | B43: Conexión con el punto de venta | C43: 0.25 | D43: 1 | E43: =D43*C43 -> 0.25 | H43: 5 | L43: =K43*J43 -> 0 | S43: Instalación (mano de obra) | U43: =$E$51 -> 3 | V43: =$P$3 -> 6 | W43: =V43*U43 -> 18
A44: 6 | B44: Prueba del embudo | C44: 0.5 | D44: 1 | E44: =D44*C44 -> 0.5 | H44: 6 | L44: =K44*J44 -> 0
A45: 7 | B45: Capacitación y cierre | C45: 0.25 | D45: 1 | E45: =D45*C45 -> 0.25 | H45: 7 | L45: 0
A46: 8 | E46: =D46*C46 -> 0 | H46: 8 | L46: 0
A47: 9 | E47: =D47*C47 -> 0 | H47: 9 | L47: 0 | S47: Total | W47: =SUM(W39:W44) -> 52 | Y47: Total | AC47: =SUM(AC39:AC44) -> 1.5
A48: 10 | E48: =D48*C48 -> 0 | H48: 10 | L48: 0
A49: 11 | E49: =D49*C49 -> 0 | H49: 11 | L49: 0
A50: 12 | E50: =D50*C50 -> 0 | H50: 12 | L50: 0
A51: Comentarios: incluye traslado y montaje del equipamiento en vidriera. | D51: Horas totales por servicio [HsTotalesXServicio] Fórmula = Σ Horas por tarea del servicio | E51: =SUM(E39:E50) -> 3 | F51: Coste por instalación | H51: Comentarios: suma el control del sensor de vidriera. | K51: Horas totales por servicio [HsTotalesXServicio] | L51: =SUM(L39:L50) -> 0.25
D52: Capacidad operativa mensual por empleado Fórmula = HsTotalesXSer / HsLaboralesXMes | E52: =E51/$B$14 -> 0.02 | F52: =$P$3*E51 -> 18 | K52: Capacidad operativa mensual por proyecto | L52: =L51/$B$14 -> 0.0016666667
A56: Alta e instalación Plan Cadena | H56: Soporte mensual Plan Cadena | S56: Kit Plan Cadena | Y56: Soporte mensual Plan Cadena
A57: N° de tarea | B57: Descripción | C57: Base horaria [BH] | D57: Cantidad requerida [Cant] | E57: Horas por tarea Fórmula = Cant * BH | H57: N° de tarea | I57: Descripción | J57: Base horaria [BH] | K57: Cantidad requerida [Cant] | L57: Horas por tarea Fórmula = Cant * BH | S57: Componente | U57: Cantidad | V57: Precio unitario | W57: Subtotal | Y57: Componente | AA57: Cantidad | AB57: Precio unitario | AC57: Subtotal
A58: 1 | B58: Relevamiento de la cadena | C58: 1 | D58: 1 | E58: =D58*C58 -> 1 | H58: 1 | I58: Monitoreo por local | J58: 0.04 | K58: 5 | L58: =K58*J58 -> 0.2 | S58: Sensor de vidriera | U58: 5 | V58: 14 | W58: =V58*U58 -> 70 | Y58: Servicio técnico | AA58: =$L$70 -> 0.6 | AB58: =$P$3 -> 6 | AC58: =AB58*AA58 -> 3.6
A59: 2 | B59: Alta de cadena y sucursales | C59: 0.5 | D59: 1 | E59: =D59*C59 -> 0.5 | H59: 2 | I59: Control de sensores | J59: 0.03 | K59: 5 | L59: =K59*J59 -> 0.15 | S59: Contador de puerta | U59: 5 | V59: 9 | W59: =V59*U59 -> 45
A60: 3 | B60: Traslado entre locales | C60: 0.5 | D60: 5 | E60: =D60*C60 -> 2.5 | H60: 3 | I60: Consultas del titular | J60: 0.1 | K60: 1 | L60: =K60*J60 -> 0.1 | S60: Gateway de conexión | U60: 5 | V60: 7 | W60: =V60*U60 -> 35
A61: 4 | B61: Montaje sensor de vidriera | C61: 0.75 | D61: 5 | E61: =D61*C61 -> 3.75 | H61: 4 | I61: Reporte comparativo | J61: 0.15 | K61: 1 | L61: =K61*J61 -> 0.15 | S61: Kit de montaje | U61: 5 | V61: 4 | W61: =V61*U61 -> 20
A62: 5 | B62: Instalación contador de puerta | C62: 0.4 | D62: 5 | E62: =D62*C62 -> 2 | H62: 5 | L62: =K62*J62 -> 0 | S62: Instalación (mano de obra) | U62: =$E$70 -> 12 | V62: =$P$3 -> 6 | W62: =V62*U62 -> 72
A63: 6 | B63: Conexión del punto de venta | C63: 0.2 | D63: 5 | E63: =D63*C63 -> 1 | H63: 6 | L63: =K63*J63 -> 0
A64: 7 | B64: Prueba comparativa | C64: 0.75 | D64: 1 | E64: =D64*C64 -> 0.75 | H64: 7 | L64: =K64*J64 -> 0
A65: 8 | B65: Capacitación del responsable | C65: 0.5 | D65: 1 | E65: =D65*C65 -> 0.5 | H65: 8 | L65: =K65*J65 -> 0 | S65: Total | W65: =SUM(W58:W64) -> 242 | Y65: Total | AC65: =SUM(AC58:AC64) -> 3.6
A66: 9 | E66: =D66*C66 -> 0 | H66: 9 | L66: 0
A67: 10 | E67: =D67*C67 -> 0 | H67: 10 | L67: 0
A68: 11 | E68: =D68*C68 -> 0 | H68: 11 | L68: 0
A69: 12 | E69: =D69*C69 -> 0 | H69: 12 | L69: 0
A70: Comentarios: cubre hasta cinco locales de una misma cadena. | D70: Horas totales por servicio [HsTotalesXServicio] Fórmula = Σ Horas por tarea del servicio | E70: =SUM(E58:E69) -> 12 | F70: Coste por instalación | H70: Comentarios: el monitoreo se repite por local. | K70: Horas totales por servicio [HsTotalesXServicio] | L70: =SUM(L58:L69) -> 0.6
D71: Capacidad operativa mensual por empleado Fórmula = HsTotalesXSer / HsLaboralesXMes | E71: =E70/$B$14 -> 0.08 | F71: =$P$3*E70 -> 72 | K71: Capacidad operativa mensual por proyecto | L71: =L70/$B$14 -> 0.004
A76: Detalle: el soporte por plan es mensual y se sostiene mientras el comercio permanece abonado.
A77: ANALISIS CAPACIDAD OPERATIVA ANUAL POR SERVICIO EN HORAS HOMBRE
A78: CAPACIDAD OPERATIVA AÑO 2026 | C78: Enero | E78: Febrero | G78: Marzo | I78: Abril | K78: Mayo | M78: Junio | O78: Julio | Q78: Agosto | S78: Septiembre | U78: Octubre | W78: Noviembre | Y78: Diciembre
C79: Unidades requeridas | D79: Horas Hombre requeridas | E79: Unidades requeridas | F79: Horas Hombre requeridos | G79: Unidades requeridas | H79: Horas Hombre requeridas | I79: Unidades requeridas | J79: Horas Hombre requeridos | K79: Unidades requeridas | L79: Horas Hombre requeridas | M79: Unidades requeridas | N79: Horas Hombre requeridas | O79: Unidades requeridas | P79: Horas Hombre requeridas | Q79: Unidades requeridas | R79: Horas Hombre requeridas | S79: Unidades requeridas | T79: Horas Hombre requeridas | U79: Unidades requeridas | V79: Horas Hombre requeridas | W79: Unidades requeridas | X79: Horas Hombre requeridas | Y79: Unidades requeridas | Z79: Horas Hombre requeridas
A80: =Hipótesis!B$58 -> Alta e instalación Plan Básico | B80: =D80+F80+H80+J80+L80+N80+P80+R80+T80+V80+X80+Z80 -> 37 | C80: ='Proy. ventas'!E19 -> 0 | D80: =C80*$E$32 -> 0 | E80: ='Proy. ventas'!G33 -> 1 | F80: =E80*$E$32 -> 0.5 | G80: ='Proy. ventas'!I33 -> 1 | H80: =G80*$E$32 -> 0.5 | I80: ='Proy. ventas'!K33 -> 2 | J80: =I80*$E$32 -> 1 | K80: ='Proy. ventas'!M33 -> 4 | L80: =K80*$E$32 -> 2 | M80: ='Proy. ventas'!O33 -> 5 | N80: =M80*$E$32 -> 2.5 | O80: ='Proy. ventas'!Q33 -> 7 | P80: =O80*$E$32 -> 3.5 | Q80: ='Proy. ventas'!S33 -> 8 | R80: =Q80*$E$32 -> 4 | S80: ='Proy. ventas'!U33 -> 9 | T80: =S80*$E$32 -> 4.5 | U80: ='Proy. ventas'!W33 -> 11 | V80: =U80*$E$32 -> 5.5 | W80: ='Proy. ventas'!Y33 -> 12 | X80: =W80*$E$32 -> 6 | Y80: ='Proy. ventas'!AA33 -> 14 | Z80: =Y80*$E$32 -> 7
A81: =Hipótesis!B$59 -> Alta e instalación Plan Vidriera | B81: =D81+F81+H81+J81+L81+N81+P81+R81+T81+V81+X81+Z81 -> 516 | C81: ='Proy. ventas'!E20 -> 0 | D81: =C81*$E$51 -> 0 | E81: ='Proy. ventas'!G34 -> 2 | F81: =E81*$E$51 -> 6 | G81: ='Proy. ventas'!I34 -> 3 | H81: =G81*$E$51 -> 9 | I81: ='Proy. ventas'!K34 -> 5 | J81: =I81*$E$51 -> 15 | K81: ='Proy. ventas'!M34 -> 9 | L81: =K81*$E$51 -> 27 | M81: ='Proy. ventas'!O34 -> 12 | N81: =M81*$E$51 -> 36 | O81: ='Proy. ventas'!Q34 -> 15 | P81: =O81*$E$51 -> 45 | Q81: ='Proy. ventas'!S34 -> 19 | R81: =Q81*$E$51 -> 57 | S81: ='Proy. ventas'!U34 -> 21 | T81: =S81*$E$51 -> 63 | U81: ='Proy. ventas'!W34 -> 26 | V81: =U81*$E$51 -> 78 | W81: ='Proy. ventas'!Y34 -> 27 | X81: =W81*$E$51 -> 81 | Y81: ='Proy. ventas'!AA34 -> 33 | Z81: =Y81*$E$51 -> 99
A82: =Hipótesis!B$60 -> Alta e instalación Plan Cadena | B82: =D82+F82+H82+J82+L82+N82+P82+R82+T82+V82+X82+Z82 -> 300 | C82: ='Proy. ventas'!E21 -> 0 | D82: =C82*$E$70 -> 0 | E82: ='Proy. ventas'!G35 -> 0 | F82: =E82*$E$70 -> 0 | G82: ='Proy. ventas'!I35 -> 0 | H82: =G82*$E$70 -> 0 | I82: ='Proy. ventas'!K35 -> 1 | J82: =I82*$E$70 -> 12 | K82: ='Proy. ventas'!M35 -> 1 | L82: =K82*$E$70 -> 12 | M82: ='Proy. ventas'!O35 -> 2 | N82: =M82*$E$70 -> 24 | O82: ='Proy. ventas'!Q35 -> 2 | P82: =O82*$E$70 -> 24 | Q82: ='Proy. ventas'!S35 -> 3 | R82: =Q82*$E$70 -> 36 | S82: ='Proy. ventas'!U35 -> 3 | T82: =S82*$E$70 -> 36 | U82: ='Proy. ventas'!W35 -> 4 | V82: =U82*$E$70 -> 48 | W82: ='Proy. ventas'!Y35 -> 4 | X82: =W82*$E$70 -> 48 | Y82: ='Proy. ventas'!AA35 -> 5 | Z82: =Y82*$E$70 -> 60
A83: =Hipótesis!B$61 -> Abono Plan Básico | B83: =D83+F83+H83+J83+L83+N83+P83+R83+T83+V83+X83+Z83 -> 44.25 | C83: ='Proy. ventas'!E22 -> 0 | D83: =C83*$L$32 -> 0 | E83: ='Proy. ventas'!G22 -> 1 | F83: =E83*$L$32 -> 0.15 | G83: ='Proy. ventas'!I22 -> 2 | H83: =G83*$L$32 -> 0.3 | I83: ='Proy. ventas'!K22 -> 4 | J83: =I83*$L$32 -> 0.6 | K83: ='Proy. ventas'!M22 -> 8 | L83: =K83*$L$32 -> 1.2 | M83: ='Proy. ventas'!O22 -> 13 | N83: =M83*$L$32 -> 1.95 | O83: ='Proy. ventas'!Q22 -> 20 | P83: =O83*$L$32 -> 3 | Q83: ='Proy. ventas'!S22 -> 28 | R83: =Q83*$L$32 -> 4.2 | S83: ='Proy. ventas'!U22 -> 37 | T83: =S83*$L$32 -> 5.55 | U83: ='Proy. ventas'!W22 -> 48 | V83: =U83*$L$32 -> 7.2 | W83: ='Proy. ventas'!Y22 -> 60 | X83: =W83*$L$32 -> 9 | Y83: ='Proy. ventas'!AA22 -> 74 | Z83: =Y83*$L$32 -> 11.1
A84: =Hipótesis!B$62 -> Abono Plan Vidriera | B84: =D84+F84+H84+J84+L84+N84+P84+R84+T84+V84+X84+Z84 -> 171.75 | C84: ='Proy. ventas'!E23 -> 0 | D84: =C84*$L$51 -> 0 | E84: ='Proy. ventas'!G23 -> 2 | F84: =E84*$L$51 -> 0.5 | G84: ='Proy. ventas'!I23 -> 5 | H84: =G84*$L$51 -> 1.25 | I84: ='Proy. ventas'!K23 -> 10 | J84: =I84*$L$51 -> 2.5 | K84: ='Proy. ventas'!M23 -> 19 | L84: =K84*$L$51 -> 4.75 | M84: ='Proy. ventas'!O23 -> 31 | N84: =M84*$L$51 -> 7.75 | O84: ='Proy. ventas'!Q23 -> 46 | P84: =O84*$L$51 -> 11.5 | Q84: ='Proy. ventas'!S23 -> 65 | R84: =Q84*$L$51 -> 16.25 | S84: ='Proy. ventas'!U23 -> 86 | T84: =S84*$L$51 -> 21.5 | U84: ='Proy. ventas'!W23 -> 112 | V84: =U84*$L$51 -> 28 | W84: ='Proy. ventas'!Y23 -> 139 | X84: =W84*$L$51 -> 34.75 | Y84: ='Proy. ventas'!AA23 -> 172 | Z84: =Y84*$L$51 -> 43
A85: =Hipótesis!B$63 -> Abono Plan Cadena | B85: =D85+F85+H85+J85+L85+N85+P85+R85+T85+V85+X85+Z85 -> 57 | C85: ='Proy. ventas'!E24 -> 0 | D85: =C85*$L$70 -> 0 | E85: ='Proy. ventas'!G24 -> 0 | F85: =E85*$L$70 -> 0 | G85: ='Proy. ventas'!I24 -> 0 | H85: =G85*$L$70 -> 0 | I85: ='Proy. ventas'!K24 -> 1 | J85: =I85*$L$70 -> 0.6 | K85: ='Proy. ventas'!M24 -> 2 | L85: =K85*$L$70 -> 1.2 | M85: ='Proy. ventas'!O24 -> 4 | N85: =M85*$L$70 -> 2.4 | O85: ='Proy. ventas'!Q24 -> 6 | P85: =O85*$L$70 -> 3.6 | Q85: ='Proy. ventas'!S24 -> 9 | R85: =Q85*$L$70 -> 5.4 | S85: ='Proy. ventas'!U24 -> 12 | T85: =S85*$L$70 -> 7.2 | U85: ='Proy. ventas'!W24 -> 16 | V85: =U85*$L$70 -> 9.6 | W85: ='Proy. ventas'!Y24 -> 20 | X85: =W85*$L$70 -> 12 | Y85: ='Proy. ventas'!AA24 -> 25 | Z85: =Y85*$L$70 -> 15
A86: TOTALES | B86: =D86+F86+H86+J86+L86+N86+P86+R86+T86+V86+X86+Z86 -> 1126 | C86: =SUM(C80:C85) -> 0 | D86: =SUM(D80:D85) -> 0 | E86: =SUM(E80:E85) -> 6 | F86: =SUM(F80:F85) -> 7.15 | G86: =SUM(G80:G85) -> 11 | H86: =SUM(H80:H85) -> 11.05 | I86: =SUM(I80:I85) -> 23 | J86: =SUM(J80:J85) -> 31.7 | ... Z86: =SUM(Z80:Z85) -> 235.1
A87: Horas contratadas a técnicos freelance (por mes completo de 150 h, a demanda) | B87: =D87+F87+H87+J87+L87+N87+P87+R87+T87+V87+X87+Z87 -> 2100 | D87: =ROUNDUP(D86/$B$14,0)*$B$14 -> 0 | F87: =ROUNDUP(F86/$B$14,0)*$B$14 -> 150 | H87: =ROUNDUP(H86/$B$14,0)*$B$14 -> 150 | J87: =ROUNDUP(J86/$B$14,0)*$B$14 -> 150 | L87: =ROUNDUP(L86/$B$14,0)*$B$14 -> 150 | N87: =ROUNDUP(N86/$B$14,0)*$B$14 -> 150 | P87: =ROUNDUP(P86/$B$14,0)*$B$14 -> 150 | R87: =ROUNDUP(R86/$B$14,0)*$B$14 -> 150 | T87: =ROUNDUP(T86/$B$14,0)*$B$14 -> 150 | V87: =ROUNDUP(V86/$B$14,0)*$B$14 -> 300 | X87: =ROUNDUP(X86/$B$14,0)*$B$14 -> 300 | Z87: =ROUNDUP(Z86/$B$14,0)*$B$14 -> 300
A88: Holgura (h) — negativo = capacidad excedida | B88: =B87-B86 -> 974 | D88: =D87-D86 -> 0 | F88: =F87-F86 -> 142.85 | H88: =H87-H86 -> 138.95 | J88: =J87-J86 -> 118.3 | L88: =L87-L86 -> 101.85 | N88: =N87-N86 -> 75.4 | P88: =P87-P86 -> 59.4 | R88: =R87-R86 -> 27.15 | T88: =T87-T86 -> 12.25 | V88: =V87-V86 -> 123.7 | X88: =X87-X86 -> 109.25 | Z88: =Z87-Z86 -> 64.9
A89: CAPACIDAD OPERATIVA AÑO 2027 | C89: Enero | E89: Febrero | G89: Marzo | I89: Abril | K89: Mayo | M89: Junio | O89: Julio | Q89: Agosto | S89: Septiembre | U89: Octubre | W89: Noviembre | Y89: Diciembre
C90: Unidades requeridas | D90: Horas Hombre requeridas | E90: Unidades requeridas | F90: Horas Hombre requeridos | G90: Unidades requeridas | H90: Horas Hombre requeridas | I90: Unidades requeridas | J90: Horas Hombre requeridos | K90: Unidades requeridas | L90: Horas Hombre requeridas | M90: Unidades requeridas | N90: Horas Hombre requeridas | O90: Unidades requeridas | P90: Horas Hombre requeridas | Q90: Unidades requeridas | R90: Horas Hombre requeridas | S90: Unidades requeridas | T90: Horas Hombre requeridas | U90: Unidades requeridas | V90: Horas Hombre requeridas | W90: Unidades requeridas | X90: Horas Hombre requeridas | Y90: Unidades requeridas | Z90: Horas Hombre requeridas
A91: =Hipótesis!B$58 -> Alta e instalación Plan Básico | B91: =D91+F91+H91+J91+L91+N91+P91+R91+T91+V91+X91+Z91 -> 44 | C91: ='Proy. ventas'!E82 -> 6 | D91: =C91*$E$32 -> 3 | E91: ='Proy. ventas'!G82 -> 6 | F91: =E91*$E$32 -> 3 | G91: ='Proy. ventas'!I82 -> 7 | H91: =G91*$E$32 -> 3.5 | I91: ='Proy. ventas'!K82 -> 7 | J91: =I91*$E$32 -> 3.5 | K91: ='Proy. ventas'!M82 -> 7 | L91: =K91*$E$32 -> 3.5 | M91: ='Proy. ventas'!O82 -> 7 | N91: =M91*$E$32 -> 3.5 | O91: ='Proy. ventas'!Q82 -> 7 | P91: =O91*$E$32 -> 3.5 | Q91: ='Proy. ventas'!S82 -> 7 | R91: =Q91*$E$32 -> 3.5 | S91: ='Proy. ventas'!U82 -> 8 | T91: =S91*$E$32 -> 4 | U91: ='Proy. ventas'!W82 -> 8 | V91: =U91*$E$32 -> 4 | W91: ='Proy. ventas'!Y82 -> 9 | X91: =W91*$E$32 -> 4.5 | Y91: ='Proy. ventas'!AA82 -> 9 | Z91: =Y91*$E$32 -> 4.5
A92: =Hipótesis!B$59 -> Alta e instalación Plan Vidriera | B92: =D92+F92+H92+J92+L92+N92+P92+R92+T92+V92+X92+Z92 -> 630 | C92: ='Proy. ventas'!E83 -> 14 | D92: =C92*$E$51 -> 42 | E92: ='Proy. ventas'!G83 -> 14 | F92: =E92*$E$51 -> 42 | G92: ='Proy. ventas'!I83 -> 16 | H92: =G92*$E$51 -> 48 | I92: ='Proy. ventas'!K83 -> 16 | J92: =I92*$E$51 -> 48 | K92: ='Proy. ventas'!M83 -> 17 | L92: =K92*$E$51 -> 51 | M92: ='Proy. ventas'!O83 -> 17 | N92: =M92*$E$51 -> 51 | O92: ='Proy. ventas'!Q83 -> 18 | P92: =O92*$E$51 -> 54 | Q92: ='Proy. ventas'!S83 -> 18 | R92: =Q92*$E$51 -> 54 | S92: ='Proy. ventas'!U83 -> 19 | T92: =S92*$E$51 -> 57 | U92: ='Proy. ventas'!W83 -> 19 | V92: =U92*$E$51 -> 57 | W92: ='Proy. ventas'!Y83 -> 21 | X92: =W92*$E$51 -> 63 | Y92: ='Proy. ventas'!AA83 -> 21 | Z92: =Y92*$E$51 -> 63
A93: =Hipótesis!B$60 -> Alta e instalación Plan Cadena | B93: =D93+F93+H93+J93+L93+N93+P93+R93+T93+V93+X93+Z93 -> 336 | C93: ='Proy. ventas'!E84 -> 2 | D93: =C93*$E$70 -> 24 | E93: ='Proy. ventas'!G84 -> 2 | F93: =E93*$E$70 -> 24 | G93: ='Proy. ventas'!I84 -> 2 | H93: =G93*$E$70 -> 24 | I93: ='Proy. ventas'!K84 -> 2 | J93: =I93*$E$70 -> 24 | K93: ='Proy. ventas'!M84 -> 2 | L93: =K93*$E$70 -> 24 | M93: ='Proy. ventas'!O84 -> 2 | N93: =M93*$E$70 -> 24 | O93: ='Proy. ventas'!Q84 -> 2 | P93: =O93*$E$70 -> 24 | Q93: ='Proy. ventas'!S84 -> 2 | R93: =Q93*$E$70 -> 24 | S93: ='Proy. ventas'!U84 -> 3 | T93: =S93*$E$70 -> 36 | U93: ='Proy. ventas'!W84 -> 3 | V93: =U93*$E$70 -> 36 | W93: ='Proy. ventas'!Y84 -> 3 | X93: =W93*$E$70 -> 36 | Y93: ='Proy. ventas'!AA84 -> 3 | Z93: =Y93*$E$70 -> 36
A94: =Hipótesis!B$61 -> Abono Plan Básico | B94: =D94+F94+H94+J94+L94+N94+P94+R94+T94+V94+X94+Z94 -> 213.6 | C94: ='Proy. ventas'!E85 -> 80 | D94: =C94*$L$32 -> 12 | E94: ='Proy. ventas'!G85 -> 86 | F94: =E94*$L$32 -> 12.9 | G94: ='Proy. ventas'!I85 -> 93 | H94: =G94*$L$32 -> 13.95 | I94: ='Proy. ventas'!K85 -> 100 | J94: =I94*$L$32 -> 15 | K94: ='Proy. ventas'!M85 -> 107 | L94: =K94*$L$32 -> 16.05 | M94: ='Proy. ventas'!O85 -> 114 | N94: =M94*$L$32 -> 17.1 | O94: ='Proy. ventas'!Q85 -> 121 | P94: =O94*$L$32 -> 18.15 | Q94: ='Proy. ventas'!S85 -> 128 | R94: =Q94*$L$32 -> 19.2 | S94: ='Proy. ventas'!U85 -> 136 | T94: =S94*$L$32 -> 20.4 | U94: ='Proy. ventas'!W85 -> 144 | V94: =U94*$L$32 -> 21.6 | W94: ='Proy. ventas'!Y85 -> 153 | X94: =W94*$L$32 -> 22.95 | Y94: ='Proy. ventas'!AA85 -> 162 | Z94: =Y94*$L$32 -> 24.3
A95: =Hipótesis!B$62 -> Abono Plan Vidriera | B95: =D95+F95+H95+J95+L95+N95+P95+R95+T95+V95+X95+Z95 -> 834.75 | C95: ='Proy. ventas'!E86 -> 186 | D95: =C95*$L$51 -> 46.5 | E95: ='Proy. ventas'!G86 -> 200 | F95: =E95*$L$51 -> 50 | G95: ='Proy. ventas'!I86 -> 216 | H95: =G95*$L$51 -> 54 | I95: ='Proy. ventas'!K86 -> 232 | J95: =I95*$L$51 -> 58 | K95: ='Proy. ventas'!M86 -> 249 | L95: =K95*$L$51 -> 62.25 | M95: ='Proy. ventas'!O86 -> 266 | N95: =M95*$L$51 -> 66.5 | O95: ='Proy. ventas'!Q86 -> 284 | P95: =O95*$L$51 -> 71 | Q95: ='Proy. ventas'!S86 -> 302 | R95: =Q95*$L$51 -> 75.5 | S95: ='Proy. ventas'!U86 -> 321 | T95: =S95*$L$51 -> 80.25 | U95: ='Proy. ventas'!W86 -> 340 | V95: =U95*$L$51 -> 85 | W95: ='Proy. ventas'!Y86 -> 361 | X95: =W95*$L$51 -> 90.25 | Y95: ='Proy. ventas'!AA86 -> 382 | Z95: =Y95*$L$51 -> 95.5
A96: =Hipótesis!B$63 -> Abono Plan Cadena | B96: =D96+F96+H96+J96+L96+N96+P96+R96+T96+V96+X96+Z96 -> 279.6 | C96: ='Proy. ventas'!E87 -> 27 | D96: =C96*$L$70 -> 16.2 | E96: ='Proy. ventas'!G87 -> 29 | F96: =E96*$L$70 -> 17.4 | G96: ='Proy. ventas'!I87 -> 31 | H96: =G96*$L$70 -> 18.6 | I96: ='Proy. ventas'!K87 -> 33 | J96: =I96*$L$70 -> 19.8 | K96: ='Proy. ventas'!M87 -> 35 | L96: =K96*$L$70 -> 21 | M96: ='Proy. ventas'!O87 -> 37 | N96: =M96*$L$70 -> 22.2 | O96: ='Proy. ventas'!Q87 -> 39 | P96: =O96*$L$70 -> 23.4 | Q96: ='Proy. ventas'!S87 -> 41 | R96: =Q96*$L$70 -> 24.6 | S96: ='Proy. ventas'!U87 -> 44 | T96: =S96*$L$70 -> 26.4 | U96: ='Proy. ventas'!W87 -> 47 | V96: =U96*$L$70 -> 28.2 | W96: ='Proy. ventas'!Y87 -> 50 | X96: =W96*$L$70 -> 30 | Y96: ='Proy. ventas'!AA87 -> 53 | Z96: =Y96*$L$70 -> 31.8
A97: TOTALES | B97: =D97+F97+H97+J97+L97+N97+P97+R97+T97+V97+X97+Z97 -> 2337.95 | C97: =SUM(C91:C96) -> 315 | D97: =SUM(D91:D96) -> 143.7 | E97: =SUM(E91:E96) -> 337 | F97: =SUM(F91:F96) -> 149.3 | G97: =SUM(G91:G96) -> 365 | H97: =SUM(H91:H96) -> 162.05 | I97: =SUM(I91:I96) -> 390 | J97: =SUM(J91:J96) -> 168.3 | ... Z97: =SUM(Z91:Z96) -> 255.1
A98: Horas contratadas a técnicos freelance (por mes completo de 150 h, a demanda) | B98: =D98+F98+H98+J98+L98+N98+P98+R98+T98+V98+X98+Z98 -> 3300 | D98: =ROUNDUP(D97/$B$14,0)*$B$14 -> 150 | F98: =ROUNDUP(F97/$B$14,0)*$B$14 -> 150 | H98: =ROUNDUP(H97/$B$14,0)*$B$14 -> 300 | J98: =ROUNDUP(J97/$B$14,0)*$B$14 -> 300 | L98: =ROUNDUP(L97/$B$14,0)*$B$14 -> 300 | N98: =ROUNDUP(N97/$B$14,0)*$B$14 -> 300 | P98: =ROUNDUP(P97/$B$14,0)*$B$14 -> 300 | R98: =ROUNDUP(R97/$B$14,0)*$B$14 -> 300 | T98: =ROUNDUP(T97/$B$14,0)*$B$14 -> 300 | V98: =ROUNDUP(V97/$B$14,0)*$B$14 -> 300 | X98: =ROUNDUP(X97/$B$14,0)*$B$14 -> 300 | Z98: =ROUNDUP(Z97/$B$14,0)*$B$14 -> 300
A99: Holgura (h) — negativo = capacidad excedida | B99: =B98-B97 -> 962.05 | D99: =D98-D97 -> 6.3 | F99: =F98-F97 -> 0.7 | H99: =H98-H97 -> 137.95 | J99: =J98-J97 -> 131.7 | L99: =L98-L97 -> 122.2 | N99: =N98-N97 -> 115.7 | P99: =P98-P97 -> 105.95 | R99: =R98-R97 -> 99.2 | T99: =T98-T97 -> 75.95 | V99: =V98-V97 -> 68.2 | X99: =X98-X97 -> 53.3 | Z99: =Z98-Z97 -> 44.9
A100: CAPACIDAD OPERATIVA AÑO 2028 | C100: Enero | E100: Febrero | G100: Marzo | I100: Abril | K100: Mayo | M100: Junio | O100: Julio | Q100: Agosto | S100: Septiembre | U100: Octubre | W100: Noviembre | Y100: Diciembre
C101: Unidades requeridas | D101: Horas Hombre requeridas | E101: Unidades requeridas | F101: Horas Hombre requeridos | G101: Unidades requeridas | H101: Horas Hombre requeridas | I101: Unidades requeridas | J101: Horas Hombre requeridos | K101: Unidades requeridas | L101: Horas Hombre requeridas | M101: Unidades requeridas | N101: Horas Hombre requeridas | O101: Unidades requeridas | P101: Horas Hombre requeridas | Q101: Unidades requeridas | R101: Horas Hombre requeridas | S101: Unidades requeridas | T101: Horas Hombre requeridas | U101: Unidades requeridas | V101: Horas Hombre requeridas | W101: Unidades requeridas | X101: Horas Hombre requeridas | Y101: Unidades requeridas | Z101: Horas Hombre requeridas
A102: =Hipótesis!B$58 -> Alta e instalación Plan Básico | B102: =D102+F102+H102+J102+L102+N102+P102+R102+T102+V102+X102+Z102 -> 59 | C102: ='Proy. ventas'!E144 -> 8 | D102: =C102*$E$32 -> 4 | E102: ='Proy. ventas'!G144 -> 8 | F102: =E102*$E$32 -> 4 | G102: ='Proy. ventas'!I144 -> 9 | H102: =G102*$E$32 -> 4.5 | I102: ='Proy. ventas'!K144 -> 9 | J102: =I102*$E$32 -> 4.5 | K102: ='Proy. ventas'!M144 -> 9 | L102: =K102*$E$32 -> 4.5 | M102: ='Proy. ventas'!O144 -> 9 | N102: =M102*$E$32 -> 4.5 | O102: ='Proy. ventas'!Q144 -> 10 | P102: =O102*$E$32 -> 5 | Q102: ='Proy. ventas'!S144 -> 10 | R102: =Q102*$E$32 -> 5 | S102: ='Proy. ventas'!U144 -> 11 | T102: =S102*$E$32 -> 5.5 | U102: ='Proy. ventas'!W144 -> 11 | V102: =U102*$E$32 -> 5.5 | W102: ='Proy. ventas'!Y144 -> 12 | X102: =W102*$E$32 -> 6 | Y102: ='Proy. ventas'!AA144 -> 12 | Z102: =Y102*$E$32 -> 6
A103: =Hipótesis!B$59 -> Alta e instalación Plan Vidriera | B103: =D103+F103+H103+J103+L103+N103+P103+R103+T103+V103+X103+Z103 -> 834 | C103: ='Proy. ventas'!E145 -> 19 | D103: =C103*$E$51 -> 57 | E103: ='Proy. ventas'!G145 -> 19 | F103: =E103*$E$51 -> 57 | G103: ='Proy. ventas'!I145 -> 21 | H103: =G103*$E$51 -> 63 | I103: ='Proy. ventas'!K145 -> 21 | J103: =I103*$E$51 -> 63 | K103: ='Proy. ventas'!M145 -> 22 | L103: =K103*$E$51 -> 66 | M103: ='Proy. ventas'!O145 -> 22 | N103: =M103*$E$51 -> 66 | O103: ='Proy. ventas'!Q145 -> 24 | P103: =O103*$E$51 -> 72 | Q103: ='Proy. ventas'!S145 -> 24 | R103: =Q103*$E$51 -> 72 | S103: ='Proy. ventas'!U145 -> 25 | T103: =S103*$E$51 -> 75 | U103: ='Proy. ventas'!W145 -> 25 | V103: =U103*$E$51 -> 75 | W103: ='Proy. ventas'!Y145 -> 28 | X103: =W103*$E$51 -> 84 | Y103: ='Proy. ventas'!AA145 -> 28 | Z103: =Y103*$E$51 -> 84
A104: =Hipótesis!B$60 -> Alta e instalación Plan Cadena | B104: =D104+F104+H104+J104+L104+N104+P104+R104+T104+V104+X104+Z104 -> 480 | C104: ='Proy. ventas'!E146 -> 3 | D104: =C104*$E$70 -> 36 | E104: ='Proy. ventas'!G146 -> 3 | F104: =E104*$E$70 -> 36 | G104: ='Proy. ventas'!I146 -> 3 | H104: =G104*$E$70 -> 36 | I104: ='Proy. ventas'!K146 -> 3 | J104: =I104*$E$70 -> 36 | K104: ='Proy. ventas'!M146 -> 3 | L104: =K104*$E$70 -> 36 | M104: ='Proy. ventas'!O146 -> 3 | N104: =M104*$E$70 -> 36 | O104: ='Proy. ventas'!Q146 -> 3 | P104: =O104*$E$70 -> 36 | Q104: ='Proy. ventas'!S146 -> 3 | R104: =Q104*$E$70 -> 36 | S104: ='Proy. ventas'!U146 -> 4 | T104: =S104*$E$70 -> 48 | U104: ='Proy. ventas'!W146 -> 4 | V104: =U104*$E$70 -> 48 | W104: ='Proy. ventas'!Y146 -> 4 | X104: =W104*$E$70 -> 48 | Y104: ='Proy. ventas'!AA146 -> 4 | Z104: =Y104*$E$70 -> 48
A105: =Hipótesis!B$61 -> Abono Plan Básico | B105: =D105+F105+H105+J105+L105+N105+P105+R105+T105+V105+X105+Z105 -> 398.55 | C105: ='Proy. ventas'!E147 -> 170 | D105: =C105*$L$32 -> 25.5 | E105: ='Proy. ventas'!G147 -> 178 | F105: =E105*$L$32 -> 26.7 | G105: ='Proy. ventas'!I147 -> 187 | H105: =G105*$L$32 -> 28.05 | I105: ='Proy. ventas'!K147 -> 196 | J105: =I105*$L$32 -> 29.4 | K105: ='Proy. ventas'!M147 -> 205 | L105: =K105*$L$32 -> 30.75 | M105: ='Proy. ventas'!O147 -> 214 | N105: =M105*$L$32 -> 32.1 | O105: ='Proy. ventas'!Q147 -> 224 | P105: =O105*$L$32 -> 33.6 | Q105: ='Proy. ventas'!S147 -> 234 | R105: =Q105*$L$32 -> 35.1 | S105: ='Proy. ventas'!U147 -> 245 | T105: =S105*$L$32 -> 36.75 | U105: ='Proy. ventas'!W147 -> 256 | V105: =U105*$L$32 -> 38.4 | W105: ='Proy. ventas'!Y147 -> 268 | X105: =W105*$L$32 -> 40.2 | Y105: ='Proy. ventas'!AA147 -> 280 | Z105: =Y105*$L$32 -> 42
A106: =Hipótesis!B$62 -> Abono Plan Vidriera | B106: =D106+F106+H106+J106+L106+N106+P106+R106+T106+V106+X106+Z106 -> 1568.25 | C106: ='Proy. ventas'!E148 -> 401 | D106: =C106*$L$51 -> 100.25 | E106: ='Proy. ventas'!G148 -> 420 | F106: =E106*$L$51 -> 105 | G106: ='Proy. ventas'!I148 -> 441 | H106: =G106*$L$51 -> 110.25 | I106: ='Proy. ventas'!K148 -> 462 | J106: =I106*$L$51 -> 115.5 | K106: ='Proy. ventas'!M148 -> 484 | L106: =K106*$L$51 -> 121 | M106: ='Proy. ventas'!O148 -> 506 | N106: =M106*$L$51 -> 126.5 | O106: ='Proy. ventas'!Q148 -> 530 | P106: =O106*$L$51 -> 132.5 | Q106: ='Proy. ventas'!S148 -> 554 | R106: =Q106*$L$51 -> 138.5 | S106: ='Proy. ventas'!U148 -> 579 | T106: =S106*$L$51 -> 144.75 | U106: ='Proy. ventas'!W148 -> 604 | V106: =U106*$L$51 -> 151 | W106: ='Proy. ventas'!Y148 -> 632 | X106: =W106*$L$51 -> 158 | Y106: ='Proy. ventas'!AA148 -> 660 | Z106: =Y106*$L$51 -> 165
A107: =Hipótesis!B$63 -> Abono Plan Cadena | B107: =D107+F107+H107+J107+L107+N107+P107+R107+T107+V107+X107+Z107 -> 528 | C107: ='Proy. ventas'!E149 -> 56 | D107: =C107*$L$70 -> 33.6 | E107: ='Proy. ventas'!G149 -> 59 | F107: =E107*$L$70 -> 35.4 | G107: ='Proy. ventas'!I149 -> 62 | H107: =G107*$L$70 -> 37.2 | I107: ='Proy. ventas'!K149 -> 65 | J107: =I107*$L$70 -> 39 | K107: ='Proy. ventas'!M149 -> 68 | L107: =K107*$L$70 -> 40.8 | M107: ='Proy. ventas'!O149 -> 71 | N107: =M107*$L$70 -> 42.6 | O107: ='Proy. ventas'!Q149 -> 74 | P107: =O107*$L$70 -> 44.4 | Q107: ='Proy. ventas'!S149 -> 77 | R107: =Q107*$L$70 -> 46.2 | S107: ='Proy. ventas'!U149 -> 81 | T107: =S107*$L$70 -> 48.6 | U107: ='Proy. ventas'!W149 -> 85 | V107: =U107*$L$70 -> 51 | W107: ='Proy. ventas'!Y149 -> 89 | X107: =W107*$L$70 -> 53.4 | Y107: ='Proy. ventas'!AA149 -> 93 | Z107: =Y107*$L$70 -> 55.8
A108: TOTALES | B108: =D108+F108+H108+J108+L108+N108+P108+R108+T108+V108+X108+Z108 -> 3867.8 | C108: =SUM(C102:C107) -> 657 | D108: =SUM(D102:D107) -> 256.35 | E108: =SUM(E102:E107) -> 687 | F108: =SUM(F102:F107) -> 264.1 | G108: =SUM(G102:G107) -> 723 | H108: =SUM(H102:H107) -> 279 | I108: =SUM(I102:I107) -> 756 | J108: =SUM(J102:J107) -> 287.4 | ... Z108: =SUM(Z102:Z107) -> 400.8
A109: Horas contratadas a técnicos freelance (por mes completo de 150 h, a demanda) | B109: =D109+F109+H109+J109+L109+N109+P109+R109+T109+V109+X109+Z109 -> 4650 | D109: =ROUNDUP(D108/$B$14,0)*$B$14 -> 300 | F109: =ROUNDUP(F108/$B$14,0)*$B$14 -> 300 | H109: =ROUNDUP(H108/$B$14,0)*$B$14 -> 300 | J109: =ROUNDUP(J108/$B$14,0)*$B$14 -> 300 | L109: =ROUNDUP(L108/$B$14,0)*$B$14 -> 300 | N109: =ROUNDUP(N108/$B$14,0)*$B$14 -> 450 | P109: =ROUNDUP(P108/$B$14,0)*$B$14 -> 450 | R109: =ROUNDUP(R108/$B$14,0)*$B$14 -> 450 | T109: =ROUNDUP(T108/$B$14,0)*$B$14 -> 450 | V109: =ROUNDUP(V108/$B$14,0)*$B$14 -> 450 | X109: =ROUNDUP(X108/$B$14,0)*$B$14 -> 450 | Z109: =ROUNDUP(Z108/$B$14,0)*$B$14 -> 450
A110: Holgura (h) — negativo = capacidad excedida | B110: =B109-B108 -> 782.2 | D110: =D109-D108 -> 43.65 | F110: =F109-F108 -> 35.9 | H110: =H109-H108 -> 21 | J110: =J109-J108 -> 12.6 | L110: =L109-L108 -> 0.95 | N110: =N109-N108 -> 142.3 | P110: =P109-P108 -> 126.5 | R110: =R109-R108 -> 117.2 | T110: =T109-T108 -> 91.4 | V110: =V109-V108 -> 81.1 | X110: =X109-X108 -> 60.4 | Z110: =Z109-Z108 -> 49.2
A112: CONCLUSIÓN
A113: El anexo dimensiona la capacidad operativa desde la demanda. Cada plan tiene un consumo horario propio, obtenido de la suma de las tareas que requiere su alta, y un consumo mensual de soporte que se sostiene mientras el comercio permanece abonado: 0,50 h el Plan Básico, 3,00 h el Plan Vidriera y 12,00 h el Plan Cadena para el alta; 0,15 h, 0,25 h y 0,60 h al mes para el soporte. Multiplicando esas bases horarias por las unidades de la proyección de ventas se obtienen las horas hombre requeridas mes a mes. El total asciende a 440,75 horas en 2026, 1.113,75 en 2027 y 1.982,10 en 2028, con picos mensuales de 87,50, 123,35 y 189,65 horas respectivamente. Contra las 150 horas laborables mensuales de un empleado, la dotación técnica necesaria es de un técnico en 2026 y 2027, y de dos a partir de marzo de 2028. El mes en que ese cociente supera la unidad es el que marca la incorporación en la estructura de costos de recursos humanos: la contratación no se decide por criterio, se desprende del volumen proyectado. El costo de mano de obra por alta resulta de USD 3 en el Plan Básico, USD 18 en el Plan Vidriera y USD 72 en el Plan Cadena, contra precios de lista de USD 25, USD 60 y USD 250. Sumado el kit de equipamiento, el alta cubre el esfuerzo técnico comprometido en los tres planes.

Sheet Mod. ingresos
E1: Modelo de ingresos
B7: Evolución de la participación
B8: 2026 | C8: 2027 | D8: 2028
B9: =Hipótesis!C24 -> 0.008 | C9: =Hipótesis!C25 -> 0.029 | D9: =Hipótesis!C26 -> 0.052
B10: =Hipótesis!D24 -> 107520 | C10: =Hipótesis!D25 -> 389760 | D10: =Hipótesis!D26 -> 698880
B15: Ingresos por servicios
B16: Servicio | C16: Ingresos 2026 | D16: Ingresos 2027 | E16: Ingresos 2028
B17: =Hipótesis!$B$58 -> Alta e instalación Plan Básico | C17: ='Proy. ventas'!D19 -> 2960 | D17: ='Proy. ventas'!D82 -> 3520 | E17: ='Proy. ventas'!D144 -> 4720
B18: =Hipótesis!$B$59 -> Alta e instalación Plan Vidriera | C18: ='Proy. ventas'!D20 -> 20640 | D18: ='Proy. ventas'!D83 -> 25200 | E18: ='Proy. ventas'!D145 -> 33360
B19: =Hipótesis!$B$60 -> Alta e instalación Plan Cadena | C19: ='Proy. ventas'!D21 -> 11250 | D19: ='Proy. ventas'!D84 -> 12600 | E19: ='Proy. ventas'!D146 -> 18000
B20: =Hipótesis!$B$61 -> Abono Plan Básico | C20: ='Proy. ventas'!D22 -> 9735 | D20: ='Proy. ventas'!D85 -> 46992 | E20: ='Proy. ventas'!D147 -> 87681
B21: =Hipótesis!$B$62 -> Abono Plan Vidriera | C21: ='Proy. ventas'!D23 -> 44655 | D21: ='Proy. ventas'!D86 -> 217035 | E21: ='Proy. ventas'!D148 -> 407745
B22: =Hipótesis!$B$63 -> Abono Plan Cadena | C22: ='Proy. ventas'!D24 -> 16625 | D22: ='Proy. ventas'!D87 -> 81550 | E22: ='Proy. ventas'!D149 -> 154000
B30: TOTALES | C30: =SUM(C17:C29) -> 105865 | D30: =SUM(D17:D29) -> 386897 | E30: =SUM(E17:E29) -> 705506

Sheet Costos fijos
F1: Estructura de costos fijos
C3: Evolución de la participación | G3: Costos fijos - Totales
C4: 2026 | D4: 2027 | E4: 2028 | G4: 2026 | H4: 2027 | I4: 2028
C5: =Hipótesis!C24 -> 0.008 | D5: =Hipótesis!C25 -> 0.029 | E5: =Hipótesis!C26 -> 0.052 | G5: =P26 -> 32640 | H5: =P44 -> 77700 | I5: =P63 -> 106860
C6: =Hipótesis!D24 -> 107520 | D6: =Hipótesis!D25 -> 389760 | E6: =Hipótesis!D26 -> 698880
G7: Costos fijos de promoción - Totales
G8: 2026 | H8: 2027 | I8: 2028
G9: =SUM(P23:P24) -> 2400 | H9: =SUM(P41:P42) -> 33240 | I9: =SUM(P60:P61) -> 52320
B11: Costos fijos - Año 2026
B12: Rubro | C12: Concepto | D12: Enero | E12: Febrero | F12: Marzo | G12: Abril | H12: Mayo | I12: Junio | J12: Julio | K12: Agosto | L12: Septiembre | M12: Octubre | N12: Noviembre | O12: Diciembre | P12: Total anual | Q12: Observaciones
B13: Servicios | C13: Luz | D13: 45 | E13: 45 | F13: 45 | G13: 45 | H13: 45 | I13: 45 | J13: 45 | K13: 45 | L13: 45 | M13: 45 | N13: 45 | O13: 45 | P13: =SUM(D13:O13) -> 540
C14: Agua | D14: 15 | E14: 15 | F14: 15 | G14: 15 | H14: 15 | I14: 15 | J14: 15 | K14: 15 | L14: 15 | M14: 15 | N14: 15 | O14: 15 | P14: =SUM(D14:O14) -> 180
C15: Internet y telefonía fija | D15: 60 | E15: 60 | F15: 60 | G15: 60 | H15: 60 | I15: 60 | J15: 60 | K15: 60 | L15: 60 | M15: 60 | N15: 60 | O15: 60 | P15: =SUM(D15:O15) -> 720
C16: Telefonía móvil | D16: 30 | E16: 30 | F16: 30 | G16: 30 | H16: 30 | I16: 30 | J16: 30 | K16: 30 | L16: 30 | M16: 30 | N16: 30 | O16: 30 | P16: =SUM(D16:O16) -> 360 | Q16: Una línea por técnico y por vendedor; escala con la dotación.
C17: Infraestructura cloud base | D17: 250 | E17: 250 | F17: 250 | G17: 250 | H17: 250 | I17: 250 | J17: 250 | K17: 250 | L17: 250 | M17: 250 | N17: 250 | O17: 250 | P17: =SUM(D17:O17) -> 3000 | Q17: Capacidad mínima para operar con independencia de la cantidad de comercios activos.
C18: Licencias de software | D18: 120 | E18: 120 | F18: 120 | G18: 120 | H18: 120 | I18: 120 | J18: 120 | K18: 120 | L18: 120 | M18: 120 | N18: 120 | O18: 120 | P18: =SUM(D18:O18) -> 1440 | Q18: Herramientas de desarrollo, monitoreo y productividad.
B19: Alquiler | C19: Oficina | D19: 600 | E19: 600 | F19: 600 | G19: 600 | H19: 600 | I19: 600 | J19: 600 | K19: 600 | L19: 600 | M19: 600 | N19: 600 | O19: 600 | P19: =SUM(D19:O19) -> 7200 | Q19: En 2028 se amplía el espacio por el crecimiento de la dotación.
C20: Auditoría y certificación ISO 27001 | D20: 0 | E20: 0 | F20: 0 | G20: 0 | H20: 0 | I20: 0 | J20: 0 | K20: 0 | L20: 0 | M20: 0 | N20: 0 | O20: 0 | P20: =SUM(D20:O20) -> 0 | Q20: Implementación durante 2027 y mantenimiento desde 2028.
B21: Honorarios | C21: Estudio Contable Externo | D21: 400 | E21: 400 | F21: 400 | G21: 400 | H21: 400 | I21: 400 | J21: 400 | K21: 400 | L21: 400 | M21: 400 | N21: 400 | O21: 400 | P21: =SUM(D21:O21) -> 4800 | Q21: Escala por tramos con la cantidad de empleados.
C22: Agencia de marketing | D22: 400 | E22: 400 | F22: 400 | G22: 400 | H22: 400 | I22: 400 | J22: 400 | K22: 400 | L22: 400 | M22: 400 | N22: 400 | O22: 400 | P22: =SUM(D22:O22) -> 4800 | Q22: Abono mensual; la pauta se imputa aparte.
B23: Publicidad online | C23: Campañas base en Meta y Google | D23: 150 | E23: 150 | F23: 150 | G23: 150 | H23: 150 | I23: 150 | J23: 150 | K23: 150 | L23: 150 | M23: 150 | N23: 150 | O23: 150 | P23: =SUM(D23:O23) -> 1800 | Q23: Pauta base permanente; las campañas de captación intensiva van en costos variables.
C24: Sitio web, SEO local y WhatsApp Business | D24: 50 | E24: 50 | F24: 50 | G24: 50 | H24: 50 | I24: 50 | J24: 50 | K24: 50 | L24: 50 | M24: 50 | N24: 50 | O24: 50 | P24: =SUM(D24:O24) -> 600
C25: Desarrollo y mantenimiento tercerizado | D25: 600 | E25: 600 | F25: 600 | G25: 600 | H25: 600 | I25: 600 | J25: 600 | K25: 600 | L25: 600 | M25: 600 | N25: 600 | O25: 600 | P25: =SUM(D25:O25) -> 7200 | Q25: Free lance, 20/40/60 h por mes según el año. Sin cargas patronales.
B26: TOTAL | D26: =SUM(D13:D25) -> 2720 | E26: =SUM(E13:E25) -> 2720 | F26: =SUM(F13:F25) -> 2720 | G26: =SUM(G13:G25) -> 2720 | H26: =SUM(H13:H25) -> 2720 | I26: =SUM(I13:I25) -> 2720 | J26: =SUM(J13:J25) -> 2720 | K26: =SUM(K13:K25) -> 2720 | ... O26: =SUM(O13:O25) -> 2720 | P26: =SUM(D26:O26) -> 32640
B29: Costos fijos - Año 2027
B30: Rubro | C30: Concepto | D30: Enero | E30: Febrero | F30: Marzo | G30: Abril | H30: Mayo | I30: Junio | J30: Julio | K30: Agosto | L30: Septiembre | M30: Octubre | N30: Noviembre | O30: Diciembre | P30: Total anual | Q30: Observaciones
B31: Servicios | C31: Luz | D31: 45 | E31: 45 | F31: 45 | G31: 45 | H31: 45 | I31: 45 | J31: 45 | K31: 45 | L31: 45 | M31: 45 | N31: 45 | O31: 45 | P31: =SUM(D31:O31) -> 540
C32: Agua | D32: 15 | E32: 15 | F32: 15 | G32: 15 | H32: 15 | I32: 15 | J32: 15 | K32: 15 | L32: 15 | M32: 15 | N32: 15 | O32: 15 | P32: =SUM(D32:O32) -> 180
C33: Internet y telefonía fija | D33: 60 | E33: 60 | F33: 60 | G33: 60 | H33: 60 | I33: 60 | J33: 60 | K33: 60 | L33: 60 | M33: 60 | N33: 60 | O33: 60 | P33: =SUM(D33:O33) -> 720
C34: Telefonía móvil | D34: 45 | E34: 45 | F34: 45 | G34: 45 | H34: 45 | I34: 45 | J34: 45 | K34: 45 | L34: 45 | M34: 45 | N34: 45 | O34: 45 | P34: =SUM(D34:O34) -> 540 | Q34: Una línea por técnico y por vendedor; escala con la dotación.
C35: Infraestructura cloud base | D35: 350 | E35: 350 | F35: 350 | G35: 350 | H35: 350 | I35: 350 | J35: 350 | K35: 350 | L35: 350 | M35: 350 | N35: 350 | O35: 350 | P35: =SUM(D35:O35) -> 4200 | Q35: Capacidad mínima para operar con independencia de la cantidad de comercios activos.
C36: Licencias de software | D36: 140 | E36: 140 | F36: 140 | G36: 140 | H36: 140 | I36: 140 | J36: 140 | K36: 140 | L36: 140 | M36: 140 | N36: 140 | O36: 140 | P36: =SUM(D36:O36) -> 1680 | Q36: Herramientas de desarrollo, monitoreo y productividad.
B37: Alquiler | C37: Oficina | D37: 600 | E37: 600 | F37: 600 | G37: 600 | H37: 600 | I37: 600 | J37: 600 | K37: 600 | L37: 600 | M37: 600 | N37: 600 | O37: 600 | P37: =SUM(D37:O37) -> 7200 | Q37: En 2028 se amplía el espacio por el crecimiento de la dotación.
C38: Auditoría y certificación ISO 27001 | D38: 400 | E38: 400 | F38: 400 | G38: 400 | H38: 400 | I38: 400 | J38: 400 | K38: 400 | L38: 400 | M38: 400 | N38: 400 | O38: 400 | P38: =SUM(D38:O38) -> 4800 | Q38: Implementación durante 2027 y mantenimiento desde 2028.
B39: Honorarios | C39: Estudio Contable Externo | D39: 450 | E39: 450 | F39: 450 | G39: 450 | H39: 450 | I39: 450 | J39: 450 | K39: 450 | L39: 450 | M39: 450 | N39: 450 | O39: 450 | P39: =SUM(D39:O39) -> 5400 | Q39: Escala por tramos con la cantidad de empleados.
C40: Agencia de marketing | D40: 400 | E40: 400 | F40: 400 | G40: 400 | H40: 400 | I40: 400 | J40: 400 | K40: 400 | L40: 400 | M40: 400 | N40: 400 | O40: 400 | P40: =SUM(D40:O40) -> 4800 | Q40: Abono mensual; la pauta se imputa aparte.
B41: Publicidad online | C41: Campañas base en Meta y Google | D41: 2720 | E41: 2720 | F41: 2720 | G41: 2720 | H41: 2720 | I41: 2720 | J41: 2720 | K41: 2720 | L41: 2720 | M41: 2720 | N41: 2720 | O41: 2720 | P41: =SUM(D41:O41) -> 32640 | Q41: Pauta base permanente; las campañas de captación intensiva van en costos variables.
C42: Sitio web, SEO local y WhatsApp Business | D42: 50 | E42: 50 | F42: 50 | G42: 50 | H42: 50 | I42: 50 | J42: 50 | K42: 50 | L42: 50 | M42: 50 | N42: 50 | O42: 50 | P42: =SUM(D42:O42) -> 600
C43: Desarrollo y mantenimiento tercerizado | D43: 1200 | E43: 1200 | F43: 1200 | G43: 1200 | H43: 1200 | I43: 1200 | J43: 1200 | K43: 1200 | L43: 1200 | M43: 1200 | N43: 1200 | O43: 1200 | P43: =SUM(D43:O43) -> 14400 | Q43: Free lance, 20/40/60 h por mes según el año. Sin cargas patronales.
B44: TOTAL | D44: =SUM(D31:D43) -> 6475 | E44: =SUM(E31:E43) -> 6475 | F44: =SUM(F31:F43) -> 6475 | G44: =SUM(G31:G43) -> 6475 | H44: =SUM(H31:H43) -> 6475 | I44: =SUM(I31:I43) -> 6475 | J44: =SUM(J31:J43) -> 6475 | K44: =SUM(K31:K43) -> 6475 | ... O44: =SUM(O31:O43) -> 6475 | P44: =SUM(D44:O44) -> 77700
B48: Costos fijos - Año 2028
B49: Rubro | C49: Concepto | D49: Enero | E49: Febrero | F49: Marzo | G49: Abril | H49: Mayo | I49: Junio | J49: Julio | K49: Agosto | L49: Septiembre | M49: Octubre | N49: Noviembre | O49: Diciembre | P49: Total anual | Q49: Observaciones
B50: Servicios | C50: Luz | D50: 50 | E50: 50 | F50: 50 | G50: 50 | H50: 50 | I50: 50 | J50: 50 | K50: 50 | L50: 50 | M50: 50 | N50: 50 | O50: 50 | P50: =SUM(D50:O50) -> 600
C51: Agua | D51: 15 | E51: 15 | F51: 15 | G51: 15 | H51: 15 | I51: 15 | J51: 15 | K51: 15 | L51: 15 | M51: 15 | N51: 15 | O51: 15 | P51: =SUM(D51:O51) -> 180
C52: Internet y telefonía fija | D52: 60 | E52: 60 | F52: 60 | G52: 60 | H52: 60 | I52: 60 | J52: 60 | K52: 60 | L52: 60 | M52: 60 | N52: 60 | O52: 60 | P52: =SUM(D52:O52) -> 720
C53: Telefonía móvil | D53: 60 | E53: 60 | F53: 60 | G53: 60 | H53: 60 | I53: 60 | J53: 60 | K53: 60 | L53: 60 | M53: 60 | N53: 60 | O53: 60 | P53: =SUM(D53:O53) -> 720 | Q53: Una línea por técnico y por vendedor; escala con la dotación.
C54: Infraestructura cloud base | D54: 500 | E54: 500 | F54: 500 | G54: 500 | H54: 500 | I54: 500 | J54: 500 | K54: 500 | L54: 500 | M54: 500 | N54: 500 | O54: 500 | P54: =SUM(D54:O54) -> 6000 | Q54: Capacidad mínima para operar con independencia de la cantidad de comercios activos.
C55: Licencias de software | D55: 160 | E55: 160 | F55: 160 | G55: 160 | H55: 160 | I55: 160 | J55: 160 | K55: 160 | L55: 160 | M55: 160 | N55: 160 | O55: 160 | P55: =SUM(D55:O55) -> 1920 | Q55: Herramientas de desarrollo, monitoreo y productividad.
B56: Alquiler | C56: Oficina | D56: 700 | E56: 700 | F56: 700 | G56: 700 | H56: 700 | I56: 700 | J56: 700 | K56: 700 | L56: 700 | M56: 700 | N56: 700 | O56: 700 | P56: =SUM(D56:O56) -> 8400 | Q56: En 2028 se amplía el espacio por el crecimiento de la dotación.
C57: Auditoría y certificación ISO 27001 | D57: 250 | E57: 250 | F57: 250 | G57: 250 | H57: 250 | I57: 250 | J57: 250 | K57: 250 | L57: 250 | M57: 250 | N57: 250 | O57: 250 | P57: =SUM(D57:O57) -> 3000 | Q57: Implementación durante 2027 y mantenimiento desde 2028.
B58: Honorarios | C58: Estudio Contable Externo | D58: 500 | E58: 500 | F58: 500 | G58: 500 | H58: 500 | I58: 500 | J58: 500 | K58: 500 | L58: 500 | M58: 500 | N58: 500 | O58: 500 | P58: =SUM(D58:O58) -> 6000 | Q58: Escala por tramos con la cantidad de empleados.
C59: Agencia de marketing | D59: 450 | E59: 450 | F59: 450 | G59: 450 | H59: 450 | I59: 450 | J59: 450 | K59: 450 | L59: 450 | M59: 450 | N59: 450 | O59: 450 | P59: =SUM(D59:O59) -> 5400 | Q59: Abono mensual; la pauta se imputa aparte.
B60: Publicidad online | C60: Campañas base en Meta y Google | D60: 4300 | E60: 4300 | F60: 4300 | G60: 4300 | H60: 4300 | I60: 4300 | J60: 4300 | K60: 4300 | L60: 4300 | M60: 4300 | N60: 4300 | O60: 4300 | P60: =SUM(D60:O60) -> 51600 | Q60: Pauta base permanente; las campañas de captación intensiva van en costos variables.
C61: Sitio web, SEO local y WhatsApp Business | D61: 60 | E61: 60 | F61: 60 | G61: 60 | H61: 60 | I61: 60 | J61: 60 | K61: 60 | L61: 60 | M61: 60 | N61: 60 | O61: 60 | P61: =SUM(D61:O61) -> 720
C62: Desarrollo y mantenimiento tercerizado | D62: 1800 | E62: 1800 | F62: 1800 | G62: 1800 | H62: 1800 | I62: 1800 | J62: 1800 | K62: 1800 | L62: 1800 | M62: 1800 | N62: 1800 | O62: 1800 | P62: =SUM(D62:O62) -> 21600 | Q62: Free lance, 20/40/60 h por mes según el año. Sin cargas patronales.
B63: TOTAL | D63: =SUM(D50:D62) -> 8905 | E63: =SUM(E50:E62) -> 8905 | F63: =SUM(F50:F62) -> 8905 | G63: =SUM(G50:G62) -> 8905 | H63: =SUM(H50:H62) -> 8905 | I63: =SUM(I50:I62) -> 8905 | J63: =SUM(J50:J62) -> 8905 | K63: =SUM(K50:K62) -> 8905 | ... O63: =SUM(O50:O62) -> 8905 | P63: =SUM(D63:O63) -> 106860

Sheet Costos variables
F1: Estructura de costos variables
B4: Evolución de la participación | H4: Costos variables - Totales
B5: 2026 | C5: 2027 | D5: 2028 | H5: 2026 | I5: 2027 | J5: 2028
B6: =Hipótesis!C24 -> 0.008 | C6: =Hipótesis!C25 -> 0.029 | D6: =Hipótesis!C26 -> 0.052 | H6: =AB32 -> 40479.8 | I6: =AB55 -> 59474.6 | J6: =AB78 -> 85346
B7: =Hipótesis!D24 -> 107520 | C7: =Hipótesis!D25 -> 389760 | D7: =Hipótesis!D26 -> 698880
H8: Costos de promoción variables - Totales
H9: 2026 | I9: 2027 | J9: 2028
H10: =SUM(AB21:AB24) -> 11265 | I10: =SUM(AB44:AB47) -> 13396 | J10: =SUM(AB67:AB70) -> 18124
B12: Costos variables - Año 2026
A13: Rubro | B13: Descripción | C13: Costo unitario | D13: Enero | F13: Febrero | H13: Marzo | J13: Abril | L13: Mayo | N13: Junio | P13: Julio | R13: Agosto | T13: Septiembre | V13: Octubre | X13: Noviembre | Z13: Diciembre | AB13: Total anual
D14: Cant. | E14: Costo | F14: Cant. | G14: Costo | H14: Cant. | I14: Costo | J14: Cant. | K14: Costo | L14: Cant. | M14: Costo | N14: Cant. | O14: Costo | P14: Cant. | Q14: Costo | R14: Cant. | S14: Costo | T14: Cant. | U14: Costo | V14: Cant. | W14: Costo | X14: Cant. | Y14: Costo | Z14: Cant. | AA14: Costo
A15: Operación | B15: Comisión del vendedor freelance por alta concretada | C15: 40 | D15: ='Proy. ventas'!E19+'Proy. ventas'!E20+'Proy. ventas'!E21 -> 0 | E15: =D15*$C15 -> 0 | F15: ='Proy. ventas'!G19+'Proy. ventas'!G20+'Proy. ventas'!G21 -> 3 | G15: =F15*$C15 -> 120 | H15: ='Proy. ventas'!I19+'Proy. ventas'!I20+'Proy. ventas'!I21 -> 4 | I15: =H15*$C15 -> 160 | J15: ='Proy. ventas'!K19+'Proy. ventas'!K20+'Proy. ventas'!K21 -> 8 | K15: =J15*$C15 -> 320 | L15: ='Proy. ventas'!M19+'Proy. ventas'!M20+'Proy. ventas'!M21 -> 14 | M15: =L15*$C15 -> 560 | N15: ='Proy. ventas'!O19+'Proy. ventas'!O20+'Proy. ventas'!O21 -> 19 | O15: =N15*$C15 -> 760 | P15: ='Proy. ventas'!Q19+'Proy. ventas'!Q20+'Proy. ventas'!Q21 -> 24 | Q15: =P15*$C15 -> 960 | R15: ='Proy. ventas'!S19+'Proy. ventas'!S20+'Proy. ventas'!S21 -> 30 | S15: =R15*$C15 -> 1200 | T15: ='Proy. ventas'!U19+'Proy. ventas'!U20+'Proy. ventas'!U21 -> 33 | U15: =T15*$C15 -> 1320 | V15: ='Proy. ventas'!W19+'Proy. ventas'!W20+'Proy. ventas'!W21 -> 41 | W15: =V15*$C15 -> 1640 | X15: ='Proy. ventas'!Y19+'Proy. ventas'!Y20+'Proy. ventas'!Y21 -> 43 | Y15: =X15*$C15 -> 1720 | Z15: ='Proy. ventas'!AA19+'Proy. ventas'!AA20+'Proy. ventas'!AA21 -> 52 | AA15: =Z15*$C15 -> 2080 | AB15: =E15+G15+I15+K15+M15+O15+Q15+S15+U15+W15+Y15+AA15 -> 10840
B16: Movilidad y viáticos de instalación | C16: 5 | D16: ='Proy. ventas'!E20+'Proy. ventas'!E21 -> 0 | E16: =D16*$C16 -> 0 | F16: ='Proy. ventas'!G20+'Proy. ventas'!G21 -> 2 | G16: =F16*$C16 -> 10 | H16: ='Proy. ventas'!I20+'Proy. ventas'!I21 -> 3 | I16: =H16*$C16 -> 15 | J16: ='Proy. ventas'!K20+'Proy. ventas'!K21 -> 6 | K16: =J16*$C16 -> 30 | L16: ='Proy. ventas'!M20+'Proy. ventas'!M21 -> 10 | M16: =L16*$C16 -> 50 | N16: ='Proy. ventas'!O20+'Proy. ventas'!O21 -> 14 | O16: =N16*$C16 -> 70 | P16: ='Proy. ventas'!Q20+'Proy. ventas'!Q21 -> 17 | Q16: =P16*$C16 -> 85 | R16: ='Proy. ventas'!S20+'Proy. ventas'!S21 -> 22 | S16: =R16*$C16 -> 110 | T16: ='Proy. ventas'!U20+'Proy. ventas'!U21 -> 24 | U16: =T16*$C16 -> 120 | V16: ='Proy. ventas'!W20+'Proy. ventas'!W21 -> 30 | W16: =V16*$C16 -> 150 | X16: ='Proy. ventas'!Y20+'Proy. ventas'!Y21 -> 31 | Y16: =X16*$C16 -> 155 | Z16: ='Proy. ventas'!AA20+'Proy. ventas'!AA21 -> 38 | AA16: =Z16*$C16 -> 190 | AB16: =E16+G16+I16+K16+M16+O16+Q16+S16+U16+W16+Y16+AA16 -> 985
B17: Consumo cloud por comercio activo | C17: 0.35 | D17: ='Proy. ventas'!E22+'Proy. ventas'!E23+'Proy. ventas'!E24 -> 0 | E17: =D17*$C17 -> 0 | F17: ='Proy. ventas'!G22+'Proy. ventas'!G23+'Proy. ventas'!G24 -> 3 | G17: =F17*$C17 -> 1.05 | H17: ='Proy. ventas'!I22+'Proy. ventas'!I23+'Proy. ventas'!I24 -> 7 | I17: =H17*$C17 -> 2.45 | J17: ='Proy. ventas'!K22+'Proy. ventas'!K23+'Proy. ventas'!K24 -> 15 | K17: =J17*$C17 -> 5.25 | L17: ='Proy. ventas'!M22+'Proy. ventas'!M23+'Proy. ventas'!M24 -> 29 | M17: =L17*$C17 -> 10.15 | N17: ='Proy. ventas'!O22+'Proy. ventas'!O23+'Proy. ventas'!O24 -> 48 | O17: =N17*$C17 -> 16.8 | P17: ='Proy. ventas'!Q22+'Proy. ventas'!Q23+'Proy. ventas'!Q24 -> 72 | Q17: =P17*$C17 -> 25.2 | R17: ='Proy. ventas'!S22+'Proy. ventas'!S23+'Proy. ventas'!S24 -> 102 | S17: =R17*$C17 -> 35.7 | T17: ='Proy. ventas'!U22+'Proy. ventas'!U23+'Proy. ventas'!U24 -> 135 | U17: =T17*$C17 -> 47.25 | V17: ='Proy. ventas'!W22+'Proy. ventas'!W23+'Proy. ventas'!W24 -> 176 | W17: =V17*$C17 -> 61.6 | X17: ='Proy. ventas'!Y22+'Proy. ventas'!Y23+'Proy. ventas'!Y24 -> 219 | Y17: =X17*$C17 -> 76.65 | Z17: ='Proy. ventas'!AA22+'Proy. ventas'!AA23+'Proy. ventas'!AA24 -> 271 | AA17: =Z17*$C17 -> 94.85 | AB17: =E17+G17+I17+K17+M17+O17+Q17+S17+U17+W17+Y17+AA17 -> 376.95
B18: Gateway de notificaciones | C18: 0.15 | D18: ='Proy. ventas'!E22+'Proy. ventas'!E23+'Proy. ventas'!E24 -> 0 | E18: =D18*$C18 -> 0 | F18: ='Proy. ventas'!G22+'Proy. ventas'!G23+'Proy. ventas'!G24 -> 3 | G18: =F18*$C18 -> 0.45 | H18: ='Proy. ventas'!I22+'Proy. ventas'!I23+'Proy. ventas'!I24 -> 7 | I18: =H18*$C18 -> 1.05 | J18: ='Proy. ventas'!K22+'Proy. ventas'!K23+'Proy. ventas'!K24 -> 15 | K18: =J18*$C18 -> 2.25 | L18: ='Proy. ventas'!M22+'Proy. ventas'!M23+'Proy. ventas'!M24 -> 29 | M18: =L18*$C18 -> 4.35 | N18: ='Proy. ventas'!O22+'Proy. ventas'!O23+'Proy. ventas'!O24 -> 48 | O18: =N18*$C18 -> 7.2 | P18: ='Proy. ventas'!Q22+'Proy. ventas'!Q23+'Proy. ventas'!Q24 -> 72 | Q18: =P18*$C18 -> 10.8 | R18: ='Proy. ventas'!S22+'Proy. ventas'!S23+'Proy. ventas'!S24 -> 102 | S18: =R18*$C18 -> 15.3 | T18: ='Proy. ventas'!U22+'Proy. ventas'!U23+'Proy. ventas'!U24 -> 135 | U18: =T18*$C18 -> 20.25 | V18: ='Proy. ventas'!W22+'Proy. ventas'!W23+'Proy. ventas'!W24 -> 176 | W18: =V18*$C18 -> 26.4 | X18: ='Proy. ventas'!Y22+'Proy. ventas'!Y23+'Proy. ventas'!Y24 -> 219 | Y18: =X18*$C18 -> 32.85 | Z18: ='Proy. ventas'!AA22+'Proy. ventas'!AA23+'Proy. ventas'!AA24 -> 271 | AA18: =Z18*$C18 -> 40.65 | AB18: =E18+G18+I18+K18+M18+O18+Q18+S18+U18+W18+Y18+AA18 -> 161.55
B19: Comisiones de medios de pago | C19: 0.9 | D19: ='Proy. ventas'!E22+'Proy. ventas'!E23+'Proy. ventas'!E24 -> 0 | E19: =D19*$C19 -> 0 | F19: ='Proy. ventas'!G22+'Proy. ventas'!G23+'Proy. ventas'!G24 -> 3 | G19: =F19*$C19 -> 2.7 | H19: ='Proy. ventas'!I22+'Proy. ventas'!I23+'Proy. ventas'!I24 -> 7 | I19: =H19*$C19 -> 6.3 | J19: ='Proy. ventas'!K22+'Proy. ventas'!K23+'Proy. ventas'!K24 -> 15 | K19: =J19*$C19 -> 13.5 | L19: ='Proy. ventas'!M22+'Proy. ventas'!M23+'Proy. ventas'!M24 -> 29 | M19: =L19*$C19 -> 26.1 | N19: ='Proy. ventas'!O22+'Proy. ventas'!O23+'Proy. ventas'!O24 -> 48 | O19: =N19*$C19 -> 43.2 | P19: ='Proy. ventas'!Q22+'Proy. ventas'!Q23+'Proy. ventas'!Q24 -> 72 | Q19: =P19*$C19 -> 64.8 | R19: ='Proy. ventas'!S22+'Proy. ventas'!S23+'Proy. ventas'!S24 -> 102 | S19: =R19*$C19 -> 91.8 | T19: ='Proy. ventas'!U22+'Proy. ventas'!U23+'Proy. ventas'!U24 -> 135 | U19: =T19*$C19 -> 121.5 | V19: ='Proy. ventas'!W22+'Proy. ventas'!W23+'Proy. ventas'!W24 -> 176 | W19: =V19*$C19 -> 158.4 | X19: ='Proy. ventas'!Y22+'Proy. ventas'!Y23+'Proy. ventas'!Y24 -> 219 | Y19: =X19*$C19 -> 197.1 | Z19: ='Proy. ventas'!AA22+'Proy. ventas'!AA23+'Proy. ventas'!AA24 -> 271 | AA19: =Z19*$C19 -> 243.9 | AB19: =E19+G19+I19+K19+M19+O19+Q19+S19+U19+W19+Y19+AA19 -> 969.3
B20: Reposición de equipamiento no recuperado | C20: 6 | D20: ='Proy. ventas'!E20+'Proy. ventas'!E21 -> 0 | E20: =D20*$C20 -> 0 | F20: ='Proy. ventas'!G20+'Proy. ventas'!G21 -> 2 | G20: =F20*$C20 -> 12 | H20: ='Proy. ventas'!I20+'Proy. ventas'!I21 -> 3 | I20: =H20*$C20 -> 18 | J20: ='Proy. ventas'!K20+'Proy. ventas'!K21 -> 6 | K20: =J20*$C20 -> 36 | L20: ='Proy. ventas'!M20+'Proy. ventas'!M21 -> 10 | M20: =L20*$C20 -> 60 | N20: ='Proy. ventas'!O20+'Proy. ventas'!O21 -> 14 | O20: =N20*$C20 -> 84 | P20: ='Proy. ventas'!Q20+'Proy. ventas'!Q21 -> 17 | Q20: =P20*$C20 -> 102 | R20: ='Proy. ventas'!S20+'Proy. ventas'!S21 -> 22 | S20: =R20*$C20 -> 132 | T20: ='Proy. ventas'!U20+'Proy. ventas'!U21 -> 24 | U20: =T20*$C20 -> 144 | V20: ='Proy. ventas'!W20+'Proy. ventas'!W21 -> 30 | W20: =V20*$C20 -> 180 | X20: ='Proy. ventas'!Y20+'Proy. ventas'!Y21 -> 31 | Y20: =X20*$C20 -> 186 | Z20: ='Proy. ventas'!AA20+'Proy. ventas'!AA21 -> 38 | AA20: =Z20*$C20 -> 228 | AB20: =E20+G20+I20+K20+M20+O20+Q20+S20+U20+W20+Y20+AA20 -> 1182
A21: Promoción | B21: Bonificación del alta - Plan Básico | C21: =Hipótesis!$C$58*0.3 -> 12 | D21: ='Proy. ventas'!E19 -> 0 | E21: =D21*$C21 -> 0 | F21: ='Proy. ventas'!G19 -> 1 | G21: =F21*$C21 -> 12 | H21: ='Proy. ventas'!I19 -> 1 | I21: =H21*$C21 -> 12 | J21: ='Proy. ventas'!K19 -> 2 | K21: =J21*$C21 -> 24 | L21: ='Proy. ventas'!M19 -> 4 | M21: =L21*$C21 -> 48 | N21: ='Proy. ventas'!O19 -> 5 | O21: =N21*$C21 -> 60 | P21: ='Proy. ventas'!Q19 -> 7 | Q21: =P21*$C21 -> 84 | R21: ='Proy. ventas'!S19 -> 8 | S21: =R21*$C21 -> 96 | T21: ='Proy. ventas'!U19 -> 9 | U21: =T21*$C21 -> 108 | V21: ='Proy. ventas'!W19 -> 11 | W21: =V21*$C21 -> 132 | X21: ='Proy. ventas'!Y19 -> 12 | Y21: =X21*$C21 -> 144 | Z21: ='Proy. ventas'!AA19 -> 14 | AA21: =Z21*$C21 -> 168 | AB21: =E21+G21+I21+K21+M21+O21+Q21+S21+U21+W21+Y21+AA21 -> 888
B22: Bonificación del alta - Plan Vidriera | C22: =Hipótesis!$C$59*0.3 -> 36 | D22: ='Proy. ventas'!E20 -> 0 | E22: =D22*$C22 -> 0 | F22: ='Proy. ventas'!G20 -> 2 | G22: =F22*$C22 -> 72 | H22: ='Proy. ventas'!I20 -> 3 | I22: =H22*$C22 -> 108 | J22: ='Proy. ventas'!K20 -> 5 | K22: =J22*$C22 -> 180 | L22: ='Proy. ventas'!M20 -> 9 | M22: =L22*$C22 -> 324 | N22: ='Proy. ventas'!O20 -> 12 | O22: =N22*$C22 -> 432 | P22: ='Proy. ventas'!Q20 -> 15 | Q22: =P22*$C22 -> 540 | R22: ='Proy. ventas'!S20 -> 19 | S22: =R22*$C22 -> 684 | T22: ='Proy. ventas'!U20 -> 21 | U22: =T22*$C22 -> 756 | V22: ='Proy. ventas'!W20 -> 26 | W22: =V22*$C22 -> 936 | X22: ='Proy. ventas'!Y20 -> 27 | Y22: =X22*$C22 -> 972 | Z22: ='Proy. ventas'!AA20 -> 33 | AA22: =Z22*$C22 -> 1188 | AB22: =E22+G22+I22+K22+M22+O22+Q22+S22+U22+W22+Y22+AA22 -> 6192
B23: Bonificación del alta - Plan Cadena | C23: =Hipótesis!$C$60*0.3 -> 135 | D23: ='Proy. ventas'!E21 -> 0 | E23: =D23*$C23 -> 0 | F23: ='Proy. ventas'!G21 -> 0 | G23: =F23*$C23 -> 0 | H23: ='Proy. ventas'!I21 -> 0 | I23: =H23*$C23 -> 0 | J23: ='Proy. ventas'!K21 -> 1 | K23: =J23*$C23 -> 135 | L23: ='Proy. ventas'!M21 -> 1 | M23: =L23*$C23 -> 135 | N23: ='Proy. ventas'!O21 -> 2 | O23: =N23*$C23 -> 270 | P23: ='Proy. ventas'!Q21 -> 2 | Q23: =P23*$C23 -> 270 | R23: ='Proy. ventas'!S21 -> 3 | S23: =R23*$C23 -> 405 | T23: ='Proy. ventas'!U21 -> 3 | U23: =T23*$C23 -> 405 | V23: ='Proy. ventas'!W21 -> 4 | W23: =V23*$C23 -> 540 | X23: ='Proy. ventas'!Y21 -> 4 | Y23: =X23*$C23 -> 540 | Z23: ='Proy. ventas'!AA21 -> 5 | AA23: =Z23*$C23 -> 675 | AB23: =E23+G23+I23+K23+M23+O23+Q23+S23+U23+W23+Y23+AA23 -> 3375
B24: Incentivo del programa de referidos | C24: 10 | D24: =ROUND(('Proy. ventas'!E19+'Proy. ventas'!E20+'Proy. ventas'!E21)*0.3,0) -> 0 | E24: =D24*$C24 -> 0 | F24: =ROUND(('Proy. ventas'!G19+'Proy. ventas'!G20+'Proy. ventas'!G21)*0.3,0) -> 1 | G24: =F24*$C24 -> 10 | H24: =ROUND(('Proy. ventas'!I19+'Proy. ventas'!I20+'Proy. ventas'!I21)*0.3,0) -> 1 | I24: =H24*$C24 -> 10 | J24: =ROUND(('Proy. ventas'!K19+'Proy. ventas'!K20+'Proy. ventas'!K21)*0.3,0) -> 2 | K24: =J24*$C24 -> 20 | L24: =ROUND(('Proy. ventas'!M19+'Proy. ventas'!M20+'Proy. ventas'!M21)*0.3,0) -> 4 | M24: =L24*$C24 -> 40 | N24: =ROUND(('Proy. ventas'!O19+'Proy. ventas'!O20+'Proy. ventas'!O21)*0.3,0) -> 6 | O24: =N24*$C24 -> 60 | P24: =ROUND(('Proy. ventas'!Q19+'Proy. ventas'!Q20+'Proy. ventas'!Q21)*0.3,0) -> 7 | Q24: =P24*$C24 -> 70 | R24: =ROUND(('Proy. ventas'!S19+'Proy. ventas'!S20+'Proy. ventas'!S21)*0.3,0) -> 9 | S24: =R24*$C24 -> 90 | T24: =ROUND(('Proy. ventas'!U19+'Proy. ventas'!U20+'Proy. ventas'!U21)*0.3,0) -> 10 | U24: =T24*$C24 -> 100 | V24: =ROUND(('Proy. ventas'!W19+'Proy. ventas'!W20+'Proy. ventas'!W21)*0.3,0) -> 12 | W24: =V24*$C24 -> 120 | X24: =ROUND(('Proy. ventas'!Y19+'Proy. ventas'!Y20+'Proy. ventas'!Y21)*0.3,0) -> 13 | Y24: =X24*$C24 -> 130 | Z24: =ROUND(('Proy. ventas'!AA19+'Proy. ventas'!AA20+'Proy. ventas'!AA21)*0.3,0) -> 16 | AA24: =Z24*$C24 -> 160 | AB24: =E24+G24+I24+K24+M24+O24+Q24+S24+U24+W24+Y24+AA24 -> 810
A25: Operación | B25: Técnico freelance de instalación y soporte (por hora, según el Anexo de capacidad) | C25: 7 | D25: ='Anexo capacidad operativa'!D87 -> 0 | E25: =D25*$C25 -> 0 | F25: ='Anexo capacidad operativa'!F87 -> 150 | G25: =F25*$C25 -> 1050 | H25: ='Anexo capacidad operativa'!H87 -> 150 | I25: =H25*$C25 -> 1050 | J25: ='Anexo capacidad operativa'!J87 -> 150 | K25: =J25*$C25 -> 1050 | L25: ='Anexo capacidad operativa'!L87 -> 150 | M25: =L25*$C25 -> 1050 | N25: ='Anexo capacidad operativa'!N87 -> 150 | O25: =N25*$C25 -> 1050 | P25: ='Anexo capacidad operativa'!P87 -> 150 | Q25: =P25*$C25 -> 1050 | R25: ='Anexo capacidad operativa'!R87 -> 150 | S25: =R25*$C25 -> 1050 | T25: ='Anexo capacidad operativa'!T87 -> 150 | U25: =T25*$C25 -> 1050 | V25: ='Anexo capacidad operativa'!V87 -> 300 | W25: =V25*$C25 -> 2100 | X25: ='Anexo capacidad operativa'!X87 -> 300 | Y25: =X25*$C25 -> 2100 | Z25: ='Anexo capacidad operativa'!Z87 -> 300 | AA25: =Z25*$C25 -> 2100 | AB25: =E25+G25+I25+K25+M25+O25+Q25+S25+U25+W25+Y25+AA25 -> 14700
B32: TOTAL | E32: =SUM(E15:E31) -> 0 | G32: =SUM(G15:G31) -> 1290.2 | I32: =SUM(I15:I31) -> 1382.8 | K32: =SUM(K15:K31) -> 1816 | M32: =SUM(M15:M31) -> 2307.6 | O32: =SUM(O15:O31) -> 2853.2 | Q32: =SUM(Q15:Q31) -> 3261.8 | S32: =SUM(S15:S31) -> 3909.8 | U32: =SUM(U15:U31) -> 4192 | W32: =SUM(W15:W31) -> 6044.4 | Y32: =SUM(Y15:Y31) -> 6253.6 | AA32: =SUM(AA15:AA31) -> 7168.4 | AB32: =SUM(AB15:AB31) -> 40479.8
B35: Costos variables - Año 2027
A36: Rubro | B36: Descripción | C36: Costo unitario | D36: Enero | F36: Febrero | H36: Marzo | J36: Abril | L36: Mayo | N36: Junio | P36: Julio | R36: Agosto | T36: Septiembre | V36: Octubre | X36: Noviembre | Z36: Diciembre | AB36: Total anual
D37: Cant. | E37: Costo | F37: Cant. | G37: Costo | H37: Cant. | I37: Costo | J37: Cant. | K37: Costo | L37: Cant. | M37: Costo | N37: Cant. | O37: Costo | P37: Cant. | Q37: Costo | R37: Cant. | S37: Costo | T37: Cant. | U37: Costo | V37: Cant. | W37: Costo | X37: Cant. | Y37: Costo | Z37: Cant. | AA37: Costo
A38: Operación | B38: Comisión del vendedor freelance por alta concretada | C38: 40 | D38: ='Proy. ventas'!E82+'Proy. ventas'!E83+'Proy. ventas'!E84 -> 22 | E38: =D38*$C38 -> 880 | F38: ='Proy. ventas'!G82+'Proy. ventas'!G83+'Proy. ventas'!G84 -> 22 | G38: =F38*$C38 -> 880 | H38: ='Proy. ventas'!I82+'Proy. ventas'!I83+'Proy. ventas'!I84 -> 25 | I38: =H38*$C38 -> 1000 | J38: ='Proy. ventas'!K82+'Proy. ventas'!K83+'Proy. ventas'!K84 -> 25 | K38: =J38*$C38 -> 1000 | L38: ='Proy. ventas'!M82+'Proy. ventas'!M83+'Proy. ventas'!M84 -> 26 | M38: =L38*$C38 -> 1040 | N38: ='Proy. ventas'!O82+'Proy. ventas'!O83+'Proy. ventas'!O84 -> 26 | O38: =N38*$C38 -> 1040 | P38: ='Proy. ventas'!Q82+'Proy. ventas'!Q83+'Proy. ventas'!Q84 -> 27 | Q38: =P38*$C38 -> 1080 | R38: ='Proy. ventas'!S82+'Proy. ventas'!S83+'Proy. ventas'!S84 -> 27 | S38: =R38*$C38 -> 1080 | T38: ='Proy. ventas'!U82+'Proy. ventas'!U83+'Proy. ventas'!U84 -> 30 | U38: =T38*$C38 -> 1200 | V38: ='Proy. ventas'!W82+'Proy. ventas'!W83+'Proy. ventas'!W84 -> 30 | W38: =V38*$C38 -> 1200 | X38: ='Proy. ventas'!Y82+'Proy. ventas'!Y83+'Proy. ventas'!Y84 -> 33 | Y38: =X38*$C38 -> 1320 | Z38: ='Proy. ventas'!AA82+'Proy. ventas'!AA83+'Proy. ventas'!AA84 -> 33 | AA38: =Z38*$C38 -> 1320 | AB38: =E38+G38+I38+K38+M38+O38+Q38+S38+U38+W38+Y38+AA38 -> 13040
B39: Movilidad y viáticos de instalación | C39: 5 | D39: ='Proy. ventas'!E83+'Proy. ventas'!E84 -> 16 | E39: =D39*$C39 -> 80 | F39: ='Proy. ventas'!G83+'Proy. ventas'!G84 -> 16 | G39: =F39*$C39 -> 80 | H39: ='Proy. ventas'!I83+'Proy. ventas'!I84 -> 18 | I39: =H39*$C39 -> 90 | J39: ='Proy. ventas'!K83+'Proy. ventas'!K84 -> 18 | K39: =J39*$C39 -> 90 | L39: ='Proy. ventas'!M83+'Proy. ventas'!M84 -> 19 | M39: =L39*$C39 -> 95 | N39: ='Proy. ventas'!O83+'Proy. ventas'!O84 -> 19 | O39: =N39*$C39 -> 95 | P39: ='Proy. ventas'!Q83+'Proy. ventas'!Q84 -> 20 | Q39: =P39*$C39 -> 100 | R39: ='Proy. ventas'!S83+'Proy. ventas'!S84 -> 20 | S39: =R39*$C39 -> 100 | T39: ='Proy. ventas'!U83+'Proy. ventas'!U84 -> 22 | U39: =T39*$C39 -> 110 | V39: ='Proy. ventas'!W83+'Proy. ventas'!W84 -> 22 | W39: =V39*$C39 -> 110 | X39: ='Proy. ventas'!Y83+'Proy. ventas'!Y84 -> 24 | Y39: =X39*$C39 -> 120 | Z39: ='Proy. ventas'!AA83+'Proy. ventas'!AA84 -> 24 | AA39: =Z39*$C39 -> 120 | AB39: =E39+G39+I39+K39+M39+O39+Q39+S39+U39+W39+Y39+AA39 -> 1190
B40: Consumo cloud por comercio activo | C40: 0.35 | D40: ='Proy. ventas'!E85+'Proy. ventas'!E86+'Proy. ventas'!E87 -> 293 | E40: =D40*$C40 -> 102.55 | F40: ='Proy. ventas'!G85+'Proy. ventas'!G86+'Proy. ventas'!G87 -> 315 | G40: =F40*$C40 -> 110.25 | H40: ='Proy. ventas'!I85+'Proy. ventas'!I86+'Proy. ventas'!I87 -> 340 | I40: =H40*$C40 -> 119 | J40: ='Proy. ventas'!K85+'Proy. ventas'!K86+'Proy. ventas'!K87 -> 365 | K40: =J40*$C40 -> 127.75 | L40: ='Proy. ventas'!M85+'Proy. ventas'!M86+'Proy. ventas'!M87 -> 391 | M40: =L40*$C40 -> 136.85 | N40: ='Proy. ventas'!O85+'Proy. ventas'!O86+'Proy. ventas'!O87 -> 417 | O40: =N40*$C40 -> 145.95 | P40: ='Proy. ventas'!Q85+'Proy. ventas'!Q86+'Proy. ventas'!Q87 -> 444 | Q40: =P40*$C40 -> 155.4 | R40: ='Proy. ventas'!S85+'Proy. ventas'!S86+'Proy. ventas'!S87 -> 471 | S40: =R40*$C40 -> 164.85 | T40: ='Proy. ventas'!U85+'Proy. ventas'!U86+'Proy. ventas'!U87 -> 501 | U40: =T40*$C40 -> 175.35 | V40: ='Proy. ventas'!W85+'Proy. ventas'!W86+'Proy. ventas'!W87 -> 531 | W40: =V40*$C40 -> 185.85 | X40: ='Proy. ventas'!Y85+'Proy. ventas'!Y86+'Proy. ventas'!Y87 -> 564 | Y40: =X40*$C40 -> 197.4 | Z40: ='Proy. ventas'!AA85+'Proy. ventas'!AA86+'Proy. ventas'!AA87 -> 597 | AA40: =Z40*$C40 -> 208.95 | AB40: =E40+G40+I40+K40+M40+O40+Q40+S40+U40+W40+Y40+AA40 -> 1830.15
B41: Gateway de notificaciones | C41: 0.15 | D41: ='Proy. ventas'!E85+'Proy. ventas'!E86+'Proy. ventas'!E87 -> 293 | E41: =D41*$C41 -> 43.95 | F41: ='Proy. ventas'!G85+'Proy. ventas'!G86+'Proy. ventas'!G87 -> 315 | G41: =F41*$C41 -> 47.25 | H41: ='Proy. ventas'!I85+'Proy. ventas'!I86+'Proy. ventas'!I87 -> 340 | I41: =H41*$C41 -> 51 | J41: ='Proy. ventas'!K85+'Proy. ventas'!K86+'Proy. ventas'!K87 -> 365 | K41: =J41*$C41 -> 54.75 | L41: ='Proy. ventas'!M85+'Proy. ventas'!M86+'Proy. ventas'!M87 -> 391 | M41: =L41*$C41 -> 58.65 | N41: ='Proy. ventas'!O85+'Proy. ventas'!O86+'Proy. ventas'!O87 -> 417 | O41: =N41*$C41 -> 62.55 | P41: ='Proy. ventas'!Q85+'Proy. ventas'!Q86+'Proy. ventas'!Q87 -> 444 | Q41: =P41*$C41 -> 66.6 | R41: ='Proy. ventas'!S85+'Proy. ventas'!S86+'Proy. ventas'!S87 -> 471 | S41: =R41*$C41 -> 70.65 | T41: ='Proy. ventas'!U85+'Proy. ventas'!U86+'Proy. ventas'!U87 -> 501 | U41: =T41*$C41 -> 75.15 | V41: ='Proy. ventas'!W85+'Proy. ventas'!W86+'Proy. ventas'!W87 -> 531 | W41: =V41*$C41 -> 79.65 | X41: ='Proy. ventas'!Y85+'Proy. ventas'!Y86+'Proy. ventas'!Y87 -> 564 | Y41: =X41*$C41 -> 84.6 | Z41: ='Proy. ventas'!AA85+'Proy. ventas'!AA86+'Proy. ventas'!AA87 -> 597 | AA41: =Z41*$C41 -> 89.55 | AB41: =E41+G41+I41+K41+M41+O41+Q41+S41+U41+W41+Y41+AA41 -> 784.35
B42: Comisiones de medios de pago | C42: 0.9 | D42: ='Proy. ventas'!E85+'Proy. ventas'!E86+'Proy. ventas'!E87 -> 293 | E42: =D42*$C42 -> 263.7 | F42: ='Proy. ventas'!G85+'Proy. ventas'!G86+'Proy. ventas'!G87 -> 315 | G42: =F42*$C42 -> 283.5 | H42: ='Proy. ventas'!I85+'Proy. ventas'!I86+'Proy. ventas'!I87 -> 340 | I42: =H42*$C42 -> 306 | J42: ='Proy. ventas'!K85+'Proy. ventas'!K86+'Proy. ventas'!K87 -> 365 | K42: =J42*$C42 -> 328.5 | L42: ='Proy. ventas'!M85+'Proy. ventas'!M86+'Proy. ventas'!M87 -> 391 | M42: =L42*$C42 -> 351.9 | N42: ='Proy. ventas'!O85+'Proy. ventas'!O86+'Proy. ventas'!O87 -> 417 | O42: =N42*$C42 -> 375.3 | P42: ='Proy. ventas'!Q85+'Proy. ventas'!Q86+'Proy. ventas'!Q87 -> 444 | Q42: =P42*$C42 -> 399.6 | R42: ='Proy. ventas'!S85+'Proy. ventas'!S86+'Proy. ventas'!S87 -> 471 | S42: =R42*$C42 -> 423.9 | T42: ='Proy. ventas'!U85+'Proy. ventas'!U86+'Proy. ventas'!U87 -> 501 | U42: =T42*$C42 -> 450.9 | V42: ='Proy. ventas'!W85+'Proy. ventas'!W86+'Proy. ventas'!W87 -> 531 | W42: =V42*$C42 -> 477.9 | X42: ='Proy. ventas'!Y85+'Proy. ventas'!Y86+'Proy. ventas'!Y87 -> 564 | Y42: =X42*$C42 -> 507.6 | Z42: ='Proy. ventas'!AA85+'Proy. ventas'!AA86+'Proy. ventas'!AA87 -> 597 | AA42: =Z42*$C42 -> 537.3 | AB42: =E42+G42+I42+K42+M42+O42+Q42+S42+U42+W42+Y42+AA42 -> 4706.1
B43: Reposición de equipamiento no recuperado | C43: 6 | D43: ='Proy. ventas'!E83+'Proy. ventas'!E84 -> 16 | E43: =D43*$C43 -> 96 | F43: ='Proy. ventas'!G83+'Proy. ventas'!G84 -> 16 | G43: =F43*$C43 -> 96 | H43: ='Proy. ventas'!I83+'Proy. ventas'!I84 -> 18 | I43: =H43*$C43 -> 108 | J43: ='Proy. ventas'!K83+'Proy. ventas'!K84 -> 18 | K43: =J43*$C43 -> 108 | L43: ='Proy. ventas'!M83+'Proy. ventas'!M84 -> 19 | M43: =L43*$C43 -> 114 | N43: ='Proy. ventas'!O83+'Proy. ventas'!O84 -> 19 | O43: =N43*$C43 -> 114 | P43: ='Proy. ventas'!Q83+'Proy. ventas'!Q84 -> 20 | Q43: =P43*$C43 -> 120 | R43: ='Proy. ventas'!S83+'Proy. ventas'!S84 -> 20 | S43: =R43*$C43 -> 120 | T43: ='Proy. ventas'!U83+'Proy. ventas'!U84 -> 22 | U43: =T43*$C43 -> 132 | V43: ='Proy. ventas'!W83+'Proy. ventas'!W84 -> 22 | W43: =V43*$C43 -> 132 | X43: ='Proy. ventas'!Y83+'Proy. ventas'!Y84 -> 24 | Y43: =X43*$C43 -> 144 | Z43: ='Proy. ventas'!AA83+'Proy. ventas'!AA84 -> 24 | AA43: =Z43*$C43 -> 144 | AB43: =E43+G43+I43+K43+M43+O43+Q43+S43+U43+W43+Y43+AA43 -> 1428
A44: Promoción | B44: Bonificación del alta - Plan Básico | C44: =Hipótesis!$C$58*0.3 -> 12 | D44: ='Proy. ventas'!E82 -> 6 | E44: =D44*$C44 -> 72 | F44: ='Proy. ventas'!G82 -> 6 | G44: =F44*$C44 -> 72 | H44: ='Proy. ventas'!I82 -> 7 | I44: =H44*$C44 -> 84 | J44: ='Proy. ventas'!K82 -> 7 | K44: =J44*$C44 -> 84 | L44: ='Proy. ventas'!M82 -> 7 | M44: =L44*$C44 -> 84 | N44: ='Proy. ventas'!O82 -> 7 | O44: =N44*$C44 -> 84 | P44: ='Proy. ventas'!Q82 -> 7 | Q44: =P44*$C44 -> 84 | R44: ='Proy. ventas'!S82 -> 7 | S44: =R44*$C44 -> 84 | T44: ='Proy. ventas'!U82 -> 8 | U44: =T44*$C44 -> 96 | V44: ='Proy. ventas'!W82 -> 8 | W44: =V44*$C44 -> 96 | X44: ='Proy. ventas'!Y82 -> 9 | Y44: =X44*$C44 -> 108 | Z44: ='Proy. ventas'!AA82 -> 9 | AA44: =Z44*$C44 -> 108 | AB44: =E44+G44+I44+K44+M44+O44+Q44+S44+U44+W44+Y44+AA44 -> 1056
B45: Bonificación del alta - Plan Vidriera | C45: =Hipótesis!$C$59*0.3 -> 36 | D45: ='Proy. ventas'!E83 -> 14 | E45: =D45*$C45 -> 504 | F45: ='Proy. ventas'!G83 -> 14 | G45: =F45*$C45 -> 504 | H45: ='Proy. ventas'!I83 -> 16 | I45: =H45*$C45 -> 576 | J45: ='Proy. ventas'!K83 -> 16 | K45: =J45*$C45 -> 576 | L45: ='Proy. ventas'!M83 -> 17 | M45: =L45*$C45 -> 612 | N45: ='Proy. ventas'!O83 -> 17 | O45: =N45*$C45 -> 612 | P45: ='Proy. ventas'!Q83 -> 18 | Q45: =P45*$C45 -> 648 | R45: ='Proy. ventas'!S83 -> 18 | S45: =R45*$C45 -> 648 | T45: ='Proy. ventas'!U83 -> 19 | U45: =T45*$C45 -> 684 | V45: ='Proy. ventas'!W83 -> 19 | W45: =V45*$C45 -> 684 | X45: ='Proy. ventas'!Y83 -> 21 | Y45: =X45*$C45 -> 756 | Z45: ='Proy. ventas'!AA83 -> 21 | AA45: =Z45*$C45 -> 756 | AB45: =E45+G45+I45+K45+M45+O45+Q45+S45+U45+W45+Y45+AA45 -> 7560
B46: Bonificación del alta - Plan Cadena | C46: =Hipótesis!$C$60*0.3 -> 135 | D46: ='Proy. ventas'!E84 -> 2 | E46: =D46*$C46 -> 270 | F46: ='Proy. ventas'!G84 -> 2 | G46: =F46*$C46 -> 270 | H46: ='Proy. ventas'!I84 -> 2 | I46: =H46*$C46 -> 270 | J46: ='Proy. ventas'!K84 -> 2 | K46: =J46*$C46 -> 270 | L46: ='Proy. ventas'!M84 -> 2 | M46: =L46*$C46 -> 270 | N46: ='Proy. ventas'!O84 -> 2 | O46: =N46*$C46 -> 270 | P46: ='Proy. ventas'!Q84 -> 2 | Q46: =P46*$C46 -> 270 | R46: ='Proy. ventas'!S84 -> 2 | S46: =R46*$C46 -> 270 | T46: ='Proy. ventas'!U84 -> 3 | U46: =T46*$C46 -> 405 | V46: ='Proy. ventas'!W84 -> 3 | W46: =V46*$C46 -> 405 | X46: ='Proy. ventas'!Y84 -> 3 | Y46: =X46*$C46 -> 405 | Z46: ='Proy. ventas'!AA84 -> 3 | AA46: =Z46*$C46 -> 405 | AB46: =E46+G46+I46+K46+M46+O46+Q46+S46+U46+W46+Y46+AA46 -> 3780
B47: Incentivo del programa de referidos | C47: 10 | D47: =ROUND(('Proy. ventas'!E82+'Proy. ventas'!E83+'Proy. ventas'!E84)*0.3,0) -> 7 | E47: =D47*$C47 -> 70 | F47: =ROUND(('Proy. ventas'!G82+'Proy. ventas'!G83+'Proy. ventas'!G84)*0.3,0) -> 7 | G47: =F47*$C47 -> 70 | H47: =ROUND(('Proy. ventas'!I82+'Proy. ventas'!I83+'Proy. ventas'!I84)*0.3,0) -> 8 | I47: =H47*$C47 -> 80 | J47: =ROUND(('Proy. ventas'!K82+'Proy. ventas'!K83+'Proy. ventas'!K84)*0.3,0) -> 8 | K47: =J47*$C47 -> 80 | L47: =ROUND(('Proy. ventas'!M82+'Proy. ventas'!M83+'Proy. ventas'!M84)*0.3,0) -> 8 | M47: =L47*$C47 -> 80 | N47: =ROUND(('Proy. ventas'!O82+'Proy. ventas'!O83+'Proy. ventas'!O84)*0.3,0) -> 8 | O47: =N47*$C47 -> 80 | P47: =ROUND(('Proy. ventas'!Q82+'Proy. ventas'!Q83+'Proy. ventas'!Q84)*0.3,0) -> 8 | Q47: =P47*$C47 -> 80 | R47: =ROUND(('Proy. ventas'!S82+'Proy. ventas'!S83+'Proy. ventas'!S84)*0.3,0) -> 8 | S47: =R47*$C47 -> 80 | T47: =ROUND(('Proy. ventas'!U82+'Proy. ventas'!U83+'Proy. ventas'!U84)*0.3,0) -> 9 | U47: =T47*$C47 -> 90 | V47: =ROUND(('Proy. ventas'!W82+'Proy. ventas'!W83+'Proy. ventas'!W84)*0.3,0) -> 9 | W47: =V47*$C47 -> 90 | X47: =ROUND(('Proy. ventas'!Y82+'Proy. ventas'!Y83+'Proy. ventas'!Y84)*0.3,0) -> 10 | Y47: =X47*$C47 -> 100 | Z47: =ROUND(('Proy. ventas'!AA82+'Proy. ventas'!AA83+'Proy. ventas'!AA84)*0.3,0) -> 10 | AA47: =Z47*$C47 -> 100 | AB47: =E47+G47+I47+K47+M47+O47+Q47+S47+U47+W47+Y47+AA47 -> 1000
A48: Operación | B48: Técnico freelance de instalación y soporte (por hora, según el Anexo de capacidad) | C48: 7 | D48: ='Anexo capacidad operativa'!D98 -> 150 | E48: =D48*$C48 -> 1050 | F48: ='Anexo capacidad operativa'!F98 -> 150 | G48: =F48*$C48 -> 1050 | H48: ='Anexo capacidad operativa'!H98 -> 300 | I48: =H48*$C48 -> 2100 | J48: ='Anexo capacidad operativa'!J98 -> 300 | K48: =J48*$C48 -> 2100 | L48: ='Anexo capacidad operativa'!L98 -> 300 | M48: =L48*$C48 -> 2100 | N48: ='Anexo capacidad operativa'!N98 -> 300 | O48: =N48*$C48 -> 2100 | P48: ='Anexo capacidad operativa'!P98 -> 300 | Q48: =P48*$C48 -> 2100 | R48: ='Anexo capacidad operativa'!R98 -> 300 | S48: =R48*$C48 -> 2100 | T48: ='Anexo capacidad operativa'!T98 -> 300 | U48: =T48*$C48 -> 2100 | V48: ='Anexo capacidad operativa'!V98 -> 300 | W48: =V48*$C48 -> 2100 | X48: ='Anexo capacidad operativa'!X98 -> 300 | Y48: =X48*$C48 -> 2100 | Z48: ='Anexo capacidad operativa'!Z98 -> 300 | AA48: =Z48*$C48 -> 2100 | AB48: =E48+G48+I48+K48+M48+O48+Q48+S48+U48+W48+Y48+AA48 -> 23100
B55: TOTAL | E55: =SUM(E38:E54) -> 3432.2 | G55: =SUM(G38:G54) -> 3463 | I55: =SUM(I38:I54) -> 4784 | K55: =SUM(K38:K54) -> 4819 | M55: =SUM(M38:M54) -> 4942.4 | O55: =SUM(O38:O54) -> 4978.8 | Q55: =SUM(Q38:Q54) -> 5103.6 | S55: =SUM(S38:S54) -> 5141.4 | U55: =SUM(U38:U54) -> 5518.4 | W55: =SUM(W38:W54) -> 5560.4 | Y55: =SUM(Y38:Y54) -> 5842.6 | AA55: =SUM(AA38:AA54) -> 5888.8 | AB55: =SUM(AB38:AB54) -> 59474.6
B58: Costos variables - Año 2028
A59: Rubro | B59: Descripción | C59: Costo unitario | D59: Enero | F59: Febrero | H59: Marzo | J59: Abril | L59: Mayo | N59: Junio | P59: Julio | R59: Agosto | T59: Septiembre | V59: Octubre | X59: Noviembre | Z59: Diciembre | AB59: Total anual
D60: Cant. | E60: Costo | F60: Cant. | G60: Costo | H60: Cant. | I60: Costo | J60: Cant. | K60: Costo | L60: Cant. | M60: Costo | N60: Cant. | O60: Costo | P60: Cant. | Q60: Costo | R60: Cant. | S60: Costo | T60: Cant. | U60: Costo | V60: Cant. | W60: Costo | X60: Cant. | Y60: Costo | Z60: Cant. | AA60: Costo
A61: Operación | B61: Comisión del vendedor freelance por alta concretada | C61: 40 | D61: ='Proy. ventas'!E144+'Proy. ventas'!E145+'Proy. ventas'!E146 -> 30 | E61: =D61*$C61 -> 1200 | F61: ='Proy. ventas'!G144+'Proy. ventas'!G145+'Proy. ventas'!G146 -> 30 | G61: =F61*$C61 -> 1200 | H61: ='Proy. ventas'!I144+'Proy. ventas'!I145+'Proy. ventas'!I146 -> 33 | I61: =H61*$C61 -> 1320 | J61: ='Proy. ventas'!K144+'Proy. ventas'!K145+'Proy. ventas'!K146 -> 33 | K61: =J61*$C61 -> 1320 | L61: ='Proy. ventas'!M144+'Proy. ventas'!M145+'Proy. ventas'!M146 -> 34 | M61: =L61*$C61 -> 1360 | N61: ='Proy. ventas'!O144+'Proy. ventas'!O145+'Proy. ventas'!O146 -> 34 | O61: =N61*$C61 -> 1360 | P61: ='Proy. ventas'!Q144+'Proy. ventas'!Q145+'Proy. ventas'!Q146 -> 37 | Q61: =P61*$C61 -> 1480 | R61: ='Proy. ventas'!S144+'Proy. ventas'!S145+'Proy. ventas'!S146 -> 37 | S61: =R61*$C61 -> 1480 | T61: ='Proy. ventas'!U144+'Proy. ventas'!U145+'Proy. ventas'!U146 -> 40 | U61: =T61*$C61 -> 1600 | V61: ='Proy. ventas'!W144+'Proy. ventas'!W145+'Proy. ventas'!W146 -> 40 | W61: =V61*$C61 -> 1600 | X61: ='Proy. ventas'!Y144+'Proy. ventas'!Y145+'Proy. ventas'!Y146 -> 44 | Y61: =X61*$C61 -> 1760 | Z61: ='Proy. ventas'!AA144+'Proy. ventas'!AA145+'Proy. ventas'!AA146 -> 44 | AA61: =Z61*$C61 -> 1760 | AB61: =E61+G61+I61+K61+M61+O61+Q61+S61+U61+W61+Y61+AA61 -> 17440
B62: Movilidad y viáticos de instalación | C62: 5 | D62: ='Proy. ventas'!E145+'Proy. ventas'!E146 -> 22 | E62: =D62*$C62 -> 110 | F62: ='Proy. ventas'!G145+'Proy. ventas'!G146 -> 22 | G62: =F62*$C62 -> 110 | H62: ='Proy. ventas'!I145+'Proy. ventas'!I146 -> 24 | I62: =H62*$C62 -> 120 | J62: ='Proy. ventas'!K145+'Proy. ventas'!K146 -> 24 | K62: =J62*$C62 -> 120 | L62: ='Proy. ventas'!M145+'Proy. ventas'!M146 -> 25 | M62: =L62*$C62 -> 125 | N62: ='Proy. ventas'!O145+'Proy. ventas'!O146 -> 25 | O62: =N62*$C62 -> 125 | P62: ='Proy. ventas'!Q145+'Proy. ventas'!Q146 -> 27 | Q62: =P62*$C62 -> 135 | R62: ='Proy. ventas'!S145+'Proy. ventas'!S146 -> 27 | S62: =R62*$C62 -> 135 | T62: ='Proy. ventas'!U145+'Proy. ventas'!U146 -> 29 | U62: =T62*$C62 -> 145 | V62: ='Proy. ventas'!W145+'Proy. ventas'!W146 -> 29 | W62: =V62*$C62 -> 145 | X62: ='Proy. ventas'!Y145+'Proy. ventas'!Y146 -> 32 | Y62: =X62*$C62 -> 160 | Z62: ='Proy. ventas'!AA145+'Proy. ventas'!AA146 -> 32 | AA62: =Z62*$C62 -> 160 | AB62: =E62+G62+I62+K62+M62+O62+Q62+S62+U62+W62+Y62+AA62 -> 1590
B63: Consumo cloud por comercio activo | C63: 0.35 | D63: ='Proy. ventas'!E147+'Proy. ventas'!E148+'Proy. ventas'!E149 -> 627 | E63: =D63*$C63 -> 219.45 | F63: ='Proy. ventas'!G147+'Proy. ventas'!G148+'Proy. ventas'!G149 -> 657 | G63: =F63*$C63 -> 229.95 | H63: ='Proy. ventas'!I147+'Proy. ventas'!I148+'Proy. ventas'!I149 -> 690 | I63: =H63*$C63 -> 241.5 | J63: ='Proy. ventas'!K147+'Proy. ventas'!K148+'Proy. ventas'!K149 -> 723 | K63: =J63*$C63 -> 253.05 | L63: ='Proy. ventas'!M147+'Proy. ventas'!M148+'Proy. ventas'!M149 -> 757 | M63: =L63*$C63 -> 264.95 | N63: ='Proy. ventas'!O147+'Proy. ventas'!O148+'Proy. ventas'!O149 -> 791 | O63: =N63*$C63 -> 276.85 | P63: ='Proy. ventas'!Q147+'Proy. ventas'!Q148+'Proy. ventas'!Q149 -> 828 | Q63: =P63*$C63 -> 289.8 | R63: ='Proy. ventas'!S147+'Proy. ventas'!S148+'Proy. ventas'!S149 -> 865 | S63: =R63*$C63 -> 302.75 | T63: ='Proy. ventas'!U147+'Proy. ventas'!U148+'Proy. ventas'!U149 -> 905 | U63: =T63*$C63 -> 316.75 | V63: ='Proy. ventas'!W147+'Proy. ventas'!W148+'Proy. ventas'!W149 -> 945 | W63: =V63*$C63 -> 330.75 | X63: ='Proy. ventas'!Y147+'Proy. ventas'!Y148+'Proy. ventas'!Y149 -> 989 | Y63: =X63*$C63 -> 346.15 | Z63: ='Proy. ventas'!AA147+'Proy. ventas'!AA148+'Proy. ventas'!AA149 -> 1033 | AA63: =Z63*$C63 -> 361.55 | AB63: =E63+G63+I63+K63+M63+O63+Q63+S63+U63+W63+Y63+AA63 -> 3433.5
B64: Gateway de notificaciones | C64: 0.15 | D64: ='Proy. ventas'!E147+'Proy. ventas'!E148+'Proy. ventas'!E149 -> 627 | E64: =D64*$C64 -> 94.05 | F64: ='Proy. ventas'!G147+'Proy. ventas'!G148+'Proy. ventas'!G149 -> 657 | G64: =F64*$C64 -> 98.55 | H64: ='Proy. ventas'!I147+'Proy. ventas'!I148+'Proy. ventas'!I149 -> 690 | I64: =H64*$C64 -> 103.5 | J64: ='Proy. ventas'!K147+'Proy. ventas'!K148+'Proy. ventas'!K149 -> 723 | K64: =J64*$C64 -> 108.45 | L64: ='Proy. ventas'!M147+'Proy. ventas'!M148+'Proy. ventas'!M149 -> 757 | M64: =L64*$C64 -> 113.55 | N64: ='Proy. ventas'!O147+'Proy. ventas'!O148+'Proy. ventas'!O149 -> 791 | O64: =N64*$C64 -> 118.65 | P64: ='Proy. ventas'!Q147+'Proy. ventas'!Q148+'Proy. ventas'!Q149 -> 828 | Q64: =P64*$C64 -> 124.2 | R64: ='Proy. ventas'!S147+'Proy. ventas'!S148+'Proy. ventas'!S149 -> 865 | S64: =R64*$C64 -> 129.75 | T64: ='Proy. ventas'!U147+'Proy. ventas'!U148+'Proy. ventas'!U149 -> 905 | U64: =T64*$C64 -> 135.75 | V64: ='Proy. ventas'!W147+'Proy. ventas'!W148+'Proy. ventas'!W149 -> 945 | W64: =V64*$C64 -> 141.75 | X64: ='Proy. ventas'!Y147+'Proy. ventas'!Y148+'Proy. ventas'!Y149 -> 989 | Y64: =X64*$C64 -> 148.35 | Z64: ='Proy. ventas'!AA147+'Proy. ventas'!AA148+'Proy. ventas'!AA149 -> 1033 | AA64: =Z64*$C64 -> 154.95 | AB64: =E64+G64+I64+K64+M64+O64+Q64+S64+U64+W64+Y64+AA64 -> 1471.5
B65: Comisiones de medios de pago | C65: 0.9 | D65: ='Proy. ventas'!E147+'Proy. ventas'!E148+'Proy. ventas'!E149 -> 627 | E65: =D65*$C65 -> 564.3 | F65: ='Proy. ventas'!G147+'Proy. ventas'!G148+'Proy. ventas'!G149 -> 657 | G65: =F65*$C65 -> 591.3 | H65: ='Proy. ventas'!I147+'Proy. ventas'!I148+'Proy. ventas'!I149 -> 690 | I65: =H65*$C65 -> 621 | J65: ='Proy. ventas'!K147+'Proy. ventas'!K148+'Proy. ventas'!K149 -> 723 | K65: =J65*$C65 -> 650.7 | L65: ='Proy. ventas'!M147+'Proy. ventas'!M148+'Proy. ventas'!M149 -> 757 | M65: =L65*$C65 -> 681.3 | N65: ='Proy. ventas'!O147+'Proy. ventas'!O148+'Proy. ventas'!O149 -> 791 | O65: =N65*$C65 -> 711.9 | P65: ='Proy. ventas'!Q147+'Proy. ventas'!Q148+'Proy. ventas'!Q149 -> 828 | Q65: =P65*$C65 -> 745.2 | R65: ='Proy. ventas'!S147+'Proy. ventas'!S148+'Proy. ventas'!S149 -> 865 | S65: =R65*$C65 -> 778.5 | T65: ='Proy. ventas'!U147+'Proy. ventas'!U148+'Proy. ventas'!U149 -> 905 | U65: =T65*$C65 -> 814.5 | V65: ='Proy. ventas'!W147+'Proy. ventas'!W148+'Proy. ventas'!W149 -> 945 | W65: =V65*$C65 -> 850.5 | X65: ='Proy. ventas'!Y147+'Proy. ventas'!Y148+'Proy. ventas'!Y149 -> 989 | Y65: =X65*$C65 -> 890.1 | Z65: ='Proy. ventas'!AA147+'Proy. ventas'!AA148+'Proy. ventas'!AA149 -> 1033 | AA65: =Z65*$C65 -> 929.7 | AB65: =E65+G65+I65+K65+M65+O65+Q65+S65+U65+W65+Y65+AA65 -> 8829
B66: Reposición de equipamiento no recuperado | C66: 6 | D66: ='Proy. ventas'!E145+'Proy. ventas'!E146 -> 22 | E66: =D66*$C66 -> 132 | F66: ='Proy. ventas'!G145+'Proy. ventas'!G146 -> 22 | G66: =F66*$C66 -> 132 | H66: ='Proy. ventas'!I145+'Proy. ventas'!I146 -> 24 | I66: =H66*$C66 -> 144 | J66: ='Proy. ventas'!K145+'Proy. ventas'!K146 -> 24 | K66: =J66*$C66 -> 144 | L66: ='Proy. ventas'!M145+'Proy. ventas'!M146 -> 25 | M66: =L66*$C66 -> 150 | N66: ='Proy. ventas'!O145+'Proy. ventas'!O146 -> 25 | O66: =N66*$C66 -> 150 | P66: ='Proy. ventas'!Q145+'Proy. ventas'!Q146 -> 27 | Q66: =P66*$C66 -> 162 | R66: ='Proy. ventas'!S145+'Proy. ventas'!S146 -> 27 | S66: =R66*$C66 -> 162 | T66: ='Proy. ventas'!U145+'Proy. ventas'!U146 -> 29 | U66: =T66*$C66 -> 174 | V66: ='Proy. ventas'!W145+'Proy. ventas'!W146 -> 29 | W66: =V66*$C66 -> 174 | X66: ='Proy. ventas'!Y145+'Proy. ventas'!Y146 -> 32 | Y66: =X66*$C66 -> 192 | Z66: ='Proy. ventas'!AA145+'Proy. ventas'!AA146 -> 32 | AA66: =Z66*$C66 -> 192 | AB66: =E66+G66+I66+K66+M66+O66+Q66+S66+U66+W66+Y66+AA66 -> 1908
A67: Promoción | B67: Bonificación del alta - Plan Básico | C67: =Hipótesis!$C$58*0.3 -> 12 | D67: ='Proy. ventas'!E144 -> 8 | E67: =D67*$C67 -> 96 | F67: ='Proy. ventas'!G144 -> 8 | G67: =F67*$C67 -> 96 | H67: ='Proy. ventas'!I144 -> 9 | I67: =H67*$C67 -> 108 | J67: ='Proy. ventas'!K144 -> 9 | K67: =J67*$C67 -> 108 | L67: ='Proy. ventas'!M144 -> 9 | M67: =L67*$C67 -> 108 | N67: ='Proy. ventas'!O144 -> 9 | O67: =N67*$C67 -> 108 | P67: ='Proy. ventas'!Q144 -> 10 | Q67: =P67*$C67 -> 120 | R67: ='Proy. ventas'!S144 -> 10 | S67: =R67*$C67 -> 120 | T67: ='Proy. ventas'!U144 -> 11 | U67: =T67*$C67 -> 132 | V67: ='Proy. ventas'!W144 -> 11 | W67: =V67*$C67 -> 132 | X67: ='Proy. ventas'!Y144 -> 12 | Y67: =X67*$C67 -> 144 | Z67: ='Proy. ventas'!AA144 -> 12 | AA67: =Z67*$C67 -> 144 | AB67: =E67+G67+I67+K67+M67+O67+Q67+S67+U67+W67+Y67+AA67 -> 1416
B68: Bonificación del alta - Plan Vidriera | C68: =Hipótesis!$C$59*0.3 -> 36 | D68: ='Proy. ventas'!E145 -> 19 | E68: =D68*$C68 -> 684 | F68: ='Proy. ventas'!G145 -> 19 | G68: =F68*$C68 -> 684 | H68: ='Proy. ventas'!I145 -> 21 | I68: =H68*$C68 -> 756 | J68: ='Proy. ventas'!K145 -> 21 | K68: =J68*$C68 -> 756 | L68: ='Proy. ventas'!M145 -> 22 | M68: =L68*$C68 -> 792 | N68: ='Proy. ventas'!O145 -> 22 | O68: =N68*$C68 -> 792 | P68: ='Proy. ventas'!Q145 -> 24 | Q68: =P68*$C68 -> 864 | R68: ='Proy. ventas'!S145 -> 24 | S68: =R68*$C68 -> 864 | T68: ='Proy. ventas'!U145 -> 25 | U68: =T68*$C68 -> 900 | V68: ='Proy. ventas'!W145 -> 25 | W68: =V68*$C68 -> 900 | X68: ='Proy. ventas'!Y145 -> 28 | Y68: =X68*$C68 -> 1008 | Z68: ='Proy. ventas'!AA145 -> 28 | AA68: =Z68*$C68 -> 1008 | AB68: =E68+G68+I68+K68+M68+O68+Q68+S68+U68+W68+Y68+AA68 -> 10008
B69: Bonificación del alta - Plan Cadena | C69: =Hipótesis!$C$60*0.3 -> 135 | D69: ='Proy. ventas'!E146 -> 3 | E69: =D69*$C69 -> 405 | F69: ='Proy. ventas'!G146 -> 3 | G69: =F69*$C69 -> 405 | H69: ='Proy. ventas'!I146 -> 3 | I69: =H69*$C69 -> 405 | J69: ='Proy. ventas'!K146 -> 3 | K69: =J69*$C69 -> 405 | L69: ='Proy. ventas'!M146 -> 3 | M69: =L69*$C69 -> 405 | N69: ='Proy. ventas'!O146 -> 3 | O69: =N69*$C69 -> 405 | P69: ='Proy. ventas'!Q146 -> 3 | Q69: =P69*$C69 -> 405 | R69: ='Proy. ventas'!S146 -> 3 | S69: =R69*$C69 -> 405 | T69: ='Proy. ventas'!U146 -> 4 | U69: =T69*$C69 -> 540 | V69: ='Proy. ventas'!W146 -> 4 | W69: =V69*$C69 -> 540 | X69: ='Proy. ventas'!Y146 -> 4 | Y69: =X69*$C69 -> 540 | Z69: ='Proy. ventas'!AA146 -> 4 | AA69: =Z69*$C69 -> 540 | AB69: =E69+G69+I69+K69+M69+O69+Q69+S69+U69+W69+Y69+AA69 -> 5400
B70: Incentivo del programa de referidos | C70: 10 | D70: =ROUND(('Proy. ventas'!E144+'Proy. ventas'!E145+'Proy. ventas'!E146)*0.3,0) -> 9 | E70: =D70*$C70 -> 90 | F70: =ROUND(('Proy. ventas'!G144+'Proy. ventas'!G145+'Proy. ventas'!G146)*0.3,0) -> 9 | G70: =F70*$C70 -> 90 | H70: =ROUND(('Proy. ventas'!I144+'Proy. ventas'!I145+'Proy. ventas'!I146)*0.3,0) -> 10 | I70: =H70*$C70 -> 100 | J70: =ROUND(('Proy. ventas'!K144+'Proy. ventas'!K145+'Proy. ventas'!K146)*0.3,0) -> 10 | K70: =J70*$C70 -> 100 | L70: =ROUND(('Proy. ventas'!M144+'Proy. ventas'!M145+'Proy. ventas'!M146)*0.3,0) -> 10 | M70: =L70*$C70 -> 100 | N70: =ROUND(('Proy. ventas'!O144+'Proy. ventas'!O145+'Proy. ventas'!O146)*0.3,0) -> 10 | O70: =N70*$C70 -> 100 | P70: =ROUND(('Proy. ventas'!Q144+'Proy. ventas'!Q145+'Proy. ventas'!Q146)*0.3,0) -> 11 | Q70: =P70*$C70 -> 110 | R70: =ROUND(('Proy. ventas'!S144+'Proy. ventas'!S145+'Proy. ventas'!S146)*0.3,0) -> 11 | S70: =R70*$C70 -> 110 | T70: =ROUND(('Proy. ventas'!U144+'Proy. ventas'!U145+'Proy. ventas'!U146)*0.3,0) -> 12 | U70: =T70*$C70 -> 120 | V70: =ROUND(('Proy. ventas'!W144+'Proy. ventas'!W145+'Proy. ventas'!W146)*0.3,0) -> 12 | W70: =V70*$C70 -> 120 | X70: =ROUND(('Proy. ventas'!Y144+'Proy. ventas'!Y145+'Proy. ventas'!Y146)*0.3,0) -> 13 | Y70: =X70*$C70 -> 130 | Z70: =ROUND(('Proy. ventas'!AA144+'Proy. ventas'!AA145+'Proy. ventas'!AA146)*0.3,0) -> 13 | AA70: =Z70*$C70 -> 130 | AB70: =E70+G70+I70+K70+M70+O70+Q70+S70+U70+W70+Y70+AA70 -> 1300
A71: Operación | B71: Técnico freelance de instalación y soporte (por hora, según el Anexo de capacidad) | C71: 7 | D71: ='Anexo capacidad operativa'!D109 -> 300 | E71: =D71*$C71 -> 2100 | F71: ='Anexo capacidad operativa'!F109 -> 300 | G71: =F71*$C71 -> 2100 | H71: ='Anexo capacidad operativa'!H109 -> 300 | I71: =H71*$C71 -> 2100 | J71: ='Anexo capacidad operativa'!J109 -> 300 | K71: =J71*$C71 -> 2100 | L71: ='Anexo capacidad operativa'!L109 -> 300 | M71: =L71*$C71 -> 2100 | N71: ='Anexo capacidad operativa'!N109 -> 450 | O71: =N71*$C71 -> 3150 | P71: ='Anexo capacidad operativa'!P109 -> 450 | Q71: =P71*$C71 -> 3150 | R71: ='Anexo capacidad operativa'!R109 -> 450 | S71: =R71*$C71 -> 3150 | T71: ='Anexo capacidad operativa'!T109 -> 450 | U71: =T71*$C71 -> 3150 | V71: ='Anexo capacidad operativa'!V109 -> 450 | W71: =V71*$C71 -> 3150 | X71: ='Anexo capacidad operativa'!X109 -> 450 | Y71: =X71*$C71 -> 3150 | Z71: ='Anexo capacidad operativa'!Z109 -> 450 | AA71: =Z71*$C71 -> 3150 | AB71: =E71+G71+I71+K71+M71+O71+Q71+S71+U71+W71+Y71+AA71 -> 32550
B78: TOTAL | E78: =SUM(E61:E77) -> 5694.8 | G78: =SUM(G61:G77) -> 5736.8 | I78: =SUM(I61:I77) -> 6019 | K78: =SUM(K61:K77) -> 6065.2 | M78: =SUM(M61:M77) -> 6199.8 | O78: =SUM(O61:O77) -> 7297.4 | Q78: =SUM(Q61:Q77) -> 7585.2 | S78: =SUM(S61:S77) -> 7637 | U78: =SUM(U61:U77) -> 8028 | W78: =SUM(W61:W77) -> 8084 | Y78: =SUM(Y61:Y77) -> 8468.6 | AA78: =SUM(AA61:AA77) -> 8530.2 | AB78: =SUM(AB61:AB77) -> 85346

Sheet Costos RRHH
E1: Estructura de costos de RRHH
B4: Evolución de la participación | H4: Costos de RRHH - Totales
B5: 2026 | C5: 2027 | D5: 2028 | H5: 2026 | I5: 2027 | J5: 2028
B6: =Hipótesis!C24 -> 0.008 | C6: =Hipótesis!C25 -> 0.029 | D6: =Hipótesis!C26 -> 0.052 | H6: =$AA$46 -> 67319.2 | I6: =$AA$67 -> 67319.2 | J6: =$AA$88 -> 67319.2
B7: =Hipótesis!D24 -> 107520 | C7: =Hipótesis!D25 -> 389760 | D7: =Hipótesis!D26 -> 698880
B11: Costo mensual por puesto
B12: Area | C12: Puesto | D12: Sueldo bruto | E12: Jubilación | F12: Ley 19032 | G12: Obra social | H12: FNE | I12: AAFF | J12: S. de Vida | K12: ART (Aprox.) | L12: Total aportes | M12: Costo mensual para empresa | N12: Quién lo cubre y dónde se imputa el costo
E13: 0.1235 | F13: 0.0157 | G13: 0.06 | H13: 0.0108 | I13: 0.054 | J13: 1.2 | K13: 0.03
B14: Gerencia | C14: Gerente General (Fundador / CEO) | D14: 2000 | E14: =$D14*E$13 -> 247 | F14: =$D14*F$13 -> 31.4 | G14: =$D14*G$13 -> 120 | H14: =$D14*H$13 -> 21.6 | I14: =$D14*I$13 -> 108 | J14: =$J$13 -> 1.2 | K14: =$D14*K$13 -> 60 | L14: =SUM(E14:K14) -> 589.2 | M14: =D14+L14 -> 2589.2 | N14: En relación de dependencia
C15: Gerente de Sistemas (Fundador / CTO) | D15: 2000 | E15: =$D15*E$13 -> 247 | F15: =$D15*F$13 -> 31.4 | G15: =$D15*G$13 -> 120 | H15: =$D15*H$13 -> 21.6 | I15: =$D15*I$13 -> 108 | J15: =$J$13 -> 1.2 | K15: =$D15*K$13 -> 60 | L15: =SUM(E15:K15) -> 589.2 | M15: =D15+L15 -> 2589.2 | N15: En relación de dependencia
B16: Administración | C16: Administrativo contable y de pagos | D16: 900 | E16: =$D16*E$13 -> 111.15 | F16: =$D16*F$13 -> 14.13 | G16: =$D16*G$13 -> 54 | H16: =$D16*H$13 -> 9.72 | I16: =$D16*I$13 -> 48.6 | J16: =$J$13 -> 1.2 | K16: =$D16*K$13 -> 27 | L16: =SUM(E16:K16) -> 265.8 | M16: =D16+L16 -> 1165.8 | N16: Lo cubre el Gerente General
C17: Liquidación de sueldos e impuestos | D17: 800 | E17: =$D17*E$13 -> 98.8 | F17: =$D17*F$13 -> 12.56 | G17: =$D17*G$13 -> 48 | H17: =$D17*H$13 -> 8.64 | I17: =$D17*I$13 -> 43.2 | J17: =$J$13 -> 1.2 | K17: =$D17*K$13 -> 24 | L17: =SUM(E17:K17) -> 236.4 | M17: =D17+L17 -> 1036.4 | N17: Estudio contable, abono mensual en costos fijos
C18: Administrativo de cobranzas | D18: 850 | E18: =$D18*E$13 -> 104.975 | F18: =$D18*F$13 -> 13.345 | G18: =$D18*G$13 -> 51 | H18: =$D18*H$13 -> 9.18 | I18: =$D18*I$13 -> 45.9 | J18: =$J$13 -> 1.2 | K18: =$D18*K$13 -> 25.5 | L18: =SUM(E18:K18) -> 251.1 | M18: =D18+L18 -> 1101.1 | N18: Lo cubre el Gerente General
B19: Comercial | C19: Ejecutivo comercial de altas | D19: 1000 | E19: =$D19*E$13 -> 123.5 | F19: =$D19*F$13 -> 15.7 | G19: =$D19*G$13 -> 60 | H19: =$D19*H$13 -> 10.8 | I19: =$D19*I$13 -> 54 | J19: =$J$13 -> 1.2 | K19: =$D19*K$13 -> 30 | L19: =SUM(E19:K19) -> 295.2 | M19: =D19+L19 -> 1295.2 | N19: Freelance por comisión sobre cada alta, en costos variables
C20: Atención al cliente y posventa | D20: 900 | E20: =$D20*E$13 -> 111.15 | F20: =$D20*F$13 -> 14.13 | G20: =$D20*G$13 -> 54 | H20: =$D20*H$13 -> 9.72 | I20: =$D20*I$13 -> 48.6 | J20: =$J$13 -> 1.2 | K20: =$D20*K$13 -> 27 | L20: =SUM(E20:K20) -> 265.8 | M20: =D20+L20 -> 1165.8 | N20: Lo cubre el Gerente General
B21: Marketing | C21: Gestión de campañas y contenidos | D21: 1100 | E21: =$D21*E$13 -> 135.85 | F21: =$D21*F$13 -> 17.27 | G21: =$D21*G$13 -> 66 | H21: =$D21*H$13 -> 11.88 | I21: =$D21*I$13 -> 59.4 | J21: =$J$13 -> 1.2 | K21: =$D21*K$13 -> 33 | L21: =SUM(E21:K21) -> 324.6 | M21: =D21+L21 -> 1424.6 | N21: Agencia de marketing, abono mensual en costos fijos
B22: Sistemas | C22: Arquitecto de software | D22: 2200 | E22: =$D22*E$13 -> 271.7 | F22: =$D22*F$13 -> 34.54 | G22: =$D22*G$13 -> 132 | H22: =$D22*H$13 -> 23.76 | I22: =$D22*I$13 -> 118.8 | J22: =$J$13 -> 1.2 | K22: =$D22*K$13 -> 66 | L22: =SUM(E22:K22) -> 648 | M22: =D22+L22 -> 2848 | N22: Contratado por proyecto; el desarrollo inicial es inversión
C23: Desarrollador | D23: 1800 | E23: =$D23*E$13 -> 222.3 | F23: =$D23*F$13 -> 28.26 | G23: =$D23*G$13 -> 108 | H23: =$D23*H$13 -> 19.44 | I23: =$D23*I$13 -> 97.2 | J23: =$J$13 -> 1.2 | K23: =$D23*K$13 -> 54 | L23: =SUM(E23:K23) -> 530.4 | M23: =D23+L23 -> 2330.4 | N23: Mantenimiento evolutivo contratado, en costos fijos
C24: Científico de datos | D24: 2000 | E24: =$D24*E$13 -> 247 | F24: =$D24*F$13 -> 31.4 | G24: =$D24*G$13 -> 120 | H24: =$D24*H$13 -> 21.6 | I24: =$D24*I$13 -> 108 | J24: =$J$13 -> 1.2 | K24: =$D24*K$13 -> 60 | L24: =SUM(E24:K24) -> 589.2 | M24: =D24+L24 -> 2589.2 | N24: Lo cubre el Gerente de Sistemas
C25: DevOps / infraestructura cloud | D25: 1900 | E25: =$D25*E$13 -> 234.65 | F25: =$D25*F$13 -> 29.83 | G25: =$D25*G$13 -> 114 | H25: =$D25*H$13 -> 20.52 | I25: =$D25*I$13 -> 102.6 | J25: =$J$13 -> 1.2 | K25: =$D25*K$13 -> 57 | L25: =SUM(E25:K25) -> 559.8 | M25: =D25+L25 -> 2459.8 | N25: Lo cubre el Gerente de Sistemas
B26: Servicio técnico | C26: Técnico de instalación y soporte | D26: 1100 | E26: =$D26*E$13 -> 135.85 | F26: =$D26*F$13 -> 17.27 | G26: =$D26*G$13 -> 66 | H26: =$D26*H$13 -> 11.88 | I26: =$D26*I$13 -> 59.4 | J26: =$J$13 -> 1.2 | K26: =$D26*K$13 -> 33 | L26: =SUM(E26:K26) -> 324.6 | M26: =D26+L26 -> 1424.6 | N26: Freelance por hora según el Anexo, en costos variables
C27: Operador de monitoreo de sensores | D27: 900 | E27: =$D27*E$13 -> 111.15 | F27: =$D27*F$13 -> 14.13 | G27: =$D27*G$13 -> 54 | H27: =$D27*H$13 -> 9.72 | I27: =$D27*I$13 -> 48.6 | J27: =$J$13 -> 1.2 | K27: =$D27*K$13 -> 27 | L27: =SUM(E27:K27) -> 265.8 | M27: =D27+L27 -> 1165.8 | N27: Lo cubre el Gerente de Sistemas
B29: Costos de RRHH - Año 2026
B30: Puesto | C30: Enero | E30: Febrero | G30: Marzo | I30: Abril | K30: Mayo | M30: Junio + SAC | O30: Julio | Q30: Agosto | S30: Septiembre | U30: Octubre | W30: Noviembre | Y30: Diciembre + SAC | AA30: Total anual
C31: Cantidad | D31: Costo | E31: Cantidad | F31: Costo | G31: Cantidad | H31: Costo | I31: Cantidad | J31: Costo | K31: Cantidad | L31: Costo | M31: Cantidad | N31: Costo | O31: Cantidad | P31: Costo | Q31: Cantidad | R31: Costo | S31: Cantidad | T31: Costo | U31: Cantidad | V31: Costo | W31: Cantidad | X31: Costo | Y31: Cantidad | Z31: Costo
B32: Gerente General (Fundador / CEO) | C32: 1 | D32: =C32*$M$14 -> 2589.2 | E32: 1 | F32: =E32*$M$14 -> 2589.2 | G32: 1 | H32: =G32*$M$14 -> 2589.2 | I32: 1 | J32: =I32*$M$14 -> 2589.2 | K32: 1 | L32: =K32*$M$14 -> 2589.2 | M32: 1 | N32: =M32*$M$14+L32/2 -> 3883.8 | O32: 1 | P32: =O32*$M$14 -> 2589.2 | Q32: 1 | R32: =Q32*$M$14 -> 2589.2 | S32: 1 | T32: =S32*$M$14 -> 2589.2 | U32: 1 | V32: =U32*$M$14 -> 2589.2 | W32: 1 | X32: =W32*$M$14 -> 2589.2 | Y32: 1 | Z32: =Y32*$M$14+X32/2 -> 3883.8 | AA32: =D32+F32+H32+J32+L32+N32+P32+R32+T32+V32+X32+Z32 -> 33659.6
B33: Gerente de Sistemas (Fundador / CTO) | C33: 1 | D33: =C33*$M$15 -> 2589.2 | E33: 1 | F33: =E33*$M$15 -> 2589.2 | G33: 1 | H33: =G33*$M$15 -> 2589.2 | I33: 1 | J33: =I33*$M$15 -> 2589.2 | K33: 1 | L33: =K33*$M$15 -> 2589.2 | M33: 1 | N33: =M33*$M$15+L33/2 -> 3883.8 | O33: 1 | P33: =O33*$M$15 -> 2589.2 | Q33: 1 | R33: =Q33*$M$15 -> 2589.2 | S33: 1 | T33: =S33*$M$15 -> 2589.2 | U33: 1 | V33: =U33*$M$15 -> 2589.2 | W33: 1 | X33: =W33*$M$15 -> 2589.2 | Y33: 1 | Z33: =Y33*$M$15+X33/2 -> 3883.8 | AA33: =D33+F33+H33+J33+L33+N33+P33+R33+T33+V33+X33+Z33 -> 33659.6
B34: Administrativo contable y de pagos | C34: 0 | D34: =C34*$M$16 -> 0 | E34: 0 | F34: =E34*$M$16 -> 0 | G34: 0 | H34: =G34*$M$16 -> 0 | I34: 0 | J34: =I34*$M$16 -> 0 | K34: 0 | L34: =K34*$M$16 -> 0 | M34: 0 | N34: =M34*$M$16+L34/2 -> 0 | O34: 0 | P34: =O34*$M$16 -> 0 | Q34: 0 | R34: =Q34*$M$16 -> 0 | S34: 0 | T34: =S34*$M$16 -> 0 | U34: 0 | V34: =U34*$M$16 -> 0 | W34: 0 | X34: =W34*$M$16 -> 0 | Y34: 0 | Z34: =Y34*$M$16+X34/2 -> 0 | AA34: =D34+F34+H34+J34+L34+N34+P34+R34+T34+V34+X34+Z34 -> 0
B35: Liquidación de sueldos e impuestos | C35: 0 | D35: =C35*$M$17 -> 0 | E35: 0 | F35: =E35*$M$17 -> 0 | G35: 0 | H35: =G35*$M$17 -> 0 | I35: 0 | J35: =I35*$M$17 -> 0 | K35: 0 | L35: =K35*$M$17 -> 0 | M35: 0 | N35: =M35*$M$17+L35/2 -> 0 | O35: 0 | P35: =O35*$M$17 -> 0 | Q35: 0 | R35: =Q35*$M$17 -> 0 | S35: 0 | T35: =S35*$M$17 -> 0 | U35: 0 | V35: =U35*$M$17 -> 0 | W35: 0 | X35: =W35*$M$17 -> 0 | Y35: 0 | Z35: =Y35*$M$17+X35/2 -> 0 | AA35: =D35+F35+H35+J35+L35+N35+P35+R35+T35+V35+X35+Z35 -> 0
B36: Administrativo de cobranzas | C36: 0 | D36: =C36*$M$18 -> 0 | E36: 0 | F36: =E36*$M$18 -> 0 | G36: 0 | H36: =G36*$M$18 -> 0 | I36: 0 | J36: =I36*$M$18 -> 0 | K36: 0 | L36: =K36*$M$18 -> 0 | M36: 0 | N36: =M36*$M$18+L36/2 -> 0 | O36: 0 | P36: =O36*$M$18 -> 0 | Q36: 0 | R36: =Q36*$M$18 -> 0 | S36: 0 | T36: =S36*$M$18 -> 0 | U36: 0 | V36: =U36*$M$18 -> 0 | W36: 0 | X36: =W36*$M$18 -> 0 | Y36: 0 | Z36: =Y36*$M$18+X36/2 -> 0 | AA36: =D36+F36+H36+J36+L36+N36+P36+R36+T36+V36+X36+Z36 -> 0
B37: Ejecutivo comercial de altas | C37: 0 | D37: =C37*$M$19 -> 0 | E37: 0 | F37: =E37*$M$19 -> 0 | G37: 0 | H37: =G37*$M$19 -> 0 | I37: 0 | J37: =I37*$M$19 -> 0 | K37: 0 | L37: =K37*$M$19 -> 0 | M37: 0 | N37: =M37*$M$19+L37/2 -> 0 | O37: 0 | P37: =O37*$M$19 -> 0 | Q37: 0 | R37: =Q37*$M$19 -> 0 | S37: 0 | T37: =S37*$M$19 -> 0 | U37: 0 | V37: =U37*$M$19 -> 0 | W37: 0 | X37: =W37*$M$19 -> 0 | Y37: 0 | Z37: =Y37*$M$19+X37/2 -> 0 | AA37: =D37+F37+H37+J37+L37+N37+P37+R37+T37+V37+X37+Z37 -> 0
B38: Atención al cliente y posventa | C38: 0 | D38: =C38*$M$20 -> 0 | E38: 0 | F38: =E38*$M$20 -> 0 | G38: 0 | H38: =G38*$M$20 -> 0 | I38: 0 | J38: =I38*$M$20 -> 0 | K38: 0 | L38: =K38*$M$20 -> 0 | M38: 0 | N38: =M38*$M$20+L38/2 -> 0 | O38: 0 | P38: =O38*$M$20 -> 0 | Q38: 0 | R38: =Q38*$M$20 -> 0 | S38: 0 | T38: =S38*$M$20 -> 0 | U38: 0 | V38: =U38*$M$20 -> 0 | W38: 0 | X38: =W38*$M$20 -> 0 | Y38: 0 | Z38: =Y38*$M$20+X38/2 -> 0 | AA38: =D38+F38+H38+J38+L38+N38+P38+R38+T38+V38+X38+Z38 -> 0
B39: Gestión de campañas y contenidos | C39: 0 | D39: =C39*$M$21 -> 0 | E39: 0 | F39: =E39*$M$21 -> 0 | G39: 0 | H39: =G39*$M$21 -> 0 | I39: 0 | J39: =I39*$M$21 -> 0 | K39: 0 | L39: =K39*$M$21 -> 0 | M39: 0 | N39: =M39*$M$21+L39/2 -> 0 | O39: 0 | P39: =O39*$M$21 -> 0 | Q39: 0 | R39: =Q39*$M$21 -> 0 | S39: 0 | T39: =S39*$M$21 -> 0 | U39: 0 | V39: =U39*$M$21 -> 0 | W39: 0 | X39: =W39*$M$21 -> 0 | Y39: 0 | Z39: =Y39*$M$21+X39/2 -> 0 | AA39: =D39+F39+H39+J39+L39+N39+P39+R39+T39+V39+X39+Z39 -> 0
B40: Arquitecto de software | C40: 0 | D40: =C40*$M$22 -> 0 | E40: 0 | F40: =E40*$M$22 -> 0 | G40: 0 | H40: =G40*$M$22 -> 0 | I40: 0 | J40: =I40*$M$22 -> 0 | K40: 0 | L40: =K40*$M$22 -> 0 | M40: 0 | N40: =M40*$M$22+L40/2 -> 0 | O40: 0 | P40: =O40*$M$22 -> 0 | Q40: 0 | R40: =Q40*$M$22 -> 0 | S40: 0 | T40: =S40*$M$22 -> 0 | U40: 0 | V40: =U40*$M$22 -> 0 | W40: 0 | X40: =W40*$M$22 -> 0 | Y40: 0 | Z40: =Y40*$M$22+X40/2 -> 0 | AA40: =D40+F40+H40+J40+L40+N40+P40+R40+T40+V40+X40+Z40 -> 0
B41: Desarrollador | C41: 0 | D41: =C41*$M$23 -> 0 | E41: 0 | F41: =E41*$M$23 -> 0 | G41: 0 | H41: =G41*$M$23 -> 0 | I41: 0 | J41: =I41*$M$23 -> 0 | K41: 0 | L41: =K41*$M$23 -> 0 | M41: 0 | N41: =M41*$M$23+L41/2 -> 0 | O41: 0 | P41: =O41*$M$23 -> 0 | Q41: 0 | R41: =Q41*$M$23 -> 0 | S41: 0 | T41: =S41*$M$23 -> 0 | U41: 0 | V41: =U41*$M$23 -> 0 | W41: 0 | X41: =W41*$M$23 -> 0 | Y41: 0 | Z41: =Y41*$M$23+X41/2 -> 0 | AA41: =D41+F41+H41+J41+L41+N41+P41+R41+T41+V41+X41+Z41 -> 0
B42: Científico de datos | C42: 0 | D42: =C42*$M$24 -> 0 | E42: 0 | F42: =E42*$M$24 -> 0 | G42: 0 | H42: =G42*$M$24 -> 0 | I42: 0 | J42: =I42*$M$24 -> 0 | K42: 0 | L42: =K42*$M$24 -> 0 | M42: 0 | N42: =M42*$M$24+L42/2 -> 0 | O42: 0 | P42: =O42*$M$24 -> 0 | Q42: 0 | R42: =Q42*$M$24 -> 0 | S42: 0 | T42: =S42*$M$24 -> 0 | U42: 0 | V42: =U42*$M$24 -> 0 | W42: 0 | X42: =W42*$M$24 -> 0 | Y42: 0 | Z42: =Y42*$M$24+X42/2 -> 0 | AA42: =D42+F42+H42+J42+L42+N42+P42+R42+T42+V42+X42+Z42 -> 0
B43: DevOps / infraestructura cloud | C43: 0 | D43: =C43*$M$25 -> 0 | E43: 0 | F43: =E43*$M$25 -> 0 | G43: 0 | H43: =G43*$M$25 -> 0 | I43: 0 | J43: =I43*$M$25 -> 0 | K43: 0 | L43: =K43*$M$25 -> 0 | M43: 0 | N43: =M43*$M$25+L43/2 -> 0 | O43: 0 | P43: =O43*$M$25 -> 0 | Q43: 0 | R43: =Q43*$M$25 -> 0 | S43: 0 | T43: =S43*$M$25 -> 0 | U43: 0 | V43: =U43*$M$25 -> 0 | W43: 0 | X43: =W43*$M$25 -> 0 | Y43: 0 | Z43: =Y43*$M$25+X43/2 -> 0 | AA43: =D43+F43+H43+J43+L43+N43+P43+R43+T43+V43+X43+Z43 -> 0
B44: Técnico de instalación y soporte | C44: 0 | D44: =C44*$M$26 -> 0 | E44: 0 | F44: =E44*$M$26 -> 0 | G44: 0 | H44: =G44*$M$26 -> 0 | I44: 0 | J44: =I44*$M$26 -> 0 | K44: 0 | L44: =K44*$M$26 -> 0 | M44: 0 | N44: =M44*$M$26+L44/2 -> 0 | O44: 0 | P44: =O44*$M$26 -> 0 | Q44: 0 | R44: =Q44*$M$26 -> 0 | S44: 0 | T44: =S44*$M$26 -> 0 | U44: 0 | V44: =U44*$M$26 -> 0 | W44: 0 | X44: =W44*$M$26 -> 0 | Y44: 0 | Z44: =Y44*$M$26+X44/2 -> 0 | AA44: =D44+F44+H44+J44+L44+N44+P44+R44+T44+V44+X44+Z44 -> 0
B45: Operador de monitoreo de sensores | C45: 0 | D45: =C45*$M$27 -> 0 | E45: 0 | F45: =E45*$M$27 -> 0 | G45: 0 | H45: =G45*$M$27 -> 0 | I45: 0 | J45: =I45*$M$27 -> 0 | K45: 0 | L45: =K45*$M$27 -> 0 | M45: 0 | N45: =M45*$M$27+L45/2 -> 0 | O45: 0 | P45: =O45*$M$27 -> 0 | Q45: 0 | R45: =Q45*$M$27 -> 0 | S45: 0 | T45: =S45*$M$27 -> 0 | U45: 0 | V45: =U45*$M$27 -> 0 | W45: 0 | X45: =W45*$M$27 -> 0 | Y45: 0 | Z45: =Y45*$M$27+X45/2 -> 0 | AA45: =D45+F45+H45+J45+L45+N45+P45+R45+T45+V45+X45+Z45 -> 0
B46: Totales | C46: =SUM(C32:C45) -> 2 | D46: =SUM(D32:D45) -> 5178.4 | E46: =SUM(E32:E45) -> 2 | F46: =SUM(F32:F45) -> 5178.4 | G46: =SUM(G32:G45) -> 2 | H46: =SUM(H32:H45) -> 5178.4 | I46: =SUM(I32:I45) -> 2 | J46: =SUM(J32:J45) -> 5178.4 | ... AA46: =SUM(AA32:AA45) -> 67319.2
B50: Costos de RRHH - Año 2027
B51: Puesto | C51: Enero | E51: Febrero | G51: Marzo | I51: Abril | K51: Mayo | M51: Junio + SAC | O51: Julio | Q51: Agosto | S51: Septiembre | U51: Octubre | W51: Noviembre | Y51: Diciembre + SAC | AA51: Total anual
C52: Cantidad | D52: Costo | E52: Cantidad | F52: Costo | G52: Cantidad | H52: Costo | I52: Cantidad | J52: Costo | K52: Cantidad | L52: Costo | M52: Cantidad | N52: Costo | O52: Cantidad | P52: Costo | Q52: Cantidad | R52: Costo | S52: Cantidad | T52: Costo | U52: Cantidad | V52: Costo | W52: Cantidad | X52: Costo | Y52: Cantidad | Z52: Costo
B53: Gerente General (Fundador / CEO) | C53: 1 | D53: =C53*$M$14 -> 2589.2 | E53: 1 | F53: =E53*$M$14 -> 2589.2 | G53: 1 | H53: =G53*$M$14 -> 2589.2 | I53: 1 | J53: =I53*$M$14 -> 2589.2 | K53: 1 | L53: =K53*$M$14 -> 2589.2 | M53: 1 | N53: =M53*$M$14+L53/2 -> 3883.8 | O53: 1 | P53: =O53*$M$14 -> 2589.2 | Q53: 1 | R53: =Q53*$M$14 -> 2589.2 | S53: 1 | T53: =S53*$M$14 -> 2589.2 | U53: 1 | V53: =U53*$M$14 -> 2589.2 | W53: 1 | X53: =W53*$M$14 -> 2589.2 | Y53: 1 | Z53: =Y53*$M$14+X53/2 -> 3883.8 | AA53: =D53+F53+H53+J53+L53+N53+P53+R53+T53+V53+X53+Z53 -> 33659.6
B54: Gerente de Sistemas (Fundador / CTO) | C54: 1 | D54: =C54*$M$15 -> 2589.2 | E54: 1 | F54: =E54*$M$15 -> 2589.2 | G54: 1 | H54: =G54*$M$15 -> 2589.2 | I54: 1 | J54: =I54*$M$15 -> 2589.2 | K54: 1 | L54: =K54*$M$15 -> 2589.2 | M54: 1 | N54: =M54*$M$15+L54/2 -> 3883.8 | O54: 1 | P54: =O54*$M$15 -> 2589.2 | Q54: 1 | R54: =Q54*$M$15 -> 2589.2 | S54: 1 | T54: =S54*$M$15 -> 2589.2 | U54: 1 | V54: =U54*$M$15 -> 2589.2 | W54: 1 | X54: =W54*$M$15 -> 2589.2 | Y54: 1 | Z54: =Y54*$M$15+X54/2 -> 3883.8 | AA54: =D54+F54+H54+J54+L54+N54+P54+R54+T54+V54+X54+Z54 -> 33659.6
B55: Administrativo contable y de pagos | C55: 0 | D55: =C55*$M$16 -> 0 | E55: 0 | F55: =E55*$M$16 -> 0 | G55: 0 | H55: =G55*$M$16 -> 0 | I55: 0 | J55: =I55*$M$16 -> 0 | K55: 0 | L55: =K55*$M$16 -> 0 | M55: 0 | N55: =M55*$M$16+L55/2 -> 0 | O55: 0 | P55: =O55*$M$16 -> 0 | Q55: 0 | R55: =Q55*$M$16 -> 0 | S55: 0 | T55: =S55*$M$16 -> 0 | U55: 0 | V55: =U55*$M$16 -> 0 | W55: 0 | X55: =W55*$M$16 -> 0 | Y55: 0 | Z55: =Y55*$M$16+X55/2 -> 0 | AA55: =D55+F55+H55+J55+L55+N55+P55+R55+T55+V55+X55+Z55 -> 0
B56: Liquidación de sueldos e impuestos | C56: 0 | D56: =C56*$M$17 -> 0 | E56: 0 | F56: =E56*$M$17 -> 0 | G56: 0 | H56: =G56*$M$17 -> 0 | I56: 0 | J56: =I56*$M$17 -> 0 | K56: 0 | L56: =K56*$M$17 -> 0 | M56: 0 | N56: =M56*$M$17+L56/2 -> 0 | O56: 0 | P56: =O56*$M$17 -> 0 | Q56: 0 | R56: =Q56*$M$17 -> 0 | S56: 0 | T56: =S56*$M$17 -> 0 | U56: 0 | V56: =U56*$M$17 -> 0 | W56: 0 | X56: =W56*$M$17 -> 0 | Y56: 0 | Z56: =Y56*$M$17+X56/2 -> 0 | AA56: =D56+F56+H56+J56+L56+N56+P56+R56+T56+V56+X56+Z56 -> 0
B57: Administrativo de cobranzas | C57: 0 | D57: =C57*$M$18 -> 0 | E57: 0 | F57: =E57*$M$18 -> 0 | G57: 0 | H57: =G57*$M$18 -> 0 | I57: 0 | J57: =I57*$M$18 -> 0 | K57: 0 | L57: =K57*$M$18 -> 0 | M57: 0 | N57: =M57*$M$18+L57/2 -> 0 | O57: 0 | P57: =O57*$M$18 -> 0 | Q57: 0 | R57: =Q57*$M$18 -> 0 | S57: 0 | T57: =S57*$M$18 -> 0 | U57: 0 | V57: =U57*$M$18 -> 0 | W57: 0 | X57: =W57*$M$18 -> 0 | Y57: 0 | Z57: =Y57*$M$18+X57/2 -> 0 | AA57: =D57+F57+H57+J57+L57+N57+P57+R57+T57+V57+X57+Z57 -> 0
B58: Ejecutivo comercial de altas | C58: 0 | D58: =C58*$M$19 -> 0 | E58: 0 | F58: =E58*$M$19 -> 0 | G58: 0 | H58: =G58*$M$19 -> 0 | I58: 0 | J58: =I58*$M$19 -> 0 | K58: 0 | L58: =K58*$M$19 -> 0 | M58: 0 | N58: =M58*$M$19+L58/2 -> 0 | O58: 0 | P58: =O58*$M$19 -> 0 | Q58: 0 | R58: =Q58*$M$19 -> 0 | S58: 0 | T58: =S58*$M$19 -> 0 | U58: 0 | V58: =U58*$M$19 -> 0 | W58: 0 | X58: =W58*$M$19 -> 0 | Y58: 0 | Z58: =Y58*$M$19+X58/2 -> 0 | AA58: =D58+F58+H58+J58+L58+N58+P58+R58+T58+V58+X58+Z58 -> 0
B59: Atención al cliente y posventa | C59: 0 | D59: =C59*$M$20 -> 0 | E59: 0 | F59: =E59*$M$20 -> 0 | G59: 0 | H59: =G59*$M$20 -> 0 | I59: 0 | J59: =I59*$M$20 -> 0 | K59: 0 | L59: =K59*$M$20 -> 0 | M59: 0 | N59: =M59*$M$20+L59/2 -> 0 | O59: 0 | P59: =O59*$M$20 -> 0 | Q59: 0 | R59: =Q59*$M$20 -> 0 | S59: 0 | T59: =S59*$M$20 -> 0 | U59: 0 | V59: =U59*$M$20 -> 0 | W59: 0 | X59: =W59*$M$20 -> 0 | Y59: 0 | Z59: =Y59*$M$20+X59/2 -> 0 | AA59: =D59+F59+H59+J59+L59+N59+P59+R59+T59+V59+X59+Z59 -> 0
B60: Gestión de campañas y contenidos | C60: 0 | D60: =C60*$M$21 -> 0 | E60: 0 | F60: =E60*$M$21 -> 0 | G60: 0 | H60: =G60*$M$21 -> 0 | I60: 0 | J60: =I60*$M$21 -> 0 | K60: 0 | L60: =K60*$M$21 -> 0 | M60: 0 | N60: =M60*$M$21+L60/2 -> 0 | O60: 0 | P60: =O60*$M$21 -> 0 | Q60: 0 | R60: =Q60*$M$21 -> 0 | S60: 0 | T60: =S60*$M$21 -> 0 | U60: 0 | V60: =U60*$M$21 -> 0 | W60: 0 | X60: =W60*$M$21 -> 0 | Y60: 0 | Z60: =Y60*$M$21+X60/2 -> 0 | AA60: =D60+F60+H60+J60+L60+N60+P60+R60+T60+V60+X60+Z60 -> 0
B61: Arquitecto de software | C61: 0 | D61: =C61*$M$22 -> 0 | E61: 0 | F61: =E61*$M$22 -> 0 | G61: 0 | H61: =G61*$M$22 -> 0 | I61: 0 | J61: =I61*$M$22 -> 0 | K61: 0 | L61: =K61*$M$22 -> 0 | M61: 0 | N61: =M61*$M$22+L61/2 -> 0 | O61: 0 | P61: =O61*$M$22 -> 0 | Q61: 0 | R61: =Q61*$M$22 -> 0 | S61: 0 | T61: =S61*$M$22 -> 0 | U61: 0 | V61: =U61*$M$22 -> 0 | W61: 0 | X61: =W61*$M$22 -> 0 | Y61: 0 | Z61: =Y61*$M$22+X61/2 -> 0 | AA61: =D61+F61+H61+J61+L61+N61+P61+R61+T61+V61+X61+Z61 -> 0
B62: Desarrollador | C62: 0 | D62: =C62*$M$23 -> 0 | E62: 0 | F62: =E62*$M$23 -> 0 | G62: 0 | H62: =G62*$M$23 -> 0 | I62: 0 | J62: =I62*$M$23 -> 0 | K62: 0 | L62: =K62*$M$23 -> 0 | M62: 0 | N62: =M62*$M$23+L62/2 -> 0 | O62: 0 | P62: =O62*$M$23 -> 0 | Q62: 0 | R62: =Q62*$M$23 -> 0 | S62: 0 | T62: =S62*$M$23 -> 0 | U62: 0 | V62: =U62*$M$23 -> 0 | W62: 0 | X62: =W62*$M$23 -> 0 | Y62: 0 | Z62: =Y62*$M$23+X62/2 -> 0 | AA62: =D62+F62+H62+J62+L62+N62+P62+R62+T62+V62+X62+Z62 -> 0
B63: Científico de datos | C63: 0 | D63: =C63*$M$24 -> 0 | E63: 0 | F63: =E63*$M$24 -> 0 | G63: 0 | H63: =G63*$M$24 -> 0 | I63: 0 | J63: =I63*$M$24 -> 0 | K63: 0 | L63: =K63*$M$24 -> 0 | M63: 0 | N63: =M63*$M$24+L63/2 -> 0 | O63: 0 | P63: =O63*$M$24 -> 0 | Q63: 0 | R63: =Q63*$M$24 -> 0 | S63: 0 | T63: =S63*$M$24 -> 0 | U63: 0 | V63: =U63*$M$24 -> 0 | W63: 0 | X63: =W63*$M$24 -> 0 | Y63: 0 | Z63: =Y63*$M$24+X63/2 -> 0 | AA63: =D63+F63+H63+J63+L63+N63+P63+R63+T63+V63+X63+Z63 -> 0
B64: DevOps / infraestructura cloud | C64: 0 | D64: =C64*$M$25 -> 0 | E64: 0 | F64: =E64*$M$25 -> 0 | G64: 0 | H64: =G64*$M$25 -> 0 | I64: 0 | J64: =I64*$M$25 -> 0 | K64: 0 | L64: =K64*$M$25 -> 0 | M64: 0 | N64: =M64*$M$25+L64/2 -> 0 | O64: 0 | P64: =O64*$M$25 -> 0 | Q64: 0 | R64: =Q64*$M$25 -> 0 | S64: 0 | T64: =S64*$M$25 -> 0 | U64: 0 | V64: =U64*$M$25 -> 0 | W64: 0 | X64: =W64*$M$25 -> 0 | Y64: 0 | Z64: =Y64*$M$25+X64/2 -> 0 | AA64: =D64+F64+H64+J64+L64+N64+P64+R64+T64+V64+X64+Z64 -> 0
B65: Técnico de instalación y soporte | C65: 0 | D65: =C65*$M$26 -> 0 | E65: 0 | F65: =E65*$M$26 -> 0 | G65: 0 | H65: =G65*$M$26 -> 0 | I65: 0 | J65: =I65*$M$26 -> 0 | K65: 0 | L65: =K65*$M$26 -> 0 | M65: 0 | N65: =M65*$M$26+L65/2 -> 0 | O65: 0 | P65: =O65*$M$26 -> 0 | Q65: 0 | R65: =Q65*$M$26 -> 0 | S65: 0 | T65: =S65*$M$26 -> 0 | U65: 0 | V65: =U65*$M$26 -> 0 | W65: 0 | X65: =W65*$M$26 -> 0 | Y65: 0 | Z65: =Y65*$M$26+X65/2 -> 0 | AA65: =D65+F65+H65+J65+L65+N65+P65+R65+T65+V65+X65+Z65 -> 0
B66: Operador de monitoreo de sensores | C66: 0 | D66: =C66*$M$27 -> 0 | E66: 0 | F66: =E66*$M$27 -> 0 | G66: 0 | H66: =G66*$M$27 -> 0 | I66: 0 | J66: =I66*$M$27 -> 0 | K66: 0 | L66: =K66*$M$27 -> 0 | M66: 0 | N66: =M66*$M$27+L66/2 -> 0 | O66: 0 | P66: =O66*$M$27 -> 0 | Q66: 0 | R66: =Q66*$M$27 -> 0 | S66: 0 | T66: =S66*$M$27 -> 0 | U66: 0 | V66: =U66*$M$27 -> 0 | W66: 0 | X66: =W66*$M$27 -> 0 | Y66: 0 | Z66: =Y66*$M$27+X66/2 -> 0 | AA66: =D66+F66+H66+J66+L66+N66+P66+R66+T66+V66+X66+Z66 -> 0
B67: Totales | C67: =SUM(C53:C66) -> 2 | D67: =SUM(D53:D66) -> 5178.4 | E67: =SUM(E53:E66) -> 2 | F67: =SUM(F53:F66) -> 5178.4 | G67: =SUM(G53:G66) -> 2 | H67: =SUM(H53:H66) -> 5178.4 | I67: =SUM(I53:I66) -> 2 | J67: =SUM(J53:J66) -> 5178.4 | ... AA67: =SUM(AA53:AA66) -> 67319.2
B71: Costos de RRHH - Año 2028
B72: Puesto | C72: Enero | E72: Febrero | G72: Marzo | I72: Abril | K72: Mayo | M72: Junio + SAC | O72: Julio | Q72: Agosto | S72: Septiembre | U72: Octubre | W72: Noviembre | Y72: Diciembre + SAC | AA72: Total anual
C73: Cantidad | D73: Costo | E73: Cantidad | F73: Costo | G73: Cantidad | H73: Costo | I73: Cantidad | J73: Costo | K73: Cantidad | L73: Costo | M73: Cantidad | N73: Costo | O73: Cantidad | P73: Costo | Q73: Cantidad | R73: Costo | S73: Cantidad | T73: Costo | U73: Cantidad | V73: Costo | W73: Cantidad | X73: Costo | Y73: Cantidad | Z73: Costo
B74: Gerente General (Fundador / CEO) | C74: 1 | D74: =C74*$M$14 -> 2589.2 | E74: 1 | F74: =E74*$M$14 -> 2589.2 | G74: 1 | H74: =G74*$M$14 -> 2589.2 | I74: 1 | J74: =I74*$M$14 -> 2589.2 | K74: 1 | L74: =K74*$M$14 -> 2589.2 | M74: 1 | N74: =M74*$M$14+L74/2 -> 3883.8 | O74: 1 | P74: =O74*$M$14 -> 2589.2 | Q74: 1 | R74: =Q74*$M$14 -> 2589.2 | S74: 1 | T74: =S74*$M$14 -> 2589.2 | U74: 1 | V74: =U74*$M$14 -> 2589.2 | W74: 1 | X74: =W74*$M$14 -> 2589.2 | Y74: 1 | Z74: =Y74*$M$14+X74/2 -> 3883.8 | AA74: =D74+F74+H74+J74+L74+N74+P74+R74+T74+V74+X74+Z74 -> 33659.6
B75: Gerente de Sistemas (Fundador / CTO) | C75: 1 | D75: =C75*$M$15 -> 2589.2 | E75: 1 | F75: =E75*$M$15 -> 2589.2 | G75: 1 | H75: =G75*$M$15 -> 2589.2 | I75: 1 | J75: =I75*$M$15 -> 2589.2 | K75: 1 | L75: =K75*$M$15 -> 2589.2 | M75: 1 | N75: =M75*$M$15+L75/2 -> 3883.8 | O75: 1 | P75: =O75*$M$15 -> 2589.2 | Q75: 1 | R75: =Q75*$M$15 -> 2589.2 | S75: 1 | T75: =S75*$M$15 -> 2589.2 | U75: 1 | V75: =U75*$M$15 -> 2589.2 | W75: 1 | X75: =W75*$M$15 -> 2589.2 | Y75: 1 | Z75: =Y75*$M$15+X75/2 -> 3883.8 | AA75: =D75+F75+H75+J75+L75+N75+P75+R75+T75+V75+X75+Z75 -> 33659.6
B76: Administrativo contable y de pagos | C76: 0 | D76: =C76*$M$16 -> 0 | E76: 0 | F76: =E76*$M$16 -> 0 | G76: 0 | H76: =G76*$M$16 -> 0 | I76: 0 | J76: =I76*$M$16 -> 0 | K76: 0 | L76: =K76*$M$16 -> 0 | M76: 0 | N76: =M76*$M$16+L76/2 -> 0 | O76: 0 | P76: =O76*$M$16 -> 0 | Q76: 0 | R76: =Q76*$M$16 -> 0 | S76: 0 | T76: =S76*$M$16 -> 0 | U76: 0 | V76: =U76*$M$16 -> 0 | W76: 0 | X76: =W76*$M$16 -> 0 | Y76: 0 | Z76: =Y76*$M$16+X76/2 -> 0 | AA76: =D76+F76+H76+J76+L76+N76+P76+R76+T76+V76+X76+Z76 -> 0
B77: Liquidación de sueldos e impuestos | C77: 0 | D77: =C77*$M$17 -> 0 | E77: 0 | F77: =E77*$M$17 -> 0 | G77: 0 | H77: =G77*$M$17 -> 0 | I77: 0 | J77: =I77*$M$17 -> 0 | K77: 0 | L77: =K77*$M$17 -> 0 | M77: 0 | N77: =M77*$M$17+L77/2 -> 0 | O77: 0 | P77: =O77*$M$17 -> 0 | Q77: 0 | R77: =Q77*$M$17 -> 0 | S77: 0 | T77: =S77*$M$17 -> 0 | U77: 0 | V77: =U77*$M$17 -> 0 | W77: 0 | X77: =W77*$M$17 -> 0 | Y77: 0 | Z77: =Y77*$M$17+X77/2 -> 0 | AA77: =D77+F77+H77+J77+L77+N77+P77+R77+T77+V77+X77+Z77 -> 0
B78: Administrativo de cobranzas | C78: 0 | D78: =C78*$M$18 -> 0 | E78: 0 | F78: =E78*$M$18 -> 0 | G78: 0 | H78: =G78*$M$18 -> 0 | I78: 0 | J78: =I78*$M$18 -> 0 | K78: 0 | L78: =K78*$M$18 -> 0 | M78: 0 | N78: =M78*$M$18+L78/2 -> 0 | O78: 0 | P78: =O78*$M$18 -> 0 | Q78: 0 | R78: =Q78*$M$18 -> 0 | S78: 0 | T78: =S78*$M$18 -> 0 | U78: 0 | V78: =U78*$M$18 -> 0 | W78: 0 | X78: =W78*$M$18 -> 0 | Y78: 0 | Z78: =Y78*$M$18+X78/2 -> 0 | AA78: =D78+F78+H78+J78+L78+N78+P78+R78+T78+V78+X78+Z78 -> 0
B79: Ejecutivo comercial de altas | C79: 0 | D79: =C79*$M$19 -> 0 | E79: 0 | F79: =E79*$M$19 -> 0 | G79: 0 | H79: =G79*$M$19 -> 0 | I79: 0 | J79: =I79*$M$19 -> 0 | K79: 0 | L79: =K79*$M$19 -> 0 | M79: 0 | N79: =M79*$M$19+L79/2 -> 0 | O79: 0 | P79: =O79*$M$19 -> 0 | Q79: 0 | R79: =Q79*$M$19 -> 0 | S79: 0 | T79: =S79*$M$19 -> 0 | U79: 0 | V79: =U79*$M$19 -> 0 | W79: 0 | X79: =W79*$M$19 -> 0 | Y79: 0 | Z79: =Y79*$M$19+X79/2 -> 0 | AA79: =D79+F79+H79+J79+L79+N79+P79+R79+T79+V79+X79+Z79 -> 0
B80: Atención al cliente y posventa | C80: 0 | D80: =C80*$M$20 -> 0 | E80: 0 | F80: =E80*$M$20 -> 0 | G80: 0 | H80: =G80*$M$20 -> 0 | I80: 0 | J80: =I80*$M$20 -> 0 | K80: 0 | L80: =K80*$M$20 -> 0 | M80: 0 | N80: =M80*$M$20+L80/2 -> 0 | O80: 0 | P80: =O80*$M$20 -> 0 | Q80: 0 | R80: =Q80*$M$20 -> 0 | S80: 0 | T80: =S80*$M$20 -> 0 | U80: 0 | V80: =U80*$M$20 -> 0 | W80: 0 | X80: =W80*$M$20 -> 0 | Y80: 0 | Z80: =Y80*$M$20+X80/2 -> 0 | AA80: =D80+F80+H80+J80+L80+N80+P80+R80+T80+V80+X80+Z80 -> 0
B81: Gestión de campañas y contenidos | C81: 0 | D81: =C81*$M$21 -> 0 | E81: 0 | F81: =E81*$M$21 -> 0 | G81: 0 | H81: =G81*$M$21 -> 0 | I81: 0 | J81: =I81*$M$21 -> 0 | K81: 0 | L81: =K81*$M$21 -> 0 | M81: 0 | N81: =M81*$M$21+L81/2 -> 0 | O81: 0 | P81: =O81*$M$21 -> 0 | Q81: 0 | R81: =Q81*$M$21 -> 0 | S81: 0 | T81: =S81*$M$21 -> 0 | U81: 0 | V81: =U81*$M$21 -> 0 | W81: 0 | X81: =W81*$M$21 -> 0 | Y81: 0 | Z81: =Y81*$M$21+X81/2 -> 0 | AA81: =D81+F81+H81+J81+L81+N81+P81+R81+T81+V81+X81+Z81 -> 0
B82: Arquitecto de software | C82: 0 | D82: =C82*$M$22 -> 0 | E82: 0 | F82: =E82*$M$22 -> 0 | G82: 0 | H82: =G82*$M$22 -> 0 | I82: 0 | J82: =I82*$M$22 -> 0 | K82: 0 | L82: =K82*$M$22 -> 0 | M82: 0 | N82: =M82*$M$22+L82/2 -> 0 | O82: 0 | P82: =O82*$M$22 -> 0 | Q82: 0 | R82: =Q82*$M$22 -> 0 | S82: 0 | T82: =S82*$M$22 -> 0 | U82: 0 | V82: =U82*$M$22 -> 0 | W82: 0 | X82: =W82*$M$22 -> 0 | Y82: 0 | Z82: =Y82*$M$22+X82/2 -> 0 | AA82: =D82+F82+H82+J82+L82+N82+P82+R82+T82+V82+X82+Z82 -> 0
B83: Desarrollador | C83: 0 | D83: =C83*$M$23 -> 0 | E83: 0 | F83: =E83*$M$23 -> 0 | G83: 0 | H83: =G83*$M$23 -> 0 | I83: 0 | J83: =I83*$M$23 -> 0 | K83: 0 | L83: =K83*$M$23 -> 0 | M83: 0 | N83: =M83*$M$23+L83/2 -> 0 | O83: 0 | P83: =O83*$M$23 -> 0 | Q83: 0 | R83: =Q83*$M$23 -> 0 | S83: 0 | T83: =S83*$M$23 -> 0 | U83: 0 | V83: =U83*$M$23 -> 0 | W83: 0 | X83: =W83*$M$23 -> 0 | Y83: 0 | Z83: =Y83*$M$23+X83/2 -> 0 | AA83: =D83+F83+H83+J83+L83+N83+P83+R83+T83+V83+X83+Z83 -> 0
B84: Científico de datos | C84: 0 | D84: =C84*$M$24 -> 0 | E84: 0 | F84: =E84*$M$24 -> 0 | G84: 0 | H84: =G84*$M$24 -> 0 | I84: 0 | J84: =I84*$M$24 -> 0 | K84: 0 | L84: =K84*$M$24 -> 0 | M84: 0 | N84: =M84*$M$24+L84/2 -> 0 | O84: 0 | P84: =O84*$M$24 -> 0 | Q84: 0 | R84: =Q84*$M$24 -> 0 | S84: 0 | T84: =S84*$M$24 -> 0 | U84: 0 | V84: =U84*$M$24 -> 0 | W84: 0 | X84: =W84*$M$24 -> 0 | Y84: 0 | Z84: =Y84*$M$24+X84/2 -> 0 | AA84: =D84+F84+H84+J84+L84+N84+P84+R84+T84+V84+X84+Z84 -> 0
B85: DevOps / infraestructura cloud | C85: 0 | D85: =C85*$M$25 -> 0 | E85: 0 | F85: =E85*$M$25 -> 0 | G85: 0 | H85: =G85*$M$25 -> 0 | I85: 0 | J85: =I85*$M$25 -> 0 | K85: 0 | L85: =K85*$M$25 -> 0 | M85: 0 | N85: =M85*$M$25+L85/2 -> 0 | O85: 0 | P85: =O85*$M$25 -> 0 | Q85: 0 | R85: =Q85*$M$25 -> 0 | S85: 0 | T85: =S85*$M$25 -> 0 | U85: 0 | V85: =U85*$M$25 -> 0 | W85: 0 | X85: =W85*$M$25 -> 0 | Y85: 0 | Z85: =Y85*$M$25+X85/2 -> 0 | AA85: =D85+F85+H85+J85+L85+N85+P85+R85+T85+V85+X85+Z85 -> 0
B86: Técnico de instalación y soporte | C86: 0 | D86: =C86*$M$26 -> 0 | E86: 0 | F86: =E86*$M$26 -> 0 | G86: 0 | H86: =G86*$M$26 -> 0 | I86: 0 | J86: =I86*$M$26 -> 0 | K86: 0 | L86: =K86*$M$26 -> 0 | M86: 0 | N86: =M86*$M$26+L86/2 -> 0 | O86: 0 | P86: =O86*$M$26 -> 0 | Q86: 0 | R86: =Q86*$M$26 -> 0 | S86: 0 | T86: =S86*$M$26 -> 0 | U86: 0 | V86: =U86*$M$26 -> 0 | W86: 0 | X86: =W86*$M$26 -> 0 | Y86: 0 | Z86: =Y86*$M$26+X86/2 -> 0 | AA86: =D86+F86+H86+J86+L86+N86+P86+R86+T86+V86+X86+Z86 -> 0
B87: Operador de monitoreo de sensores | C87: 0 | D87: =C87*$M$27 -> 0 | E87: 0 | F87: =E87*$M$27 -> 0 | G87: 0 | H87: =G87*$M$27 -> 0 | I87: 0 | J87: =I87*$M$27 -> 0 | K87: 0 | L87: =K87*$M$27 -> 0 | M87: 0 | N87: =M87*$M$27+L87/2 -> 0 | O87: 0 | P87: =O87*$M$27 -> 0 | Q87: 0 | R87: =Q87*$M$27 -> 0 | S87: 0 | T87: =S87*$M$27 -> 0 | U87: 0 | V87: =U87*$M$27 -> 0 | W87: 0 | X87: =W87*$M$27 -> 0 | Y87: 0 | Z87: =Y87*$M$27+X87/2 -> 0 | AA87: =D87+F87+H87+J87+L87+N87+P87+R87+T87+V87+X87+Z87 -> 0
B88: Totales | C88: =SUM(C74:C87) -> 2 | D88: =SUM(D74:D87) -> 5178.4 | E88: =SUM(E74:E87) -> 2 | F88: =SUM(F74:F87) -> 5178.4 | G88: =SUM(G74:G87) -> 2 | H88: =SUM(H74:H87) -> 5178.4 | I88: =SUM(I74:I87) -> 2 | J88: =SUM(J74:J87) -> 5178.4 | ... AA88: =SUM(AA74:AA87) -> 67319.2

Sheet Mod. egresos
F1: Modelo de egresos
B3: Evolución de la participación
B4: 2026 | C4: 2027 | D4: 2028
B5: =Hipótesis!C24 -> 0.008 | C5: =Hipótesis!C25 -> 0.029 | D5: =Hipótesis!C26 -> 0.052
B6: =Hipótesis!D24 -> 107520 | C6: =Hipótesis!D25 -> 389760 | D6: =Hipótesis!D26 -> 698880
B8: Costos totales (USD)
A9: Concepto | B9: 2026 | C9: 2027 | D9: 2028
A10: Costos fijos | B10: ='Costos fijos'!$G$5 -> 32640 | C10: ='Costos fijos'!$H$5 -> 77700 | D10: ='Costos fijos'!$I$5 -> 106860
A11: Costos variables | B11: ='Costos variables'!$H$6 -> 40479.8 | C11: ='Costos variables'!$I$6 -> 59474.6 | D11: ='Costos variables'!$J$6 -> 85346
A12: Costos de RRHH | B12: ='Costos RRHH'!$H$6 -> 67319.2 | C12: ='Costos RRHH'!$I$6 -> 67319.2 | D12: ='Costos RRHH'!$J$6 -> 67319.2
A13: Egresos totales | B13: =SUM(B10:B12) -> 140439 | C13: =SUM(C10:C12) -> 204493.8 | D13: =SUM(D10:D12) -> 259525.2
A14: Ingresos proyectados | B14: =+'Mod. ingresos'!C30 -> 105865 | C14: =+'Mod. ingresos'!D30 -> 386897 | D14: =+'Mod. ingresos'!E30 -> 705506
A15: Resultado operativo (antes de inversión, amortizaciones e impuestos) | B15: =B14-B13 -> -34574 | C15: =C14-C13 -> 182403.2 | D15: =D14-D13 -> 445980.8
A16: Egresos sobre ingresos | B16: =IFERROR(B13/B14,"") -> 1.3265857 | C16: =IFERROR(C13/C14,"") -> 0.52854843 | D16: =IFERROR(D13/D14,"") -> 0.36785683
C18: Composición de los egresos
A19: Concepto | B19: 2026 | C19: 2027 | D19: 2028
A20: Costos fijos | B20: =IFERROR(B10/B$13,"") -> 0.23241407 | C20: =IFERROR(C10/C$13,"") -> 0.37996262 | D20: =IFERROR(D10/D$13,"") -> 0.41175192
A21: Costos variables | B21: =IFERROR(B11/B$13,"") -> 0.2882376 | C21: =IFERROR(C11/C$13,"") -> 0.29083816 | D21: =IFERROR(D11/D$13,"") -> 0.32885438
A22: Costos de RRHH | B22: =IFERROR(B12/B$13,"") -> 0.47934833 | C22: =IFERROR(C12/C$13,"") -> 0.32919922 | D22: =IFERROR(D12/D$13,"") -> 0.25939369

Sheet Mod. inversión
F1: Modelo de inversión
B3: Evolución de la participación | G3: Modelo de Inversión
B4: 2026 | C4: 2027 | D4: 2028 | G4: Inversión Inicial | H4: 2026 | I4: 2027 | J4: 2028
B5: =Hipótesis!$C$24 -> 0.008 | C5: =Hipótesis!$C$25 -> 0.029 | D5: =Hipótesis!$C$26 -> 0.052 | G5: =$E$28 -> 67705 | H5: =$E$45 -> 10098 | I5: =$E$63 -> 11900 | J5: =$E$81 -> 18132
B6: =Hipótesis!$D$24 -> 107520 | C6: =Hipótesis!$D$25 -> 389760 | D6: =Hipótesis!$D$26 -> 698880
B9: Inversión inicial - Año cero
B10: Concepto | C10: Cantidad | D10: Precio unitario | E10: Subtotal | F10: Referencia
B11: Desarrollo de la plataforma | C11: 1 | D11: 64880 | E11: =C11*D11 -> 64880 | F11: Cronograma en Microsoft Project: cuatro roles contratados, 2.324 h a valor hora de mercado (ver informe de recursos abajo)
B12: Notebooks | C12: 2 | D12: 940 | E12: =C12*D12 -> 1880 | F12: Acer Aspire Go 15, Ryzen 7, 16 GB / 512 GB. Mercado Libre 9/2026: $1.450.000 a $1.545 por dólar
B13: Escritorios | C13: 2 | D13: 100 | E13: =C13*D13 -> 200 | F13: Escritorio de oficina 120×60. Mercado Libre 9/2026, en el orden de $150.000
B14: Sillas de escritorio | C14: 2 | D14: 85 | E14: =C14*D14 -> 170 | F14: Silla ergonómica de malla. Mercado Libre 9/2026, entre $90.000 y $156.000
B15: Equipamiento de red y periféricos | C15: 1 | D15: 205 | E15: =C15*D15 -> 205 | F15: Router TP-Link Archer AX23 ($96.190) + switch 8 puertos + UPS 650 VA
B16: Registración de marca y constitución legal | C16: 1 | D16: 370 | E16: =C16*D16 -> 370 | F16: INPI, 2 clases con honorarios (~$170.000) + constitución de SAS (~$400.000)
E17: =C17*D17 -> 0
E18: =C18*D18 -> 0
E19: =C19*D19 -> 0
E20: =C20*D20 -> 0
B28: Total | E28: =SUM(E11:E27) -> 67705
B30: Inversión - Año 2026
B31: Concepto | C31: Cantidad | D31: Precio unitario | E31: Subtotal
B32: Dispositivos IoT en comodato - Plan Vidriera (sensor de vidriera, contador de puerta, gateway y kit de montaje) | C32: ='Proy. ventas'!C20 -> 172 | D32: 34 | E32: =C32*D32 -> 5848 | F32: Una unidad por instalación del Plan Vidriera, según las altas de Proy. ventas. Se entrega en comodato, vuelve a la empresa en la baja y se reinstala: es stock que rota, no un bien de uso, y por eso no se amortiza.
B33: Dispositivos IoT en comodato - Plan Cadena (cinco locales por alta) | C33: ='Proy. ventas'!C21 -> 25 | D33: 170 | E33: =C33*D33 -> 4250 | F33: Un kit de cinco locales por instalación del Plan Cadena, según las altas de Proy. ventas. Mismo criterio: comodato reutilizable, no se amortiza.
B45: Total | E45: =SUM(E32:E44) -> 10098
B48: Inversión - Año 2027
B49: Concepto | C49: Cantidad | D49: Precio unitario | E49: Subtotal
B50: Dispositivos IoT en comodato - Plan Vidriera (sensor de vidriera, contador de puerta, gateway y kit de montaje) | C50: ='Proy. ventas'!C83 -> 210 | D50: 34 | E50: =C50*D50 -> 7140 | F50: Una unidad por instalación del Plan Vidriera, según las altas de Proy. ventas. Se entrega en comodato, vuelve a la empresa en la baja y se reinstala: es stock que rota, no un bien de uso, y por eso no se amortiza.
B51: Dispositivos IoT en comodato - Plan Cadena (cinco locales por alta) | C51: ='Proy. ventas'!C84 -> 28 | D51: 170 | E51: =C51*D51 -> 4760 | F51: Un kit de cinco locales por instalación del Plan Cadena, según las altas de Proy. ventas. Mismo criterio: comodato reutilizable, no se amortiza.
B63: Total | E63: =SUM(E50:E62) -> 11900
B66: Inversión - Año 2028
B67: Concepto | C67: Cantidad | D67: Precio unitario | E67: Subtotal
B69: Notebooks (renovación a los 3 años) | C69: 2 | D69: 940 | E69: =C69*D69 -> 1880
B70: Dispositivos IoT en comodato - Plan Vidriera (sensor de vidriera, contador de puerta, gateway y kit de montaje) | C70: ='Proy. ventas'!C145 -> 278 | D70: 34 | E70: =C70*D70 -> 9452 | F70: Una unidad por instalación del Plan Vidriera, según las altas de Proy. ventas. Se entrega en comodato, vuelve a la empresa en la baja y se reinstala: es stock que rota, no un bien de uso, y por eso no se amortiza.
B71: Dispositivos IoT en comodato - Plan Cadena (cinco locales por alta) | C71: ='Proy. ventas'!C146 -> 40 | D71: 170 | E71: =C71*D71 -> 6800 | F71: Un kit de cinco locales por instalación del Plan Cadena, según las altas de Proy. ventas. Mismo criterio: comodato reutilizable, no se amortiza.
B81: Total | E81: =SUM(E68:E80) -> 18132

Sheet Amortizaciones
G1: Amortizaciones
B3: Evolución de la participación | I3: Amortizaciones
B4: 2026 | C4: 2027 | D4: 2028 | I4: 2026 | J4: 2027 | K4: 2028
B5: =Hipótesis!$C$24 -> 0.008 | C5: =Hipótesis!$C$25 -> 0.029 | D5: =Hipótesis!$C$26 -> 0.052 | I5: =$K$27 -> 2148.6667 | J5: =$L$27 -> 3735.3333 | K5: =$M$27 -> 5292.2
B6: =Hipótesis!$D$24 -> 107520 | C6: =Hipótesis!$D$25 -> 389760 | D6: =Hipótesis!$D$26 -> 698880
B8: Amortizaciones
B9: Rubro | C9: Concepto | D9: Cantidad | E9: Precio unitario | F9: Amortización ( en años ) | G9: Valor de adquisiciones | K9: Amortización
G10: Año cero | H10: Año 2026 | I10: Año 2027 | J10: Año 2028 | K10: Año 2026 | L10: Año 2027 | M10: Año 2028
B11: Informática y comunicaciones | C11: Notebooks | D11: ='Mod. inversión'!C12 -> 2 | E11: ='Mod. inversión'!D12 -> 940 | F11: 3 | G11: =D11*E11 -> 1880 | H11: 0 | I11: 0 | J11: 0 | K11: =$G$11/$F$11 -> 626.66667 | L11: =$G$11/$F$11 -> 626.66667 | M11: 0
C12: Notebooks | D12: ='Mod. inversión'!C33 -> 25 | E12: ='Mod. inversión'!D33 -> 170 | F12: 3 | G12: 0 | H12: =D12*E12 -> 4250 | I12: 0 | J12: 0 | K12: =$H$12/$F$12 -> 1416.6667 | L12: =$H$12/$F$12 -> 1416.6667 | M12: =$H$12/$F$12 -> 1416.6667
C13: Notebooks | D13: ='Mod. inversión'!C51 -> 28 | E13: ='Mod. inversión'!D51 -> 170 | F13: 3 | G13: 0 | H13: 0 | I13: =D13*E13 -> 4760 | J13: 0 | K13: 0 | L13: =$I$13/$F$13 -> 1586.6667 | M13: =$I$13/$F$13 -> 1586.6667
C14: Notebooks | D14: ='Mod. inversión'!C69 -> 2 | E14: ='Mod. inversión'!D69 -> 940 | F14: 3 | G14: 0 | H14: 0 | I14: 0 | J14: =D14*E14 -> 1880 | K14: 0 | L14: 0 | M14: =$J$14/$F$14 -> 626.66667
B15: Muebles de oficina | C15: Escritorios | D15: ='Mod. inversión'!C13 -> 2 | E15: ='Mod. inversión'!D13 -> 100 | F15: 10 | G15: =D15*E15 -> 200 | H15: 0 | I15: 0 | J15: 0 | K15: =$G$15/$F$15 -> 20 | L15: =$G$15/$F$15 -> 20 | M15: =$G$15/$F$15 -> 20
C16: Escritorios | D16: ='Mod. inversión'!C34 -> 0 | E16: ='Mod. inversión'!D34 -> 0 | F16: 10 | G16: 0 | H16: =D16*E16 -> 0 | I16: 0 | J16: 0 | K16: =$H$16/$F$16 -> 0 | L16: =$H$16/$F$16 -> 0 | M16: =$H$16/$F$16 -> 0
C17: Escritorios | D17: ='Mod. inversión'!C52 -> 0 | E17: ='Mod. inversión'!D52 -> 0 | F17: 10 | G17: 0 | H17: 0 | I17: =D17*E17 -> 0 | J17: 0 | K17: 0 | L17: =$I$17/$F$17 -> 0 | M17: =$I$17/$F$17 -> 0
C18: Escritorios | D18: ='Mod. inversión'!C70 -> 278 | E18: ='Mod. inversión'!D70 -> 34 | F18: 10 | G18: 0 | H18: 0 | I18: 0 | J18: =D18*E18 -> 9452 | K18: 0 | L18: 0 | M18: =$J$18/$F$18 -> 945.2
C19: Sillas de escritorio | D19: ='Mod. inversión'!C14 -> 2 | E19: ='Mod. inversión'!D14 -> 85 | F19: 10 | G19: =D19*E19 -> 170 | H19: 0 | I19: 0 | J19: 0 | K19: =$G$19/$F$19 -> 17 | L19: =$G$19/$F$19 -> 17 | M19: =$G$19/$F$19 -> 17
C20: Sillas de escritorio | D20: ='Mod. inversión'!C35 -> 0 | E20: ='Mod. inversión'!D35 -> 0 | F20: 10 | G20: 0 | H20: =D20*E20 -> 0 | I20: 0 | J20: 0 | K20: =$H$20/$F$20 -> 0 | L20: =$H$20/$F$20 -> 0 | M20: =$H$20/$F$20 -> 0
C21: Sillas de escritorio | D21: ='Mod. inversión'!C53 -> 0 | E21: ='Mod. inversión'!D53 -> 0 | F21: 10 | G21: 0 | H21: 0 | I21: =D21*E21 -> 0 | J21: 0 | K21: 0 | L21: =$I$21/$F$21 -> 0 | M21: =$I$21/$F$21 -> 0
C22: Sillas de escritorio | D22: ='Mod. inversión'!C71 -> 40 | E22: ='Mod. inversión'!D71 -> 170 | F22: 10 | G22: 0 | H22: 0 | I22: 0 | J22: =D22*E22 -> 6800 | K22: 0 | L22: 0 | M22: =$J$22/$F$22 -> 680
B23: Equipamiento de red | C23: Red y periféricos | D23: ='Mod. inversión'!C15 -> 1 | E23: ='Mod. inversión'!D15 -> 205 | F23: 3 | G23: =D23*E23 -> 205 | H23: 0 | I23: 0 | J23: 0 | K23: =$G$23/$F$23 -> 68.333333 | L23: =$G$23/$F$23 -> 68.333333 | M23: 0
C24: Red y periféricos | D24: ='Mod. inversión'!C36 -> 0 | E24: ='Mod. inversión'!D36 -> 0 | F24: 3 | G24: 0 | H24: =D24*E24 -> 0 | I24: 0 | J24: 0 | K24: =$H$24/$F$24 -> 0 | L24: =$H$24/$F$24 -> 0 | M24: =$H$24/$F$24 -> 0
B27: Totales | K27: =SUM(K11:K26) -> 2148.6667 | L27: =SUM(L11:L26) -> 3735.3333 | M27: =SUM(M11:M26) -> 5292.2

Sheet Presupuesto financiero
E1: Presupuesto financiero
K3: Evolución de la participación
K4: 2026 | L4: 2027 | M4: 2028
K5: =Hipótesis!$C$24 -> 0.008 | L5: =Hipótesis!$C$25 -> 0.029 | M5: =Hipótesis!$C$26 -> 0.052
K6: =Hipótesis!$D$24 -> 107520 | L6: =Hipótesis!$D$25 -> 389760 | M6: =Hipótesis!$D$26 -> 698880
K8: Costos
K9: 2026 | L9: 2027 | M9: 2028
B10: Presupuesto financiero | J10: Costos fijos | K10: ='Costos fijos'!$G$5 -> 32640 | L10: ='Costos fijos'!$H$5 -> 77700 | M10: ='Costos fijos'!$I$5 -> 106860
B11: Ejercicio | D11: 0 | E11: 2026 | F11: 2027 | G11: 2028 | J11: Costos variables | K11: ='Costos variables'!$H$6 -> 40479.8 | L11: ='Costos variables'!$I$6 -> 59474.6 | M11: ='Costos variables'!$J$6 -> 85346
B12: Ingresos | D12: - | E12: =+'Mod. ingresos'!C30 -> 105865 | F12: =+'Mod. ingresos'!D30 -> 386897 | G12: =+'Mod. ingresos'!E30 -> 705506 | J12: Costos de RRHH | K12: ='Costos RRHH'!$H$6 -> 67319.2 | L12: ='Costos RRHH'!$I$6 -> 67319.2 | M12: ='Costos RRHH'!$J$6 -> 67319.2
B13: Egresos | C13: Costos fijos | D13: - | E13: =+'Mod. egresos'!B10 -> 32640 | F13: =+'Mod. egresos'!C10 -> 77700 | G13: =+'Mod. egresos'!D10 -> 106860
C14: Costos variables | D14: - | E14: =+'Mod. egresos'!B11 -> 40479.8 | F14: =+'Mod. egresos'!C11 -> 59474.6 | G14: =+'Mod. egresos'!D11 -> 85346 | K14: Amortizaciones
C15: Costos de RRHH | D15: - | E15: =+'Mod. egresos'!B12 -> 67319.2 | F15: =+'Mod. egresos'!C12 -> 67319.2 | G15: =+'Mod. egresos'!D12 -> 67319.2 | K15: 2026 | L15: 2027 | M15: 2028
B16: Utilidad Antes de Impuestos (UAII) | D16: - | E16: =E12-E13-E14-E15 -> -34574 | F16: =F12-F13-F14-F15 -> 182403.2 | G16: =G12-G13-G14-G15 -> 445980.8 | K16: =Amortizaciones!$I$5 -> 2148.6667 | L16: =Amortizaciones!$J$5 -> 3735.3333 | M16: =Amortizaciones!$K$5 -> 5292.2
B17: Impuesto Ingresos Brutos (3%) (IIB) | D17: - | E17: =E12*0.03 -> 3175.95 | F17: =F12*0.03 -> 11606.91 | G17: =G12*0.03 -> 21165.18
J18: Modelo de Inversión
B19: Impuesto a las ganancias (35%) (IIGG) | D19: - | E19: 0 | F19: =MAX(0,$L$23)*0.35 -> 0 | G19: =MAX(0,$M$23)*0.35 -> 58471.335 | J19: Inversión Inicial | K19: 2026 | L19: 2027 | M19: 2028
B20: Utilidad despues de Impuestos (UDII) | D20: - | E20: =E16-E17-E19 -> -37749.95 | F20: =F16-F17-F19 -> 170796.29 | G20: =G16-G17-G19 -> 366344.29 | J20: ='Mod. inversión'!$G$5 -> 67705 | K20: ='Mod. inversión'!$H$5 -> 10098 | L20: ='Mod. inversión'!$I$5 -> 11900 | M20: ='Mod. inversión'!$J$5 -> 18132
B21: Inversión | D21: =-J20 -> -67705 | E21: =-K20 -> -10098 | F21: =-L20 -> -11900 | G21: =-M20 -> -18132
B22: Flujo de Fondos (FF) | D22: =D21 -> -67705 | E22: =E20+E21 -> -47847.95 | F22: =F20+F21 -> 158896.29 | G22: =G20+G21 -> 348212.29 | K22: 2025 | L22: 2026 | M22: 2027 | N22: 2028
I23: Monto Imponible | L23: =E16-E17-K16 -> -39898.617 | M23: =F16-F17-L16 -> 167060.96 | N23: =G16-G17-M16 -> 419523.42
B24: Costo de promoción y publicidad | D24: - | E24: ='Costos variables'!H10 + 'Costos fijos'!G9 -> 13665 | F24: ='Costos variables'!I10 + 'Costos fijos'!H9 -> 46636 | G24: ='Costos variables'!J10 + 'Costos fijos'!I9 -> 70444
B25: Costo de promocion relacionados con ventas | E25: =E24/E$12 -> 0.12907949 | F25: =F24/F12 -> 0.12053854 | G25: =G24/G12 -> 0.099848903
B27: Costos fijos relacionados con ingresos | E27: =E13/E$12 -> 0.3083172 | F27: =F13/F$12 -> 0.20082864 | G27: =G13/G$12 -> 0.15146576
B28: Costos variables relacionados con ingresos | E28: =E14/E$12 -> 0.38237189 | F28: =F14/F$12 -> 0.15372205 | G28: =G14/G$12 -> 0.12097133
B29: Costos de RRHH relacionados con ingresos | E29: =E15/E$12 -> 0.63589666 | F29: =F15/F$12 -> 0.17399773 | G29: =G15/G$12 -> 0.095419741
F33: Tasa de Corte | G33: 0.3
F34: VAN | G34: =NPV($G$33,E22:G22)+D22 -> 148004.8 | I34: Se recupera la inversión en el 3er año
F35: TIR | G35: =IRR(D22:G22,$G$33) -> 0.91701938

Sheet Estructura
B2: Escalas Comunes
B4: Probabilidad (1 a 5):
B5: 1: Muy improbable
B6: 2: No es probable
B7: 3: Posible
B8: 4: Probable
B9: 5: Muy probable
B10: Impacto (1 a 5):
B11: 1: Insignificante
B12: 2: Menor
B13: 3: Moderado
B14: 4: Importante
... B21: Esto indica que el riesgo tiene un nivel moderado-alto y debe ser monitoreado y gestionado adecuadamente.
B23: Interpretación del Nivel de Riesgo | E23: Impacto \ Probabilidad | F23: Muy improbable (1) | G23: No es probable (2) | H23: Posible (3) | I23: Probable (4) | J23: Muy probable (5)
E24: Catastrófico (5)
B25: Bajo (1-6) : Riesgos que probablemente no sucederán o que, si lo hacen, no tendrán consecuencias significativas. | E25: Importante (4)
B26: Moderado (7-12) : Riesgos que pueden causar contratiempos en el proyecto, pero son manejables con medidas adecuadas. | E26: Moderado (3)
B27: Alto (13-20) : Riesgos que requieren atención inmediata y estrategias de mitigación rigurosas. | E27: Menor (2)
B28: Crítico (21-25) : Riesgos extremadamente altos que pueden poner en peligro la viabilidad del proyecto y requieren acciones urgentes. | E28: Insignificante (1)

Sheet Riesgos
B1: Riesgos
B3: Posibles riesgos
B5: R1: Caída de la plataforma o de la infraestructura en la nube
B6: R2: Baja anticipada de comercios adheridos
B7: R3: Ruptura de un conector con un sistema de punto de venta
B8: R4: Interrupción de la conectividad de los dispositivos de conteo
B9: R5: Restricción a la importación de sensores y gateways
B10: R6: Salto cambiario o inflación por encima de lo proyectado
B11: R7: Incidente de privacidad o pérdida de datos del comercio
B12: R8: Pérdida, robo o rotura del equipamiento en comodato
B13: R9: Dependencia de los dos socios fundadores
B14: R10: Entrada de un competidor local con precio agresivo

Sheet Matriz de riesgos
B2: Riesgo | C2: Descripción | D2: Causas | E2: Efectos cuantitativos (USD) | F2: Efectos cualitativos | G2: Probabilidad (1-5) | H2: Impacto (1-5) | I2: Nivel de riesgo (P x I)
B3: R1 | C3: Caída de la plataforma o de la infraestructura en la nube. El servicio deja de responder para toda la base de comercios a la vez: sin tablero, sin alertas y sin ingesta de ventas mientras dura la caída. | D3: - Falla del proveedor de nube o de la base de datos | E3: Una caída de 72 horas deja a toda la base sin servicio. Se bonifica el abono del período (unos USD 5.800 en 2028) y una de cada diez cuentas se da de baja en el trimestre: ingreso 2027 y 2028 un 10% por debajo, más USD 3.000 por ejercicio de recuperación y horas de DevOps. | F3: Pérdida de confianza en un servicio que se vende como tiempo real, y daño reputacional en un corredor donde los comerciantes se conocen entre sí. | G3: 3 | H3: 5 | I3: =+G3*H3 -> 15 | L3: Probabilidad (1 a 5): | M3: Impacto (1 a 5): | N3: Impacto \ Probabilidad | O3: Muy improbable (1) | P3: No es probable (2) | Q3: Posible (3) | R3: Probable (4) | S3: Muy probable (5)
D4: - Error en un despliegue que deja la API sin servicio | G4: 3 | H4: 5 | I4: =+G4*H4 -> 15 | L4: 1: Muy improbable | M4: 1: Insignificante | N4: Catastrófico (5) | P4: R7 | Q4: R1
D5: - Ataque de denegación de servicio o incidente de seguridad | G5: 3 | H5: 5 | I5: =+G5*H5 -> 15 | L5: 2: No es probable | M5: 2: Menor | N5: Importante (4) | P5: R10 | Q5: R5 - R6 - R9 | R5: R2 - R3 - R4
B6: R2 | C6: Baja anticipada de comercios adheridos. El comercio se da de baja a los pocos meses de instalado: la visita y las horas de técnico ya se pagaron, el dispositivo vuelve y hay que reacondicionarlo, y el abono mensual que la proyección daba por cobrado deja de entrar. | D6: - Alta rotación propia del comercio minorista | E6: Una baja del Plan Vidriera antes del mes doce deja sin recuperar los USD 60 del alta más las tres horas de técnico y el reacondicionamiento del equipo retirado. | F6: Erosión de la base instalada, mayor esfuerzo comercial para sostener el mismo stock de clientes y deterioro de la comparación sectorial. | G6: 4 | H6: 4 | I6: =+G6*H6 -> 16 | L6: 3: Posible | M6: 3: Moderado | N6: Moderado (3) | Q6: R8
D7: - Bajo uso de la plataforma tras las primeras semanas | G7: 4 | H7: 4 | I7: =+G7*H7 -> 16 | L7: 4: Probable | M7: 4: Importante | N7: Menor (2)
D8: - Estacionalidad del rubro indumentaria | G8: 4 | H8: 4 | I8: =+G8*H8 -> 16 | L8: 5: Muy probable | M8: 5: Catastrófico
B9: R3 | C9: Ruptura de un conector con un sistema de punto de venta. Uno de los siete sistemas de punto de venta integrados cambia o deprecia su API y el conector deja de funcionar. | D9: - Deprecación de la API por el proveedor del punto de venta | E9: Horas del Desarrollador destinadas a rehacer el conector en lugar de al roadmap, más el ingreso en riesgo de los comercios que operan con ese sistema. | F9: Incumplimiento del acuerdo de nivel de servicio y pérdida de confianza en un diferencial que es la principal barrera de entrada de la empresa. | G9: 4 | H9: 4 | I9: =+G9*H9 -> 16 | O9: Bajo (1-6) : Riesgos que probablemente no sucederán o que, si lo hacen, no tendrán consecuencias significativas.
D10: - Cambio de versión sin aviso previo | G10: 4 | H10: 4 | I10: =+G10*H10 -> 16 | O10: Moderado (7-12) : Riesgos que pueden causar contratiempos en el proyecto, pero son manejables con medidas adecuadas.
D11: - Consolidación o discontinuidad de un proveedor | G11: 4 | H11: 4 | I11: =+G11*H11 -> 16 | O11: Alto (13-20) : Riesgos que requieren atención inmediata y estrategias de mitigación rigurosas.
B12: R4 | C12: Interrupción de la conectividad de los dispositivos de conteo. Los sensores y contadores dejan de reportar: el comercio sigue vendiendo pero el sistema no ve el tráfico, y sin tráfico no hay conversión. | D12: - Falla de la red celular en galerías y subsuelos | E12: Un 20% de los dispositivos sin reportar durante un mes deja a esos comercios sin la métrica de conversión, que es el producto. Se bonifica su abono (unos USD 11.800 en 2028), la mitad no renueva y hay que reinstalar gateways: ingreso 2027 y 2028 un 8% por debajo, más USD 6.000 por ejercicio de visitas técnicas. | F12: El dato deja de ser confiable justo donde se apoya la propuesta de valor; el comerciante vuelve a decidir a ojo. | G12: 4 | H12: 4 | I12: =+G12*H12 -> 16 | O12: Crítico (21-25) : Riesgos extremadamente altos que pueden poner en peligro la viabilidad del proyecto y requieren acciones urgentes.
D13: - Gateway sin energía o desconectado por el propio comercio | G13: 4 | H13: 4 | I13: =+G13*H13 -> 16 | L13: 5: Muy probable | M13: 5: Catastrófico | N13: Insignificante (1)
D14: - Cambio de operador o de plan de datos sin aviso | G14: 4 | H14: 4 | I14: =+G14*H14 -> 16
B15: R5 | C15: Restricción a la importación de sensores y gateways. El equipamiento de conteo, de origen importado, no puede reponerse en tiempo o su costo se incrementa de manera significativa. | D15: - Cambios en el régimen de importaciones y licencias no automáticas | E15: Mayor costo del capital de trabajo por lote de reposición y altas del Plan Vidriera postergadas por falta de stock, con el ingreso recurrente diferido. | F15: Incumplimiento de las fechas de instalación comprometidas por el vendedor y deterioro de la experiencia inicial del cliente. | G15: 3 | H15: 4 | I15: =+G15*H15 -> 12
D16: - Demoras aduaneras en la nacionalización | G16: 3 | H16: 4 | I16: =+G16*H16 -> 12
D17: - Aumento del costo en origen o del flete | G17: 3 | H17: 4 | I17: =+G17*H17 -> 12
B18: R6 | C18: Salto cambiario o inflación por encima de lo proyectado. La lista de precios está denominada en dólares pero se cobra en pesos con ajuste por índice, mientras los sueldos se pagan en pesos. | D18: - Volatilidad cambiaria y ampliación de la brecha | E18: Erosión del valor real del abono cobrado entre la facturación y la cobranza, y aumento de la masa salarial por encima del ingreso ajustado. | F18: Necesidad de renegociar precios con la base instalada, con riesgo de bajas, y pérdida de previsibilidad en la planificación. | G18: 3 | H18: 4 | I18: =+G18*H18 -> 12
D19: - Inflación superior a la proyección del REM | G19: 3 | H19: 4 | I19: =+G19*H19 -> 12
D20: - Rezago del índice de ajuste frente a la suba de costos | G20: 3 | H20: 4 | I20: =+G20*H20 -> 12
B21: R7 | C21: Incidente de privacidad o pérdida de datos del comercio. Acceso indebido, filtración o pérdida de los datos de ventas y de conteo que los comercios confían a la plataforma. | D21: - Vulnerabilidad en la plataforma o en un conector | E21: Costos de recuperación, notificación y eventual sanción bajo la Ley 25.326, más el ingreso perdido por las bajas que el incidente provoque. | F21: Daño reputacional severo en un negocio cuya propuesta de valor se apoya en la privacidad por diseño; pérdida de la principal respuesta a la objeción del comerciante. | G21: 2 | H21: 5 | I21: =+G21*H21 -> 10
D22: - Error humano en la gestión de credenciales | G22: 2 | H22: 5 | I22: =+G22*H22 -> 10
D23: - Falla en la política de respaldos | G23: 2 | H23: 5 | I23: =+G23*H23 -> 10
B24: R8 | C24: Pérdida, robo o rotura del equipamiento en comodato. Los sensores, contadores y gateways entregados en comodato no se recuperan o se recuperan sin posibilidad de reacondicionamiento. | D24: - Cierre abrupto del local sin devolución del equipo | E24: Reposición del equipamiento no recuperado, que se suma al capital de trabajo del período sin generar una nueva alta. | F24: Deterioro de la rotación del capital de trabajo, que es una de las condiciones que vuelven viable el modelo de abono bajo. | G24: 3 | H24: 3 | I24: =+G24*H24 -> 9
D25: - Robo o daño en el punto de instalación | G25: 3 | H25: 3 | I25: =+G25*H25 -> 9
D26: - Desgaste por encima de la vida útil estimada | G26: 3 | H26: 3 | I26: =+G26*H26 -> 9
B27: R9 | C27: Dependencia de los dos socios fundadores. La conducción estratégica, técnica y comercial se concentra en dos personas que además ejecutan tareas operativas. | D27: - Ausencia prolongada o desvinculación de un socio | E27: Detención del desarrollo o de la conducción comercial, con impacto directo sobre el ritmo de altas y sobre el mantenimiento de los conectores. | F27: Vulnerabilidad estructural de la organización y dificultad para incorporar inversores que evalúan la continuidad del equipo. | G27: 3 | H27: 4 | I27: =+G27*H27 -> 12
D28: - Concentración del conocimiento técnico sin documentar | G28: 3 | H28: 4 | I28: =+G28*H28 -> 12
D29: - Sobrecarga por acumulación de funciones | G29: 3 | H29: 4 | I29: =+G29*H29 -> 12
B30: R10 | C30: Entrada de un competidor local con precio agresivo. Un competidor local replica la propuesta con un abono menor, apoyado en los mismos dispositivos de conteo disponibles en el mercado. | D30: - Baja barrera de entrada en la capa de hardware | E30: Presión a la baja sobre el abono y aumento del costo de adquisición por comercio en los ejes disputados. | F30: Pérdida de la ventaja de ser el primero en el corredor y erosión del margen que sostiene la estructura. | G30: 2 | H30: 4 | I30: =+G30*H30 -> 8
D31: - Imitación del modelo comercial una vez validado | G31: 2 | H31: 4 | I31: =+G31*H31 -> 8
D32: - Estrategia de precio por debajo del costo para ganar participación | G32: 2 | H32: 4 | I32: =+G32*H32 -> 8

Sheet Cuadro de evaluación de riesgos
C3: Impacto \ Probabilidad | D3: Muy improbable (1) | E3: No es probable (2) | F3: Posible (3) | G3: Probable (4) | H3: Muy probable (5)
C4: Catastrófico (5) | E4: R7 | F4: R1 | K4: Bajo (1-6) : Riesgos que probablemente no sucederán o que, si lo hacen, no tendrán consecuencias significativas.
C5: Importante (4) | E5: R10 | F5: R5 - R6 - R9 | G5: R2 - R3 - R4 | K5: Moderado (7-12) : Riesgos que pueden causar contratiempos en el proyecto, pero son manejables con medidas adecuadas.
C6: Moderado (3) | F6: R8 | K6: Alto (13-20) : Riesgos que requieren atención inmediata y estrategias de mitigación rigurosas.
C7: Menor (2) | K7: Crítico (21-25) : Riesgos extremadamente altos que pueden poner en peligro la viabilidad del proyecto y requieren acciones urgentes.
C8: Insignificante (1)

Sheet Escenario 1
B2: Presupuesto financiero
B3: Ejercicio | D3: Inicio | E3: 2026 | F3: 2027 | G3: 2028 | I3: RIESGO: R1 · Caída de la plataforma o de la infraestructura en la nube
B4: Ingresos | D4: - | E4: =+'Presupuesto financiero'!E12 -> 105865 | F4: =+'Presupuesto financiero'!F12*0.9 -> 348207.3 | G4: =+'Presupuesto financiero'!G12*0.9 -> 634955.4 | I4: R 1 | J4: - Falla del proveedor de nube o de la base de datos - Error en un despliegue que deja la API sin servicio - Ataque de denegación de servicio | K4: - 72 horas sin servicio para toda la base: se bonifica el abono y una de cada diez cuentas se da de baja - Ingreso 2027 y 2028 un 10% menor - Recuperación y horas de DevOps: USD 3.000 por ejercicio - Los costos variables acompañan la baja de ventas | L4: - Pérdida de confianza en un servicio vendido como tiempo real - Daño reputacional en el corredor
B5: Egresos | C5: Costos fijos | D5: - | E5: =+'Presupuesto financiero'!E13 -> 32640 | F5: =+'Presupuesto financiero'!F13 -> 77700 | G5: =+'Presupuesto financiero'!G13 -> 106860
C6: Costos variables | D6: - | E6: =+'Presupuesto financiero'!E14 -> 40479.8 | F6: =+'Presupuesto financiero'!F14*0.9 + 3000 -> 56527.14 | G6: =+'Presupuesto financiero'!G14*0.9 + 3000 -> 79811.4
C7: Costos de RRHH | D7: - | E7: =+'Presupuesto financiero'!E15 -> 67319.2 | F7: =+'Presupuesto financiero'!F15 -> 67319.2 | G7: =+'Presupuesto financiero'!G15 -> 67319.2 | K7: Año 2 | L7: Año 3
B8: Utilidad Antes de Impuestos (UAII) | D8: - | E8: =+E4-E5-E6-E7 -> -34574 | F8: =+F4-F5-F6-F7 -> 146660.96 | G8: =+G4-G5-G6-G7 -> 380964.8
B9: Impuesto Ingresos Brutos | C9: 0.03 | D9: - | E9: =+E4*$C$9 -> 3175.95 | F9: =+F4*$C$9 -> 10446.219 | G9: =+G4*$C$9 -> 19048.662
B10: Impuesto a las ganancias 35% | E10: 0 | F10: =MAX(0,$E$22)*0.35 -> 0 | G10: =MAX(0,$F$22)*0.35 -> 46367.793
B12: Utilidad despues de Impuestos (UDII) | D12: - | E12: =+E8-E9-E10 -> -37749.95 | F12: =+F8-F9-F10 -> 136214.74 | G12: =+G8-G9-G10 -> 315548.35
B13: Inversión | D13: =+'Presupuesto financiero'!D21 -> -67705 | E13: =+'Presupuesto financiero'!E21 -> -10098 | F13: =+'Presupuesto financiero'!F21 -> -11900 | G13: =+'Presupuesto financiero'!G21 -> -18132
B14: Flujo de Fondos (FF) | D14: =+D13 -> -67705 | E14: =+E12+E13 -> -47847.95 | F14: =+F12+F13 -> 124314.74 | G14: =+G12+G13 -> 297416.35
E18: Tasa de Corte | F18: =+'Presupuesto financiero'!$G$33 -> 0.3
E19: VAN | F19: =NPV($F$18,E14:G14)+D14 -> 104421.75
E20: TIR | F20: =IRR(D14:G14,$F$18) -> 0.75834076
B22: Monto imponible del ejercicio (neto de amortizaciones) | E22: =+E8-E9-Amortizaciones!$I$5 -> -39898.617 | F22: =+F8-F9-Amortizaciones!$J$5 -> 132479.41 | G22: =+G8-G9-Amortizaciones!$K$5 -> 356623.94

Sheet Escenario 2
B2: Presupuesto financiero
B3: Ejercicio | D3: Inicio | E3: 2026 | F3: 2027 | G3: 2028 | I3: RIESGO: R2 · Baja anticipada de comercios adheridos
B4: Ingresos | D4: - | E4: =+'Presupuesto financiero'!E12 -> 105865 | F4: =+'Presupuesto financiero'!F12*0.85 -> 328862.45 | G4: =+'Presupuesto financiero'!G12*0.85 -> 599680.1 | I4: R 2 | J4: - Alta rotación propia del comercio minorista de barrio - Bajo uso de la plataforma tras las primeras semanas - Estacionalidad del rubro indumentaria | K4: - Ingreso recurrente 2027 y 2028 un 15% menor por las bajas - Reposición y reacondicionamiento del equipamiento retirado: USD 12.000 por ejercicio | L4: - Erosión de la base instalada - Mayor esfuerzo comercial para sostener el mismo stock de clientes
B5: Egresos | C5: Costos fijos | D5: - | E5: =+'Presupuesto financiero'!E13 -> 32640 | F5: =+'Presupuesto financiero'!F13 -> 77700 | G5: =+'Presupuesto financiero'!G13 -> 106860
C6: Costos variables | D6: - | E6: =+'Presupuesto financiero'!E14 -> 40479.8 | F6: =+'Presupuesto financiero'!F14*0.85 + 12000 -> 62553.41 | G6: =+'Presupuesto financiero'!G14*0.85 + 12000 -> 84544.1
C7: Costos de RRHH | D7: - | E7: =+'Presupuesto financiero'!E15 -> 67319.2 | F7: =+'Presupuesto financiero'!F15 -> 67319.2 | G7: =+'Presupuesto financiero'!G15 -> 67319.2 | K7: Año 2 | L7: Año 3
B8: Utilidad Antes de Impuestos (UAII) | D8: - | E8: =+E4-E5-E6-E7 -> -34574 | F8: =+F4-F5-F6-F7 -> 121289.84 | G8: =+G4-G5-G6-G7 -> 340956.8
B9: Impuesto Ingresos Brutos | C9: 0.03 | D9: - | E9: =+E4*$C$9 -> 3175.95 | F9: =+F4*$C$9 -> 9865.8735 | G9: =+G4*$C$9 -> 17990.403
B10: Impuesto a las ganancias 35% | E10: 0 | F10: =MAX(0,$E$22)*0.35 -> 0 | G10: =MAX(0,$F$22)*0.35 -> 37691.022
B12: Utilidad despues de Impuestos (UDII) | D12: - | E12: =+E8-E9-E10 -> -37749.95 | F12: =+F8-F9-F10 -> 111423.97 | G12: =+G8-G9-G10 -> 285275.38
B13: Inversión | D13: =+'Presupuesto financiero'!D21 -> -67705 | E13: =+'Presupuesto financiero'!E21 -> -10098 | F13: =+'Presupuesto financiero'!F21 -> -11900 | G13: =+'Presupuesto financiero'!G21 -> -18132
B14: Flujo de Fondos (FF) | D14: =+D13 -> -67705 | E14: =+E12+E13 -> -47847.95 | F14: =+F12+F13 -> 99523.966 | G14: =+G12+G13 -> 267143.38
E18: Tasa de Corte | F18: =+'Presupuesto financiero'!$G$33 -> 0.3
E19: VAN | F19: =NPV($F$18,E14:G14)+D14 -> 75973.423
E20: TIR | F20: =IRR(D14:G14,$F$18) -> 0.64499961
B22: Monto imponible del ejercicio (neto de amortizaciones) | E22: =+E8-E9-Amortizaciones!$I$5 -> -39898.617 | F22: =+F8-F9-Amortizaciones!$J$5 -> 107688.63 | G22: =+G8-G9-Amortizaciones!$K$5 -> 317674.2

Sheet Escenario 3
B2: Presupuesto financiero
B3: Ejercicio | D3: Inicio | E3: 2026 | F3: 2027 | G3: 2028 | I3: RIESGO: Combinado · R1 caída de plataforma + R2 baja anticipada + R10 competidor
B4: Ingresos | D4: - | E4: =+'Presupuesto financiero'!E12 -> 105865 | F4: =+'Presupuesto financiero'!F12*0.6 -> 232138.2 | G4: =+'Presupuesto financiero'!G12*0.6 -> 423303.6 | I4: R1+R2+R10 | J4: - Una caída prolongada de la plataforma - Los comercios que entran se van antes del año - Un competidor local con precio agresivo | K4: - Ingreso 2027 y 2028 un 40% por debajo: la caída hace perder cuentas, las bajas no se reponen y el competidor presiona el precio - Reposición y reinstalación de equipamiento: USD 15.000 por ejercicio - Los costos variables acompañan la baja de ventas | L4: - El proyecto deja de cubrir su costo de capital - Se pierde la masa crítica que da sentido al benchmarking
B5: Egresos | C5: Costos fijos | D5: - | E5: =+'Presupuesto financiero'!E13 -> 32640 | F5: =+'Presupuesto financiero'!F13 -> 77700 | G5: =+'Presupuesto financiero'!G13 -> 106860
C6: Costos variables | D6: - | E6: =+'Presupuesto financiero'!E14 -> 40479.8 | F6: =+'Presupuesto financiero'!F14*0.6 + 15000 -> 50684.76 | G6: =+'Presupuesto financiero'!G14*0.6 + 15000 -> 66207.6
C7: Costos de RRHH | D7: - | E7: =+'Presupuesto financiero'!E15 -> 67319.2 | F7: =+'Presupuesto financiero'!F15 - 15534 -> 51785.2 | G7: =+'Presupuesto financiero'!G15 - 15534 -> 51785.2 | K7: Año 2 | L7: Año 3
B8: Utilidad Antes de Impuestos (UAII) | D8: - | E8: =+E4-E5-E6-E7 -> -34574 | F8: =+F4-F5-F6-F7 -> 51968.24 | G8: =+G4-G5-G6-G7 -> 198450.8
B9: Impuesto Ingresos Brutos | C9: 0.03 | D9: - | E9: =+E4*$C$9 -> 3175.95 | F9: =+F4*$C$9 -> 6964.146 | G9: =+G4*$C$9 -> 12699.108
B10: Impuesto a las ganancias 35% | E10: 0 | F10: =MAX(0,$E$22)*0.35 -> 0 | G10: =MAX(0,$F$22)*0.35 -> 14444.066
B12: Utilidad despues de Impuestos (UDII) | D12: - | E12: =+E8-E9-E10 -> -37749.95 | F12: =+F8-F9-F10 -> 45004.094 | G12: =+G8-G9-G10 -> 171307.63
B13: Inversión | D13: =+'Presupuesto financiero'!D21 -> -67705 | E13: =+'Presupuesto financiero'!E21 -> -10098 | F13: =+'Presupuesto financiero'!F21 + 1200 -> -10700 | G13: =+'Presupuesto financiero'!G21 + 1200 -> -16932
B14: Flujo de Fondos (FF) | D14: =+D13 -> -67705 | E14: =+E12+E13 -> -47847.95 | F14: =+F12+F13 -> 34304.094 | G14: =+G12+G13 -> 154375.63
E18: Tasa de Corte | F18: =+'Presupuesto financiero'!$G$33 -> 0.3
E19: VAN | F19: =NPV($F$18,E14:G14)+D14 -> -13946.278
E20: TIR | F20: =IRR(D14:G14,$F$18) -> 0.22535206
B22: Monto imponible del ejercicio (neto de amortizaciones) | E22: =+E8-E9-Amortizaciones!$I$5 -> -39898.617 | F22: =+F8-F9-Amortizaciones!$J$5 -> 41268.761 | G22: =+G8-G9-Amortizaciones!$K$5 -> 180459.49

Sheet Plan de Contingencia
B2: PLAN DE CONTINGENCIA
B4: Objetivos del Plan de Contingencia
B5: · Sostener el servicio aunque falle la nube principal.
B6: · Devolver el proyecto por encima de su costo de capital.
B7: · Proteger la base instalada frente al competidor.
B10: Presupuesto financiero
B11: Ejercicio | D11: Inicio | E11: 2026 | F11: 2027 | G11: 2028 | I11: RIESGO: Plan sobre el escenario 3, que es el que no resiste
B12: Ingresos | D12: - | E12: =+'Presupuesto financiero'!E12 -> 105865 | F12: =+'Presupuesto financiero'!F12*0.66 -> 255352.02 | G12: =+'Presupuesto financiero'!G12*0.66 -> 465633.96 | I12: R1+R2+R10 | J12: - Escenario 3 con las medidas aplicadas | K12: - Segunda nube y monitoreo: +USD 4.000 de costo fijo - Retención y referidos: +USD 5.000 | L12: - Vuelve a cubrir el costo de capital - Conserva la masa crítica
B13: Egresos | C13: Costos fijos | D13: - | E13: =+'Presupuesto financiero'!E13 -> 32640 | F13: =+'Presupuesto financiero'!F13 + 9000 -> 86700 | G13: =+'Presupuesto financiero'!G13 + 9000 -> 115860
C14: Costos variables | D14: - | E14: =+'Presupuesto financiero'!E14 -> 40479.8 | F14: =+'Presupuesto financiero'!F14*0.66 + 15000 -> 54253.236 | G14: =+'Presupuesto financiero'!G14*0.66 + 15000 -> 71328.36
C15: Costos de RRHH | D15: - | E15: =+'Presupuesto financiero'!E15 -> 67319.2 | F15: =+'Presupuesto financiero'!F15 - 15534 -> 51785.2 | G15: =+'Presupuesto financiero'!G15 - 15534 -> 51785.2 | K15: Año 2 | L15: Año 3
B16: Utilidad Antes de Impuestos (UAII) | D16: - | E16: =+E12-E13-E14-E15 -> -34574 | F16: =+F12-F13-F14-F15 -> 62613.584 | G16: =+G12-G13-G14-G15 -> 226660.4
B17: Impuesto Ingresos Brutos | C17: 0.03 | D17: - | E17: =+E12*$C$17 -> 3175.95 | F17: =+F12*$C$17 -> 7660.5606 | G17: =+G12*$C$17 -> 13969.019 | I17: PLAN DE CONTINGENCIA
B18: Impuesto a las ganancias 35% | E18: 0 | F18: =MAX(0,$E$30)*0.35 -> 0 | G18: =MAX(0,$F$30)*0.35 -> 17926.192 | I18: El plan se aplica sobre el escenario 3, que es el único de los tres que no resiste: con la caída de la plataforma, las bajas anticipadas y el competidor a la vez, la TIR cae a 22,54% contra una tasa de corte del 30% y el VAN queda negativo. 1ª medida: respaldo en una segunda nube con conmutación automática y monitoreo permanente, para que una caída del proveedor principal no deje a la base sin servicio. Suma USD 4.000 por ejercicio al costo fijo. 2ª medida: campaña de retención sobre la base instalada y canal de captación por referidos, que es donde el competidor no llega. Suma USD 5.000 por ejercicio. Entre las dos recuperan 6 de los 40 puntos de caída de ventas. La dotación se mantiene en la del escenario: no se incorpora el segundo ejecutivo comercial. El plan nivela, no mejora: la TIR queda en 31,34%, apenas por encima de la tasa de corte y muy por debajo del 91,70% del presupuesto original.
B20: Utilidad despues de Impuestos (UDII) | D20: - | E20: =+E16-E17-E18 -> -37749.95 | F20: =+F16-F17-F18 -> 54953.023 | G20: =+G16-G17-G18 -> 194765.19
B21: Inversión | D21: =+'Presupuesto financiero'!D21 -> -67705 | E21: =+'Presupuesto financiero'!E21 -> -10098 | F21: =+'Presupuesto financiero'!F21 + 1200 -> -10700 | G21: =+'Presupuesto financiero'!G21 + 1200 -> -16932
B22: Flujo de Fondos (FF) | D22: =+D21 -> -67705 | E22: =+E20+E21 -> -47847.95 | F22: =+F20+F21 -> 44253.023 | G22: =+G20+G21 -> 177833.19
E26: Tasa de Corte | F26: =+'Presupuesto financiero'!$G$33 -> 0.3
E27: VAN | F27: =NPV($F$26,E22:G22)+D22 -> 2617.7513
E28: TIR | F28: =IRR(D22:G22,$F$26) -> 0.31344923
B30: Monto imponible del ejercicio (neto de amortizaciones) | E30: =+E16-E17-Amortizaciones!$I$5 -> -39898.617 | F30: =+F16-F17-Amortizaciones!$J$5 -> 51217.69 | G30: =+G16-G17-Amortizaciones!$K$5 -> 207399.18
